Workbook

Sheet NOMINA TEJIDO 
A1: 1 | AA1: MARTES 06/03 | AF1: MIERCOLES 07/03 | AK1: JUEVES 08/03 | AP1: VIERNES 09/03 | AU1: SABADO 10/03 | BU1: 1
A2: 2 | B2: TEJIDO | T2: SUELDO ESTIMADO FALTA SOLO RELOJ | U2: BONO | V2: DEL 08 AL 14 ENERO 24 | X2: 7.18 | Y2: 7.18 | BA2: 0 | BU2: 2
A3: 3 | E3: L | G3: M | I3: M | K3: J | M3: V | O3: S | R3: COSTOS | V3: 0 | W3: NOMINA | X3: PXP | Y3: PXA | Z3: TOTAL | AA3: INC | AB3: NOMINA | AC3: PXP | AD3: PXA | AE3: TOTAL | AF3: INC | AG3: NOMINA | AH3: PXP | AI3: PXA | AJ3: TOTAL | AK3: INC | AL3: NOMINA | AM3: PXP | AN3: PXA | AO3: TOTAL | AP3: INC | AQ3: NOMINA | AR3: PXP | AS3: PXA | AT3: TOTAL | AU3: INC | AV3: NOMINA | AW3: PXP | AX3: PXA | AY3: TOTAL | BB3: CB | BC3: FP | BD3: L | BE3: R | BI3: INC | BJ3: B ASISTENCIA | BK3: T EXT | BM3: PRIMAS | BN3: PAGO EXTRA | BQ3: 3 | BR3: =0.167*4+4 -> 4.668 | BU3: 3
B4: 164 | C4: =+C3+1 -> 1 | E4: 1 | G4: 1 | I4: 1 | K4: 1 | M4: 1 | O4: 1 | Q4: =IF((E4+G4+I4+K4+M4+O4)=6,1,0) -> 1 | R4: =IF(Q4=1,1550,850) -> 1550 | S4: =+BH4 -> 0 | T4: =+BA4 -> 929 | U4: =+BP4 -> 0 | V4: =+BG4 -> BONO+ B ASIS | W4: =(R4-86.16)/6*E4 -> 243.97333 | X4: =$Y$2*E4*Q4 -> 7.18 | Y4: =$Y$2*E4*Q4 -> 7.18 | Z4: =Y4+X4+W4 -> 258.33333 | AB4: =(R4-86.16)/6*G4 -> 243.97333 | AC4: =$Y$2*G4*Q4 -> 7.18 | AD4: =$Y$2*G4*Q4 -> 7.18 | AE4: =AD4+AC4+AB4 -> 258.33333 | AG4: =(R4-86.16)/6*I4 -> 243.97333 | AH4: =$Y$2*I4*Q4 -> 7.18 | AI4: =$Y$2*I4*Q4 -> 7.18 | AJ4: =AI4+AH4+AG4 -> 258.33333 | AL4: =(R4-86.16)/6*K4 -> 243.97333 | AM4: =$Y$2*K4*Q4 -> 7.18 | AN4: =$Y$2*K4*Q4 -> 7.18 | AO4: =AN4+AM4+AL4 -> 258.33333 | AQ4: =(R4-86.16)/6*M4 -> 243.97333 | AR4: =$Y$2*M4*Q4 -> 7.18 | AS4: =$Y$2*M4*Q4 -> 7.18 | AT4: =AS4+AR4+AQ4 -> 258.33333 | AV4: =(R4-86.16)/6*O4 -> 243.97333 | AW4: =$Y$2*O4*Q4 -> 7.18 | AX4: =$Y$2*O4*Q4 -> 7.18 | AY4: =AX4+AW4+AV4 -> 258.33333 | AZ4: =+AY4+AT4+AO4++AJ4+AE4+Z4 -> 1550 | BA4: 929 | BG4: BONO+ B ASIS
A5: 420 | B5: 2 | C5: =+C4+1 -> 2 | D5: Antunez Requejo Gabriela | E5: 1 | G5: 1 | I5: 1 | K5: 1 | M5: 1 | O5: 1 | Q5: =IF((E5+G5+I5+K5+M5+O5)=6,1,0) -> 1 | R5: =IF(Q5=1,1550,850) -> 1550 | S5: =+BH5 -> 0 | T5: =+BA5 -> 2100 | U5: =+BP5 -> 0 | V5: =+BG5 -> BONO+ B ASIS | W5: =(R5-86.16)/6*E5 -> 243.97333 | X5: =$Y$2*E5*Q5 -> 7.18 | Y5: =$Y$2*E5*Q5 -> 7.18 | Z5: =Y5+X5+W5 -> 258.33333 | AB5: =(R5-86.16)/6*G5 -> 243.97333 | AC5: =$Y$2*G5*Q5 -> 7.18 | AD5: =$Y$2*G5*Q5 -> 7.18 | AE5: =AD5+AC5+AB5 -> 258.33333 | AG5: =(R5-86.16)/6*I5 -> 243.97333 | AH5: =$Y$2*I5*Q5 -> 7.18 | AI5: =$Y$2*I5*Q5 -> 7.18 | AJ5: =AI5+AH5+AG5 -> 258.33333 | AL5: =(R5-86.16)/6*K5 -> 243.97333 | AM5: =$Y$2*K5*Q5 -> 7.18 | AN5: =$Y$2*K5*Q5 -> 7.18 | AO5: =AN5+AM5+AL5 -> 258.33333 | AQ5: =(R5-86.16)/6*M5 -> 243.97333 | AR5: =$Y$2*M5*Q5 -> 7.18 | AS5: =$Y$2*M5*Q5 -> 7.18 | AT5: =AS5+AR5+AQ5 -> 258.33333 | AV5: =(R5-86.16)/6*O5 -> 243.97333 | AW5: =$Y$2*O5*Q5 -> 7.18 | AX5: =$Y$2*O5*Q5 -> 7.18 | AY5: =AX5+AW5+AV5 -> 258.33333 | AZ5: =+AY5+AT5+AO5++AJ5+AE5+Z5 -> 1550 | BA5: =((AZ5-BB5-BC5-BD5-BE5-BF5)+BI5+BJ5+BK5+BL5+BM5+BN5+BO5) -> 2100 | BG5: BONO+ B ASIS | BI5: 300 | BJ5: 250 | BU5: 420
A6: 424 | B6: 6 | C6: =+C5+1 -> 3 | D6: Balderas Balderas Myriam Ivet | E6: 1 | G6: 1 | I6: 1 | K6: 1 | M6: 1 | O6: 1 | Q6: =IF((E6+G6+I6+K6+M6+O6)=6,1,0) -> 1 | R6: 3000 | S6: =+BH6 -> 0 | T6: =+BA6 -> 3000 | U6: =+BP6 -> 0 | V6: =+BG6 -> 0 | W6: =(R6-86.16)/6*E6 -> 485.64 | X6: =$Y$2*E6*Q6 -> 7.18 | Y6: =$Y$2*E6*Q6 -> 7.18 | Z6: =Y6+X6+W6 -> 500 | AB6: =(R6-86.16)/6*G6 -> 485.64 | AC6: =$Y$2*G6*Q6 -> 7.18 | AD6: =$Y$2*G6*Q6 -> 7.18 | AE6: =AD6+AC6+AB6 -> 500 | AG6: =(R6-86.16)/6*I6 -> 485.64 | AH6: =$Y$2*I6*Q6 -> 7.18 | AI6: =$Y$2*I6*Q6 -> 7.18 | AJ6: =AI6+AH6+AG6 -> 500 | AL6: =(R6-86.16)/6*K6 -> 485.64 | AM6: =$Y$2*K6*Q6 -> 7.18 | AN6: =$Y$2*K6*Q6 -> 7.18 | AO6: =AN6+AM6+AL6 -> 500 | AQ6: =(R6-86.16)/6*M6 -> 485.64 | AR6: =$Y$2*M6*Q6 -> 7.18 | AS6: =$Y$2*M6*Q6 -> 7.18 | AT6: =AS6+AR6+AQ6 -> 500 | AV6: =(R6-86.16)/6*O6 -> 485.64 | AW6: =$Y$2*O6*Q6 -> 7.18 | AX6: =$Y$2*O6*Q6 -> 7.18 | AY6: =AX6+AW6+AV6 -> 500 | AZ6: =+AY6+AT6+AO6++AJ6+AE6+Z6 -> 3000 | BA6: =((AZ6-BB6-BC6-BD6-BE6-BF6)+BI6+BJ6+BK6+BL6+BM6+BN6+BO6) -> 3000 | BU6: 424
B7: 149 | C7: =+C6+1 -> 4 | D7: Carrillo Alvarado Erika Miranda | E7: 1 | G7: 1 | I7: 1 | K7: 1 | M7: 1 | O7: 1 | Q7: =IF((E7+G7+I7+K7+M7+O7)=6,1,0) -> 1 | R7: =IF(Q7=1,1550,850) -> 1550 | S7: =+BH7 -> 0 | T7: =+BA7 -> 1800 | U7: =+BP7 -> 0 | V7: =+BG7 -> BONO+ B ASIS | W7: =(R7-86.16)/6*E7 -> 243.97333 | X7: =$Y$2*E7*Q7 -> 7.18 | Y7: =$Y$2*E7*Q7 -> 7.18 | Z7: =Y7+X7+W7 -> 258.33333 | AB7: =(R7-86.16)/6*G7 -> 243.97333 | AC7: =$Y$2*G7*Q7 -> 7.18 | AD7: =$Y$2*G7*Q7 -> 7.18 | AE7: =AD7+AC7+AB7 -> 258.33333 | AG7: =(R7-86.16)/6*I7 -> 243.97333 | AH7: =$Y$2*I7*Q7 -> 7.18 | AI7: =$Y$2*I7*Q7 -> 7.18 | AJ7: =AI7+AH7+AG7 -> 258.33333 | AL7: =(R7-86.16)/6*K7 -> 243.97333 | AM7: =$Y$2*K7*Q7 -> 7.18 | AN7: =$Y$2*K7*Q7 -> 7.18 | AO7: =AN7+AM7+AL7 -> 258.33333 | AQ7: =(R7-86.16)/6*M7 -> 243.97333 | AR7: =$Y$2*M7*Q7 -> 7.18 | AS7: =$Y$2*M7*Q7 -> 7.18 | AT7: =AS7+AR7+AQ7 -> 258.33333 | AV7: =(R7-86.16)/6*O7 -> 243.97333 | AW7: =$Y$2*O7*Q7 -> 7.18 | AX7: =$Y$2*O7*Q7 -> 7.18 | AY7: =AX7+AW7+AV7 -> 258.33333 | AZ7: =+AY7+AT7+AO7++AJ7+AE7+Z7 -> 1550 | BA7: =((AZ7-BB7-BC7-BD7-BE7-BF7)+BI7+BJ7+BK7+BL7+BM7+BN7+BO7) -> 1800 | BG7: BONO+ B ASIS | BI7: 100 | BJ7: 150
B8: 95 | C8: =+C7+1 -> 5 | D8: Carrillo Delgado Judith | E8: 1 | G8: 1 | I8: 1 | K8: 1 | M8: 1 | O8: 1 | Q8: =IF((E8+G8+I8+K8+M8+O8)=6,1,0) -> 1 | R8: =IF(Q8=1,1550,850) -> 1550 | S8: =+BH8 -> 0 | T8: =+BA8 -> 1950 | U8: =+BP8 -> 0 | V8: =+BG8 -> BONO+ B ASIS | W8: =(R8-86.16)/6*E8 -> 243.97333 | X8: =$Y$2*E8*Q8 -> 7.18 | Y8: =$Y$2*E8*Q8 -> 7.18 | Z8: =Y8+X8+W8 -> 258.33333 | AB8: =(R8-86.16)/6*G8 -> 243.97333 | AC8: =$Y$2*G8*Q8 -> 7.18 | AD8: =$Y$2*G8*Q8 -> 7.18 | AE8: =AD8+AC8+AB8 -> 258.33333 | AG8: =(R8-86.16)/6*I8 -> 243.97333 | AH8: =$Y$2*I8*Q8 -> 7.18 | AI8: =$Y$2*I8*Q8 -> 7.18 | AJ8: =AI8+AH8+AG8 -> 258.33333 | AL8: =(R8-86.16)/6*K8 -> 243.97333 | AM8: =$Y$2*K8*Q8 -> 7.18 | AN8: =$Y$2*K8*Q8 -> 7.18 | AO8: =AN8+AM8+AL8 -> 258.33333 | AQ8: =(R8-86.16)/6*M8 -> 243.97333 | AR8: =$Y$2*M8*Q8 -> 7.18 | AS8: =$Y$2*M8*Q8 -> 7.18 | AT8: =AS8+AR8+AQ8 -> 258.33333 | AV8: =(R8-86.16)/6*O8 -> 243.97333 | AW8: =$Y$2*O8*Q8 -> 7.18 | AX8: =$Y$2*O8*Q8 -> 7.18 | AY8: =AX8+AW8+AV8 -> 258.33333 | AZ8: =+AY8+AT8+AO8++AJ8+AE8+Z8 -> 1550 | BA8: =((AZ8-BB8-BC8-BD8-BE8-BF8)+BI8+BJ8+BK8+BL8+BM8+BN8+BO8) -> 1950 | BG8: BONO+ B ASIS | BI8: 250 | BJ8: 150
B9: 59 | C9: =+C8+1 -> 6 | D9: Castro Viaña Mario Ivan | E9: 1 | G9: 1 | I9: 1 | K9: 1 | M9: 1 | O9: 1 | Q9: =IF((E9+G9+I9+K9+M9+O9)=6,1,0) -> 1 | R9: =IF(Q9=1,1550,850) -> 1550 | S9: =+BH9 -> 0 | T9: =+BA9 -> 1950 | U9: =+BP9 -> 0 | V9: =+BG9 -> BONO+ B ASIS | W9: =(R9-86.16)/6*E9 -> 243.97333 | X9: =$Y$2*E9*Q9 -> 7.18 | Y9: =$Y$2*E9*Q9 -> 7.18 | Z9: =Y9+X9+W9 -> 258.33333 | AB9: =(R9-86.16)/6*G9 -> 243.97333 | AC9: =$Y$2*G9*Q9 -> 7.18 | AD9: =$Y$2*G9*Q9 -> 7.18 | AE9: =AD9+AC9+AB9 -> 258.33333 | AG9: =(R9-86.16)/6*I9 -> 243.97333 | AH9: =$Y$2*I9*Q9 -> 7.18 | AI9: =$Y$2*I9*Q9 -> 7.18 | AJ9: =AI9+AH9+AG9 -> 258.33333 | AL9: =(R9-86.16)/6*K9 -> 243.97333 | AM9: =$Y$2*K9*Q9 -> 7.18 | AN9: =$Y$2*K9*Q9 -> 7.18 | AO9: =AN9+AM9+AL9 -> 258.33333 | AQ9: =(R9-86.16)/6*M9 -> 243.97333 | AR9: =$Y$2*M9*Q9 -> 7.18 | AS9: =$Y$2*M9*Q9 -> 7.18 | AT9: =AS9+AR9+AQ9 -> 258.33333 | AV9: =(R9-86.16)/6*O9 -> 243.97333 | AW9: =$Y$2*O9*Q9 -> 7.18 | AX9: =$Y$2*O9*Q9 -> 7.18 | AY9: =AX9+AW9+AV9 -> 258.33333 | AZ9: =+AY9+AT9+AO9++AJ9+AE9+Z9 -> 1550 | BA9: =((AZ9-BB9-BC9-BD9-BE9-BF9)+BI9+BJ9+BK9+BL9+BM9+BN9+BO9) -> 1950 | BG9: BONO+ B ASIS | BI9: 250 | BJ9: 150
B10: 73 | C10: =+C9+1 -> 7 | D10: Garcia Ortega Leslie Coraima | E10: 1 | G10: 1 | I10: 1 | K10: 1 | M10: 1 | O10: 1 | Q10: =IF((E10+G10+I10+K10+M10+O10)=6,1,0) -> 1 | R10: =IF(Q10=1,1550,850) -> 1550 | S10: =+BH10 -> 0 | T10: =+BA10 -> 1950 | U10: =+BP10 -> 0 | V10: =+BG10 -> BONO+ B ASIS | W10: =(R10-86.16)/6*E10 -> 243.97333 | X10: =$Y$2*E10*Q10 -> 7.18 | Y10: =$Y$2*E10*Q10 -> 7.18 | Z10: =Y10+X10+W10 -> 258.33333 | AB10: =(R10-86.16)/6*G10 -> 243.97333 | AC10: =$Y$2*G10*Q10 -> 7.18 | AD10: =$Y$2*G10*Q10 -> 7.18 | AE10: =AD10+AC10+AB10 -> 258.33333 | AG10: =(R10-86.16)/6*I10 -> 243.97333 | AH10: =$Y$2*I10*Q10 -> 7.18 | AI10: =$Y$2*I10*Q10 -> 7.18 | AJ10: =AI10+AH10+AG10 -> 258.33333 | AL10: =(R10-86.16)/6*K10 -> 243.97333 | AM10: =$Y$2*K10*Q10 -> 7.18 | AN10: =$Y$2*K10*Q10 -> 7.18 | AO10: =AN10+AM10+AL10 -> 258.33333 | AQ10: =(R10-86.16)/6*M10 -> 243.97333 | AR10: =$Y$2*M10*Q10 -> 7.18 | AS10: =$Y$2*M10*Q10 -> 7.18 | AT10: =AS10+AR10+AQ10 -> 258.33333 | AV10: =(R10-86.16)/6*O10 -> 243.97333 | AW10: =$Y$2*O10*Q10 -> 7.18 | AX10: =$Y$2*O10*Q10 -> 7.18 | AY10: =AX10+AW10+AV10 -> 258.33333 | AZ10: =+AY10+AT10+AO10++AJ10+AE10+Z10 -> 1550 | BA10: =((AZ10-BB10-BC10-BD10-BE10-BF10)+BI10+BJ10+BK10+BL10+BM10+BN10+BO10) -> 1950 | BG10: BONO+ B ASIS | BI10: 250 | BJ10: 150
A11: 424 | B11: 26 | C11: =+C10+1 -> 8 | D11: Medrano Suarez Jose Adolfo | E11: 1 | G11: 1 | I11: 1 | K11: 1 | M11: 1 | O11: 1 | Q11: =IF((E11+G11+I11+K11+M11+O11)=6,1,0) -> 1 | R11: 2500 | S11: =+BH11 -> 0 | T11: =+BA11 -> 2500 | U11: =+BP11 -> 0 | V11: =+BG11 -> 0 | W11: =(R11-86.16)/6*E11 -> 402.30667 | X11: =$Y$2*E11*Q11 -> 7.18 | Y11: =$Y$2*E11*Q11 -> 7.18 | Z11: =Y11+X11+W11 -> 416.66667 | AB11: =(R11-86.16)/6*G11 -> 402.30667 | AC11: =$Y$2*G11*Q11 -> 7.18 | AD11: =$Y$2*G11*Q11 -> 7.18 | AE11: =AD11+AC11+AB11 -> 416.66667 | AG11: =(R11-86.16)/6*I11 -> 402.30667 | AH11: =$Y$2*I11*Q11 -> 7.18 | AI11: =$Y$2*I11*Q11 -> 7.18 | AJ11: =AI11+AH11+AG11 -> 416.66667 | AL11: =(R11-86.16)/6*K11 -> 402.30667 | AM11: =$Y$2*K11*Q11 -> 7.18 | AN11: =$Y$2*K11*Q11 -> 7.18 | AO11: =AN11+AM11+AL11 -> 416.66667 | AQ11: =(R11-86.16)/6*M11 -> 402.30667 | AR11: =$Y$2*M11*Q11 -> 7.18 | AS11: =$Y$2*M11*Q11 -> 7.18 | AT11: =AS11+AR11+AQ11 -> 416.66667 | AV11: =(R11-86.16)/6*O11 -> 402.30667 | AW11: =$Y$2*O11*Q11 -> 7.18 | AX11: =$Y$2*O11*Q11 -> 7.18 | AY11: =AX11+AW11+AV11 -> 416.66667 | AZ11: =+AY11+AT11+AO11++AJ11+AE11+Z11 -> 2500 | BA11: =((AZ11-BB11-BC11-BD11-BE11-BF11)+BI11+BJ11+BK11+BL11+BM11+BN11+BO11) -> 2500 | BU11: 424
B12: 169 | C12: =+C11+1 -> 9 | D12: Ramirez Requejo Maria Guadalupe | E12: 1 | G12: 1 | I12: 1 | K12: 1 | M12: 1 | O12: 1 | Q12: =IF((E12+G12+I12+K12+M12+O12)=6,1,0) -> 1 | R12: =IF(Q12=1,1550,850) -> 1550 | S12: =+BH12 -> 0 | T12: =+BA12 -> 1700 | U12: =+BP12 -> 0 | V12: =+BG12 -> BONO | W12: =(R12-86.16)/6*E12 -> 243.97333 | X12: =$Y$2*E12*Q12 -> 7.18 | Y12: =$Y$2*E12*Q12 -> 7.18 | Z12: =Y12+X12+W12 -> 258.33333 | AB12: =(R12-86.16)/6*G12 -> 243.97333 | AC12: =$Y$2*G12*Q12 -> 7.18 | AD12: =$Y$2*G12*Q12 -> 7.18 | AE12: =AD12+AC12+AB12 -> 258.33333 | AG12: =(R12-86.16)/6*I12 -> 243.97333 | AH12: =$Y$2*I12*Q12 -> 7.18 | AI12: =$Y$2*I12*Q12 -> 7.18 | AJ12: =AI12+AH12+AG12 -> 258.33333 | AL12: =(R12-86.16)/6*K12 -> 243.97333 | AM12: =$Y$2*K12*Q12 -> 7.18 | AN12: =$Y$2*K12*Q12 -> 7.18 | AO12: =AN12+AM12+AL12 -> 258.33333 | AQ12: =(R12-86.16)/6*M12 -> 243.97333 | AR12: =$Y$2*M12*Q12 -> 7.18 | AS12: =$Y$2*M12*Q12 -> 7.18 | AT12: =AS12+AR12+AQ12 -> 258.33333 | AV12: =(R12-86.16)/6*O12 -> 243.97333 | AW12: =$Y$2*O12*Q12 -> 7.18 | AX12: =$Y$2*O12*Q12 -> 7.18 | AY12: =AX12+AW12+AV12 -> 258.33333 | AZ12: =+AY12+AT12+AO12++AJ12+AE12+Z12 -> 1550 | BA12: =((AZ12-BB12-BC12-BD12-BE12-BF12)+BI12+BJ12+BK12+BL12+BM12+BN12+BO12) -> 1700 | BG12: BONO | BJ12: 150
B13: 152 | C13: =+C12+1 -> 10 | D13: Ruiz Valenzuela Cynthia Marissa | E13: 1 | G13: 1 | I13: 1 | K13: 1 | M13: 1 | O13: 1 | Q13: =IF((E13+G13+I13+K13+M13+O13)=6,1,0) -> 1 | R13: =IF(Q13=1,1550,850) -> 1550 | S13: =+BH13 -> 0 | T13: =+BA13 -> 2000 | U13: =+BP13 -> 0 | V13: =+BG13 -> BONO+B ASIS | W13: =(R13-86.16)/6*E13 -> 243.97333 | X13: =$Y$2*E13*Q13 -> 7.18 | Y13: =$Y$2*E13*Q13 -> 7.18 | Z13: =Y13+X13+W13 -> 258.33333 | AB13: =(R13-86.16)/6*G13 -> 243.97333 | AC13: =$Y$2*G13*Q13 -> 7.18 | AD13: =$Y$2*G13*Q13 -> 7.18 | AE13: =AD13+AC13+AB13 -> 258.33333 | AG13: =(R13-86.16)/6*I13 -> 243.97333 | AH13: =$Y$2*I13*Q13 -> 7.18 | AI13: =$Y$2*I13*Q13 -> 7.18 | AJ13: =AI13+AH13+AG13 -> 258.33333 | AL13: =(R13-86.16)/6*K13 -> 243.97333 | AM13: =$Y$2*K13*Q13 -> 7.18 | AN13: =$Y$2*K13*Q13 -> 7.18 | AO13: =AN13+AM13+AL13 -> 258.33333 | AQ13: =(R13-86.16)/6*M13 -> 243.97333 | AR13: =$Y$2*M13*Q13 -> 7.18 | AS13: =$Y$2*M13*Q13 -> 7.18 | AT13: =AS13+AR13+AQ13 -> 258.33333 | AV13: =(R13-86.16)/6*O13 -> 243.97333 | AW13: =$Y$2*O13*Q13 -> 7.18 | AX13: =$Y$2*O13*Q13 -> 7.18 | AY13: =AX13+AW13+AV13 -> 258.33333 | AZ13: =+AY13+AT13+AO13++AJ13+AE13+Z13 -> 1550 | BA13: =((AZ13-BB13-BC13-BD13-BE13-BF13)+BI13+BJ13+BK13+BL13+BM13+BN13+BO13) -> 2000 | BG13: BONO+B ASIS | BI13: 300 | BJ13: 150
B14: 146 | C14: =+C13+1 -> 11 | D14: Salazar Martinez Yohana Cecilia | E14: 1 | G14: 1 | I14: 1 | K14: 1 | M14: 1 | O14: 1 | Q14: =IF((E14+G14+I14+K14+M14+O14)=6,1,0) -> 1 | R14: =IF(Q14=1,1550,850) -> 1550 | S14: =+BH14 -> 0 | T14: =+BA14 -> 1950 | U14: =+BP14 -> 0 | V14: =+BG14 -> BONO+B ASIS | W14: =(R14-86.16)/6*E14 -> 243.97333 | X14: =$Y$2*E14*Q14 -> 7.18 | Y14: =$Y$2*E14*Q14 -> 7.18 | Z14: =Y14+X14+W14 -> 258.33333 | AB14: =(R14-86.16)/6*G14 -> 243.97333 | AC14: =$Y$2*G14*Q14 -> 7.18 | AD14: =$Y$2*G14*Q14 -> 7.18 | AE14: =AD14+AC14+AB14 -> 258.33333 | AG14: =(R14-86.16)/6*I14 -> 243.97333 | AH14: =$Y$2*I14*Q14 -> 7.18 | AI14: =$Y$2*I14*Q14 -> 7.18 | AJ14: =AI14+AH14+AG14 -> 258.33333 | AL14: =(R14-86.16)/6*K14 -> 243.97333 | AM14: =$Y$2*K14*Q14 -> 7.18 | AN14: =$Y$2*K14*Q14 -> 7.18 | AO14: =AN14+AM14+AL14 -> 258.33333 | AQ14: =(R14-86.16)/6*M14 -> 243.97333 | AR14: =$Y$2*M14*Q14 -> 7.18 | AS14: =$Y$2*M14*Q14 -> 7.18 | AT14: =AS14+AR14+AQ14 -> 258.33333 | AV14: =(R14-86.16)/6*O14 -> 243.97333 | AW14: =$Y$2*O14*Q14 -> 7.18 | AX14: =$Y$2*O14*Q14 -> 7.18 | AY14: =AX14+AW14+AV14 -> 258.33333 | AZ14: =+AY14+AT14+AO14++AJ14+AE14+Z14 -> 1550 | BA14: =((AZ14-BB14-BC14-BD14-BE14-BF14)+BI14+BJ14+BK14+BL14+BM14+BN14+BO14) -> 1950 | BG14: BONO+B ASIS | BI14: 250 | BJ14: 150
A15: 470 | B15: 51 | C15: =+C14+1 -> 12 | D15: Valenzuela Rosales Jose Miguel | E15: 1 | G15: 1 | I15: 1 | K15: 1 | M15: 1 | O15: 1 | Q15: =IF((E15+G15+I15+K15+M15+O15)=6,1,0) -> 1 | R15: 3000 | S15: =+BH15 -> 0 | T15: =+BA15 -> 5585.71 | U15: =+BP15 -> 0 | V15: =+BG15 -> BONO+FINIQUITO | W15: =(R15-86.16)/6*E15 -> 485.64 | X15: =$Y$2*E15*Q15 -> 7.18 | Y15: =$Y$2*E15*Q15 -> 7.18 | Z15: =Y15+X15+W15 -> 500 | AB15: =(R15-86.16)/6*G15 -> 485.64 | AC15: =$Y$2*G15*Q15 -> 7.18 | AD15: =$Y$2*G15*Q15 -> 7.18 | AE15: =AD15+AC15+AB15 -> 500 | AG15: =(R15-86.16)/6*I15 -> 485.64 | AH15: =$Y$2*I15*Q15 -> 7.18 | AI15: =$Y$2*I15*Q15 -> 7.18 | AJ15: =AI15+AH15+AG15 -> 500 | AL15: =(R15-86.16)/6*K15 -> 485.64 | AM15: =$Y$2*K15*Q15 -> 7.18 | AN15: =$Y$2*K15*Q15 -> 7.18 | AO15: =AN15+AM15+AL15 -> 500 | AQ15: =(R15-86.16)/6*M15 -> 485.64 | AR15: =$Y$2*M15*Q15 -> 7.18 | AS15: =$Y$2*M15*Q15 -> 7.18 | AT15: =AS15+AR15+AQ15 -> 500 | AV15: =(R15-86.16)/6*O15 -> 485.64 | AW15: =$Y$2*O15*Q15 -> 7.18 | AX15: =$Y$2*O15*Q15 -> 7.18 | AY15: =AX15+AW15+AV15 -> 500 | AZ15: =+AY15+AT15+AO15++AJ15+AE15+Z15 -> 3000 | BA15: =((AZ15-BB15-BC15-BD15-BE15-BF15)+BI15+BJ15+BK15+BL15+BM15+BN15+BO15) -> 5585.71 | BG15: BONO+FINIQUITO | BI15: 1000 | BL15: 1585.71 | BU15: 470
A16: 429 | E16: =SUM(E4:E15) -> 12 | G16: =SUM(G4:G15) -> 12 | I16: =SUM(I4:I15) -> 12 | K16: =SUM(K4:K15) -> 12 | M16: =SUM(M4:M15) -> 12 | O16: =SUM(O4:O15) -> 12 | BU16: 429
A17: 430 | BU17: 430
A18: 431 | B18: REAL | C18: PR | G18: L | I18: M | K18: M | M18: J | O18: V | Q18: S | BU18: 431
A19: 432 | B19: =E16 -> 12 | C19: =G25 -> 12 | D19: =+B19-C19 -> 0 | R19: PROM | BU19: 432
A20: 433 | B20: =G16 -> 12 | C20: =I25 -> 12 | D20: =+B20-C20 -> 0 | E20: LIDER | G20: 1 | I20: 1 | K20: 1 | M20: 1 | O20: 1 | Q20: 1 | R20: =AVERAGE(G20,I20,K20,M20,O20,Q20) -> 1 | BU20: 433
A21: 434 | B21: =I16 -> 12 | C21: =K25 -> 12 | D21: =+B21-C21 -> 0 | E21: CALIDAD | G21: 1 | I21: 1 | K21: 1 | M21: 1 | O21: 1 | Q21: 1 | R21: =AVERAGE(G21,I21,K21,M21,O21,Q21) -> 1 | BU21: 434
A22: 435 | B22: =K16 -> 12 | C22: =M25 -> 12 | D22: =+B22-C22 -> 0 | E22: MECANICO | G22: 2 | I22: 2 | K22: 2 | M22: 2 | O22: 2 | Q22: 2 | R22: =AVERAGE(G22,I22,K22,M22,O22,Q22) -> 2 | BU22: 435
A23: 436 | B23: =M16 -> 12 | C23: =O25 -> 12 | D23: =+B23-C23 -> 0 | E23: MANUAL | G23: 8 | I23: 8 | K23: 8 | M23: 8 | O23: 8 | Q23: 8 | R23: =AVERAGE(G23,I23,K23,M23,O23,Q23) -> 8 | BU23: 436
A24: 437 | B24: =O16 -> 12 | C24: =Q25 -> 12 | D24: =+B24-C24 -> 0 | E24: MTTO | G24: 0 | I24: 0 | K24: 0 | M24: 0 | O24: 0 | Q24: 0 | R24: =AVERAGE(G24,I24,K24,M24,O24,Q24) -> 0 | BU24: 437
A25: 438 | G25: =SUM(G20:G24) -> 12 | I25: =SUM(I20:I24) -> 12 | K25: =SUM(K20:K24) -> 12 | M25: =SUM(M20:M24) -> 12 | O25: =SUM(O20:O24) -> 12 | Q25: =SUM(Q20:Q24) -> 12 | R25: =AVERAGE(G25,I25,K25,M25,O25,Q25) -> 12 | BU25: 438
A26: 439 | BU26: 439
A27: 440 | BU27: 440
A28: 441 | BU28: 441
A29: 442 | B29: TEJIDO 2 | D29: 3ER TURNO | R29: =$V2 -> DEL 08 AL 14 ENERO 24 | BU29: 442
A30: 443 | E30: L | G30: M | I30: M | K30: J | M30: V | O30: S | V30: 3 | BU30: 443
A31: 444 | B31: 9 | C31: =+C30+1 -> 1 | D31: Bustamante Villegas Osvaldo | E31: 1 | G31: 1 | I31: 1 | K31: 1 | M31: 1 | O31: 1 | Q31: =IF((E31+G31+I31+K31+M31+O31)=6,1,0) -> 1 | R31: 3000 | S31: =+BH31 -> 0 | T31: =+BA31 -> 3000 | U31: =+BP31 -> 0 | V31: =+BG31 -> 0 | W31: =(R31-86.16)/6*E31 -> 485.64 | X31: =$Y$2*E31*Q31 -> 7.18 | Y31: =$Y$2*E31*Q31 -> 7.18 | Z31: =Y31+X31+W31 -> 500 | AB31: =(R31-86.16)/6*G31 -> 485.64 | AC31: =$Y$2*G31*Q31 -> 7.18 | AD31: =$Y$2*G31*Q31 -> 7.18 | AE31: =AD31+AC31+AB31 -> 500 | AG31: =(R31-86.16)/6*I31 -> 485.64 | AH31: =$Y$2*I31*Q31 -> 7.18 | AI31: =$Y$2*I31*Q31 -> 7.18 | AJ31: =AI31+AH31+AG31 -> 500 | AL31: =(R31-86.16)/6*K31 -> 485.64 | AM31: =$Y$2*K31*Q31 -> 7.18 | AN31: =$Y$2*K31*Q31 -> 7.18 | AO31: =AN31+AM31+AL31 -> 500 | AQ31: =(R31-86.16)/6*M31 -> 485.64 | AR31: =$Y$2*M31*Q31 -> 7.18 | AS31: =$Y$2*M31*Q31 -> 7.18 | AT31: =AS31+AR31+AQ31 -> 500 | AV31: =(R31-86.16)/6*O31 -> 485.64 | AW31: =$Y$2*O31*Q31 -> 7.18 | AX31: =$Y$2*O31*Q31 -> 7.18 | AY31: =AX31+AW31+AV31 -> 500 | AZ31: =+AY31+AT31+AO31++AJ31+AE31+Z31 -> 3000 | BA31: =((AZ31-BB31-BC31-BD31-BE31-BF31)+BI31+BJ31+BK31+BL31+BM31+BN31+BO31) -> 3000 | BU31: 444
A32: 445 | B32: 12 | C32: =+C31+1 -> 2 | D32: Diaz Martinez Angela Elizabeth | E32: 1 | G32: 1 | I32: 1 | K32: 1 | M32: 1 | O32: 1 | Q32: =IF((E32+G32+I32+K32+M32+O32)=6,1,0) -> 1 | R32: =IF(Q32=1,1550,850) -> 1550 | S32: =+BH32 -> 0 | T32: =+BA32 -> 2100 | U32: =+BP32 -> 0 | V32: =+BG32 -> BONO+B ASIS | W32: =(R32-86.16)/6*E32 -> 243.97333 | X32: =$Y$2*E32*Q32 -> 7.18 | Y32: =$Y$2*E32*Q32 -> 7.18 | Z32: =Y32+X32+W32 -> 258.33333 | AB32: =(R32-86.16)/6*G32 -> 243.97333 | AC32: =$Y$2*G32*Q32 -> 7.18 | AD32: =$Y$2*G32*Q32 -> 7.18 | AE32: =AD32+AC32+AB32 -> 258.33333 | AG32: =(R32-86.16)/6*I32 -> 243.97333 | AH32: =$Y$2*I32*Q32 -> 7.18 | AI32: =$Y$2*I32*Q32 -> 7.18 | AJ32: =AI32+AH32+AG32 -> 258.33333 | AL32: =(R32-86.16)/6*K32 -> 243.97333 | AM32: =$Y$2*K32*Q32 -> 7.18 | AN32: =$Y$2*K32*Q32 -> 7.18 | AO32: =AN32+AM32+AL32 -> 258.33333 | AQ32: =(R32-86.16)/6*M32 -> 243.97333 | AR32: =$Y$2*M32*Q32 -> 7.18 | AS32: =$Y$2*M32*Q32 -> 7.18 | AT32: =AS32+AR32+AQ32 -> 258.33333 | AV32: =(R32-86.16)/6*O32 -> 243.97333 | AW32: =$Y$2*O32*Q32 -> 7.18 | AX32: =$Y$2*O32*Q32 -> 7.18 | AY32: =AX32+AW32+AV32 -> 258.33333 | AZ32: =+AY32+AT32+AO32++AJ32+AE32+Z32 -> 1550 | BA32: =((AZ32-BB32-BC32-BD32-BE32-BF32)+BI32+BJ32+BK32+BL32+BM32+BN32+BO32) -> 2100 | BG32: BONO+B ASIS | BI32: 300 | BJ32: 250 | BU32: 445
B33: 168 | C33: =+C32+1 -> 3 | D33: Espinoza Ponce Juan Jose | E33: 1 | G33: 1 | I33: 1 | K33: 1 | M33: 1 | O33: 1 | Q33: =IF((E33+G33+I33+K33+M33+O33)=6,1,0) -> 1 | R33: =IF(Q33=1,1550,850) -> 1550 | S33: =+BH33 -> 0 | T33: =+BA33 -> 1800 | U33: =+BP33 -> 0 | V33: =+BG33 -> B ASIS | W33: =(R33-86.16)/6*E33 -> 243.97333 | X33: =$Y$2*E33*Q33 -> 7.18 | Y33: =$Y$2*E33*Q33 -> 7.18 | Z33: =Y33+X33+W33 -> 258.33333 | AB33: =(R33-86.16)/6*G33 -> 243.97333 | AC33: =$Y$2*G33*Q33 -> 7.18 | AD33: =$Y$2*G33*Q33 -> 7.18 | AE33: =AD33+AC33+AB33 -> 258.33333 | AG33: =(R33-86.16)/6*I33 -> 243.97333 | AH33: =$Y$2*I33*Q33 -> 7.18 | AI33: =$Y$2*I33*Q33 -> 7.18 | AJ33: =AI33+AH33+AG33 -> 258.33333 | AL33: =(R33-86.16)/6*K33 -> 243.97333 | AM33: =$Y$2*K33*Q33 -> 7.18 | AN33: =$Y$2*K33*Q33 -> 7.18 | AO33: =AN33+AM33+AL33 -> 258.33333 | AQ33: =(R33-86.16)/6*M33 -> 243.97333 | AR33: =$Y$2*M33*Q33 -> 7.18 | AS33: =$Y$2*M33*Q33 -> 7.18 | AT33: =AS33+AR33+AQ33 -> 258.33333 | AV33: =(R33-86.16)/6*O33 -> 243.97333 | AW33: =$Y$2*O33*Q33 -> 7.18 | AX33: =$Y$2*O33*Q33 -> 7.18 | AY33: =AX33+AW33+AV33 -> 258.33333 | AZ33: =+AY33+AT33+AO33++AJ33+AE33+Z33 -> 1550 | BA33: =((AZ33-BB33-BC33-BD33-BE33-BF33)+BI33+BJ33+BK33+BL33+BM33+BN33+BO33) -> 1800 | BG33: B ASIS | BI33: 100 | BJ33: 150
A34: 445 | B34: 16 | C34: =+C33+1 -> 4 | D34: Favela Saucedo Idalia Azucena | E34: 0 | F34: INC | G34: 0 | H34: INC | I34: 0 | J34: INC | K34: 0 | L34: INC | M34: 0 | N34: INC | O34: 0 | P34: INC | Q34: =IF((E34+G34+I34+K34+M34+O34)=6,1,0) -> 0 | R34: =IF(Q34=1,1550,850) -> 850 | S34: =+BH34 -> 0 | T34: =+BA34 -> 0 | U34: =+BP34 -> 0 | V34: =+BG34 -> 0 | W34: =(R34-86.16)/6*E34 -> 0 | X34: =$Y$2*E34*Q34 -> 0 | Y34: =$Y$2*E34*Q34 -> 0 | Z34: =Y34+X34+W34 -> 0 | AB34: =(R34-86.16)/6*G34 -> 0 | AC34: =$Y$2*G34*Q34 -> 0 | AD34: =$Y$2*G34*Q34 -> 0 | AE34: =AD34+AC34+AB34 -> 0 | AG34: =(R34-86.16)/6*I34 -> 0 | AH34: =$Y$2*I34*Q34 -> 0 | AI34: =$Y$2*I34*Q34 -> 0 | AJ34: =AI34+AH34+AG34 -> 0 | AL34: =(R34-86.16)/6*K34 -> 0 | AM34: =$Y$2*K34*Q34 -> 0 | AN34: =$Y$2*K34*Q34 -> 0 | AO34: =AN34+AM34+AL34 -> 0 | AQ34: =(R34-86.16)/6*M34 -> 0 | AR34: =$Y$2*M34*Q34 -> 0 | AS34: =$Y$2*M34*Q34 -> 0 | AT34: =AS34+AR34+AQ34 -> 0 | AV34: =(R34-86.16)/6*O34 -> 0 | AW34: =$Y$2*O34*Q34 -> 0 | AX34: =$Y$2*O34*Q34 -> 0 | AY34: =AX34+AW34+AV34 -> 0 | AZ34: =+AY34+AT34+AO34++AJ34+AE34+Z34 -> 0 | BA34: =((AZ34-BB34-BC34-BD34-BE34-BF34)+BI34+BJ34+BK34+BL34+BM34+BN34+BO34) -> 0 | BU34: 445
B35: 171 | C35: =+C34+1 -> 5 | D35: Juarez Sifuentes Sandra | E35: 1 | G35: 1 | I35: 1 | K35: 1 | M35: 1 | O35: 0 | P35: F | Q35: =IF((E35+G35+I35+K35+M35+O35)=6,1,0) -> 0 | R35: =IF(Q35=1,1550,850) -> 850 | S35: =+BH35 -> 0 | T35: =+BA35 -> 966.66333 | U35: =+BP35 -> 0 | V35: =+BG35 -> 0 | W35: =(R35-86.16)/6*E35 -> 127.30667 | X35: =$Y$2*E35*Q35 -> 0 | Y35: =$Y$2*E35*Q35 -> 0 | Z35: =Y35+X35+W35 -> 127.30667 | AB35: =(R35-86.16)/6*G35 -> 127.30667 | AC35: =$Y$2*G35*Q35 -> 0 | AD35: =$Y$2*G35*Q35 -> 0 | AE35: =AD35+AC35+AB35 -> 127.30667 | AG35: =(R35-86.16)/6*I35 -> 127.30667 | AH35: =$Y$2*I35*Q35 -> 0 | AI35: =$Y$2*I35*Q35 -> 0 | AJ35: =AI35+AH35+AG35 -> 127.30667 | AL35: =(R35-86.16)/6*K35 -> 127.30667 | AM35: =$Y$2*K35*Q35 -> 0 | AN35: =$Y$2*K35*Q35 -> 0 | AO35: =AN35+AM35+AL35 -> 127.30667 | AQ35: =(R35-86.16)/6*M35 -> 127.30667 | AR35: =$Y$2*M35*Q35 -> 0 | AS35: =$Y$2*M35*Q35 -> 0 | AT35: =AS35+AR35+AQ35 -> 127.30667 | AV35: =(R35-86.16)/6*O35 -> 0 | AW35: =$Y$2*O35*Q35 -> 0 | AX35: =$Y$2*O35*Q35 -> 0 | AY35: =AX35+AW35+AV35 -> 0 | AZ35: =+AY35+AT35+AO35++AJ35+AE35+Z35 -> 636.53333 | BA35: =((AZ35-BB35-BC35-BD35-BE35-BF35)+BI35+BJ35+BK35+BL35+BM35+BN35+BO35) -> 966.66333 | BL35: 330.13
B36: 92 | C36: =+C35+1 -> 6 | D36: Martinez Sifuentes Mariana | E36: 1 | G36: 1 | I36: 1 | K36: 1 | M36: 1 | O36: 1 | Q36: =IF((E36+G36+I36+K36+M36+O36)=6,1,0) -> 1 | R36: =IF(Q36=1,1550,850) -> 1550 | S36: =+BH36 -> 0 | T36: =+BA36 -> 1800 | U36: =+BP36 -> 0 | V36: =+BG36 -> B ASIS | W36: =(R36-86.16)/6*E36 -> 243.97333 | X36: =$Y$2*E36*Q36 -> 7.18 | Y36: =$Y$2*E36*Q36 -> 7.18 | Z36: =Y36+X36+W36 -> 258.33333 | AB36: =(R36-86.16)/6*G36 -> 243.97333 | AC36: =$Y$2*G36*Q36 -> 7.18 | AD36: =$Y$2*G36*Q36 -> 7.18 | AE36: =AD36+AC36+AB36 -> 258.33333 | AG36: =(R36-86.16)/6*I36 -> 243.97333 | AH36: =$Y$2*I36*Q36 -> 7.18 | AI36: =$Y$2*I36*Q36 -> 7.18 | AJ36: =AI36+AH36+AG36 -> 258.33333 | AL36: =(R36-86.16)/6*K36 -> 243.97333 | AM36: =$Y$2*K36*Q36 -> 7.18 | AN36: =$Y$2*K36*Q36 -> 7.18 | AO36: =AN36+AM36+AL36 -> 258.33333 | AQ36: =(R36-86.16)/6*M36 -> 243.97333 | AR36: =$Y$2*M36*Q36 -> 7.18 | AS36: =$Y$2*M36*Q36 -> 7.18 | AT36: =AS36+AR36+AQ36 -> 258.33333 | AV36: =(R36-86.16)/6*O36 -> 243.97333 | AW36: =$Y$2*O36*Q36 -> 7.18 | AX36: =$Y$2*O36*Q36 -> 7.18 | AY36: =AX36+AW36+AV36 -> 258.33333 | AZ36: =+AY36+AT36+AO36++AJ36+AE36+Z36 -> 1550 | BA36: =((AZ36-BB36-BC36-BD36-BE36-BF36)+BI36+BJ36+BK36+BL36+BM36+BN36+BO36) -> 1800 | BG36: B ASIS | BI36: 100 | BJ36: 150
B37: 91 | C37: =+C36+1 -> 7 | D37: Medellin Rodriguez Yesenia Abigail | E37: 1 | G37: 1 | I37: 1 | K37: 1 | M37: 1 | O37: 1 | Q37: =IF((E37+G37+I37+K37+M37+O37)=6,1,0) -> 1 | R37: =IF(Q37=1,1550,850) -> 1550 | S37: =+BH37 -> 0 | T37: =+BA37 -> 1950 | U37: =+BP37 -> 0 | V37: =+BG37 -> BONO+B ASIS | W37: =(R37-86.16)/6*E37 -> 243.97333 | X37: =$Y$2*E37*Q37 -> 7.18 | Y37: =$Y$2*E37*Q37 -> 7.18 | Z37: =Y37+X37+W37 -> 258.33333 | AB37: =(R37-86.16)/6*G37 -> 243.97333 | AC37: =$Y$2*G37*Q37 -> 7.18 | AD37: =$Y$2*G37*Q37 -> 7.18 | AE37: =AD37+AC37+AB37 -> 258.33333 | AG37: =(R37-86.16)/6*I37 -> 243.97333 | AH37: =$Y$2*I37*Q37 -> 7.18 | AI37: =$Y$2*I37*Q37 -> 7.18 | AJ37: =AI37+AH37+AG37 -> 258.33333 | AL37: =(R37-86.16)/6*K37 -> 243.97333 | AM37: =$Y$2*K37*Q37 -> 7.18 | AN37: =$Y$2*K37*Q37 -> 7.18 | AO37: =AN37+AM37+AL37 -> 258.33333 | AQ37: =(R37-86.16)/6*M37 -> 243.97333 | AR37: =$Y$2*M37*Q37 -> 7.18 | AS37: =$Y$2*M37*Q37 -> 7.18 | AT37: =AS37+AR37+AQ37 -> 258.33333 | AV37: =(R37-86.16)/6*O37 -> 243.97333 | AW37: =$Y$2*O37*Q37 -> 7.18 | AX37: =$Y$2*O37*Q37 -> 7.18 | AY37: =AX37+AW37+AV37 -> 258.33333 | AZ37: =+AY37+AT37+AO37++AJ37+AE37+Z37 -> 1550 | BA37: =((AZ37-BB37-BC37-BD37-BE37-BF37)+BI37+BJ37+BK37+BL37+BM37+BN37+BO37) -> 1950 | BG37: BONO+B ASIS | BI37: 250 | BJ37: 150
A38: 448 | B38: 27 | C38: =+C37+1 -> 8 | D38: Minor Flores Adilene | E38: 1 | G38: 1 | I38: 1 | K38: 0 | L38: PSG | M38: 1 | O38: 1 | Q38: =IF((E38+G38+I38+K38+M38+O38)=6,1,0) -> 0 | R38: =IF(Q38=1,1550,850) -> 850 | S38: =+BH38 -> 0 | T38: =+BA38 -> 1508.3333 | U38: =+BP38 -> 0 | V38: =+BG38 -> BONO | W38: =(R38-86.16)/6*E38 -> 127.30667 | X38: =$Y$2*E38*Q38 -> 0 | Y38: =$Y$2*E38*Q38 -> 0 | Z38: =Y38+X38+W38 -> 127.30667 | AB38: =(R38-86.16)/6*G38 -> 127.30667 | AC38: =$Y$2*G38*Q38 -> 0 | AD38: =$Y$2*G38*Q38 -> 0 | AE38: =AD38+AC38+AB38 -> 127.30667 | AG38: =(R38-86.16)/6*I38 -> 127.30667 | AH38: =$Y$2*I38*Q38 -> 0 | AI38: =$Y$2*I38*Q38 -> 0 | AJ38: =AI38+AH38+AG38 -> 127.30667 | AL38: =(R38-86.16)/6*K38 -> 0 | AM38: =$Y$2*K38*Q38 -> 0 | AN38: =$Y$2*K38*Q38 -> 0 | AO38: =AN38+AM38+AL38 -> 0 | AQ38: =(R38-86.16)/6*M38 -> 127.30667 | AR38: =$Y$2*M38*Q38 -> 0 | AS38: =$Y$2*M38*Q38 -> 0 | AT38: =AS38+AR38+AQ38 -> 127.30667 | AV38: =(R38-86.16)/6*O38 -> 127.30667 | AW38: =$Y$2*O38*Q38 -> 0 | AX38: =$Y$2*O38*Q38 -> 0 | AY38: =AX38+AW38+AV38 -> 127.30667 | AZ38: =+AY38+AT38+AO38++AJ38+AE38+Z38 -> 636.53333 | BA38: =((AZ38-BB38-BC38-BD38-BE38-BF38)+BI38+BJ38+BK38+BL38+BM38+BN38+BO38) -> 1508.3333 | BG38: BONO | BI38: 300 | BL38: =271.8+300 -> 571.8 | BU38: 448
A39: 449 | B39: 28 | C39: =+C38+1 -> 9 | D39: Moran Hernandez Raul | E39: 1 | G39: 1 | I39: 1 | K39: 1 | M39: 1 | O39: 1 | Q39: =IF((E39+G39+I39+K39+M39+O39)=6,1,0) -> 1 | R39: =IF(Q39=1,3000,850) -> 3000 | S39: =+BH39 -> 0 | T39: =+BA39 -> 3000 | U39: =+BP39 -> 0 | V39: =+BG39 -> 0 | W39: =(R39-86.16)/6*E39 -> 485.64 | X39: =$Y$2*E39*Q39 -> 7.18 | Y39: =$Y$2*E39*Q39 -> 7.18 | Z39: =Y39+X39+W39 -> 500 | AB39: =(R39-86.16)/6*G39 -> 485.64 | AC39: =$Y$2*G39*Q39 -> 7.18 | AD39: =$Y$2*G39*Q39 -> 7.18 | AE39: =AD39+AC39+AB39 -> 500 | AG39: =(R39-86.16)/6*I39 -> 485.64 | AH39: =$Y$2*I39*Q39 -> 7.18 | AI39: =$Y$2*I39*Q39 -> 7.18 | AJ39: =AI39+AH39+AG39 -> 500 | AL39: =(R39-86.16)/6*K39 -> 485.64 | AM39: =$Y$2*K39*Q39 -> 7.18 | AN39: =$Y$2*K39*Q39 -> 7.18 | AO39: =AN39+AM39+AL39 -> 500 | AQ39: =(R39-86.16)/6*M39 -> 485.64 | AR39: =$Y$2*M39*Q39 -> 7.18 | AS39: =$Y$2*M39*Q39 -> 7.18 | AT39: =AS39+AR39+AQ39 -> 500 | AV39: =(R39-86.16)/6*O39 -> 485.64 | AW39: =$Y$2*O39*Q39 -> 7.18 | AX39: =$Y$2*O39*Q39 -> 7.18 | AY39: =AX39+AW39+AV39 -> 500 | AZ39: =+AY39+AT39+AO39++AJ39+AE39+Z39 -> 3000 | BA39: =((AZ39-BB39-BC39-BD39-BE39-BF39)+BI39+BJ39+BK39+BL39+BM39+BN39+BO39) -> 3000 | BU39: 449
A40: 448 | B40: 170 | C40: =+C39+1 -> 10 | D40: Ochoa Vital Edna Lizeth | E40: 1 | G40: 1 | I40: 1 | K40: 1 | M40: 1 | O40: 1 | Q40: =IF((E40+G40+I40+K40+M40+O40)=6,1,0) -> 1 | R40: =IF(Q40=1,1550,850) -> 1550 | S40: =+BH40 -> 0 | T40: =+BA40 -> 1950 | U40: =+BP40 -> 0 | V40: =+BG40 -> BONO+B ASIS | W40: =(R40-86.16)/6*E40 -> 243.97333 | X40: =$Y$2*E40*Q40 -> 7.18 | Y40: =$Y$2*E40*Q40 -> 7.18 | Z40: =Y40+X40+W40 -> 258.33333 | AB40: =(R40-86.16)/6*G40 -> 243.97333 | AC40: =$Y$2*G40*Q40 -> 7.18 | AD40: =$Y$2*G40*Q40 -> 7.18 | AE40: =AD40+AC40+AB40 -> 258.33333 | AG40: =(R40-86.16)/6*I40 -> 243.97333 | AH40: =$Y$2*I40*Q40 -> 7.18 | AI40: =$Y$2*I40*Q40 -> 7.18 | AJ40: =AI40+AH40+AG40 -> 258.33333 | AL40: =(R40-86.16)/6*K40 -> 243.97333 | AM40: =$Y$2*K40*Q40 -> 7.18 | AN40: =$Y$2*K40*Q40 -> 7.18 | AO40: =AN40+AM40+AL40 -> 258.33333 | AQ40: =(R40-86.16)/6*M40 -> 243.97333 | AR40: =$Y$2*M40*Q40 -> 7.18 | AS40: =$Y$2*M40*Q40 -> 7.18 | AT40: =AS40+AR40+AQ40 -> 258.33333 | AV40: =(R40-86.16)/6*O40 -> 243.97333 | AW40: =$Y$2*O40*Q40 -> 7.18 | AX40: =$Y$2*O40*Q40 -> 7.18 | AY40: =AX40+AW40+AV40 -> 258.33333 | AZ40: =+AY40+AT40+AO40++AJ40+AE40+Z40 -> 1550 | BA40: =((AZ40-BB40-BC40-BD40-BE40-BF40)+BI40+BJ40+BK40+BL40+BM40+BN40+BO40) -> 1950 | BG40: BONO+B ASIS | BI40: 250 | BJ40: 150 | BU40: 448
A41: 467 | B41: 32 | C41: =+C44+1 -> 1 | D41: Ramirez Flores Jose Alejandro | E41: 1 | G41: 1 | I41: 1 | K41: 1 | M41: 1 | O41: 1 | Q41: =IF((E41+G41+I41+K41+M41+O41)=6,1,0) -> 1 | R41: =IF(Q41=1,1550,850) -> 1550 | S41: =+BH41 -> 0 | T41: =+BA41 -> 1950 | U41: =+BP41 -> 0 | V41: =+BG41 -> BONO+B ASIS | W41: =(R41-86.16)/6*E41 -> 243.97333 | X41: =$Y$2*E41*Q41 -> 7.18 | Y41: =$Y$2*E41*Q41 -> 7.18 | Z41: =Y41+X41+W41 -> 258.33333 | AB41: =(R41-86.16)/6*G41 -> 243.97333 | AC41: =$Y$2*G41*Q41 -> 7.18 | AD41: =$Y$2*G41*Q41 -> 7.18 | AE41: =AD41+AC41+AB41 -> 258.33333 | AG41: =(R41-86.16)/6*I41 -> 243.97333 | AH41: =$Y$2*I41*Q41 -> 7.18 | AI41: =$Y$2*I41*Q41 -> 7.18 | AJ41: =AI41+AH41+AG41 -> 258.33333 | AL41: =(R41-86.16)/6*K41 -> 243.97333 | AM41: =$Y$2*K41*Q41 -> 7.18 | AN41: =$Y$2*K41*Q41 -> 7.18 | AO41: =AN41+AM41+AL41 -> 258.33333 | AQ41: =(R41-86.16)/6*M41 -> 243.97333 | AR41: =$Y$2*M41*Q41 -> 7.18 | AS41: =$Y$2*M41*Q41 -> 7.18 | AT41: =AS41+AR41+AQ41 -> 258.33333 | AV41: =(R41-86.16)/6*O41 -> 243.97333 | AW41: =$Y$2*O41*Q41 -> 7.18 | AX41: =$Y$2*O41*Q41 -> 7.18 | AY41: =AX41+AW41+AV41 -> 258.33333 | AZ41: =+AY41+AT41+AO41++AJ41+AE41+Z41 -> 1550 | BA41: =((AZ41-BB41-BC41-BD41-BE41-BF41)+BI41+BJ41+BK41+BL41+BM41+BN41+BO41) -> 1950 | BG41: BONO+B ASIS | BI41: 250 | BJ41: 150 | BU41: 467
A42: 448 | B42: 33 | C42: =+C41+1 -> 2 | D42: Ramirez Vital Jose Armando | E42: 1 | G42: 1 | I42: 1 | K42: 1 | M42: 1 | O42: 1 | Q42: =IF((E42+G42+I42+K42+M42+O42)=6,1,0) -> 1 | R42: =IF(Q42=1,1550,850) -> 1550 | S42: =+BH42 -> 0 | T42: =+BA42 -> 1950 | U42: =+BP42 -> 0 | V42: =+BG42 -> BONO+B ASIS | W42: =(R42-86.16)/6*E42 -> 243.97333 | X42: =$Y$2*E42*Q42 -> 7.18 | Y42: =$Y$2*E42*Q42 -> 7.18 | Z42: =Y42+X42+W42 -> 258.33333 | AB42: =(R42-86.16)/6*G42 -> 243.97333 | AC42: =$Y$2*G42*Q42 -> 7.18 | AD42: =$Y$2*G42*Q42 -> 7.18 | AE42: =AD42+AC42+AB42 -> 258.33333 | AG42: =(R42-86.16)/6*I42 -> 243.97333 | AH42: =$Y$2*I42*Q42 -> 7.18 | AI42: =$Y$2*I42*Q42 -> 7.18 | AJ42: =AI42+AH42+AG42 -> 258.33333 | AL42: =(R42-86.16)/6*K42 -> 243.97333 | AM42: =$Y$2*K42*Q42 -> 7.18 | AN42: =$Y$2*K42*Q42 -> 7.18 | AO42: =AN42+AM42+AL42 -> 258.33333 | AQ42: =(R42-86.16)/6*M42 -> 243.97333 | AR42: =$Y$2*M42*Q42 -> 7.18 | AS42: =$Y$2*M42*Q42 -> 7.18 | AT42: =AS42+AR42+AQ42 -> 258.33333 | AV42: =(R42-86.16)/6*O42 -> 243.97333 | AW42: =$Y$2*O42*Q42 -> 7.18 | AX42: =$Y$2*O42*Q42 -> 7.18 | AY42: =AX42+AW42+AV42 -> 258.33333 | AZ42: =+AY42+AT42+AO42++AJ42+AE42+Z42 -> 1550 | BA42: =((AZ42-BB42-BC42-BD42-BE42-BF42)+BI42+BJ42+BK42+BL42+BM42+BN42+BO42) -> 1950 | BG42: BONO+B ASIS | BI42: 250 | BJ42: 150 | BU42: 448
B43: 156 | C43: =+C39+1 -> 10 | D43: Padilla Reyes Laura Monserrat | E43: 0 | F43: B | G43: 0 | H43: B | I43: 0 | J43: B | K43: 0 | L43: B | M43: 0 | N43: B | O43: 0 | P43: B | Q43: 0 | R43: 0 | S43: =+BH43 -> 0 | T43: =+BA43 -> 0 | U43: =+BP43 -> 0 | V43: =+BG43 -> 0 | W43: =(R43-86.16)/6*E43 -> 0 | X43: =$Y$2*E43*Q43 -> 0 | Y43: =$Y$2*E43*Q43 -> 0 | Z43: =Y43+X43+W43 -> 0 | AB43: =(R43-86.16)/6*G43 -> 0 | AC43: =$Y$2*G43*Q43 -> 0 | AD43: =$Y$2*G43*Q43 -> 0 | AE43: =AD43+AC43+AB43 -> 0 | AG43: =(R43-86.16)/6*I43 -> 0 | AH43: =$Y$2*I43*Q43 -> 0 | AI43: =$Y$2*I43*Q43 -> 0 | AJ43: =AI43+AH43+AG43 -> 0 | AL43: =(R43-86.16)/6*K43 -> 0 | AM43: =$Y$2*K43*Q43 -> 0 | AN43: =$Y$2*K43*Q43 -> 0 | AO43: =AN43+AM43+AL43 -> 0 | AQ43: =(R43-86.16)/6*M43 -> 0 | AR43: =$Y$2*M43*Q43 -> 0 | AS43: =$Y$2*M43*Q43 -> 0 | AT43: =AS43+AR43+AQ43 -> 0 | AV43: =(R43-86.16)/6*O43 -> 0 | AW43: =$Y$2*O43*Q43 -> 0 | AX43: =$Y$2*O43*Q43 -> 0 | AY43: =AX43+AW43+AV43 -> 0 | AZ43: =+AY43+AT43+AO43++AJ43+AE43+Z43 -> 0 | BA43: 0
A44: 451 | E44: =SUM(E31:E42) -> 11 | G44: =SUM(G31:G42) -> 11 | I44: =SUM(I31:I42) -> 11 | K44: =SUM(K31:K42) -> 10 | M44: =SUM(M31:M42) -> 11 | O44: =SUM(O31:O42) -> 10 | BU44: 451
A45: 452 | BU45: 452
A46: 453 | B46: REAL | C46: PR | G46: L | I46: M | K46: M | M46: J | O46: V | Q46: S | BU46: 453
A47: 454 | B47: =E44 -> 11 | C47: =G51 -> 11 | D47: =+B47-C47 -> 0 | R47: PROM | BU47: 454
A48: 455 | B48: =G44 -> 11 | C48: =I51 -> 11 | D48: =+B48-C48 -> 0 | E48: LIDER | G48: 0 | I48: 0 | K48: 0 | M48: 0 | O48: 0 | Q48: 0 | R48: =AVERAGE(G48,I48,K48,M48,O48,Q48) -> 0 | BU48: 455
A49: 456 | B49: =I44 -> 11 | C49: =K51 -> 11 | D49: =+B49-C49 -> 0 | E49: MECANICO | G49: 2 | I49: 2 | K49: 2 | M49: 2 | O49: 2 | Q49: 2 | R49: =AVERAGE(G49,I49,K49,M49,O49,Q49) -> 2 | BU49: 456
A50: 457 | B50: =K44 -> 10 | C50: =M51 -> 10 | D50: =+B50-C50 -> 0 | E50: MANUAL | G50: 9 | I50: 9 | K50: 9 | M50: 8 | O50: 9 | Q50: 8 | R50: =AVERAGE(G50,I50,K50,M50,O50,Q50) -> 8.6666667 | BU50: 457
A51: 458 | B51: =M44 -> 11 | C51: =O51 -> 11 | D51: =+B51-C51 -> 0 | G51: =SUM(G48:G50) -> 11 | I51: =SUM(I48:I50) -> 11 | K51: =SUM(K48:K50) -> 11 | M51: =SUM(M48:M50) -> 10 | O51: =SUM(O48:O50) -> 11 | Q51: =SUM(Q44:Q50) -> 10 | R51: =AVERAGE(G51,I51,K51,M51,O51,Q51) -> 10.666667 | BU51: 458
A52: 459 | B52: =O44 -> 10 | C52: =Q51 -> 10 | D52: =+B52-C52 -> 0 | T52: =SUM(R48:R50) -> 10.666667 | BU52: 459
A53: 463 | BU53: 463
A54: 464 | B54: TEJIDO 3 | D54: 3ER TURNO | R54: =$V2 -> DEL 08 AL 14 ENERO 24 | BU54: 464
A55: 465 | E55: L | G55: M | I55: M | K55: J | M55: V | O55: S | BU55: 465
B56: 116 | C56: =+C55+1 -> 1 | D56: Antunez Orona Juan Manuel | E56: 1 | G56: 1 | I56: 1 | K56: 1 | M56: 1 | O56: 1 | Q56: 1 | R56: =IF(Q56=1,1550,850) -> 1550 | S56: =+BH56 -> 0 | T56: =+BA56 -> 2050 | U56: =+BP56 -> 0 | V56: =+BG56 -> BONO+B ASIS | W56: =(R56-86.16)/6*E56 -> 243.97333 | X56: =$Y$2*E56*Q56 -> 7.18 | Y56: =$Y$2*E56*Q56 -> 7.18 | Z56: =Y56+X56+W56 -> 258.33333 | AB56: =(R56-86.16)/6*G56 -> 243.97333 | AC56: =$Y$2*G56*Q56 -> 7.18 | AD56: =$Y$2*G56*Q56 -> 7.18 | AE56: =AD56+AC56+AB56 -> 258.33333 | AG56: =(R56-86.16)/6*I56 -> 243.97333 | AH56: =$Y$2*I56*Q56 -> 7.18 | AI56: =$Y$2*I56*Q56 -> 7.18 | AJ56: =AI56+AH56+AG56 -> 258.33333 | AL56: =(R56-86.16)/6*K56 -> 243.97333 | AM56: =$Y$2*K56*Q56 -> 7.18 | AN56: =$Y$2*K56*Q56 -> 7.18 | AO56: =AN56+AM56+AL56 -> 258.33333 | AQ56: =(R56-86.16)/6*M56 -> 243.97333 | AR56: =$Y$2*M56*Q56 -> 7.18 | AS56: =$Y$2*M56*Q56 -> 7.18 | AT56: =AS56+AR56+AQ56 -> 258.33333 | AV56: =(R56-86.16)/6*O56 -> 243.97333 | AW56: =$Y$2*O56*Q56 -> 7.18 | AX56: =$Y$2*O56*Q56 -> 7.18 | AY56: =AX56+AW56+AV56 -> 258.33333 | AZ56: =+AY56+AT56+AO56++AJ56+AE56+Z56 -> 1550 | BA56: =((AZ56-BB56-BC56-BD56-BE56-BF56)+BI56+BJ56+BK56+BL56+BM56+BN56+BO56) -> 2050 | BG56: BONO+B ASIS | BI56: 250 | BJ56: 250
B57: 117 | C57: =+C56+1 -> 2 | D57: Antunez Salazar Aracely | E57: 1 | G57: 1 | I57: 1 | K57: 1 | M57: 1 | O57: 1 | Q57: 1 | R57: =IF(Q57=1,1550,850) -> 1550 | S57: =+BH57 -> 0 | T57: =+BA57 -> 2050 | U57: =+BP57 -> 0 | V57: =+BG57 -> BONO+B ASIS | W57: =(R57-86.16)/6*E57 -> 243.97333 | X57: =$Y$2*E57*Q57 -> 7.18 | Y57: =$Y$2*E57*Q57 -> 7.18 | Z57: =Y57+X57+W57 -> 258.33333 | AB57: =(R57-86.16)/6*G57 -> 243.97333 | AC57: =$Y$2*G57*Q57 -> 7.18 | AD57: =$Y$2*G57*Q57 -> 7.18 | AE57: =AD57+AC57+AB57 -> 258.33333 | AG57: =(R57-86.16)/6*I57 -> 243.97333 | AH57: =$Y$2*I57*Q57 -> 7.18 | AI57: =$Y$2*I57*Q57 -> 7.18 | AJ57: =AI57+AH57+AG57 -> 258.33333 | AL57: =(R57-86.16)/6*K57 -> 243.97333 | AM57: =$Y$2*K57*Q57 -> 7.18 | AN57: =$Y$2*K57*Q57 -> 7.18 | AO57: =AN57+AM57+AL57 -> 258.33333 | AQ57: =(R57-86.16)/6*M57 -> 243.97333 | AR57: =$Y$2*M57*Q57 -> 7.18 | AS57: =$Y$2*M57*Q57 -> 7.18 | AT57: =AS57+AR57+AQ57 -> 258.33333 | AV57: =(R57-86.16)/6*O57 -> 243.97333 | AW57: =$Y$2*O57*Q57 -> 7.18 | AX57: =$Y$2*O57*Q57 -> 7.18 | AY57: =AX57+AW57+AV57 -> 258.33333 | AZ57: =+AY57+AT57+AO57++AJ57+AE57+Z57 -> 1550 | BA57: =((AZ57-BB57-BC57-BD57-BE57-BF57)+BI57+BJ57+BK57+BL57+BM57+BN57+BO57) -> 2050 | BG57: BONO+B ASIS | BI57: 250 | BJ57: 250
B58: 162 | C58: =+C57+1 -> 3 | D58: Armijo Tostado Liliana Jaretzy | E58: 1 | G58: 1 | I58: 1 | K58: 1 | M58: 1 | O58: 1 | Q58: 1 | R58: =IF(Q58=1,1550,850) -> 1550 | S58: =+BH58 -> 0 | T58: =+BA58 -> 2050 | U58: =+BP58 -> 0 | V58: =+BG58 -> BONO+B ASIS | W58: =(R58-86.16)/6*E58 -> 243.97333 | X58: =$Y$2*E58*Q58 -> 7.18 | Y58: =$Y$2*E58*Q58 -> 7.18 | Z58: =Y58+X58+W58 -> 258.33333 | AB58: =(R58-86.16)/6*G58 -> 243.97333 | AC58: =$Y$2*G58*Q58 -> 7.18 | AD58: =$Y$2*G58*Q58 -> 7.18 | AE58: =AD58+AC58+AB58 -> 258.33333 | AG58: =(R58-86.16)/6*I58 -> 243.97333 | AH58: =$Y$2*I58*Q58 -> 7.18 | AI58: =$Y$2*I58*Q58 -> 7.18 | AJ58: =AI58+AH58+AG58 -> 258.33333 | AL58: =(R58-86.16)/6*K58 -> 243.97333 | AM58: =$Y$2*K58*Q58 -> 7.18 | AN58: =$Y$2*K58*Q58 -> 7.18 | AO58: =AN58+AM58+AL58 -> 258.33333 | AQ58: =(R58-86.16)/6*M58 -> 243.97333 | AR58: =$Y$2*M58*Q58 -> 7.18 | AS58: =$Y$2*M58*Q58 -> 7.18 | AT58: =AS58+AR58+AQ58 -> 258.33333 | AV58: =(R58-86.16)/6*O58 -> 243.97333 | AW58: =$Y$2*O58*Q58 -> 7.18 | AX58: =$Y$2*O58*Q58 -> 7.18 | AY58: =AX58+AW58+AV58 -> 258.33333 | AZ58: =+AY58+AT58+AO58++AJ58+AE58+Z58 -> 1550 | BA58: =((AZ58-BB58-BC58-BD58-BE58-BF58)+BI58+BJ58+BK58+BL58+BM58+BN58+BO58) -> 2050 | BG58: BONO+B ASIS | BI58: 250 | BJ58: 250
A59: 470 | B59: 7 | C59: =+C58+1 -> 4 | D59: Beberaje Cruz Ramon Humberto | E59: 1 | G59: 1 | I59: 1 | K59: 1 | M59: 1 | O59: 1 | Q59: 1 | R59: =IF(Q59=1,6000,850) -> 6000 | S59: =+BH59 -> 0 | T59: =+BA59 -> 6000 | U59: =+BP59 -> 0 | V59: =+BG59 -> 0 | W59: =(R59-86.16)/6*E59 -> 985.64 | X59: =$Y$2*E59*Q59 -> 7.18 | Y59: =$Y$2*E59*Q59 -> 7.18 | Z59: =Y59+X59+W59 -> 1000 | AB59: =(R59-86.16)/6*G59 -> 985.64 | AC59: =$Y$2*G59*Q59 -> 7.18 | AD59: =$Y$2*G59*Q59 -> 7.18 | AE59: =AD59+AC59+AB59 -> 1000 | AG59: =(R59-86.16)/6*I59 -> 985.64 | AH59: =$Y$2*I59*Q59 -> 7.18 | AI59: =$Y$2*I59*Q59 -> 7.18 | AJ59: =AI59+AH59+AG59 -> 1000 | AL59: =(R59-86.16)/6*K59 -> 985.64 | AM59: =$Y$2*K59*Q59 -> 7.18 | AN59: =$Y$2*K59*Q59 -> 7.18 | AO59: =AN59+AM59+AL59 -> 1000 | AQ59: =(R59-86.16)/6*M59 -> 985.64 | AR59: =$Y$2*M59*Q59 -> 7.18 | AS59: =$Y$2*M59*Q59 -> 7.18 | AT59: =AS59+AR59+AQ59 -> 1000 | AV59: =(R59-86.16)/6*O59 -> 985.64 | AW59: =$Y$2*O59*Q59 -> 7.18 | AX59: =$Y$2*O59*Q59 -> 7.18 | AY59: =AX59+AW59+AV59 -> 1000 | AZ59: =+AY59+AT59+AO59++AJ59+AE59+Z59 -> 6000 | BA59: =((AZ59-BB59-BC59-BD59-BE59-BF59)+BI59+BJ59+BK59+BL59+BM59+BN59+BO59) -> 6000 | BU59: 470
B60: 175 | C60: =+C59+1 -> 5 | D60: Carrillo Ojeda Jose Guadalupe | E60: 1 | G60: 1 | I60: 1 | K60: 1 | M60: 0 | N60: F | O60: 0 | P60: F | Q60: 1 | R60: =IF(Q60=1,1550,850) -> 1550 | S60: =+BH60 -> 0 | T60: =+BA60 -> 828.56 | U60: =+BP60 -> 0 | V60: =+BG60 -> 0 | W60: =(R60-86.16)/6*E60 -> 243.97333 | X60: =$Y$2*E60*Q60 -> 7.18 | Y60: =$Y$2*E60*Q60 -> 7.18 | Z60: =Y60+X60+W60 -> 258.33333 | AB60: =(R60-86.16)/6*G60 -> 243.97333 | AC60: =$Y$2*G60*Q60 -> 7.18 | AD60: =$Y$2*G60*Q60 -> 7.18 | AE60: =AD60+AC60+AB60 -> 258.33333 | AG60: =(R60-86.16)/6*I60 -> 243.97333 | AH60: =$Y$2*I60*Q60 -> 7.18 | AI60: =$Y$2*I60*Q60 -> 7.18 | AJ60: =AI60+AH60+AG60 -> 258.33333 | AL60: =(R60-86.16)/6*K60 -> 243.97333 | AM60: =$Y$2*K60*Q60 -> 7.18 | AN60: =$Y$2*K60*Q60 -> 7.18 | AO60: =AN60+AM60+AL60 -> 258.33333 | AQ60: =(R60-86.16)/6*M60 -> 0 | AR60: =$Y$2*M60*Q60 -> 0 | AS60: =$Y$2*M60*Q60 -> 0 | AT60: =AS60+AR60+AQ60 -> 0 | AV60: =(R60-86.16)/6*O60 -> 0 | AW60: =$Y$2*O60*Q60 -> 0 | AX60: =$Y$2*O60*Q60 -> 0 | AY60: =AX60+AW60+AV60 -> 0 | AZ60: =+AY60+AT60+AO60++AJ60+AE60+Z60 -> 1033.3333 | BA60: 828.56
A61: 468 | B61: 14 | C61: =+C60+1 -> 6 | D61: Esquivel Picon Miguel Angel | E61: 1 | G61: 1 | I61: 1 | K61: 1 | M61: 1 | O61: 1 | Q61: 1 | R61: =IF(Q61=1,1550,850) -> 1550 | S61: =+BH61 -> 0 | T61: =+BA61 -> 1950 | U61: =+BP61 -> 0 | V61: =+BG61 -> BONO+B ASIS | W61: =(R61-86.16)/6*E61 -> 243.97333 | X61: =$Y$2*E61*Q61 -> 7.18 | Y61: =$Y$2*E61*Q61 -> 7.18 | Z61: =Y61+X61+W61 -> 258.33333 | AB61: =(R61-86.16)/6*G61 -> 243.97333 | AC61: =$Y$2*G61*Q61 -> 7.18 | AD61: =$Y$2*G61*Q61 -> 7.18 | AE61: =AD61+AC61+AB61 -> 258.33333 | AG61: =(R61-86.16)/6*I61 -> 243.97333 | AH61: =$Y$2*I61*Q61 -> 7.18 | AI61: =$Y$2*I61*Q61 -> 7.18 | AJ61: =AI61+AH61+AG61 -> 258.33333 | AL61: =(R61-86.16)/6*K61 -> 243.97333 | AM61: =$Y$2*K61*Q61 -> 7.18 | AN61: =$Y$2*K61*Q61 -> 7.18 | AO61: =AN61+AM61+AL61 -> 258.33333 | AQ61: =(R61-86.16)/6*M61 -> 243.97333 | AR61: =$Y$2*M61*Q61 -> 7.18 | AS61: =$Y$2*M61*Q61 -> 7.18 | AT61: =AS61+AR61+AQ61 -> 258.33333 | AV61: =(R61-86.16)/6*O61 -> 243.97333 | AW61: =$Y$2*O61*Q61 -> 7.18 | AX61: =$Y$2*O61*Q61 -> 7.18 | AY61: =AX61+AW61+AV61 -> 258.33333 | AZ61: =+AY61+AT61+AO61++AJ61+AE61+Z61 -> 1550 | BA61: =((AZ61-BB61-BC61-BD61-BE61-BF61)+BI61+BJ61+BK61+BL61+BM61+BN61+BO61) -> 1950 | BG61: BONO+B ASIS | BI61: 250 | BJ61: 150 | BU61: 468
B62: 174 | C62: =+C61+1 -> 7 | D62: Mijarez Rodriguez San Juana Guadalupe | E62: 0 | F62: F | G62: 1 | I62: 1 | K62: 1 | M62: 1 | O62: 1 | Q62: 1 | R62: =IF(Q62=1,1550,850) -> 1550 | S62: =+BH62 -> 0 | T62: =+BA62 -> 2114.2767 | U62: =+BP62 -> 0 | V62: =+BG62 -> 0 | W62: =(R62-86.16)/6*E62 -> 0 | X62: =$Y$2*E62*Q62 -> 0 | Y62: =$Y$2*E62*Q62 -> 0 | Z62: =Y62+X62+W62 -> 0 | AB62: =(R62-86.16)/6*G62 -> 243.97333 | AC62: =$Y$2*G62*Q62 -> 7.18 | AD62: =$Y$2*G62*Q62 -> 7.18 | AE62: =AD62+AC62+AB62 -> 258.33333 | AG62: =(R62-86.16)/6*I62 -> 243.97333 | AH62: =$Y$2*I62*Q62 -> 7.18 | AI62: =$Y$2*I62*Q62 -> 7.18 | AJ62: =AI62+AH62+AG62 -> 258.33333 | AL62: =(R62-86.16)/6*K62 -> 243.97333 | AM62: =$Y$2*K62*Q62 -> 7.18 | AN62: =$Y$2*K62*Q62 -> 7.18 | AO62: =AN62+AM62+AL62 -> 258.33333 | AQ62: =(R62-86.16)/6*M62 -> 243.97333 | AR62: =$Y$2*M62*Q62 -> 7.18 | AS62: =$Y$2*M62*Q62 -> 7.18 | AT62: =AS62+AR62+AQ62 -> 258.33333 | AV62: =(R62-86.16)/6*O62 -> 243.97333 | AW62: =$Y$2*O62*Q62 -> 7.18 | AX62: =$Y$2*O62*Q62 -> 7.18 | AY62: =AX62+AW62+AV62 -> 258.33333 | AZ62: =+AY62+AT62+AO62++AJ62+AE62+Z62 -> 1291.6667 | BA62: =((AZ62-BB62-BC62-BD62-BE62-BF62)+BI62+BJ62+BK62+BL62+BM62+BN62+BO62) -> 2114.2767 | BI62: 250 | BL62: =414.28+158.33 -> 572.61
B63: 140 | C63: =+C62+1 -> 8 | D63: Morales Holguin Sergio Joel | E63: 0 | F63: F | G63: 1 | I63: 0 | J63: F | K63: 0 | L63: F | M63: 1 | O63: 1 | Q63: 1 | R63: =IF(Q63=1,1550,850) -> 1550 | S63: =+BH63 -> 0 | T63: =+BA63 -> 414.28 | U63: =+BP63 -> 0 | V63: =+BG63 -> 0 | W63: =(R63-86.16)/6*E63 -> 0 | X63: =$Y$2*E63*Q63 -> 0 | Y63: =$Y$2*E63*Q63 -> 0 | Z63: =Y63+X63+W63 -> 0 | AB63: =(R63-86.16)/6*G63 -> 243.97333 | AC63: =$Y$2*G63*Q63 -> 7.18 | AD63: =$Y$2*G63*Q63 -> 7.18 | AE63: =AD63+AC63+AB63 -> 258.33333 | AG63: =(R63-86.16)/6*I63 -> 0 | AH63: =$Y$2*I63*Q63 -> 0 | AI63: =$Y$2*I63*Q63 -> 0 | AJ63: =AI63+AH63+AG63 -> 0 | AL63: =(R63-86.16)/6*K63 -> 0 | AM63: =$Y$2*K63*Q63 -> 0 | AN63: =$Y$2*K63*Q63 -> 0 | AO63: =AN63+AM63+AL63 -> 0 | AQ63: =(R63-86.16)/6*M63 -> 243.97333 | AR63: =$Y$2*M63*Q63 -> 7.18 | AS63: =$Y$2*M63*Q63 -> 7.18 | AT63: =AS63+AR63+AQ63 -> 258.33333 | AV63: =(R63-86.16)/6*O63 -> 243.97333 | AW63: =$Y$2*O63*Q63 -> 7.18 | AX63: =$Y$2*O63*Q63 -> 7.18 | AY63: =AX63+AW63+AV63 -> 258.33333 | AZ63: =+AY63+AT63+AO63++AJ63+AE63+Z63 -> 775 | BA63: 414.28
B64: 176 | C64: =+C63+1 -> 9 | D64: Sandoval Martinez Vianey Nataly | E64: 1 | G64: 1 | I64: 1 | K64: 1 | M64: 1 | O64: 1 | Q64: 1 | R64: =IF(Q64=1,1550,850) -> 1550 | T64: =+BA64 -> 1950 | U64: =+BP64 -> 0 | V64: =+BG64 -> B ASIS | W64: =(R64-86.16)/6*E64 -> 243.97333 | X64: =$Y$2*E64*Q64 -> 7.18 | Y64: =$Y$2*E64*Q64 -> 7.18 | Z64: =Y64+X64+W64 -> 258.33333 | AB64: =(R64-86.16)/6*G64 -> 243.97333 | AC64: =$Y$2*G64*Q64 -> 7.18 | AD64: =$Y$2*G64*Q64 -> 7.18 | AE64: =AD64+AC64+AB64 -> 258.33333 | AG64: =(R64-86.16)/6*I64 -> 243.97333 | AH64: =$Y$2*I64*Q64 -> 7.18 | AI64: =$Y$2*I64*Q64 -> 7.18 | AJ64: =AI64+AH64+AG64 -> 258.33333 | AL64: =(R64-86.16)/6*K64 -> 243.97333 | AM64: =$Y$2*K64*Q64 -> 7.18 | AN64: =$Y$2*K64*Q64 -> 7.18 | AO64: =AN64+AM64+AL64 -> 258.33333 | AQ64: =(R64-86.16)/6*M64 -> 243.97333 | AR64: =$Y$2*M64*Q64 -> 7.18 | AS64: =$Y$2*M64*Q64 -> 7.18 | AT64: =AS64+AR64+AQ64 -> 258.33333 | AV64: =(R64-86.16)/6*O64 -> 243.97333 | AW64: =$Y$2*O64*Q64 -> 7.18 | AX64: =$Y$2*O64*Q64 -> 7.18 | AY64: =AX64+AW64+AV64 -> 258.33333 | AZ64: =+AY64+AT64+AO64++AJ64+AE64+Z64 -> 1550 | BA64: =((AZ64-BB64-BC64-BD64-BE64-BF64)+BI64+BJ64+BK64+BL64+BM64+BN64+BO64) -> 1950 | BG64: B ASIS | BI64: 150 | BJ64: 250
B65: 53 | C65: =+C64+1 -> 10 | D65: Vargas Cuellar Juana Gabriela | E65: 1 | G65: 1 | I65: 1 | K65: 1 | M65: 1 | O65: 1 | Q65: 1 | R65: =IF(Q65=1,1600,850) -> 1600 | S65: =+BH65 -> 0 | T65: =+BA65 -> 2107.14 | U65: =+BP65 -> 0 | V65: =+BG65 -> BONO+B ASIS+ T EXT | W65: =(R65-86.16)/6*E65 -> 252.30667 | X65: =$Y$2*E65*Q65 -> 7.18 | Y65: =$Y$2*E65*Q65 -> 7.18 | Z65: =Y65+X65+W65 -> 266.66667 | AB65: =(R65-86.16)/6*G65 -> 252.30667 | AC65: =$Y$2*G65*Q65 -> 7.18 | AD65: =$Y$2*G65*Q65 -> 7.18 | AE65: =AD65+AC65+AB65 -> 266.66667 | AG65: =(R65-86.16)/6*I65 -> 252.30667 | AH65: =$Y$2*I65*Q65 -> 7.18 | AI65: =$Y$2*I65*Q65 -> 7.18 | AJ65: =AI65+AH65+AG65 -> 266.66667 | AL65: =(R65-86.16)/6*K65 -> 252.30667 | AM65: =$Y$2*K65*Q65 -> 7.18 | AN65: =$Y$2*K65*Q65 -> 7.18 | AO65: =AN65+AM65+AL65 -> 266.66667 | AQ65: =(R65-86.16)/6*M65 -> 252.30667 | AR65: =$Y$2*M65*Q65 -> 7.18 | AS65: =$Y$2*M65*Q65 -> 7.18 | AT65: =AS65+AR65+AQ65 -> 266.66667 | AV65: =(R65-86.16)/6*O65 -> 252.30667 | AW65: =$Y$2*O65*Q65 -> 7.18 | AX65: =$Y$2*O65*Q65 -> 7.18 | AY65: =AX65+AW65+AV65 -> 266.66667 | AZ65: =+AY65+AT65+AO65++AJ65+AE65+Z65 -> 1600 | BA65: =((AZ65-BB65-BC65-BD65-BE65-BF65)+BI65+BJ65+BK65+BL65+BM65+BN65+BO65) -> 2107.14 | BG65: BONO+B ASIS+ T EXT | BI65: 300 | BJ65: 150 | BK65: 57.14
B66: 0 | C66: =+C65+1 -> 11 | D66: JUAREZ/SIFUENTES,BENITO | E66: 0 | F66: B | G66: 0 | H66: B | I66: 0 | J66: B | K66: 0 | L66: B | M66: 0 | N66: B | O66: 0 | P66: B | Q66: 0 | R66: 0 | S66: =+BH66 -> 0 | T66: =+BA66 -> 0 | U66: =+BP66 -> 0 | V66: =+BG66 -> 0 | W66: =(R66-86.16)/6*E66 -> 0 | X66: =$Y$2*E66*Q66 -> 0 | Z66: =Y66+X66+W66 -> 0 | AB66: =(R66-86.16)/6*G66 -> 0 | AG66: =(R66-86.16)/6*I66 -> 0 | AH66: =$Y$2*I66*Q66 -> 0 | AI66: =$Y$2*I66*Q66 -> 0 | AJ66: =AI66+AH66+AG66 -> 0 | AL66: =(R66-86.16)/6*K66 -> 0 | AM66: =$Y$2*K66*Q66 -> 0 | AQ66: =(R66-86.16)/6*M66 -> 0 | AR66: =$Y$2*M66*Q66 -> 0 | AS66: =$Y$2*M66*Q66 -> 0 | AT66: =AS66+AR66+AQ66 -> 0 | AV66: =(R66-86.16)/6*O66 -> 0 | AW66: =$Y$2*O66*Q66 -> 0 | AX66: =$Y$2*O66*Q66 -> 0 | AY66: =AX66+AW66+AV66 -> 0 | AZ66: 0
B67: 161 | C67: =+C66+1 -> 12 | D67: Vargas Chavez Sarai del Carmen | E67: 0 | F67: B | G67: 0 | H67: B | I67: 0 | J67: B | K67: 0 | L67: B | M67: 0 | N67: B | O67: 0 | P67: B | Q67: 0 | R67: 0 | S67: =+BH67 -> 0 | T67: =+BA67 -> 0 | U67: =+BP67 -> 0 | V67: =+BG67 -> 0 | W67: =(R67-86.16)/6*E67 -> 0 | X67: =$Y$2*E67*Q67 -> 0 | Y67: =$Y$2*E67*Q67 -> 0 | Z67: =Y67+X67+W67 -> 0 | AB67: =(R67-86.16)/6*G67 -> 0 | AC67: =$Y$2*G67*Q67 -> 0 | AD67: =$Y$2*G67*Q67 -> 0 | AE67: =AD67+AC67+AB67 -> 0 | AG67: =(R67-86.16)/6*I67 -> 0 | AH67: =$Y$2*I67*Q67 -> 0 | AI67: =$Y$2*I67*Q67 -> 0 | AJ67: =AI67+AH67+AG67 -> 0 | AL67: =(R67-86.16)/6*K67 -> 0 | AM67: =$Y$2*K67*Q67 -> 0 | AN67: =$Y$2*K67*Q67 -> 0 | AO67: =AN67+AM67+AL67 -> 0 | AQ67: =(R67-86.16)/6*M67 -> 0 | AR67: =$Y$2*M67*Q67 -> 0 | AS67: =$Y$2*M67*Q67 -> 0 | AT67: =AS67+AR67+AQ67 -> 0 | AV67: =(R67-86.16)/6*O67 -> 0 | AW67: =$Y$2*O67*Q67 -> 0 | AX67: =$Y$2*O67*Q67 -> 0 | AY67: =AX67+AW67+AV67 -> 0 | AZ67: =+AY67+AT67+AO67++AJ67+AE67+Z67 -> 0 | BA67: 0
A68: 472 | E68: =SUM(E56:E67) -> 8 | G68: =SUM(G56:G67) -> 10 | I68: =SUM(I56:I67) -> 9 | K68: =SUM(K56:K67) -> 9 | M68: =SUM(M56:M67) -> 9 | O68: =SUM(O56:O67) -> 9 | BU68: 472
A69: 473 | BU69: 473
A70: 474 | B70: REAL | C70: PR | G70: L | I70: M | K70: M | M70: J | O70: V | Q70: S | BU70: 474
A71: 475 | B71: =E68 -> 8 | C71: =G75 -> 8 | D71: =+B71-C71 -> 0 | R71: PROM | BU71: 475
A72: 476 | B72: =G68 -> 10 | C72: =I75 -> 10 | D72: =+B72-C72 -> 0 | E72: LIDER | G72: 1 | I72: 1 | K72: 1 | M72: 1 | O72: 1 | Q72: 1 | R72: =AVERAGE(G72,I72,K72,M72,O72,Q72) -> 1 | BU72: 476
A73: 477 | B73: =I68 -> 9 | C73: =K75 -> 9 | D73: =+B73-C73 -> 0 | E73: MECANICO | G73: 1 | I73: 1 | K73: 1 | M73: 1 | O73: 1 | Q73: 1 | R73: =AVERAGE(G73,I73,K73,M73,O73,Q73) -> 1 | BU73: 477
A74: 478 | B74: =K68 -> 9 | C74: =M75 -> 9 | D74: =+B74-C74 -> 0 | E74: MANUAL | G74: 6 | I74: 8 | K74: 7 | M74: 7 | O74: 7 | Q74: 7 | R74: =AVERAGE(G74,I74,K74,M74,O74,Q74) -> 7 | BU74: 478
A75: 479 | B75: =M68 -> 9 | C75: =O75 -> 9 | D75: =+B75-C75 -> 0 | G75: =SUM(G72:G74) -> 8 | I75: =SUM(I72:I74) -> 10 | K75: =SUM(K72:K74) -> 9 | M75: =SUM(M72:M74) -> 9 | O75: =SUM(O72:O74) -> 9 | Q75: =SUM(Q68:Q74) -> 9 | R75: =AVERAGE(G75,I75,K75,M75,O75,Q75) -> 9 | BU75: 479
A76: 480 | B76: =O68 -> 9 | C76: =Q75 -> 9 | D76: =+B76-C76 -> 0 | T76: =SUM(R72:R74) -> 9 | BU76: 480
A78: 482 | BU78: 482
A79: 483 | B79: PUÑO | D79: 3ER TURNO | R79: =$V2 -> DEL 08 AL 14 ENERO 24 | BU79: 483
A80: 484 | E80: L | G80: M | I80: M | K80: J | M80: V | O80: S | BU80: 484
B81: 71 | C81: =C80+1 -> 1 | D81: Aguilar Muñoz Eduardo | E81: 1 | G81: 1 | I81: 1 | K81: 0 | L81: SUSP | M81: 1 | O81: 1 | Q81: 1 | R81: 2000 | S81: =+BH81 -> 0 | T81: =+BA81 -> 1714 | U81: =+BP81 -> 0 | V81: =+BG81 -> 0 | W81: =(R81-86.16)/6*E81 -> 318.97333 | X81: =$Y$2*E81*Q81 -> 7.18 | Y81: =$Y$2*E81*Q81 -> 7.18 | Z81: =Y81+X81+W81 -> 333.33333 | AB81: =(R81-86.16)/6*G81 -> 318.97333 | AC81: =$Y$2*G81*Q81 -> 7.18 | AD81: =$Y$2*G81*Q81 -> 7.18 | AE81: =AD81+AC81+AB81 -> 333.33333 | AG81: =(R81-86.16)/6*I81 -> 318.97333 | AH81: =$Y$2*I81*Q81 -> 7.18 | AI81: =$Y$2*I81*Q81 -> 7.18 | AJ81: =AI81+AH81+AG81 -> 333.33333 | AL81: =(R81-86.16)/6*K81 -> 0 | AM81: =$Y$2*K81*Q81 -> 0 | AN81: =$Y$2*K81*Q81 -> 0 | AO81: =AN81+AM81+AL81 -> 0 | AQ81: =(R81-86.16)/6*M81 -> 318.97333 | AR81: =$Y$2*M81*Q81 -> 7.18 | AS81: =$Y$2*M81*Q81 -> 7.18 | AT81: =AS81+AR81+AQ81 -> 333.33333 | AV81: =(R81-86.16)/6*O81 -> 318.97333 | AW81: =$Y$2*O81*Q81 -> 7.18 | AX81: =$Y$2*O81*Q81 -> 7.18 | AY81: =AX81+AW81+AV81 -> 333.33333 | AZ81: =+AY81+AT81+AO81++AJ81+AE81+Z81 -> 1666.6667 | BA81: 1714
B82: 147 | C82: =C81+1 -> 2 | D82: Alaniz Mayorga Yulissa | E82: 1 | G82: 1 | I82: 1 | K82: 1 | M82: 1 | O82: 1 | Q82: 1 | R82: =IF(Q82=1,1550,850) -> 1550 | S82: =+BH82 -> 0 | T82: =+BA82 -> 2000 | U82: =+BP82 -> 0 | V82: =+BG82 -> BONO+B ASIS | W82: =(R82-86.16)/6*E82 -> 243.97333 | X82: =$Y$2*E82*Q82 -> 7.18 | Y82: =$Y$2*E82*Q82 -> 7.18 | Z82: =Y82+X82+W82 -> 258.33333 | AB82: =(R82-86.16)/6*G82 -> 243.97333 | AC82: =$Y$2*G82*Q82 -> 7.18 | AD82: =$Y$2*G82*Q82 -> 7.18 | AE82: =AD82+AC82+AB82 -> 258.33333 | AG82: =(R82-86.16)/6*I82 -> 243.97333 | AH82: =$Y$2*I82*Q82 -> 7.18 | AI82: =$Y$2*I82*Q82 -> 7.18 | AJ82: =AI82+AH82+AG82 -> 258.33333 | AL82: =(R82-86.16)/6*K82 -> 243.97333 | AM82: =$Y$2*K82*Q82 -> 7.18 | AN82: =$Y$2*K82*Q82 -> 7.18 | AO82: =AN82+AM82+AL82 -> 258.33333 | AQ82: =(R82-86.16)/6*M82 -> 243.97333 | AR82: =$Y$2*M82*Q82 -> 7.18 | AS82: =$Y$2*M82*Q82 -> 7.18 | AT82: =AS82+AR82+AQ82 -> 258.33333 | AV82: =(R82-86.16)/6*O82 -> 243.97333 | AW82: =$Y$2*O82*Q82 -> 7.18 | AX82: =$Y$2*O82*Q82 -> 7.18 | AY82: =AX82+AW82+AV82 -> 258.33333 | AZ82: =+AY82+AT82+AO82++AJ82+AE82+Z82 -> 1550 | BA82: =((AZ82-BB82-BC82-BD82-BE82-BF82)+BI82+BJ82+BK82+BL82+BM82+BN82+BO82) -> 2000 | BG82: BONO+B ASIS | BI82: 300 | BJ82: 150
B83: 127 | C83: =C82+1 -> 3 | D83: Carranza Chavarria Esmeralda | E83: 1 | G83: 1 | I83: 1 | K83: 1 | M83: 1 | O83: 1 | Q83: 1 | R83: =IF(Q83=1,1550,850) -> 1550 | S83: =+BH83 -> 0 | T83: =+BA83 -> 1800 | U83: =+BP83 -> 0 | V83: =+BG83 -> BONO | W83: =(R83-86.16)/6*E83 -> 243.97333 | X83: =$Y$2*E83*Q83 -> 7.18 | Y83: =$Y$2*E83*Q83 -> 7.18 | Z83: =Y83+X83+W83 -> 258.33333 | AB83: =(R83-86.16)/6*G83 -> 243.97333 | AC83: =$Y$2*G83*Q83 -> 7.18 | AD83: =$Y$2*G83*Q83 -> 7.18 | AE83: =AD83+AC83+AB83 -> 258.33333 | AG83: =(R83-86.16)/6*I83 -> 243.97333 | AH83: =$Y$2*I83*Q83 -> 7.18 | AI83: =$Y$2*I83*Q83 -> 7.18 | AJ83: =AI83+AH83+AG83 -> 258.33333 | AL83: =(R83-86.16)/6*K83 -> 243.97333 | AM83: =$Y$2*K83*Q83 -> 7.18 | AN83: =$Y$2*K83*Q83 -> 7.18 | AO83: =AN83+AM83+AL83 -> 258.33333 | AQ83: =(R83-86.16)/6*M83 -> 243.97333 | AR83: =$Y$2*M83*Q83 -> 7.18 | AS83: =$Y$2*M83*Q83 -> 7.18 | AT83: =AS83+AR83+AQ83 -> 258.33333 | AV83: =(R83-86.16)/6*O83 -> 243.97333 | AW83: =$Y$2*O83*Q83 -> 7.18 | AX83: =$Y$2*O83*Q83 -> 7.18 | AY83: =AX83+AW83+AV83 -> 258.33333 | AZ83: =+AY83+AT83+AO83++AJ83+AE83+Z83 -> 1550 | BA83: =((AZ83-BB83-BC83-BD83-BE83-BF83)+BI83+BJ83+BK83+BL83+BM83+BN83+BO83) -> 1800 | BG83: BONO | BI83: 250 | BJ83: 0
B84: 69 | C84: =C83+1 -> 4 | D84: Carranza Hernandez Maria Fernanda | E84: 1 | G84: 1 | I84: 1 | K84: 1 | M84: 1 | O84: 1 | Q84: 1 | R84: =IF(Q84=1,1550,850) -> 1550 | S84: =+BH84 -> 0 | T84: =+BA84 -> 1800 | U84: =+BP84 -> 0 | V84: =+BG84 -> BONO | W84: =(R84-86.16)/6*E84 -> 243.97333 | X84: =$Y$2*E84*Q84 -> 7.18 | Y84: =$Y$2*E84*Q84 -> 7.18 | Z84: =Y84+X84+W84 -> 258.33333 | AB84: =(R84-86.16)/6*G84 -> 243.97333 | AC84: =$Y$2*G84*Q84 -> 7.18 | AD84: =$Y$2*G84*Q84 -> 7.18 | AE84: =AD84+AC84+AB84 -> 258.33333 | AG84: =(R84-86.16)/6*I84 -> 243.97333 | AH84: =$Y$2*I84*Q84 -> 7.18 | AI84: =$Y$2*I84*Q84 -> 7.18 | AJ84: =AI84+AH84+AG84 -> 258.33333 | AL84: =(R84-86.16)/6*K84 -> 243.97333 | AM84: =$Y$2*K84*Q84 -> 7.18 | AN84: =$Y$2*K84*Q84 -> 7.18 | AO84: =AN84+AM84+AL84 -> 258.33333 | AQ84: =(R84-86.16)/6*M84 -> 243.97333 | AR84: =$Y$2*M84*Q84 -> 7.18 | AS84: =$Y$2*M84*Q84 -> 7.18 | AT84: =AS84+AR84+AQ84 -> 258.33333 | AV84: =(R84-86.16)/6*O84 -> 243.97333 | AW84: =$Y$2*O84*Q84 -> 7.18 | AX84: =$Y$2*O84*Q84 -> 7.18 | AY84: =AX84+AW84+AV84 -> 258.33333 | AZ84: =+AY84+AT84+AO84++AJ84+AE84+Z84 -> 1550 | BA84: =((AZ84-BB84-BC84-BD84-BE84-BF84)+BI84+BJ84+BK84+BL84+BM84+BN84+BO84) -> 1800 | BG84: BONO | BI84: 250
B85: 107 | C85: =C84+1 -> 5 | D85: Chavarria Machado Samuel | E85: 1 | G85: 1 | I85: 1 | K85: 1 | M85: 1 | O85: 1 | Q85: 1 | R85: 2000 | S85: =+BH85 -> 0 | T85: =+BA85 -> 2500 | U85: =+BP85 -> 0 | V85: =+BG85 -> BONO+B ASIS | W85: =(R85-86.16)/6*E85 -> 318.97333 | X85: =$Y$2*E85*Q85 -> 7.18 | Y85: =$Y$2*E85*Q85 -> 7.18 | Z85: =Y85+X85+W85 -> 333.33333 | AB85: =(R85-86.16)/6*G85 -> 318.97333 | AC85: =$Y$2*G85*Q85 -> 7.18 | AD85: =$Y$2*G85*Q85 -> 7.18 | AE85: =AD85+AC85+AB85 -> 333.33333 | AG85: =(R85-86.16)/6*I85 -> 318.97333 | AH85: =$Y$2*I85*Q85 -> 7.18 | AI85: =$Y$2*I85*Q85 -> 7.18 | AJ85: =AI85+AH85+AG85 -> 333.33333 | AL85: =(R85-86.16)/6*K85 -> 318.97333 | AM85: =$Y$2*K85*Q85 -> 7.18 | AN85: =$Y$2*K85*Q85 -> 7.18 | AO85: =AN85+AM85+AL85 -> 333.33333 | AQ85: =(R85-86.16)/6*M85 -> 318.97333 | AR85: =$Y$2*M85*Q85 -> 7.18 | AS85: =$Y$2*M85*Q85 -> 7.18 | AT85: =AS85+AR85+AQ85 -> 333.33333 | AV85: =(R85-86.16)/6*O85 -> 318.97333 | AW85: =$Y$2*O85*Q85 -> 7.18 | AX85: =$Y$2*O85*Q85 -> 7.18 | AY85: =AX85+AW85+AV85 -> 333.33333 | AZ85: =+AY85+AT85+AO85++AJ85+AE85+Z85 -> 2000 | BA85: =((AZ85-BB85-BC85-BD85-BE85-BF85)+BI85+BJ85+BK85+BL85+BM85+BN85+BO85) -> 2500 | BG85: BONO+B ASIS | BI85: 350 | BJ85: 150
A86: 421 | B86: 63 | C86: =C85+1 -> 6 | D86: Cuapio Flores Mario | E86: 1 | G86: 1 | I86: 1 | K86: 1 | M86: 1 | O86: 1 | Q86: 1 | R86: 7000 | S86: =+BH86 -> 0 | T86: =+BA86 -> 10500 | U86: =+BP86 -> 0 | V86: =+BG86 -> PV2A 2/2 | W86: =(R86-86.16)/6*E86 -> 1152.3067 | X86: =$Y$2*E86*Q86 -> 7.18 | Y86: =$Y$2*E86*Q86 -> 7.18 | Z86: =Y86+X86+W86 -> 1166.6667 | AB86: =(R86-86.16)/6*G86 -> 1152.3067 | AC86: =$Y$2*G86*Q86 -> 7.18 | AD86: =$Y$2*G86*Q86 -> 7.18 | AE86: =AD86+AC86+AB86 -> 1166.6667 | AG86: =(R86-86.16)/6*I86 -> 1152.3067 | AH86: =$Y$2*I86*Q86 -> 7.18 | AI86: =$Y$2*I86*Q86 -> 7.18 | AJ86: =AI86+AH86+AG86 -> 1166.6667 | AL86: =(R86-86.16)/6*K86 -> 1152.3067 | AM86: =$Y$2*K86*Q86 -> 7.18 | AN86: =$Y$2*K86*Q86 -> 7.18 | AO86: =AN86+AM86+AL86 -> 1166.6667 | AQ86: =(R86-86.16)/6*M86 -> 1152.3067 | AR86: =$Y$2*M86*Q86 -> 7.18 | AS86: =$Y$2*M86*Q86 -> 7.18 | AT86: =AS86+AR86+AQ86 -> 1166.6667 | AV86: =(R86-86.16)/6*O86 -> 1152.3067 | AW86: =$Y$2*O86*Q86 -> 7.18 | AX86: =$Y$2*O86*Q86 -> 7.18 | AY86: =AX86+AW86+AV86 -> 1166.6667 | AZ86: =+AY86+AT86+AO86++AJ86+AE86+Z86 -> 7000 | BA86: =7000+BI86+BJ86+BK86+BL86+BM86 -> 10500 | BG86: PV2A 2/2 | BM86: 3500 | BU86: 421
B87: 94 | C87: =C86+1 -> 7 | D87: Dominguez Soto Jesus Alberto | E87: 1 | G87: 1 | I87: 1 | K87: 1 | M87: 1 | O87: 1 | Q87: 1 | R87: 2000 | S87: =+BH87 -> 0 | T87: =+BA87 -> 2600 | U87: =+BP87 -> 0 | V87: =+BG87 -> BONO+B ASIS | W87: =(R87-86.16)/6*E87 -> 318.97333 | X87: =$Y$2*E87*Q87 -> 7.18 | Y87: =$Y$2*E87*Q87 -> 7.18 | Z87: =Y87+X87+W87 -> 333.33333 | AB87: =(R87-86.16)/6*G87 -> 318.97333 | AC87: =$Y$2*G87*Q87 -> 7.18 | AD87: =$Y$2*G87*Q87 -> 7.18 | AE87: =AD87+AC87+AB87 -> 333.33333 | AG87: =(R87-86.16)/6*I87 -> 318.97333 | AH87: =$Y$2*I87*Q87 -> 7.18 | AI87: =$Y$2*I87*Q87 -> 7.18 | AJ87: =AI87+AH87+AG87 -> 333.33333 | AL87: =(R87-86.16)/6*K87 -> 318.97333 | AM87: =$Y$2*K87*Q87 -> 7.18 | AN87: =$Y$2*K87*Q87 -> 7.18 | AO87: =AN87+AM87+AL87 -> 333.33333 | AQ87: =(R87-86.16)/6*M87 -> 318.97333 | AR87: =$Y$2*M87*Q87 -> 7.18 | AS87: =$Y$2*M87*Q87 -> 7.18 | AT87: =AS87+AR87+AQ87 -> 333.33333 | AV87: =(R87-86.16)/6*O87 -> 318.97333 | AW87: =$Y$2*O87*Q87 -> 7.18 | AX87: =$Y$2*O87*Q87 -> 7.18 | AY87: =AX87+AW87+AV87 -> 333.33333 | AZ87: =+AY87+AT87+AO87++AJ87+AE87+Z87 -> 2000 | BA87: =((AZ87-BB87-BC87-BD87-BE87-BF87)+BI87+BJ87+BK87+BL87+BM87+BN87+BO87) -> 2600 | BG87: BONO+B ASIS | BI87: 350 | BJ87: 250
B88: 167 | C88: =C87+1 -> 8 | D88: Dominguez Soto Maria de los Angeles | E88: 1 | G88: 1 | I88: 1 | K88: 1 | M88: 1 | O88: 1 | Q88: 1 | R88: =IF(Q88=1,1550,850) -> 1550 | S88: =+BH88 -> 0 | T88: =+BA88 -> 1800 | U88: =+BP88 -> 0 | V88: =+BG88 -> B ASIS | W88: =(R88-86.16)/6*E88 -> 243.97333 | X88: =$Y$2*E88*Q88 -> 7.18 | Y88: =$Y$2*E88*Q88 -> 7.18 | Z88: =Y88+X88+W88 -> 258.33333 | AB88: =(R88-86.16)/6*G88 -> 243.97333 | AC88: =$Y$2*G88*Q88 -> 7.18 | AD88: =$Y$2*G88*Q88 -> 7.18 | AE88: =AD88+AC88+AB88 -> 258.33333 | AG88: =(R88-86.16)/6*I88 -> 243.97333 | AH88: =$Y$2*I88*Q88 -> 7.18 | AI88: =$Y$2*I88*Q88 -> 7.18 | AJ88: =AI88+AH88+AG88 -> 258.33333 | AL88: =(R88-86.16)/6*K88 -> 243.97333 | AM88: =$Y$2*K88*Q88 -> 7.18 | AN88: =$Y$2*K88*Q88 -> 7.18 | AO88: =AN88+AM88+AL88 -> 258.33333 | AQ88: =(R88-86.16)/6*M88 -> 243.97333 | AR88: =$Y$2*M88*Q88 -> 7.18 | AS88: =$Y$2*M88*Q88 -> 7.18 | AT88: =AS88+AR88+AQ88 -> 258.33333 | AV88: =(R88-86.16)/6*O88 -> 243.97333 | AW88: =$Y$2*O88*Q88 -> 7.18 | AX88: =$Y$2*O88*Q88 -> 7.18 | AY88: =AX88+AW88+AV88 -> 258.33333 | AZ88: =+AY88+AT88+AO88++AJ88+AE88+Z88 -> 1550 | BA88: =((AZ88-BB88-BC88-BD88-BE88-BF88)+BI88+BJ88+BK88+BL88+BM88+BN88+BO88) -> 1800 | BG88: B ASIS | BI88: 100 | BJ88: 150
B89: 143 | C89: =C88+1 -> 9 | D89: Estrada Hernandez Arantxa | E89: 1 | G89: 1 | I89: 1 | K89: 1 | M89: 1 | O89: 1 | Q89: 1 | R89: =IF(Q89=1,1550,850) -> 1550 | S89: =+BH89 -> 0 | T89: =+BA89 -> 2107.14 | U89: =+BP89 -> 0 | V89: =+BG89 -> BONO+B ASIS+T EXT | W89: =(R89-86.16)/6*E89 -> 243.97333 | X89: =$Y$2*E89*Q89 -> 7.18 | Y89: =$Y$2*E89*Q89 -> 7.18 | Z89: =Y89+X89+W89 -> 258.33333 | AB89: =(R89-86.16)/6*G89 -> 243.97333 | AC89: =$Y$2*G89*Q89 -> 7.18 | AD89: =$Y$2*G89*Q89 -> 7.18 | AE89: =AD89+AC89+AB89 -> 258.33333 | AG89: =(R89-86.16)/6*I89 -> 243.97333 | AH89: =$Y$2*I89*Q89 -> 7.18 | AI89: =$Y$2*I89*Q89 -> 7.18 | AJ89: =AI89+AH89+AG89 -> 258.33333 | AL89: =(R89-86.16)/6*K89 -> 243.97333 | AM89: =$Y$2*K89*Q89 -> 7.18 | AN89: =$Y$2*K89*Q89 -> 7.18 | AO89: =AN89+AM89+AL89 -> 258.33333 | AQ89: =(R89-86.16)/6*M89 -> 243.97333 | AR89: =$Y$2*M89*Q89 -> 7.18 | AS89: =$Y$2*M89*Q89 -> 7.18 | AT89: =AS89+AR89+AQ89 -> 258.33333 | AV89: =(R89-86.16)/6*O89 -> 243.97333 | AW89: =$Y$2*O89*Q89 -> 7.18 | AX89: =$Y$2*O89*Q89 -> 7.18 | AY89: =AX89+AW89+AV89 -> 258.33333 | AZ89: =+AY89+AT89+AO89++AJ89+AE89+Z89 -> 1550 | BA89: =((AZ89-BB89-BC89-BD89-BE89-BF89)+BI89+BJ89+BK89+BL89+BM89+BN89+BO89) -> 2107.14 | BG89: BONO+B ASIS+T EXT | BI89: 250 | BJ89: 250 | BK89: 57.14
B90: 70 | C90: =C89+1 -> 10 | D90: Gonzalez Lopez Violeta | E90: 0 | F90: INC | G90: 0 | H90: INC | I90: 0 | J90: INC | K90: 0 | L90: INC | M90: 0 | N90: INC | O90: 0 | P90: INC | Q90: 0 | R90: =IF(Q90=1,1550,850) -> 850 | S90: =+BH90 -> 0 | T90: =+BA90 -> 0 | U90: =+BP90 -> 0 | V90: =+BG90 -> 0 | W90: =(R90-86.16)/6*E90 -> 0 | X90: =$Y$2*E90*Q90 -> 0 | Y90: =$Y$2*E90*Q90 -> 0 | Z90: =Y90+X90+W90 -> 0 | AB90: =(R90-86.16)/6*G90 -> 0 | AC90: =$Y$2*G90*Q90 -> 0 | AD90: =$Y$2*G90*Q90 -> 0 | AE90: =AD90+AC90+AB90 -> 0 | AG90: =(R90-86.16)/6*I90 -> 0 | AH90: =$Y$2*I90*Q90 -> 0 | AI90: =$Y$2*I90*Q90 -> 0 | AJ90: =AI90+AH90+AG90 -> 0 | AL90: =(R90-86.16)/6*K90 -> 0 | AM90: =$Y$2*K90*Q90 -> 0 | AN90: =$Y$2*K90*Q90 -> 0 | AO90: =AN90+AM90+AL90 -> 0 | AQ90: =(R90-86.16)/6*M90 -> 0 | AR90: =$Y$2*M90*Q90 -> 0 | AS90: =$Y$2*M90*Q90 -> 0 | AT90: =AS90+AR90+AQ90 -> 0 | AV90: =(R90-86.16)/6*O90 -> 0 | AW90: =$Y$2*O90*Q90 -> 0 | AX90: =$Y$2*O90*Q90 -> 0 | AY90: =AX90+AW90+AV90 -> 0 | AZ90: =+AY90+AT90+AO90++AJ90+AE90+Z90 -> 0
A91: 522 | B91: 120 | C91: =C90+1 -> 11 | D91: Guerrero Zamarron Melani Abigail | E91: 1 | G91: 1 | I91: 1 | K91: 1 | M91: 1 | O91: 1 | Q91: 1 | R91: =IF(Q91=1,1550,850) -> 1550 | S91: =+BH91 -> 0 | T91: =+BA91 -> 1950 | U91: =+BP91 -> 0 | V91: =+BG91 -> BONO+B ASIS | W91: =(R91-86.16)/6*E91 -> 243.97333 | X91: =$Y$2*E91*Q91 -> 7.18 | Y91: =$Y$2*E91*Q91 -> 7.18 | Z91: =Y91+X91+W91 -> 258.33333 | AB91: =(R91-86.16)/6*G91 -> 243.97333 | AC91: =$Y$2*G91*Q91 -> 7.18 | AD91: =$Y$2*G91*Q91 -> 7.18 | AE91: =AD91+AC91+AB91 -> 258.33333 | AG91: =(R91-86.16)/6*I91 -> 243.97333 | AH91: =$Y$2*I91*Q91 -> 7.18 | AI91: =$Y$2*I91*Q91 -> 7.18 | AJ91: =AI91+AH91+AG91 -> 258.33333 | AL91: =(R91-86.16)/6*K91 -> 243.97333 | AM91: =$Y$2*K91*Q91 -> 7.18 | AN91: =$Y$2*K91*Q91 -> 7.18 | AO91: =AN91+AM91+AL91 -> 258.33333 | AQ91: =(R91-86.16)/6*M91 -> 243.97333 | AR91: =$Y$2*M91*Q91 -> 7.18 | AS91: =$Y$2*M91*Q91 -> 7.18 | AT91: =AS91+AR91+AQ91 -> 258.33333 | AV91: =(R91-86.16)/6*O91 -> 243.97333 | AW91: =$Y$2*O91*Q91 -> 7.18 | AX91: =$Y$2*O91*Q91 -> 7.18 | AY91: =AX91+AW91+AV91 -> 258.33333 | AZ91: =+AY91+AT91+AO91++AJ91+AE91+Z91 -> 1550 | BA91: =((AZ91-BB91-BC91-BD91-BE91-BF91)+BI91+BJ91+BK91+BL91+BM91+BN91+BO91) -> 1950 | BG91: BONO+B ASIS | BI91: 250 | BJ91: 150 | BU91: 522
B92: 142 | C92: =C91+1 -> 12 | D92: Limon Campos Beatriz Adriana | E92: 1 | G92: 1 | I92: 1 | K92: 1 | M92: 1 | O92: 1 | Q92: 1 | R92: =IF(Q92=1,1550,850) -> 1550 | S92: =+BH92 -> 0 | T92: =+BA92 -> 1950 | U92: =+BP92 -> 0 | V92: =+BG92 -> BONO+B ASIS | W92: =(R92-86.16)/6*E92 -> 243.97333 | X92: =$Y$2*E92*Q92 -> 7.18 | Y92: =$Y$2*E92*Q92 -> 7.18 | Z92: =Y92+X92+W92 -> 258.33333 | AB92: =(R92-86.16)/6*G92 -> 243.97333 | AC92: =$Y$2*G92*Q92 -> 7.18 | AD92: =$Y$2*G92*Q92 -> 7.18 | AE92: =AD92+AC92+AB92 -> 258.33333 | AG92: =(R92-86.16)/6*I92 -> 243.97333 | AH92: =$Y$2*I92*Q92 -> 7.18 | AI92: =$Y$2*I92*Q92 -> 7.18 | AJ92: =AI92+AH92+AG92 -> 258.33333 | AL92: =(R92-86.16)/6*K92 -> 243.97333 | AM92: =$Y$2*K92*Q92 -> 7.18 | AN92: =$Y$2*K92*Q92 -> 7.18 | AO92: =AN92+AM92+AL92 -> 258.33333 | AQ92: =(R92-86.16)/6*M92 -> 243.97333 | AR92: =$Y$2*M92*Q92 -> 7.18 | AS92: =$Y$2*M92*Q92 -> 7.18 | AT92: =AS92+AR92+AQ92 -> 258.33333 | AV92: =(R92-86.16)/6*O92 -> 243.97333 | AW92: =$Y$2*O92*Q92 -> 7.18 | AX92: =$Y$2*O92*Q92 -> 7.18 | AY92: =AX92+AW92+AV92 -> 258.33333 | AZ92: =+AY92+AT92+AO92++AJ92+AE92+Z92 -> 1550 | BA92: =((AZ92-BB92-BC92-BD92-BE92-BF92)+BI92+BJ92+BK92+BL92+BM92+BN92+BO92) -> 1950 | BG92: BONO+B ASIS | BI92: 250 | BJ92: 150
B93: 138 | C93: =C92+1 -> 13 | D93: Martinez Robles Luis Miguel | E93: 1 | G93: 1 | I93: 1 | K93: 1 | M93: 1 | O93: 1 | Q93: 1 | R93: 2000 | S93: =+BH93 -> 0 | T93: =+BA93 -> 2150 | U93: =+BP93 -> 0 | V93: =+BG93 -> B ASIS | W93: =(R93-86.16)/6*E93 -> 318.97333 | X93: =$Y$2*E93*Q93 -> 7.18 | Y93: =$Y$2*E93*Q93 -> 7.18 | Z93: =Y93+X93+W93 -> 333.33333 | AB93: =(R93-86.16)/6*G93 -> 318.97333 | AC93: =$Y$2*G93*Q93 -> 7.18 | AD93: =$Y$2*G93*Q93 -> 7.18 | AE93: =AD93+AC93+AB93 -> 333.33333 | AG93: =(R93-86.16)/6*I93 -> 318.97333 | AH93: =$Y$2*I93*Q93 -> 7.18 | AI93: =$Y$2*I93*Q93 -> 7.18 | AJ93: =AI93+AH93+AG93 -> 333.33333 | AL93: =(R93-86.16)/6*K93 -> 318.97333 | AM93: =$Y$2*K93*Q93 -> 7.18 | AN93: =$Y$2*K93*Q93 -> 7.18 | AO93: =AN93+AM93+AL93 -> 333.33333 | AQ93: =(R93-86.16)/6*M93 -> 318.97333 | AR93: =$Y$2*M93*Q93 -> 7.18 | AS93: =$Y$2*M93*Q93 -> 7.18 | AT93: =AS93+AR93+AQ93 -> 333.33333 | AV93: =(R93-86.16)/6*O93 -> 318.97333 | AW93: =$Y$2*O93*Q93 -> 7.18 | AX93: =$Y$2*O93*Q93 -> 7.18 | AY93: =AX93+AW93+AV93 -> 333.33333 | AZ93: =+AY93+AT93+AO93++AJ93+AE93+Z93 -> 2000 | BA93: =((AZ93-BB93-BC93-BD93-BE93-BF93)+BI93+BJ93+BK93+BL93+BM93+BN93+BO93) -> 2150 | BG93: B ASIS | BJ93: 150
B94: 135 | C94: =C93+1 -> 14 | D94: Martinez Rosales Sugey Marisol | E94: 1 | G94: 1 | I94: 1 | K94: 1 | M94: 1 | O94: 1 | Q94: 1 | R94: =IF(Q94=1,1550,850) -> 1550 | S94: =+BH94 -> 0 | T94: =+BA94 -> 1950 | U94: =+BP94 -> 0 | V94: =+BG94 -> BONO+B ASIS | W94: =(R94-86.16)/6*E94 -> 243.97333 | X94: =$Y$2*E94*Q94 -> 7.18 | Y94: =$Y$2*E94*Q94 -> 7.18 | Z94: =Y94+X94+W94 -> 258.33333 | AB94: =(R94-86.16)/6*G94 -> 243.97333 | AC94: =$Y$2*G94*Q94 -> 7.18 | AD94: =$Y$2*G94*Q94 -> 7.18 | AE94: =AD94+AC94+AB94 -> 258.33333 | AG94: =(R94-86.16)/6*I94 -> 243.97333 | AH94: =$Y$2*I94*Q94 -> 7.18 | AI94: =$Y$2*I94*Q94 -> 7.18 | AJ94: =AI94+AH94+AG94 -> 258.33333 | AL94: =(R94-86.16)/6*K94 -> 243.97333 | AM94: =$Y$2*K94*Q94 -> 7.18 | AN94: =$Y$2*K94*Q94 -> 7.18 | AO94: =AN94+AM94+AL94 -> 258.33333 | AQ94: =(R94-86.16)/6*M94 -> 243.97333 | AR94: =$Y$2*M94*Q94 -> 7.18 | AS94: =$Y$2*M94*Q94 -> 7.18 | AT94: =AS94+AR94+AQ94 -> 258.33333 | AV94: =(R94-86.16)/6*O94 -> 243.97333 | AW94: =$Y$2*O94*Q94 -> 7.18 | AX94: =$Y$2*O94*Q94 -> 7.18 | AY94: =AX94+AW94+AV94 -> 258.33333 | AZ94: =+AY94+AT94+AO94++AJ94+AE94+Z94 -> 1550 | BA94: =((AZ94-BB94-BC94-BD94-BE94-BF94)+BI94+BJ94+BK94+BL94+BM94+BN94+BO94) -> 1950 | BG94: BONO+B ASIS | BI94: 250 | BJ94: 150
B95: 150 | C95: =C94+1 -> 15 | D95: Moreno Martinez Marisol | E95: 1 | G95: 1 | I95: 1 | K95: 1 | M95: 1 | O95: 1 | Q95: 1 | R95: =IF(Q95=1,1550,850) -> 1550 | S95: =+BH95 -> 0 | T95: =+BA95 -> 1950 | U95: =+BP95 -> 0 | V95: =+BG95 -> BONO+B ASIS | W95: =(R95-86.16)/6*E95 -> 243.97333 | X95: =$Y$2*E95*Q95 -> 7.18 | Y95: =$Y$2*E95*Q95 -> 7.18 | Z95: =Y95+X95+W95 -> 258.33333 | AB95: =(R95-86.16)/6*G95 -> 243.97333 | AC95: =$Y$2*G95*Q95 -> 7.18 | AD95: =$Y$2*G95*Q95 -> 7.18 | AE95: =AD95+AC95+AB95 -> 258.33333 | AG95: =(R95-86.16)/6*I95 -> 243.97333 | AH95: =$Y$2*I95*Q95 -> 7.18 | AI95: =$Y$2*I95*Q95 -> 7.18 | AJ95: =AI95+AH95+AG95 -> 258.33333 | AL95: =(R95-86.16)/6*K95 -> 243.97333 | AM95: =$Y$2*K95*Q95 -> 7.18 | AN95: =$Y$2*K95*Q95 -> 7.18 | AO95: =AN95+AM95+AL95 -> 258.33333 | AQ95: =(R95-86.16)/6*M95 -> 243.97333 | AR95: =$Y$2*M95*Q95 -> 7.18 | AS95: =$Y$2*M95*Q95 -> 7.18 | AT95: =AS95+AR95+AQ95 -> 258.33333 | AV95: =(R95-86.16)/6*O95 -> 243.97333 | AW95: =$Y$2*O95*Q95 -> 7.18 | AX95: =$Y$2*O95*Q95 -> 7.18 | AY95: =AX95+AW95+AV95 -> 258.33333 | AZ95: =+AY95+AT95+AO95++AJ95+AE95+Z95 -> 1550 | BA95: =((AZ95-BB95-BC95-BD95-BE95-BF95)+BI95+BJ95+BK95+BL95+BM95+BN95+BO95) -> 1950 | BG95: BONO+B ASIS | BI95: 250 | BJ95: 150
B96: 145 | C96: =C95+1 -> 16 | D96: Muñoz Rodriguez Susana | E96: 1 | G96: 1 | I96: 1 | K96: 1 | M96: 1 | O96: 1 | Q96: 1 | R96: =IF(Q96=1,1550,850) -> 1550 | S96: =+BH96 -> 0 | T96: =+BA96 -> 1950 | U96: =+BP96 -> 0 | V96: =+BG96 -> BONO+B ASIS | W96: =(R96-86.16)/6*E96 -> 243.97333 | X96: =$Y$2*E96*Q96 -> 7.18 | Y96: =$Y$2*E96*Q96 -> 7.18 | Z96: =Y96+X96+W96 -> 258.33333 | AB96: =(R96-86.16)/6*G96 -> 243.97333 | AC96: =$Y$2*G96*Q96 -> 7.18 | AD96: =$Y$2*G96*Q96 -> 7.18 | AE96: =AD96+AC96+AB96 -> 258.33333 | AG96: =(R96-86.16)/6*I96 -> 243.97333 | AH96: =$Y$2*I96*Q96 -> 7.18 | AI96: =$Y$2*I96*Q96 -> 7.18 | AJ96: =AI96+AH96+AG96 -> 258.33333 | AL96: =(R96-86.16)/6*K96 -> 243.97333 | AM96: =$Y$2*K96*Q96 -> 7.18 | AN96: =$Y$2*K96*Q96 -> 7.18 | AO96: =AN96+AM96+AL96 -> 258.33333 | AQ96: =(R96-86.16)/6*M96 -> 243.97333 | AR96: =$Y$2*M96*Q96 -> 7.18 | AS96: =$Y$2*M96*Q96 -> 7.18 | AT96: =AS96+AR96+AQ96 -> 258.33333 | AV96: =(R96-86.16)/6*O96 -> 243.97333 | AW96: =$Y$2*O96*Q96 -> 7.18 | AX96: =$Y$2*O96*Q96 -> 7.18 | AY96: =AX96+AW96+AV96 -> 258.33333 | AZ96: =+AY96+AT96+AO96++AJ96+AE96+Z96 -> 1550 | BA96: =((AZ96-BB96-BC96-BD96-BE96-BF96)+BI96+BJ96+BK96+BL96+BM96+BN96+BO96) -> 1950 | BG96: BONO+B ASIS | BI96: 250 | BJ96: 150
A97: 469 | B97: 45 | C97: =C96+1 -> 17 | D97: Sanchez Flores Miguel Angel | E97: 1 | G97: 1 | I97: 1 | K97: 1 | M97: 1 | O97: 1 | Q97: 1 | R97: =IF(Q97=1,3500,600) -> 3500 | S97: =+BH97 -> 0 | T97: =+BA97 -> 3500 | U97: =+BP97 -> 0 | V97: =+BG97 -> 0 | W97: =(R97-86.16)/6*E97 -> 568.97333 | X97: =$Y$2*E97*Q97 -> 7.18 | Y97: =$Y$2*E97*Q97 -> 7.18 | Z97: =Y97+X97+W97 -> 583.33333 | AB97: =(R97-86.16)/6*G97 -> 568.97333 | AC97: =$Y$2*G97*Q97 -> 7.18 | AD97: =$Y$2*G97*Q97 -> 7.18 | AE97: =AD97+AC97+AB97 -> 583.33333 | AG97: =(R97-86.16)/6*I97 -> 568.97333 | AH97: =$Y$2*I97*Q97 -> 7.18 | AI97: =$Y$2*I97*Q97 -> 7.18 | AJ97: =AI97+AH97+AG97 -> 583.33333 | AL97: =(R97-86.16)/6*K97 -> 568.97333 | AM97: =$Y$2*K97*Q97 -> 7.18 | AN97: =$Y$2*K97*Q97 -> 7.18 | AO97: =AN97+AM97+AL97 -> 583.33333 | AQ97: =(R97-86.16)/6*M97 -> 568.97333 | AR97: =$Y$2*M97*Q97 -> 7.18 | AS97: =$Y$2*M97*Q97 -> 7.18 | AT97: =AS97+AR97+AQ97 -> 583.33333 | AV97: =(R97-86.16)/6*O97 -> 568.97333 | AW97: =$Y$2*O97*Q97 -> 7.18 | AX97: =$Y$2*O97*Q97 -> 7.18 | AY97: =AX97+AW97+AV97 -> 583.33333 | AZ97: =+AY97+AT97+AO97++AJ97+AE97+Z97 -> 3500 | BA97: =((AZ97-BB97-BC97-BD97-BE97-BF97)+BI97+BJ97+BK97+BL97+BM97+BN97+BO97) -> 3500 | BU97: 469
B98: 179 | C98: =C97+1 -> 18 | D98: Vargas Juarez Jorge | E98: 1 | G98: 1 | I98: 1 | K98: 1 | M98: 1 | O98: 1 | Q98: 1 | R98: =IF(Q98=1,1550,850) -> 1550 | S98: =+BH98 -> 0 | T98: =+BA98 -> 1850 | U98: =+BP98 -> 0 | V98: =+BG98 -> 0 | W98: =(R98-86.16)/6*E98 -> 243.97333 | X98: =$Y$2*E98*Q98 -> 7.18 | Y98: =$Y$2*E98*Q98 -> 7.18 | Z98: =Y98+X98+W98 -> 258.33333 | AB98: =(R98-86.16)/6*G98 -> 243.97333 | AC98: =$Y$2*G98*Q98 -> 7.18 | AD98: =$Y$2*G98*Q98 -> 7.18 | AE98: =AD98+AC98+AB98 -> 258.33333 | AG98: =(R98-86.16)/6*I98 -> 243.97333 | AH98: =$Y$2*I98*Q98 -> 7.18 | AI98: =$Y$2*I98*Q98 -> 7.18 | AJ98: =AI98+AH98+AG98 -> 258.33333 | AL98: =(R98-86.16)/6*K98 -> 243.97333 | AM98: =$Y$2*K98*Q98 -> 7.18 | AN98: =$Y$2*K98*Q98 -> 7.18 | AO98: =AN98+AM98+AL98 -> 258.33333 | AQ98: =(R98-86.16)/6*M98 -> 243.97333 | AR98: =$Y$2*M98*Q98 -> 7.18 | AS98: =$Y$2*M98*Q98 -> 7.18 | AT98: =AS98+AR98+AQ98 -> 258.33333 | AV98: =(R98-86.16)/6*O98 -> 243.97333 | AW98: =$Y$2*O98*Q98 -> 7.18 | AX98: =$Y$2*O98*Q98 -> 7.18 | AY98: =AX98+AW98+AV98 -> 258.33333 | AZ98: =+AY98+AT98+AO98++AJ98+AE98+Z98 -> 1550 | BA98: =((AZ98-BB98-BC98-BD98-BE98-BF98)+BI98+BJ98+BK98+BL98+BM98+BN98+BO98) -> 1850 | BI98: 150 | BJ98: 150
B99: 111 | C99: =C98+1 -> 19 | D99: Viaña Dominguez Gladis Nayeli | E99: 1 | G99: 1 | I99: 1 | K99: 1 | M99: 1 | O99: 1 | Q99: 1 | R99: =IF(Q99=1,1550,850) -> 1550 | S99: =+BH99 -> 0 | T99: =+BA99 -> 1950 | U99: =+BP99 -> 0 | V99: =+BG99 -> BONO+B ASIS | W99: =(R99-86.16)/6*E99 -> 243.97333 | X99: =$Y$2*E99*Q99 -> 7.18 | Y99: =$Y$2*E99*Q99 -> 7.18 | Z99: =Y99+X99+W99 -> 258.33333 | AB99: =(R99-86.16)/6*G99 -> 243.97333 | AC99: =$Y$2*G99*Q99 -> 7.18 | AD99: =$Y$2*G99*Q99 -> 7.18 | AE99: =AD99+AC99+AB99 -> 258.33333 | AG99: =(R99-86.16)/6*I99 -> 243.97333 | AH99: =$Y$2*I99*Q99 -> 7.18 | AI99: =$Y$2*I99*Q99 -> 7.18 | AJ99: =AI99+AH99+AG99 -> 258.33333 | AL99: =(R99-86.16)/6*K99 -> 243.97333 | AM99: =$Y$2*K99*Q99 -> 7.18 | AN99: =$Y$2*K99*Q99 -> 7.18 | AO99: =AN99+AM99+AL99 -> 258.33333 | AQ99: =(R99-86.16)/6*M99 -> 243.97333 | AR99: =$Y$2*M99*Q99 -> 7.18 | AS99: =$Y$2*M99*Q99 -> 7.18 | AT99: =AS99+AR99+AQ99 -> 258.33333 | AV99: =(R99-86.16)/6*O99 -> 243.97333 | AW99: =$Y$2*O99*Q99 -> 7.18 | AX99: =$Y$2*O99*Q99 -> 7.18 | AY99: =AX99+AW99+AV99 -> 258.33333 | AZ99: =+AY99+AT99+AO99++AJ99+AE99+Z99 -> 1550 | BA99: =((AZ99-BB99-BC99-BD99-BE99-BF99)+BI99+BJ99+BK99+BL99+BM99+BN99+BO99) -> 1950 | BG99: BONO+B ASIS | BI99: 250 | BJ99: 150
B100: 173 | C100: =C99+1 -> 20 | D100: Villegas Galvan Cristian Jose | E100: 1 | F100: NI | G100: 1 | I100: 1 | K100: 1 | M100: 1 | O100: 1 | Q100: 1 | R100: 2000 | S100: =+BH100 -> 0 | T100: =+BA100 -> 2150 | U100: =+BP100 -> 0 | V100: =+BG100 -> B ASIS | W100: =(R100-86.16)/6*E100 -> 318.97333 | X100: =$Y$2*E100*Q100 -> 7.18 | Y100: =$Y$2*E100*Q100 -> 7.18 | Z100: =Y100+X100+W100 -> 333.33333 | AB100: =(R100-86.16)/6*G100 -> 318.97333 | AC100: =$Y$2*G100*Q100 -> 7.18 | AD100: =$Y$2*G100*Q100 -> 7.18 | AE100: =AD100+AC100+AB100 -> 333.33333 | AG100: =(R100-86.16)/6*I100 -> 318.97333 | AH100: =$Y$2*I100*Q100 -> 7.18 | AI100: =$Y$2*I100*Q100 -> 7.18 | AJ100: =AI100+AH100+AG100 -> 333.33333 | AL100: =(R100-86.16)/6*K100 -> 318.97333 | AM100: =$Y$2*K100*Q100 -> 7.18 | AN100: =$Y$2*K100*Q100 -> 7.18 | AO100: =AN100+AM100+AL100 -> 333.33333 | AQ100: =(R100-86.16)/6*M100 -> 318.97333 | AR100: =$Y$2*M100*Q100 -> 7.18 | AS100: =$Y$2*M100*Q100 -> 7.18 | AT100: =AS100+AR100+AQ100 -> 333.33333 | AV100: =(R100-86.16)/6*O100 -> 318.97333 | AW100: =$Y$2*O100*Q100 -> 7.18 | AX100: =$Y$2*O100*Q100 -> 7.18 | AY100: =AX100+AW100+AV100 -> 333.33333 | AZ100: =+AY100+AT100+AO100++AJ100+AE100+Z100 -> 2000 | BA100: =((AZ100-BB100-BC100-BD100-BE100-BF100)+BI100+BJ100+BK100+BL100+BM100+BN100+BO100) -> 2150 | BG100: B ASIS | BJ100: 150
A101: 489 | E101: =SUM(E81:E100) -> 19 | G101: =SUM(G81:G100) -> 19 | I101: =SUM(I81:I100) -> 19 | K101: =SUM(K81:K100) -> 18 | M101: =SUM(M81:M100) -> 19 | O101: =SUM(O81:O100) -> 19 | AI101: =$Y$2*I101*Q101 -> 0 | AT101: =AS101+AR101+AQ101 -> 0 | BU101: 489
...

Sheet nom
B1: SEMANA DEL 09 AL 15 DE DICIEMBRE DEL 2024 | Y1: REBAJE POR FALTAS
B2: TEJIDO
B3: TURNO1
B4: Responsable de llenado: | R4: Salario | S4: Bono productividad | T4: Bono de asitencia | U4: Bono extra | V4: Primas, finiquitos, etc | W4: otros | X4: Nominal
B5: # EMP | C5: NOMBRE | D5: PUESTO | E5: L | G5: M | I5: M | K5: J | M5: V | O5: S | Q5: D
B6: 234 | C6: Alvarado Avalos Mayra Daniela | D6: Operador | E6: 1 | G6: 1 | I6: 1 | K6: 1 | M6: 1 | R6: 1550 | S6: 300 | T6: 150 | X6: =+R6+S6+T6+U6+V6+W6 -> 2000
B7: 116 | C7: Antunez Orona Juan Manuel | D7: Creeler | E7: 1 | G7: 1 | I7: 1 | K7: 1 | M7: 1 | R7: 1550 | S7: 300 | T7: 150 | X7: =+R7+S7+T7+U7+V7+W7 -> 2000
A8: =A4+1 -> 1 | B8: 2 | C8: Antunez Requejo Gabriela | D8: Calidad | E8: 1 | G8: 1 | I8: 1 | K8: 1 | M8: 1 | R8: 1550 | S8: 300 | T8: 150 | U8: 300 | X8: =+R8+S8+T8+U8+V8+W8 -> 2300
A9: =A70+1 -> 1 | B9: 6 | C9: Balderas Balderas Myriam Ivet | D9: Lider | E9: 1 | G9: 1 | I9: 1 | K9: 1 | M9: 1 | N9: VAC | R9: 3000 | X9: =+R9+S9+T9+U9+V9+W9 -> 3000
A10: 4 | B10: 9 | C10: Bustamante Villegas Osvaldo | D10: Mecanico | E10: 1 | F10: VAC | G10: 1 | I10: 1 | K10: 1 | M10: 1 | R10: 3000 | U10: 250 | X10: =+R10+S10+T10+U10+V10+W10 -> 3250
A11: =#REF!+1 -> #REF! | B11: 95 | C11: Carrillo Delgado Judith | D11: Operador | E11: 1 | G11: 1 | I11: 1 | K11: 1 | M11: 1 | R11: 1550 | S11: 300 | T11: 150 | W11: 200 | X11: =+R11+S11+T11+U11+V11+W11 -> 2200
A12: =A11+1 -> #REF! | B12: 59 | C12: Castro Viaña Mario Ivan | D12: Mecanico | E12: 1 | G12: 1 | I12: 1 | K12: 1 | M12: 1 | R12: 1550 | S12: 300 | T12: 150 | U12: 500 | X12: =+R12+S12+T12+U12+V12+W12 -> 2500
B13: 12 | C13: Diaz Martinez Angela Elizabeth | D13: calidad | E13: 1 | G13: 1 | I13: 1 | K13: 1 | M13: 1 | R13: 1550 | S13: 300 | T13: 150 | U13: 200 | X13: =+R13+S13+T13+U13+V13+W13 -> 2200
B14: 247 | C14: Gomez Mendoza Ruben Dario | D14: Mecanico | E14: 1 | G14: 1 | I14: 1 | K14: 1 | M14: 1 | R14: 10000 | X14: =+R14+S14+T14+U14+V14+W14 -> 10000
B15: 222 | C15: Hernandez de la Rosa Maria Fernanda | D15: Operador | E15: 1 | G15: 1 | I15: 1 | K15: 1 | M15: 1 | R15: 1550 | S15: 300 | T15: 150 | X15: =+R15+S15+T15+U15+V15+W15 -> 2000
B16: 212 | C16: Hernandez Favela Margarita | D16: operador | E16: 1 | G16: 1 | I16: 1 | K16: 1 | M16: 1 | R16: 1550 | S16: 300 | T16: 150 | X16: =+R16+S16+T16+U16+V16+W16 -> 2000
B17: 236 | C17: Martinez Martinez Maria Azucena | D17: Operador | E17: 1 | G17: 1 | I17: 1 | K17: 1 | M17: 1 | R17: 1550 | S17: 300 | T17: 150 | X17: =+R17+S17+T17+U17+V17+W17 -> 2000
A18: =#REF!+1 -> #REF! | B18: 26 | C18: Medrano Suarez Jose Adolfo | D18: Mecanico | E18: 1 | G18: 1 | I18: 1 | K18: 1 | M18: 1 | R18: 2500 | U18: 200 | X18: =+R18+S18+T18+U18+V18+W18 -> 2700
A19: =#REF!+1 -> #REF! | B19: 28 | C19: Moran Hernandez Raul | D19: Mecanico | E19: 1 | G19: 1 | I19: 1 | K19: 1 | M19: 1 | R19: 5000 | X19: =+R19+S19+T19+U19+V19+W19 -> 5000
B20: 205 | C20: Moreno Favela Sonia Gisela | D20: calidad | E20: 0 | F20: F | G20: 1 | I20: 1 | K20: 1 | M20: 1 | R20: 1240 | U20: 200 | X20: =+R20+S20+T20+U20+V20+W20 -> 1440 | Y20: -310
A21: =#REF!+1 -> #REF! | B21: 169 | C21: Ramirez Requejo Maria Guadalupe | D21: operador | E21: 1 | G21: 1 | I21: 1 | K21: 1 | M21: 1 | R21: 1550 | S21: 300 | T21: 150 | X21: =+R21+S21+T21+U21+V21+W21 -> 2000
B22: 237 | C22: Rodriguez Martinez Jose Antonio | D22: Creeler | E22: 1 | G22: 1 | I22: 1 | K22: 1 | M22: 1 | R22: 1550 | S22: 300 | T22: 150 | X22: =+R22+S22+T22+U22+V22+W22 -> 2000
A23: =#REF!+1 -> #REF! | B23: 146 | C23: Salazar Martinez Yohana Cecilia | D23: Operador | E23: 1 | G23: 1 | I23: 1 | K23: 1 | M23: 1 | R23: 1550 | S23: 300 | T23: 150 | X23: =+R23+S23+T23+U23+V23+W23 -> 2000
B24: 217 | C24: Torres Limones Frida Aurora Shikinkira | D24: Operadora | E24: 1 | G24: 1 | I24: 0 | J24: PSG | K24: 0 | L24: PSG | M24: 0 | N24: PSG | R24: 620 | X24: =+R24+S24+T24+U24+V24+W24 -> 620 | Y24: -930
A25: =A23+1 -> #REF! | B25: 51 | C25: Valenzuela Rosales Jose Miguel | D25: Mecanico | E25: 1 | G25: 1 | H25: VAC | I25: 1 | K25: 1 | M25: 1 | R25: 5000 | U25: 1000 | X25: =+R25+S25+T25+U25+V25+W25 -> 6000
B26: 220 | C26: Vargas Torres Pedro | D26: Creeler | E26: 1 | G26: 1 | I26: 1 | K26: 1 | M26: 1 | R26: 1550 | S26: 250 | T26: 150 | X26: =+R26+S26+T26+U26+V26+W26 -> 1950
B27: 249 | C27: Hernandez Gonzalez Elsa | D27: Operador | E27: 0 | F27: B | G27: 0 | H27: B | I27: 0 | J27: B | K27: 0 | L27: B | M27: 0 | N27: B | X27: 0
E28: =SUM(E6:E27) -> 20 | G28: =SUM(G6:G27) -> 21 | I28: =SUM(I6:I27) -> 20 | K28: =SUM(K6:K27) -> 20 | M28: =SUM(M6:M27) -> 20 | O28: =SUM(O6:O27) -> 0 | R28: =SUM(R6:R27) -> 50510 | S28: =SUM(S6:S27) -> 3850 | T28: =SUM(T6:T27) -> 1950 | U28: =SUM(U6:U27) -> 2650 | V28: =SUM(V6:V27) -> 0 | W28: =SUM(W6:W27) -> 200 | X28: =SUM(X6:X27)-Y24-Y20 -> 60400
X29: =F43-X28 -> 0
D30: NOMINA | E30: EXTRA | F30: TOTAL | K30: L | M30: M | O30: M | Q30: J | S30: V | U30: S
B31: 1 | C31: LIDER | D31: =3000*B31 -> 3000 | E31: 0 | F31: =D31 -> 3000 | V31: PROM
B32: 3 | C32: CALIDAD | D32: =1550*B32 -> 4650 | E32: 0 | F32: =D32 -> 4650 | I32: LIDER | K32: 1 | M32: 1 | O32: 1 | Q32: 1 | S32: 1 | U32: 0 | V32: =AVERAGE(K32,M32,O32,Q32,S32) -> 1
B33: 6 | C33: MECANICO | D33: =3000+1550+10000+2500+5000+5000 -> 27050 | E33: 0 | F33: =D33 -> 27050 | I33: CALIDAD | K33: 2 | M33: 3 | O33: 3 | Q33: 3 | S33: 3 | U33: 0 | V33: =AVERAGE(K33,M33,O33,Q33,S33) -> 2.8
B34: 11 | C34: MANUAL | D34: =1550*B34 -> 17050 | E34: 0 | F34: =D34 -> 17050 | I34: MECANICO | K34: 6 | M34: 6 | O34: 6 | Q34: 6 | S34: 6 | U34: 0 | V34: =AVERAGE(K34,M34,O34,Q34,S34) -> 6
I35: MANUAL | K35: 11 | M35: 11 | O35: 10 | Q35: 10 | S35: 10 | U35: 0 | V35: =AVERAGE(K35,M35,O35,Q35,S35) -> 10.4
B36: =SUM(B31:B35) -> 21 | F36: =SUM(F31:F35) -> 51750 | K36: =SUM(K32:K35) -> 20 | M36: =SUM(M32:M35) -> 21 | O36: =SUM(O32:O35) -> 20 | Q36: =SUM(Q32:Q35) -> 20 | S36: =SUM(S32:S35) -> 20 | U36: =SUM(U32:U35) -> 0 | V36: =AVERAGE(K36,M36,O36,Q36,S36) -> 20.2
E37: BONO | F37: =+S28 -> 3850
E38: BONO ASISTENCIA | F38: =+T28 -> 1950
E39: BONOS EXTRA | F39: =+U28 -> 2650
E40: BONO PRODUCCION EXTRA | F40: =W28 -> 200
F43: =SUM(F36:F42) -> 60400
B46: =+B1 -> SEMANA DEL 09 AL 15 DE DICIEMBRE DEL 2024
B47: TURNO 2
B48: Responsable de llenado: | R48: Salario | S48: Bono productividas | T48: Bono de asitencia | U48: Bono extra | V48: Primas, finiquitos, etc | W48: otros | X48: Nominal
B49: # EMP | C49: NOMBRE | D49: PUESTO | E49: L | G49: M | I49: M | K49: J | M49: V | O49: S | Q49: D
A50: 5 | B50: 147 | C50: Alaniz Mayorga Yulissa | D50: operador | E50: 0 | F50: INC | G50: 0 | H50: INC | I50: 0 | J50: INC | K50: 0 | L50: INC | M50: 0 | N50: INC | O50: 0 | R50: 0 | X50: 0
E51: =SUM(E50:E50) -> 0 | F51: =SUM(F50:F50) -> 0 | G51: =SUM(G50:G50) -> 0 | H51: =SUM(H50:H50) -> 0 | I51: =SUM(I50:I50) -> 0 | J51: =SUM(J50:J50) -> 0 | K51: =SUM(K50:K50) -> 0 | L51: =SUM(L50:L50) -> 0 | ... O51: =SUM(O50:O50) -> 0 | R51: =SUM(R50:R50) -> 0 | S51: =SUM(S50:S50) -> 0 | T51: =SUM(T50:T50) -> 0 | U51: =SUM(U50:U50) -> 0 | V51: =SUM(V50:V50) -> 0 | W51: =SUM(W50:W50) -> 0 | X51: =SUM(X50:X50) -> 0
X52: =F62-X51 -> 0
D53: NOMINA | E53: EXTRA | F53: TOTAL
B54: 0 | C54: SUPERVISORA | D54: 0 | E54: 0 | F54: =D54 -> 0 | K54: L | M54: M | O54: M | Q54: J | S54: V | U54: S
B55: 0 | C55: CALIDAD | D55: =1550*B55 -> 0 | E55: 0 | F55: =D55 -> 0 | V55: PROM
B56: 0 | C56: MECANICO | D56: 0 | E56: 0 | F56: =+D56 -> 0 | I56: SUPERVISORA | K56: 0 | M56: 0 | O56: 0 | Q56: 0 | S56: 0 | U56: 0 | V56: =AVERAGE(K56,M56,O56,Q56,S56,U56) -> 0
B57: 0 | C57: MANUAL | D57: =1550*B57 -> 0 | E57: 0 | F57: =D57 -> 0 | I57: CALIDAD | K57: 0 | M57: 0 | O57: 0 | Q57: 0 | S57: 0 | U57: 0 | V57: =AVERAGE(K57,M57,O57,Q57,S57,U57) -> 0
F58: =SUM(F54:F57) -> 0 | I58: MECANICO | K58: 0 | M58: 0 | O58: 0 | Q58: 0 | S58: 0 | U58: 0 | V58: =AVERAGE(K58,M58,O58,Q58,S58,U58) -> 0
B59: =SUM(B54:B58) -> 0 | I59: MANUAL | K59: 0 | M59: 0 | O59: 0 | Q59: 0 | S59: 0 | U59: 0 | V59: =AVERAGE(K59,M59,O59,Q59,S59,U59) -> 0
F60: =W51 -> 0 | K60: =SUM(K56:K59) -> 0 | M60: =SUM(M56:M59) -> 0 | O60: =SUM(O56:O59) -> 0 | Q60: =SUM(Q56:Q59) -> 0 | S60: =SUM(S56:S59) -> 0 | U60: =SUM(U56:U59) -> 0 | V60: =AVERAGE(K60,M60,O60,Q60,S60,U60) -> 0
F61: =+T51 -> 0
F62: =SUM(F58:F61) -> 0
B65: =+B1 -> SEMANA DEL 09 AL 15 DE DICIEMBRE DEL 2024
B66: =+B2 -> TEJIDO
B67: TURNO 3 | R67: Salario | S67: Bono productividas | T67: Bono de asitencia | U67: Bono extra | V67: Primas, finiquitos, etc | W67: otros | X67: Nominal
B68: Responsable de llenado:
B69: # EMP | C69: NOMBRE | D69: PUESTO | E69: L | G69: M | I69: M | K69: J | M69: V | O69: S | Q69: D
B70: 209 | C70: Armijo Mendez Geronimo | D70: Mecanico | X70: 10000 | Y70: FIN 3/3
B71: 208 | C71: Avalos Villegas Chayanne | D71: Mecanico | X71: 5210.66 | Y71: FIN
B72: 251 | C72: Balderas Aguilar Yhair Otoniel | D72: Operador | E72: 1 | G72: 1 | I72: 1 | K72: 1 | M72: 1 | R72: 1550 | S72: 300 | T72: 250 | X72: =+R72+S72+T72+U72+V72+W72 -> 2100
A73: =#REF!+1 -> #REF! | B73: 7 | C73: Beberaje Cruz Ramon Humberto | D73: Mecanico | E73: 1 | G73: 1 | I73: 1 | K73: 1 | M73: 1 | R73: 6000 | X73: =+R73+S73+T73+U73+V73+W73 -> 6000
A74: 1 | B74: 158 | C74: Caballero Coyoc Jose Alberto | D74: Mecanico | E74: 1 | G74: 1 | I74: 1 | K74: 1 | M74: 1 | R74: 6000 | X74: =+R74+S74+T74+U74+V74+W74 -> 6000
B75: 14 | C75: Esquivel Picon Miguel Angel | D75: operador | E75: 1 | G75: 1 | I75: 1 | K75: 1 | M75: 1 | R75: 1550 | S75: 300 | T75: 250 | X75: =+R75+S75+T75+U75+V75+W75 -> 2100
B76: 214 | C76: Gress Padilla Leidy Daniela | D76: Operador | E76: 1 | G76: 1 | I76: 1 | K76: 1 | M76: 1 | R76: 1550 | S76: 300 | T76: 250 | X76: =+R76+S76+T76+U76+V76+W76 -> 2100
B77: 181 | C77: Hernandez Garcia Santa Maria Magdalena | D77: operador | E77: 1 | G77: 1 | I77: 1 | K77: 1 | M77: 1 | R77: 1550 | S77: 300 | T77: 250 | X77: =+R77+S77+T77+U77+V77+W77 -> 2100
B78: 215 | C78: Holguin Salas Hilda Yudit | D78: Operador | E78: 1 | G78: 1 | I78: 0 | J78: F | K78: 0 | L78: PSG | M78: 1 | R78: 1240 | S78: 200 | W78: 300 | X78: =+R78+S78+T78+U78+V78+W78 -> 1740
B79: 223 | C79: Martinez Hernandez Irvin Adolfo | D79: creeler | E79: 0 | F79: SAN | G79: 0 | H79: SAN | I79: 1 | K79: 1 | M79: 1 | R79: 930 | X79: =+R79+S79+T79+U79+V79+W79 -> 930
A80: =#REF!+1 -> #REF! | B80: 91 | C80: Medellin Rodriguez Yesenia Abigail | D80: Operador | E80: 1 | G80: 1 | I80: 1 | K80: 0 | L80: F | M80: 1 | R80: 1240 | X80: =+R80+S80+T80+U80+V80+W80 -> 1240
A81: =A79+1 -> 1 | B81: 27 | C81: Minor Flores Adilene | D81: Calidad | E81: 1 | G81: 1 | I81: 1 | K81: 1 | M81: 1 | R81: 1550 | S81: 300 | T81: 250 | U81: 200 | X81: =+R81+S81+T81+U81+V81+W81 -> 2300
B82: 210 | C82: Padilla Armijo Nancy Lorena | D82: calidad | E82: 1 | G82: 1 | I82: 1 | K82: 1 | M82: 1 | R82: 1550 | S82: 300 | U82: 200 | X82: =+R82+S82+T82+U82+V82+W82 -> 2050
B83: 159 | C83: Perez Suarez Herber Antony | D83: Mecanico | E83: 1 | G83: 1 | I83: 1 | K83: 1 | M83: 1 | R83: 6000 | X83: =+R83+S83+T83+U83+V83+W83 -> 6000
B84: 33 | C84: Ramirez Vital Jose Armando | D84: Operador | E84: 1 | G84: 1 | I84: 1 | K84: 1 | M84: 1 | R84: 1550 | S84: 300 | T84: 250 | W84: 200 | X84: =+R84+S84+T84+U84+V84+W84 -> 2300
B85: 38 | C85: Rodriguez Uribe Edan Ivonne | X85: 3315 | Y85: FIN
B86: 231 | C86: Solis Carranza Efrain | D86: Creeler | E86: 1 | G86: 1 | I86: 1 | K86: 1 | M86: 1 | R86: 1550 | S86: 300 | X86: =+R86+S86+T86+U86+V86+W86 -> 1850
A87: =A91+1 -> 1 | B87: 228 | C87: Tostado Sifuentes Haxel Rodrigo | D87: creeler | E87: 1 | G87: 1 | I87: 1 | K87: 1 | M87: 0 | N87: SAN | R87: 1240 | X87: =+R87+S87+T87+U87+V87+W87 -> 1240
B88: 242 | C88: Villegas Reyes Jesus Maria | D88: Mecanico | E88: 1 | G88: 1 | I88: 1 | K88: 1 | M88: 1 | R88: 2500 | X88: =+R88+S88+T88+U88+V88+W88 -> 2500
B89: 204 | C89: Mendez Reyes Yesica Ivon | D89: operador | E89: 0 | F89: B | G89: 0 | H89: B | I89: 0 | J89: B | K89: 0 | L89: B | M89: 0 | N89: B | X89: 0
E90: =SUM(E70:E88) -> 15 | G90: =SUM(G70:G88) -> 15 | I90: =SUM(I70:I88) -> 15 | K90: =SUM(K70:K88) -> 14 | M90: =SUM(M70:M88) -> 15 | R90: =SUM(R70:R89) -> 37550 | S90: =SUM(S70:S89) -> 2600 | T90: =SUM(T70:T89) -> 1500 | U90: =SUM(U70:U89) -> 400 | V90: =SUM(V70:V89) -> 0 | W90: =SUM(W70:W89) -> 500 | X90: =SUM(X70:X89) -> 61075.66
X91: =F106-X90 -> 0
D92: NOMINA | E92: EXTRA | F92: TOTAL | K92: L | M92: M | O92: M | Q92: J | S92: V | U92: S
B93: 0 | C93: SUPERVISORA | D93: 0 | E93: 0 | F93: =D93 -> 0 | V93: PROM
B94: 2 | C94: CALIDAD | D94: =1550*B94 -> 3100 | E94: 0 | F94: =D94 -> 3100 | I94: SUPERVISOR | K94: 0 | M94: 0 | O94: 0 | Q94: 0 | S94: 0 | U94: 0 | V94: =AVERAGE(K94,M94,O94,Q94,S94) -> 0
B95: 4 | C95: MECANICO | D95: =2500+6000+6000+6000 -> 20500 | E95: 0 | F95: =D95 -> 20500 | I95: CALIDAD | K95: 2 | M95: 2 | O95: 2 | Q95: 2 | S95: 2 | U95: 0 | V95: =AVERAGE(K95,M95,O95,Q95,S95) -> 2
B96: 9 | C96: MANUAL | D96: =1550*B96 -> 13950 | E96: 0 | F96: =D96 -> 13950 | I96: MECANICO | K96: 4 | M96: 4 | O96: 4 | Q96: 4 | S96: 4 | U96: 0 | V96: =AVERAGE(K96,M96,O96,Q96,S96) -> 4
B97: =SUM(B93:B96) -> 15 | F97: =SUM(F93:F96) -> 37550 | I97: MANUAL | K97: 9 | M97: 9 | O97: 9 | Q97: 8 | S97: 9 | U97: 0 | V97: =AVERAGE(K97,M97,O97,Q97,S97) -> 8.8
E98: BONO | F98: =+S90 -> 2600 | K98: =SUM(K94:K97) -> 15 | M98: =SUM(M94:M97) -> 15 | O98: =SUM(O94:O97) -> 15 | Q98: =SUM(Q94:Q97) -> 14 | S98: =SUM(S94:S97) -> 15 | U98: =SUM(U94:U97) -> 0 | V98: =AVERAGE(K98,M98,O98,Q98,S98) -> 14.8
E99: BONO ASISTENCIA | F99: =+T90 -> 1500
E100: BONO EXTRA | F100: =U90 -> 400
E101: BONO PRODUCCION EXTRA | F101: =W90 -> 500
E102: FIN ARMIJO MENDEZ GERONIMO 3/3 | F102: 10000
E103: FIN AVALOS VILLEGAS CHAYANNE | F103: 5210.66
E104: FIN RODRIGUEZ URIBE EDNA IVONNE | F104: 3315
F106: =SUM(F97:F104) -> 61075.66
B109: =+B1 -> SEMANA DEL 09 AL 15 DE DICIEMBRE DEL 2024
...

Sheet Lista 
B2: SEMANA DEL 02 AL 08 DIC DEL 2024 | L2: PARAMETROS A EVALUAR PARA BONO
L3: Deteccion de defectos | M3: limpieza de area | N3: Llenado de formatos | O3: Permisos | P3: Retardos | Q3: BONO
C4: TEJIDO
B5: TURNO1
B6: Responsable de llenado: Myriam Iveth Balderas Balderas
B7: # EMP | C7: NOMBRE | D7: PUESTO | E7: L | F7: M | G7: M | H7: J | I7: V | J7: S | K7: D
A8: 1 | B8: 234 | C8: Alvarado Avalos Mayra Daniela | D8: Operador | E8: A | F8: A | G8: A | H8: A | I8: A
A9: 2 | B9: 116 | C9: Antunez Orona Juan Manuel | D9: Creeler | E9: A | F9: A | G9: A | H9: A | I9: A
A10: 3 | B10: 2 | C10: Antunez Requejo Gabriela | D10: Calidad | E10: A | F10: A | G10: A | H10: A | I10: A
A11: 4 | B11: 6 | C11: Balderas Balderas Myriam Ivet | D11: Lider | E11: A | F11: A | G11: A | H11: A | I11: vac
A12: 5 | B12: 95 | C12: Carrillo Delgado Judith | D12: Operador | E12: A | F12: A | G12: A | H12: A | I12: A
A13: 6 | B13: 12 | C13: Diaz Martinez Angela Elizabeth | D13: calidad | E13: A | F13: A | G13: A | H13: A | I13: A
A14: 7 | B14: 247 | C14: Gomez Mendoza Ruben Dario | D14: Mecanico | E14: A | F14: A | G14: A | H14: A | I14: A
A15: 8 | B15: 222 | C15: Hernandez de la Rosa Maria Fernanda | D15: Operador | E15: A | F15: A | G15: A | H15: A | I15: A
A16: 10 | B16: 236 | C16: Martinez/Martinez Maria Azucena | D16: Operador | E16: A | F16: A | G16: A | H16: A | I16: A
A17: 11 | B17: 26 | C17: Medrano Suarez Jose Adolfo | D17: Mecanico | E17: A | F17: A | G17: A | H17: A | I17: A
A18: 12 | B18: 28 | C18: Moran Hernandez Raul | D18: Mecanico | E18: A | F18: A | G18: A | H18: A | I18: A
A19: 13 | B19: 146 | C19: Salazar Martinez Yohana Cecilia | D19: Operador | E19: A | F19: A | G19: A | H19: A | I19: A
... A22: 16 | B22: 220 | C22: Vargas Torres Pedro | D22: Creeler | E22: A | F22: A | G22: A | H22: A | I22: A
B24: =+B2 -> SEMANA DEL 02 AL 08 DIC DEL 2024 | L24: PARAMETROS A EVALUAR PARA BONO
L25: Deteccion de defectos | M25: limpieza de area | N25: Llenado de formatos | O25: Permisos | P25: Retardos | Q25: BONO
C26: TEJIDO
B27: TURNO1
B28: Responsable de llenado: Myriam Iveth Balderas Balderas
B29: # EMP | C29: NOMBRE | D29: PUESTO | E29: L | F29: M | G29: M | H29: J | I29: V | J29: S | K29: D
A30: 1 | B30: 147 | C30: Alaniz Mayorga Yulissa | D30: OPERADOR | E30: INC | F30: INC | G30: INC | H30: INC | I30: INC | J30: INC
A31: 2 | B31: 132 | C31: Alvarado Ojeda Dulce Violeta | D31: operador | E31: A | F31: A | G31: A | H31: A | I31: A
A32: 3 | B32: 208 | C32: Avalos Villegas Chayanne | D32: Mecanico | E32: A | F32: A | G32: A | H32: A | I32: A
A33: 4 | B33: 7 | C33: Beberaje Cruz Ramon Humberto | D33: Mecanico | E33: A | F33: A | G33: A | H33: A | I33: A
A34: 5 | B34: 225 | C34: Flores Ortiz Elizabeth | D34: operador | E34: B | F34: B | G34: B | H34: B | I34: B
A35: 6 | B35: 70 | C35: Gonzales Lopez Violeta | D35: OPERADOR | E35: SAN | F35: SAN | G35: A | H35: A | I35: A
A36: 7 | B36: 212 | C36: Hernandez Favela Margarita | D36: operador | E36: A | F36: A | G36: A | H36: A | I36: A
A37: 8 | B37: 181 | C37: Hernandez Garcia Santa Maria Magdalena | D37: operador | E37: A | F37: A | G37: A | H37: A | I37: A
A38: 9 | B38: 223 | C38: Martinez Hernandez Irvin Adolfo | D38: creler | E38: SAN | F38: SAN | G38: A | H38: A | I38: A
A39: 10 | B39: 204 | C39: Mendez Reyes Yesica Ivon | D39: calidad | E39: B | F39: B | G39: B | H39: B | I39: B
A40: 11 | B40: 205 | C40: Moreno Favela Sonia Gisela | D40: calidad | E40: A | F40: A | G40: A | H40: A | I40: F
A41: 12 | B41: 169 | C41: Ramirez Requejo Maria Guadalupe | D41: Operador | E41: A | F41: A | G41: A | H41: A | I41: A
A42: 13 | B42: 207 | C42: Silva Moreno Maria guadalupe | D42: operadora | E42: A | F42: A | G42: A | H42: A | I42: A
A43: 14 | B43: 228 | C43: Tostado Sifuentes Haxel Rodrigo | D43: creler | E43: A | F43: A | G43: A | H43: A | I43: SAN
B47: =+B2 -> SEMANA DEL 02 AL 08 DIC DEL 2024 | L47: PARAMETROS A EVALUAR PARA BONO
B48: TEJIDO | L48: Deteccion de defectos | M48: limpieza de area | N48: Llenado de formatos | O48: Permisos | P48: Retardos | Q48: BONO
B49: TURNO 3
B50: Responsable de llenado:Perez Suarez Herber Antony
B51: # EMP | C51: NOMBRE | D51: PUESTO | E51: L | F51: M | G51: M | H51: J | I51: V | J51: S | K51: D
A52: 1 | B52: 209 | C52: Armijo Mendez Geronimo | D52: Mecanico | E52: B | F52: B | G52: B | H52: B | I52: B
A53: 2 | B53: 9 | C53: Bustamante Villegas Osvaldo | D53: Mecanico | E53: vac | F53: A | G53: A | H53: A | I53: A
A54: 3 | B54: 158 | C54: Caballero Coyoc Jose Alberto | D54: Mecanico | E54: A | F54: A | G54: A | H54: A | I54: A
A55: 4 | B55: 14 | C55: Esquivel Picon Miguel Angel | D55: operador | E55: A | F55: A | G55: A | H55: A | I55: A
A56: 5 | B56: 214 | C56: Gress Padilla Leidy Daniela | D56: Operador | E56: A | F56: A | G56: A | H56: A | I56: A
A57: 6 | B57: 215 | C57: Holguin Salas Hilda Yudit | D57: Operador | E57: A | F57: A | G57: F | H57: PSG | I57: A
A58: 7 | B58: 91 | C58: Medellin Rodriguez Yesenia Abigail | D58: Operador | E58: A | F58: A | G58: A | H58: F | I58: A
A59: 8 | B59: 27 | C59: Minor Flores Adilene | D59: Calidad | E59: A | F59: A | G59: A | H59: A | I59: A
A60: 9 | B60: 210 | C60: Padilla Armijo Nancy Lorena | D60: calidad | E60: A | F60: A | G60: A | H60: A | I60: A
A61: 10 | B61: 159 | C61: Perez Suarez Herber Antony | D61: Mecanico | E61: A | F61: A | G61: A | H61: A | I61: A
A62: 11 | B62: 33 | C62: Ramirez Vital Jose Armando | D62: Operador | E62: A | F62: A | G62: A | H62: A | I62: A
A63: 12 | B63: 237 | C63: Rodriguez Martinez Jose Antonio | D63: Criler | E63: A | F63: A | G63: A | H63: A | I63: A
... A65: 16 | B65: 242 | C65: Villegas Reyes Jesus Maria | D65: Mecanico | E65: A | F65: A | G65: A | H65: A | I65: A
B71: =+B2 -> SEMANA DEL 02 AL 08 DIC DEL 2024 | L71: PARAMETROS A EVALUAR PARA BONO
B72: AE | L72: Deteccion de defectos | M72: limpieza de area | N72: Llenado de formatos | O72: Permisos | P72: Retardos | Q72: BONO
B73: TURNO 1
B74: Responsable de llenado:Garcia Nuñez Elizabeth
B75: # EMP | C75: NOMBRE | D75: PUESTO | E75: L | F75: M | G75: M | H75: J | I75: V | J75: S | K75: D
A76: 1 | B76: 166 | C76: Enriquez Gutierrez Acacia | D76: Operadora D | E76: A | F76: A | G76: A | H76: A | I76: A
A77: 2 | B77: 58 | C77: Feria Cruz Carlos Ignacio | D77: Mecanico | E77: A | F77: A | G77: A | H77: A | I77: A
A78: 3 | B78: 19 | C78: Garcia Nuñez Elizabeth | D78: Mecanico | E78: A | F78: A | G78: A | H78: A | I78: VAC
A79: 4 | B79: 39 | C79: Rodriguez Uribe Erika Elizabeth | D79: Calidad | E79: A | F79: A | G79: A | H79: A | I79: A
A80: 5 | B80: 64 | C80: Torres Garcia Xiomara Abigail | D80: Operador | E80: A | F80: A | G80: A | H80: VAC | I80: A
A81: 6 | B81: 141 | C81: Vargas Mendez Ma. Isabel | D81: Operador D | E81: A | F81: A | G81: A | H81: A | I81: A
B87: =+B71 -> SEMANA DEL 02 AL 08 DIC DEL 2024 | L87: PARAMETROS A EVALUAR PARA BONO
B88: AE | L88: Deteccion de defectos | M88: limpieza de area | N88: Llenado de formatos | O88: Permisos | P88: Retardos | Q88: BONO
B89: TURNO 2
B90: Responsable de llenado:Garcia Nuñez Elizabeth
B91: # EMP | C91: NOMBRE | D91: PUESTO | E91: L | F91: M | G91: M | H91: J | I91: V | J91: S | K91: D
A92: 1 | B92: 30 | C92: Pacheco Viaña Jaquelin | D92: Mecanico | E92: A | F92: A | G92: A | H92: A | I92: A | J92: A
A93: 2 | B93: 195 | C93: Ramirez Rodriguez Perla Nohemi | D93: OPERADOR | E93: A | F93: F | G93: A | H93: A | I93: A | J93: A
B97: =+B2 -> SEMANA DEL 02 AL 08 DIC DEL 2024 | L97: PARAMETROS A EVALUAR PARA BONO
L98: Deteccion de defectos | M98: limpieza de area | N98: Llenado de formatos | O98: Permisos | P98: Retardos | Q98: BONO
B99: Responsable de llenado:Hernandez Gonzalez Myrtala
B100: # EMP | C100: NOMBRE | D100: PUESTO | E100: L | F100: M | G100: M | H100: J | I100: V | J100: S | K100: D
A101: 1 | B101: 75 | C101: Flores Miranda Aislen | D101: Operador | E101: A | F101: A | G101: A | H101: A | I101: F
A102: 2 | B102: 74 | C102: Hernandez Gonzalez Myrtala | D102: Operador | E102: A | F102: A | G102: A | H102: A | I102: A
A103: 3 | B103: 29 | C103: Nuñez Viaña Maria del Rosario | D103: Operador | E103: A | F103: A | G103: A | H103: A | I103: A
A104: 4 | B104: 37 | C104: Rodriguez Castillo Rosa Karen | D104: Mecanico | E104: A | F104: A | G104: A | H104: A | I104: A
B108: =+B2 -> SEMANA DEL 02 AL 08 DIC DEL 2024 | L108: PARAMETROS A EVALUAR PARA BONO
B109: PUÑO | L109: Deteccion de defectos | M109: limpieza de area | N109: Llenado de formatos | O109: Permisos | P109: Retardos | Q109: BONO
B110: TURNO 1
B111: Responsable de llenado:Muñoz Rodriguez Susana
B112: # EMP | C112: NOMBRE | D112: PUESTO | E112: L | F112: M | G112: M | H112: J | I112: V | J112: S | K112: D
A113: 1 | B113: 63 | C113: Cuapio Flores Mario | D113: MECANICO | E113: A | F113: A | G113: A | H113: A | I113: A | J113: A
A114: 2 | B114: 73 | C114: Garcia Ortega Leslie Coraima | D114: Calidad | E114: A | F114: A | G114: A | H114: VAC | I114: A | J114: A
A115: 3 | B115: 230 | C115: Llamas Perez Prince Anais | D115: Operador | E115: A | F115: A | G115: A | H115: A | I115: A | J115: A
A116: 4 | B116: 111 | C116: Viaña Dominguez Gladis Nayeli | D116: MECANICO | E116: A | F116: A | G116: A | H116: A | I116: A | J116: A
A117: 5 | B117: 241 | C117: Molina Sifuentes Monserrat Guadalupe | D117: OPERADOR | E117: A | F117: A | G117: A | H117: A | I117: A | J117: A
A118: 6 | B118: 239 | C118: Cardona Perez Rosa Velia | D118: OPERADOR | E118: A | F118: A | G118: A | H118: A | I118: A | J118: A
B120: =+B108 -> SEMANA DEL 02 AL 08 DIC DEL 2024 | L120: PARAMETROS A EVALUAR PARA BONO
B121: PUÑO | L121: Deteccion de defectos | M121: limpieza de area | N121: Llenado de formatos | O121: Permisos | P121: Retardos | Q121: BONO
B122: TURNO 1
B123: Responsable de llenado:Muñoz Rodriguez Susana
B124: # EMP | C124: NOMBRE | D124: PUESTO | E124: L | F124: M | G124: M | H124: J | I124: V | J124: S | K124: D
A125: 1 | B125: 69 | C125: Carranza Hernandez Maria Fernanda | D125: OPERADOR | E125: A | F125: A | G125: A | H125: A | I125: A | J125: A
...

Sheet resumen rh
A6: =+nom!B1 -> SEMANA DEL 09 AL 15 DE DICIEMBRE DEL 2024
A7: =+AVERAGE(C7,E7,G7,I7,K7,M7) -> 16.833333 | C7: =+nom!K36 -> 20 | E7: =+nom!M36 -> 21 | G7: =+nom!O36 -> 20 | I7: =+nom!Q36 -> 20 | K7: =+nom!S36 -> 20 | M7: =+nom!U36 -> 0 | N7: TEJIDO
A8: =+AVERAGE(C8,E8,G8,I8,K8) -> 0 | C8: =+nom!E51 -> 0 | E8: =+nom!G51 -> 0 | G8: =+nom!I51 -> 0 | I8: =+nom!K51 -> 0 | K8: =+nom!M51 -> 0 | M8: =+nom!O51 -> 0 | N8: TEJIDO 2
A9: =+AVERAGE(C9,E9,G9,I9,K9) -> 14.8 | C9: =+nom!K98 -> 15 | E9: =+nom!M98 -> 15 | G9: =+nom!O98 -> 15 | I9: =+nom!Q98 -> 14 | K9: =+nom!S98 -> 15 | M9: =+nom!U98 -> 0 | N9: TEJIDO 3
A10: =+AVERAGE(C10,E10,G10,I10,K10,M10) -> 6 | C10: =+nom!K199 -> 6 | E10: =+nom!M199 -> 6 | G10: =+nom!O199 -> 6 | I10: =+nom!Q199 -> 6 | K10: =+nom!S199 -> 6 | M10: =+nom!U199 -> 6 | N10: PUÑO
A11: =+AVERAGE(C11,E11,G11,I11,K11,M11) -> 7.6666667 | C11: =+nom!K232 -> 7 | E11: =+nom!M232 -> 7 | G11: =+nom!O232 -> 8 | I11: =+nom!Q232 -> 8 | K11: =+nom!S232 -> 8 | M11: =+nom!U232 -> 8 | N11: PUÑO2
A12: =+AVERAGE(C12,E12,G12,I12,K12) -> 4.6 | C12: =+nom!K259 -> 4 | E12: =+nom!M259 -> 4 | G12: =+nom!O259 -> 5 | I12: =+nom!Q259 -> 5 | K12: =+nom!S259 -> 5 | M12: =+nom!U259 -> 0 | N12: PUÑO3
A13: =+AVERAGE(C13,E13,G13,I13,K13) -> 6.8 | C13: =+nom!K129 -> 7 | E13: =+nom!M129 -> 6 | G13: =+nom!O129 -> 7 | I13: =+nom!Q129 -> 7 | K13: =+nom!S129 -> 7 | M13: =+nom!U129 -> 0 | N13: AE
A14: =+AVERAGE(C14,E14,G14,I14,K14) -> 0 | C14: =+nom!K150 -> 0 | E14: =+nom!M150 -> 0 | G14: =+nom!O150 -> 0 | I14: =+nom!Q150 -> 0 | K14: =+nom!S150 -> 0 | M14: =+nom!U150 -> 0 | N14: AE 2
A15: =+AVERAGE(C15,E15,G15,I15,K15) -> 4.8 | C15: =+nom!K174 -> 5 | E15: =+nom!M174 -> 5 | G15: =+nom!O174 -> 5 | I15: =+nom!Q174 -> 5 | K15: =+nom!S174 -> 4 | M15: =+nom!U174 -> 0 | N15: AE 3
A16: =+AVERAGE(C16,E16,G16,I16,K16) -> 11.4 | C16: =+nom!L298 -> 12 | E16: =+nom!N298 -> 12 | G16: =+nom!P298 -> 12 | I16: =+nom!R298 -> 11 | K16: =+nom!T298 -> 10 | M16: 0 | N16: TEJIDO LEON
A17: =+AVERAGE(C17,E17,G17,I17,K17) -> 1 | C17: =+nom!E309 -> 1 | E17: =+nom!G309 -> 1 | G17: =+nom!I309 -> 1 | I17: =+nom!K309 -> 1 | K17: =+nom!M309 -> 1 | M17: =+nom!O309 -> 1 | N17: APOYO LG
A19: =+AVERAGE(C19,E19,G19,I19,K19) -> 77.2 | C19: =SUM(C7:C18) -> 77 | E19: =SUM(E7:E18) -> 77 | G19: =SUM(G7:G18) -> 79 | I19: =SUM(I7:I18) -> 77 | K19: =SUM(K7:K18) -> 76 | M19: =SUM(M7:M18) -> 15 | N19: TOT

Sheet CHECADAS
A1: Nominas
A2: N+A2:N48umero | B2: NombreCompleto | C2: FechaInicio | D2: FechaFin | E2: L.Entrada | F2: L.Salida | G2: MA.Entrada | H2: MA.Salida | I2: MI.Entrada | J2: MI.Salida | K2: J.Entrada | L2: J.Salida | M2: V.Entrada | N2: V.Salida | O2: S.Entrada | P2: S.Salida | Q2: D.Entrada | R2: D.Salida
A3: 107 | B3: SAMUEL CHAVARRIA MACHADO | C3: 2024-12-09 | D3: 2024-12-15 | E3: 15:31:00 | F3: 0.98003472 | G3: 15:33:00 | H3: 0.98616898 | I3: 15:22:00 | J3: 0.97959491 | K3: 15:28:00 | L3: 11:35:36 p. m. | M3: 15:26:00 | N3: 0.98320602 | O3: 15:29:00 | P3: 08:33:01 p. m.
A4: 111 | B4: GLADIS NAYELI VIAÑA DOMINGUEZ | C4: 2024-12-09 | D4: 2024-12-15 | E4: 07:26:00 | F4: 15:31:00 | G4: 07:29:00 | H4: 15:31:00 | I4: 07:29:00 | J4: 03:29:14 p. m. | K4: 07:32:00 | L4: 15:34:00 | M4: 07:32:00 | N4: 15:30:00 | O4: 07:28:00
A5: 116 | B5: JUAN MANUEL ANTUNEZ ORONA | C5: 2024-12-09 | D5: 2024-12-15 | E5: 07:29:00 | F5: 17:02:00 | G5: 07:36:00 | H5: 17:02:00 | I5: 07:31:00 | J5: 17:01:00 | K5: 07:31:00 | L5: 16:59:00 | M5: 07:34:00 | N5: 17:00:00
A6: 12 | B6: ANGELA ELIZABETH DIAZ MARTINEZ | C6: 2024-12-09 | D6: 2024-12-15 | E6: 07:17:00 | F6: 0.70957176 | G6: 0.30185185 | H6: 0.70961806 | I6: 07:18:00 | J6: 0.70797454 | K6: 07:27:00 | L6: 04:57:20 p. m. | M6: 0.30197917 | N6: 04:55:13 p. m.
A7: 135 | B7: SUGEY MARISOL MARTINEZ ROSALES | C7: 2024-12-09 | D7: 2024-12-15 | E7: 11:32:58 p. m. | F7: 07:33:36 a. m. | G7: 0.98303241 | H7: 07:33:49 a. m. | I7: 0.98252315 | J7: 0.31326389 | K7: 0.98013889 | L7: 0.31391204 | M7: 11:38:13 p. m. | N7: 0.31340278
A8: 14 | B8: MIGUEL ANGEL ESQUIVEL PICON | C8: 2024-12-09 | D8: 2024-12-15 | E8: 0.96398148 | F8: 07:32:00 | G8: 0.96053241 | H8: 07:32:00 | I8: 0.96232639 | J8: 07:36:00 | K8: 0.96474537 | L8: 07:32:00 | M8: 11:07:30 p. m. | N8: 07:31:00
A9: 141 | B9: MA. ISABEL VARGAS MENDEZ | C9: 2024-12-09 | D9: 2024-12-15 | E9: 07:25:00 | F9: 17:00:00 | G9: 07:25:00 | H9: 17:02:00 | I9: 07:25:00 | J9: 17:00:00 | K9: 07:25:00 | L9: 17:01:00 | M9: 07:25:00 | N9: 17:00:00
A10: 1446 | B10: SAUL BAUTISTA REVUELTAS | C10: 2024-12-09 | D10: 2024-12-15
A11: 146 | B11: YOHANA CECILIA SALAZAR MARTINEZ | C11: 2024-12-09 | D11: 2024-12-15 | E11: 07:25:00 | F11: 0.70924769 | G11: 07:23:00 | H11: 0.70983796 | I11: 07:21:00 | J11: 05:00:59 p. m. | K11: 07:24:00 | L11: 0.70633102 | M11: 07:22:00 | N11: 0.70596065
A12: 147 | B12: YULISSA ALANIZ MAYORGA | C12: 2024-12-09 | D12: 2024-12-15 | E12: inc | G12: inc | I12: inc | K12: inc | M12: inc
A13: 158 | B13: JOSE ALBERTO CABALLERO COYOC | C13: 2024-12-09 | D13: 2024-12-15 | E13: 0.98157407 | F13: 07:32:00 | G13: 0.97608796 | I13: 0.97109954 | J13: 07:33:00 | K13: 0.97957176 | L13: 07:34:00 | M13: 0.97413194 | N13: 07:30:00
A14: 159 | B14: HERBER ANTONY PEREZ SUAREZ | C14: 2024-12-09 | D14: 2024-12-15 | E14: 0.96412037 | F14: 07:30:00 | G14: 0.96040509 | H14: 07:34:00 | I14: 0.96165509 | J14: 07:39:00 | K14: 0.96366898 | L14: 07:38:00 | M14: 11:05:57 p. m. | N14: 07:30:00
A15: 165 | B15: DIEGO FRANCO ALATORRE | C15: 2024-12-09 | D15: 2024-12-15
A16: 166 | B16: ACACIA ENRIQUEZ GUTIERREZ | C16: 2024-12-09 | D16: 2024-12-15 | E16: 07:25:00 | F16: 05:00:39 p. m. | G16: 07:25:00 | H16: 0.7100463 | I16: 07:25:00 | J16: 05:00:48 p. m. | K16: 07:25:00 | L16: 05:01:37 p. m. | M16: 07:25:00 | N16: 0.70869213
A17: 169 | B17: MARIA GUADALUPE RAMIREZ REQUEJO | C17: 2024-12-09 | D17: 2024-12-15 | E17: 07:32:00 | F17: 17:02:00 | G17: 07:36:00 | H17: 17:02:00 | I17: 07:30:00 | J17: 17:00:00 | K17: 07:26:00 | L17: 0.70795139 | M17: 07:27:00 | N17: 17:00:00
A18: 172 | B18: MARIA ELENA HERNANDEZ CAMPISTA | C18: 2024-12-09 | D18: 2024-12-15 | E18: 0.2852662 | F18: 0.68082176 | G18: 06:50:11 a. m. | H18: 04:21:10 p. m. | I18: 06:47:03 a. m. | J18: 0.68109954 | K18: vac | M18: vac
A19: 181 | B19: SANTA MARIA MAGDALENA HERNANDEZ GARCIA | C19: 2024-12-09 | D19: 2024-12-15 | E19: 11:19:22 p. m. | F19: 07:30:00 | G19: 11:25:27 p. m. | H19: 07:21:00 | I19: 0.97550926 | J19: 07:31:00 | K19: 0.97516204 | L19: 07:25:00 | M19: 0.97255787 | N19: 07:30:00
A20: 19 | B20: ELIZABETH GARCIA NUÑEZ | C20: 2024-12-09 | D20: 2024-12-15 | E20: 07:32:00 | F20: 17:01:00 | G20: 07:31:00 | H20: 17:03:00 | I20: 07:34:00 | J20: 17:01:00 | K20: 07:37:00 | L20: 17:03:00
A21: 195 | B21: PERLA NOHEMI FLORES ORTIZ | C21: 2024-12-09 | D21: 2024-12-15 | E21: 0.31259259 | F21: 0.70931713 | G21: falta | I21: 0.31758102 | J21: 0.70891204 | K21: 0.31949074 | L21: 0.70987269 | M21: 0.31890046 | N21: 0.71012731
A22: 2 | B22: GABRIELA ANTUNEZ REQUEJO | C22: 2024-12-09 | D22: 2024-12-15 | E22: 07:31:00 | G22: 07:30:00 | H22: 0.71023148 | I22: 07:28:00 | J22: 05:01:42 p. m. | K22: 07:26:00 | L22: 05:02:16 p. m. | M22: 07:32:00 | N22: 0.71017361
A23: 205 | B23: SONIA GISELA MORENO FAVELA | C23: 2024-12-09 | D23: 2024-12-15 | E23: falta | G23: 0.31716435 | H23: 0.71064815 | I23: 07:35:58 a. m. | J23: 0.70940972 | L23: 0.70773148 | M23: 07:29:30 a. m. | N23: 03:32:02 p. m.
A24: 207 | B24: MARIA GUADALUPE SILVA MORENO | C24: 2024-12-09 | D24: 2024-12-15 | E24: 0.64784722 | F24: 11:31:43 p. m. | G24: 0.64528935 | H24: 11:32:46 p. m. | I24: 03:24:40 p. m. | J24: 11:30:58 p. m. | K24: 0.64511574 | L24: 0.98184028 | M24: 0.64704861 | N24: 0.97966435 | O24: 03:32:17 p. m. | P24: 0.85719907
A25: 210 | B25: NANCY LORENA PADILLA ARMIJO | C25: 2024-12-09 | D25: 2024-12-15 | E25: 0.98703704 | F25: 0.31706019 | G25: 11:39:51 p. m. | H25: 0.32371528 | I25: 11:37:08 p. m. | J25: 07:35:15 a. m. | K25: 0.98784722 | L25: 0.31966435 | M25: 0.98813657 | N25: 0.31287037
A26: 212 | B26: MARGARITA HERNANDEZ FAVELA | C26: 2024-12-09 | D26: 2024-12-15 | E26: 0.31071759 | F26: 05:00:24 p. m. | G26: 0.3140625 | H26: 05:01:56 p. m. | I26: 0.31163194 | J26: 0.70916667 | K26: 0.31234954 | L26: 0.70777778 | M26: 07:26:55 a. m. | N26: 0.70887731
A27: 214 | B27: LEIDY DANIELA GRESS PADILLA | C27: 2024-12-09 | D27: 2024-12-15 | E27: 0.97842593 | F27: 07:31:00 | G27: 0.97474537 | H27: 07:32:00 | I27: 11:23:05 p. m. | J27: 07:31:00 | K27: 0.97596065 | L27: 07:31:00 | M27: 0.97392361 | N27: 07:30:00
A28: 215 | B28: HILDA YUDITH HOLGUIN SALAS | C28: 2024-12-09 | D28: 2024-12-15 | G28: 11:27:59 p. m. | H28: 07:31:00 | M28: 0.9791088 | N28: 07:30:00
A29: 216 | B29: JAVIER ARMANDO ANTUNEZ ROMERO | C29: 2024-12-09 | D29: 2024-12-15 | E29: 07:46:00 | F29: 01:06:02 p. m. | G29: 07:20:00 | H29: 05:39:35 p. m. | I29: 07:48:00 | J29: 0.70979167 | K29: 07:37:00 | L29: 03:31:25 p. m. | M29: falta
A30: 217 | B30: FRIDA AURORA TORRES LIMONES | C30: 2024-12-09 | D30: 2024-12-15 | E30: 07:11:28 a. m. | F30: 0.70868056 | G30: 0.29376157 | H30: 0.62751157 | I30: psg | K30: psg | M30: psg
A31: 220 | B31: PEDRO VARGAS TORRES | C31: 2024-12-09 | D31: 2024-12-15 | E31: 07:28:00 | G31: 07:29:00 | H31: 05:02:36 p. m. | I31: 07:30:00 | J31: 0.70954861 | K31: 07:29:00 | L31: 04:59:36 p. m. | M31: 07:30:00 | N31: 0.70883102
A32: 222 | B32: MARIA FERNANDA HERNANDEZ DE LA ROSA | C32: 2024-12-09 | D32: 2024-12-15 | E32: 07:38:00 | F32: 0.70865741 | G32: 07:37:00 | H32: 0.70971065 | I32: 07:38:00 | J32: 0.70975694 | K32: 07:21:00 | L32: 04:59:15 p. m. | M32: 07:22:00 | N32: 0.70877315
A33: 223 | B33: IRVIN ADOLFO MARTINEZ HERNANDEZ | C33: 2024-12-09 | D33: 2024-12-15 | E33: sanc | G33: san | I33: 0.97444444 | J33: 07:37:08 a. m. | K33: 11:24:10 p. m. | L33: 0.31252315 | M33: 0.97261574 | N33: 0.31376157
A34: 226 | B34: JOSE URIEL MORENO MARTINEZ | C34: 2024-12-09 | D34: 2024-12-15 | E34: 15:31:00 | F34: 0.98065972 | G34: 15:34:00 | H34: 0.98079861 | I34: 15:22:00 | J34: 0.97987269 | K34: 15:29:00 | L34: 0.97987269 | M34: 15:26:00 | N34: 0.98028935 | O34: 15:30:00 | P34: 0.85783565
A35: 227 | B35: JOSE LUIS MARTINEZ ROSALES | C35: 2024-12-09 | D35: 2024-12-15 | E35: 11:33:01 p. m. | F35: 07:32:00 | G35: 0.98306713 | H35: 07:33:00 | I35: 0.98244213 | J35: 07:31:00 | K35: 0.98017361 | L35: 07:32:00 | M35: 0.98421296 | N35: 07:31:00 | O35: 0.98163194
A36: 228 | B36: HAXEL RODRIGO TOSTADO SIFUENTES | C36: 2024-12-09 | D36: 2024-12-15 | E36: 0.97766204 | F36: 0.31334491 | G36: 0.9828125 | H36: 0.31461806 | I36: 11:30:40 p. m. | J36: 0.31315972 | K36: 11:27:24 p. m. | L36: 0.31489583 | M36: san
A37: 230 | B37: PRINCE ANAIS LLAMAS PEREZ | C37: 2024-12-09 | D37: 2024-12-15 | E37: 0.30128472 | F37: 0.64645833 | G37: 07:20:00 | H37: 0.64643519 | I37: 07:16:00 | J37: 03:30:09 p. m. | K37: 07:15:00 | L37: 0.69238426 | M37: 07:21:00 | N37: 0.64658565 | O37: 07:45:00 | P37: 0.64797454
A38: 231 | B38: EFRAIN SOLIS CARRANZA | C38: 2024-12-09 | D38: 2024-12-15 | E38: 0.99008102 | F38: 07:31:00 | G38: 0.98799769 | H38: 07:33:00 | I38: 0.99005787 | J38: 07:30:00 | K38: 0.98708333 | L38: 07:33:00 | M38: 0.0023263889 | N38: 07:30:00
A39: 232 | B39: NORMA CECILIA GONZALEZ OJEDA | C39: 2024-12-09 | D39: | | E39: 15:31:00 | F39: 0.98059028 | G39: 15:29:00 | H39: 0.98113426 | I39: 15:24:00 | J39: 0.97954861 | K39: 15:28:00 | L39: 0.98179398 | M39: 15:31:00 | N39: 0.97950231 | O39: 15:32:00 | P39: 0.85773148
A40: 237 | B40: JOSE ANTONIO RODRIGUEZ MARTINEZ | C40: 2024-12-09 | D40: 2024-12-15 | E40: 0.31519676 | F40: 0.70946759 | G40: 0.31231481 | H40: 05:02:40 p. m. | I40: 0.31422454 | J40: 0.70927083 | K40: 07:29:44 a. m. | L40: 07:32:00 | N40: 0.70857639
A41: 241 | B41: MONSERRAT GUADALUPE MOLINA SIFUENTES | C41: 2024-12-09 | D41: 2024-12-15 | E41: 0.29824074 | F41: 0.64665509 | G41: 0.30168981 | H41: 0.64707176 | I41: 0.29952546 | J41: 0.64533565 | K41: 07:06:43 a. m. | L41: 0.64880787 | M41: 0.29858796 | N41: 0.64634259 | O41: 0.29332176 | P41: 0.64769676
A42: 242 | B42: JESUS MARIA VILLEGAS REYES | C42: 2024-12-09 | D42: 2024-12-15 | E42: 0.97438657 | F42: 07:30:10 a. m. | G42: 11:24:46 p. m. | H42: 0.31584491 | I42: 0.97724537 | J42: 0.32092593 | K42: 11:20:15 p. m. | L42: 0.31834491 | M42: 11:30:33 p. m. | N42: 07:30:15 a. m.
A43: 26 | B43: JOSE ADOLFO MEDRANO SUAREZ | C43: 2024-12-09 | D43: 2024-12-15 | E43: 07:22:00 | F43: 17:00:00 | G43: 07:20:00 | H43: 17:02:00 | I43: 07:19:00 | J43: 17:01:00 | K43: 07:21:00 | L43: 17:06:00 | M43: 07:20:00 | N43: 17:00:00
A44: 27 | B44: ADILENE MINOR FLORES | C44: 2024-12-09 | D44: 2024-12-15 | E44: 0.97111111 | F44: 07:32:00 | G44: 0.9722338 | H44: 07:33:00 | I44: 11:17:39 p. m. | J44: 07:37:00 | K44: 0.97686343 | L44: 07:32:00 | M44: 11:19:00 p. m. | N44: 07:35:00
A45: 28 | B45: RAUL MORAN HERNANDEZ | C45: 2024-12-09 | D45: 2024-12-15 | E45: 0.30321759 | F45: 0.70849537 | G45: 0.30675926 | H45: 07:17:00 | I45: 05:02:33 p. m. | J45: 07:19:00 | K45: 0.70957176 | L45: 07:19:00 | M45: 0.70844907
A46: 29 | B46: MARIA DEL ROSARIO NUÑEZ VIAÑA | C46: 2024-12-09 | D46: 2024-12-15 | E46: 0.96877315 | F46: 07:31:00 | G46: 0.97726852 | H46: 07:32:00 | I46: 0.97584491 | J46: 07:36:00 | K46: 0.97290509 | L46: 07:32:00 | M46: 0.97305556 | N46: 07:30:00
A47: 30 | B47: JAQUELINE PACHECO VIAÑA | C47: 2024-12-09 | D47: 2024-12-15 | E47: 07:30:00 | F47: 17:01:00 | G47: 07:40:00 | H47: 17:02:00 | I47: 07:37:00 | J47: 17:01:00 | K47: 07:40:00 | L47: 17:04:00 | M47: 07:39:00 | N47: 17:05:00
A48: 32 | B48: JOSE ALEJANDRO RAMIREZ FLORES | C48: 2024-12-09 | D48: 2024-12-15 | E48: 07:20:00 | F48: 17:02:00 | G48: 07:17:00 | H48: 0.7065625 | I48: 07:23:00 | J48: 04:56:42 p. m. | K48: 07:20:00 | L48: 0.70248843 | M48: 07:23:00 | N48: 17:33:00
A49: 33 | B49: JOSE ARMANDO RAMIREZ VITAL | C49: 2024-12-09 | D49: 2024-12-15 | E49: 11:10:43 p. m. | F49: 07:35:00 | G49: 0.97238426 | H49: 07:41:00 | I49: 0.9702662 | J49: 07:37:00 | K49: 0.97747685 | L49: 07:35:00 | M49: 0.97165509 | N49: 07:43:00
A50: 34 | B50: NOE REQUEJO HERNANDEZ | C50: 2024-12-09 | D50: 2024-12-15 | E50: 07:47:00 | F50: 0.69730324 | G50: 07:59:00 | H50: 0.69730324 | I50: 0.35075231 | J50: 0.70644676 | K50: 08:16:58 a. m. | L50: 04:50:20 p. m. | M50: 0.33667824 | N50: 0.78298611 | O50: 0.7571875
A51: 35 | B51: JOSE EMILIO REYES CHAVARRIA | C51: 2024-12-09 | D51: 2024-12-15 | E51: 07:43:00 | G51: 07:55:00 | I51: 07:28:00 | K51: 07:47:00 | M51: 07:46:00 | O51: 07:50:00 | Q51: 07:49:00
A52: 37 | B52: ROSA KAREN RODRIGUEZ CASTILLO | C52: 2024-12-09 | D52: 2024-12-15 | E52: 0.97135417 | F52: 0.31619213 | G52: 0.97243056 | H52: 0.97591435 | I52: 07:45:38 a. m. | J52: 0.97244213 | K52: 07:45:00 | L52: 0.97244213 | M52: 07:35:00 | N52: 0.97123843 | O52: 07:30:00
A53: 39 | B53: ERIKA ELIZABETH RODRIGUEZ URIBE | C53: 2024-12-09 | D53: 2024-12-15 | E53: 07:39:00 | F53: 17:00:00 | G53: 07:30:00 | H53: 17:02:00 | I53: 07:16:00 | J53: 16:59:00 | K53: 07:21:00 | L53: 17:02:00 | M53: 07:22:00 | N53: 17:00:00
A54: 41 | B54: ANA LILIANA SALAZAR HOLGUIN | C54: 2024-12-09 | D54: 2024-12-15 | E54: 0.33893519 | F54: 0.69736111 | G54: 07:55:00 | H54: 0.71662037 | I54: 07:52:00 | J54: 04:52:24 p. m. | K54: 0.34628472 | L54: 05:07:30 p. m. | M54: 08:05:00 a. m. | N54: 0.71203704
A55: 45 | B55: MIGUEL ANGEL SANCHEZ FLORES | C55: 2024-12-09 | D55: 2024-12-15 | E55: 23:25:00 | F55: 07:39:00 | G55: 23:33:00 | H55: 07:40:00 | I55: 23:26:00 | J55: 07:32:00 | K55: 23:30:00 | L55: 07:48:00 | M55: 23:30:00 | N55: 07:35:00
A56: 51 | B56: JOSE MIGUEL VALENZUELA ROSALES | C56: 2024-12-09 | D56: 2024-12-15 | E56: 0.28219907 | F56: 0.70885417 | G56: 07:29:00 | I56: VAC | K56: 07:31:00 | L56: 04:59:03 p. m. | M56: 07:32:00 | N56: 0.70758102
A57: 58 | B57: CARLOS IGNACIO FERIA CRUZ | C57: 2024-12-09 | D57: 2024-12-15 | E57: 0.32538194 | G57: 07:42:00 | H57: 17:03:00 | I57: 07:44:00 | J57: 17:01:00 | K57: 07:26:00 | L57: 17:04:00 | M57: 07:33:00 | N57: 17:05:00
A58: 59 | B58: MARIO IVAN CASTRO VIAÑA | C58: 2024-12-09 | D58: 2024-12-15 | E58: 07:21:00 | G58: 07:22:00 | H58: 17:02:00 | I58: 07:18:00 | J58: 17:01:00 | K58: 07:20:00 | L58: 17:01:00 | M58: 07:20:00 | N58: 17:00:00
A59: 6 | B59: MYRIAM IVET BALDERAS BALDERAS | C59: 2024-12-09 | D59: 2024-12-15 | E59: 07:31:00 | F59: 0.70795139 | G59: 07:33:00 | H59: 0.70827546 | I59: 07:36:00 | J59: 0.70958333 | K59: 07:37:00 | L59: 05:03:16 p. m. | M59: VAC
A60: 63 | B60: MARIO CUAPIO FLORES | C60: 2024-12-09 | D60: 2024-12-15 | E60: 07:43:00 | F60: 16:11:00 | G60: 07:39:00 | I60: 07:41:00 | K60: 07:32:00 | M60: 07:37:00
A61: 64 | B61: XIOMARA ABIGAIL TORRES GARCIA | C61: 2024-12-09 | D61: 2024-12-15 | E61: 0.30122685 | F61: 17:00:00 | G61: 07:20:00 | H61: 17:02:00 | I61: 07:16:00 | J61: 17:01:00 | K61: VAC | M61: 07:21:00
A62: 69 | B62: MARIA FERNANDA CARRANZA HERNANDEZ | C62: 2024-12-09 | D62: 2024-12-15 | E62: 0.64630787 | F62: 0.98027778 | G62: 15:37:00 | H62: 11:32:27 p. m. | I62: 15:32:00 | J62: 0.97979167 | K62: 11:33:17 p. m. | L62: 03:31:10 p. m. | M62: 15:31:00 | N62: 0.98020833 | O62: 15:36:00 | P62: 0.85762731
A63: 7 | B63: RAMON HUMBERTO BEBERAJE CRUZ | C63: 2024-12-09 | D63: 2024-12-15 | E63: 0.96637731 | F63: 07:31:43 a. m. | G63: 0.96043981 | H63: 0.31445602 | I63: 0.9628125 | J63: 0.31489583 | K63: 0.96428241 | L63: 0.31293981 | M63: 11:05:54 p. m.
A64: 70 | B64: VIOLETA GONZALEZ LOPEZ | C64: 2024-12-09 | D64: 2024-12-15 | E64: SANC | G64: SANC | J64: 23:19:00 | K64: 07:31:03 a. m. | L64: 23:31:00 | M64: 0.31386574
A65: 73 | B65: LESLIE CORAIMA GARCIA ORTEGA | C65: 2024-12-09 | D65: 2024-12-15 | E65: 07:13:00 | F65: 0.64653935 | G65: 07:20:00 | H65: 0.64711806 | I65: 07:16:00 | J65: 0.6452662 | K65: 0.30646991 | L65: 0.64652778 | M65: VAC | O65: 07:09:00 | P65: 0.6478125
A66: 74 | B66: MYRTALA HERNANDEZ GONZALEZ | C66: 2024-12-09 | D66: 2024-12-15 | E66: VAC | G66: 0.97797454 | H66: 07:32:00 | I66: VAC | K66: VAC | M66: 0.9790625 | N66: 07:30:00
A67: 75 | B67: AILEN FLORES MIRANDA | C67: 2024-12-09 | D67: 2024-12-15 | E67: 0.98074074 | F67: 07:33:00 | G67: 0.97748843 | H67: 07:31:00 | I67: 0.97634259 | J67: 07:36:00 | K67: 11:27:20 p. m. | L67: 07:31:00 | M67: falta
A68: 82382 | B68: MONSERRAT NUÑEZ MARTINEZ | C68: 2024-12-09 | D68: 2024-12-15
A69: 82497 | B69: CATALINA ACEVEDO CAMACHO | C69: 2024-12-09 | D69: 2024-12-15 | H69: 07:57:00 | J69: 07:31:00
A70: 82589 | B70: GABRIELA LIZBETH LOZANO GUILLEN | C70: 2024-12-09 | D70: 2024-12-15
A71: 89 | B71: MARIA GUADALUPE HERNANDEZ FLORES | C71: 2024-12-09 | D71: 2024-12-15 | E71: 07:37:00 | F71: 0.63821759 | G71: 07:40:00 | H71: 0.71399306 | I71: 07:44:00 | J71: 0.70965278 | K71: 07:44:00 | L71: 0.70615741 | M71: 07:44:00 | N71: 0.70614583
A72: 9 | B72: OSVALDO BUSTAMANTE VILLEGAS | C72: 2024-12-09 | D72: 2024-12-15 | E72: VAC | G72: 0.30626157 | H72: 0.7097338 | I72: 0.30357639 | J72: 0.70909722 | K72: 07:22:03 a. m. | L72: 05:01:44 p. m. | M72: 0.30741898 | N72: 05:00:04 p. m.
A73: 91 | B73: YESENIA ABIGAIL MEDILLIN RODRIGUEZ | C73: 2024-12-09 | D73: 2024-12-15 | E73: 0.96616898 | F73: 07:33:00 | G73: 0.97226852 | H73: 07:41:00 | I73: 0.97015046 | J73: 07:38:00 | K73: falta | M73: 11:19:21 p. m.
A74: 94 | B74: JESUS ALBERTO DOMINGUEZ SOTO | C74: 2024-12-09 | D74: 2024-12-15 | E74: 23:08:00 | F74: 07:39:00 | G74: 23:05:00 | H74: 07:41:00 | I74: 23:07:00 | J74: 07:32:00 | K74: 23:04:00 | L74: 07:48:00 | M74: 23:08:00 | N74: 07:39:00
A75: 95 | B75: JUDITH CARRILLO DELGADO | C75: 2024-12-09 | D75: 2024-12-15 | E75: 07:30:00 | F75: 0.7096412 | G75: 07:26:00 | H75: 0.71033565 | I75: 07:33:00 | J75: 0.70923611 | K75: 07:27:00 | L75: 0.70798611 | M75: 07:26:00 | N75: 0.70586806
A76: 97 | B76: MARISA ISABEL BURCIAGA AGUIRRE | C76: 2024-12-09 | D76: 2024-12-15 | E76: 0.3600463 | F76: 0.69728009 | G76: 0.35652778 | H76: 17:13:00 | I76: 0.36590278 | J76: 0.70559028 | K76: 0.3558912 | L76: 17:07:00 | M76: 0.35084491 | N76: 17:05:00

Sheet REPORTE
A1: Date | B1: Device ID | C1: Device | D1: User Group | E1: User | F1: Event
A2: 45641.979 | B2: 542361075 | C2: FaceStation 2 542361075 (192.168.50.204) | D2: All Users | E2: 45 | F2: 1:N authentication succeeded (Face)
A3: 45641.967 | B3: 542361075 | C3: FaceStation 2 542361075 (192.168.50.204) | D3: All Users | E3: 94 | F3: 1:N authentication succeeded (Face)
A4: 45641.757 | B4: 542361075 | C4: FaceStation 2 542361075 (192.168.50.204) | D4: All Users | E4: 34 | F4: 1:N authentication succeeded (Face)
A5: 45641.754 | B5: 542361075 | C5: FaceStation 2 542361075 (192.168.50.204) | F5: DHCP connected
A6: 45641.752 | B6: 542361075 | C6: FaceStation 2 542361075 (192.168.50.204) | F6: DHCP connected
A7: 45641.752 | B7: 542361075 | C7: FaceStation 2 542361075 (192.168.50.204) | F7: Network connected
A8: 45641.752 | B8: 542361075 | C8: FaceStation 2 542361075 (192.168.50.204) | F8: Network disconnected
A9: 45641.752 | B9: 542361075 | C9: FaceStation 2 542361075 (192.168.50.204) | F9: Network connected
A10: 45641.752 | B10: 542361075 | C10: FaceStation 2 542361075 (192.168.50.204) | F10: Network disconnected
A11: 45641.752 | B11: 542361075 | C11: FaceStation 2 542361075 (192.168.50.204) | F11: Tamper off
A12: 45641.752 | B12: 542361075 | C12: FaceStation 2 542361075 (192.168.50.204) | F12: DHCP connected
A13: 45641.752 | B13: 542361075 | C13: FaceStation 2 542361075 (192.168.50.204) | F13: Device started
A14: 45641.752 | B14: 542361075 | C14: FaceStation 2 542361075 (192.168.50.204) | F14: Network connected
A15: 45641.746 | B15: 542361075 | C15: FaceStation 2 542361075 (192.168.50.204) | F15: Tamper off
A16: 45641.746 | B16: 542361075 | C16: FaceStation 2 542361075 (192.168.50.204) | F16: DHCP connected
... A18: 45641.746 | B18: 542361075 | C18: FaceStation 2 542361075 (192.168.50.204) | F18: Network connected
A19: 45641.688 | B19: 542361075 | C19: FaceStation 2 542361075 (192.168.50.204) | D19: All Users | E19: 34 | F19: 1:N authentication succeeded (Face)
A20: 45641.556 | B20: 542361075 | C20: FaceStation 2 542361075 (192.168.50.204) | F20: Tamper off
A21: 45641.556 | B21: 542361075 | C21: FaceStation 2 542361075 (192.168.50.204) | F21: DHCP connected
A22: 45641.556 | B22: 542361075 | C22: FaceStation 2 542361075 (192.168.50.204) | F22: Device started
A23: 45641.556 | B23: 542361075 | C23: FaceStation 2 542361075 (192.168.50.204) | F23: Network connected
A24: 45641.504 | B24: 542361075 | C24: FaceStation 2 542361075 (192.168.50.204) | D24: All Users | E24: 63 | F24: 1:N authentication succeeded (Face)
A25: 45641.326 | B25: 542361075 | C25: FaceStation 2 542361075 (192.168.50.204) | D25: All Users | E25: 35 | F25: 1:N authentication succeeded (Face)
A26: 45641.324 | B26: 542361075 | C26: FaceStation 2 542361075 (192.168.50.204) | D26: All Users | E26: 94 | F26: 1:N authentication succeeded (Face)
A27: 45641.324 | B27: 542361075 | C27: FaceStation 2 542361075 (192.168.50.204) | D27: All Users | E27: 45 | F27: 1:N authentication succeeded (Face)
A28: 45641.316 | B28: 542361075 | C28: FaceStation 2 542361075 (192.168.50.204) | D28: All Users | E28: 63 | F28: 1:N authentication succeeded (Face)
A29: 45641.315 | B29: 542361075 | C29: FaceStation 2 542361075 (192.168.50.204) | D29: All Users | E29: 227 | F29: 1:N authentication succeeded (Face)
A30: 45641.168 | B30: 542361075 | C30: FaceStation 2 542361075 (192.168.50.204) | D30: All Users | E30: 94 | F30: 1:N authentication succeeded (Face)
A31: 45641.147 | B31: 542361075 | C31: FaceStation 2 542361075 (192.168.50.204) | D31: All Users | E31: 94 | F31: 1:N authentication succeeded (Face)
A32: 45641.145 | B32: 542361075 | C32: FaceStation 2 542361075 (192.168.50.204) | D32: All Users | E32: 227 | F32: 1:N authentication succeeded (Face)
A33: 45641.123 | B33: 542361075 | C33: FaceStation 2 542361075 (192.168.50.204) | D33: All Users | E33: 227 | F33: 1:N authentication succeeded (Face)
A34: 45641.015 | B34: 542361075 | C34: FaceStation 2 542361075 (192.168.50.204) | D34: All Users | E34: 94 | F34: 1:N authentication succeeded (Face)
A35: 45640.982 | B35: 542361075 | C35: FaceStation 2 542361075 (192.168.50.204) | D35: All Users | E35: 227 | F35: 1:N authentication succeeded (Face)
... A44: 45640.856 | B44: 542361075 | C44: FaceStation 2 542361075 (192.168.50.204) | D44: All Users | E44: 107 | F44: 1:N authentication succeeded (Face)
A45: 45640.797 | B45: 542361075 | C45: FaceStation 2 542361075 (192.168.50.204) | F45: DHCP connected
A46: 45640.794 | B46: 542361075 | C46: FaceStation 2 542361075 (192.168.50.204) | F46: Network connected
A47: 45640.794 | B47: 542361075 | C47: FaceStation 2 542361075 (192.168.50.204) | F47: Network disconnected
A48: 45640.729 | B48: 542361075 | C48: FaceStation 2 542361075 (192.168.50.204) | D48: All Users | E48: 63 | F48: 1:N authentication succeeded (Face)
A49: 45640.65 | B49: 542361075 | C49: FaceStation 2 542361075 (192.168.50.204) | D49: All Users | E49: 69 | F49: 1:N authentication succeeded (Face)
A50: 45640.648 | B50: 542361075 | C50: FaceStation 2 542361075 (192.168.50.204) | D50: All Users | E50: 230 | F50: 1:N authentication succeeded (Face)
A51: 45640.648 | B51: 542361075 | C51: FaceStation 2 542361075 (192.168.50.204) | D51: All Users | E51: 239 | F51: 1:N authentication succeeded (Face)
A52: 45640.648 | B52: 542361075 | C52: FaceStation 2 542361075 (192.168.50.204) | D52: All Users | E52: 73 | F52: 1:N authentication succeeded (Face)
A53: 45640.648 | B53: 542361075 | C53: FaceStation 2 542361075 (192.168.50.204) | D53: All Users | E53: 241 | F53: 1:N authentication succeeded (Face)
A54: 45640.647 | B54: 542361075 | C54: FaceStation 2 542361075 (192.168.50.204) | D54: All Users | E54: 232 | F54: 1:N authentication succeeded (Face)
A55: 45640.647 | B55: 542361075 | C55: FaceStation 2 542361075 (192.168.50.204) | D55: All Users | E55: 207 | F55: 1:N authentication succeeded (Face)
A56: 45640.646 | B56: 542361075 | C56: FaceStation 2 542361075 (192.168.50.204) | D56: All Users | E56: 235 | F56: 1:N authentication succeeded (Face)
A57: 45640.646 | B57: 542361075 | C57: FaceStation 2 542361075 (192.168.50.204) | D57: All Users | E57: 226 | F57: 1:N authentication succeeded (Face)
A58: 45640.646 | B58: 542361075 | C58: FaceStation 2 542361075 (192.168.50.204) | D58: All Users | E58: 107 | F58: 1:N authentication succeeded (Face)
A59: 45640.64 | B59: 542361075 | C59: FaceStation 2 542361075 (192.168.50.204) | D59: All Users | E59: 250 | F59: 1:N authentication succeeded (Face)
... A85: 45640.311 | B85: 542361075 | C85: FaceStation 2 542361075 (192.168.50.204) | D85: All Users | E85: 111 | F85: 1:N authentication succeeded (Face)
A86: 45640.309 | B86: 542361075 | C86: FaceStation 2 542361075 (192.168.50.204) | F86: Tamper off
A87: 45640.309 | B87: 542361075 | C87: FaceStation 2 542361075 (192.168.50.204) | F87: DHCP connected
A88: 45640.309 | B88: 542361075 | C88: FaceStation 2 542361075 (192.168.50.204) | F88: Device started
A89: 45640.309 | B89: 542361075 | C89: FaceStation 2 542361075 (192.168.50.204) | F89: Network connected
A90: 45640.298 | B90: 542361075 | C90: FaceStation 2 542361075 (192.168.50.204) | D90: All Users | E90: 73 | F90: 1:N authentication succeeded (Face)
A91: 45640.293 | B91: 542361075 | C91: FaceStation 2 542361075 (192.168.50.204) | D91: All Users | E91: 241 | F91: 1:N authentication succeeded (Face)
A92: 45640.196 | B92: 542361075 | C92: FaceStation 2 542361075 (192.168.50.204) | D92: All Users | E92: 242 | F92: 1:N authentication succeeded (Face)
A93: 45640.196 | B93: 542361075 | C93: FaceStation 2 542361075 (192.168.50.204) | D93: All Users | E93: 159 | F93: 1:N authentication succeeded (Face)
A94: 45640.177 | B94: 542361075 | C94: FaceStation 2 542361075 (192.168.50.204) | D94: All Users | E94: 158 | F94: 1:N authentication succeeded (Face)
A95: 45640.177 | B95: 542361075 | C95: FaceStation 2 542361075 (192.168.50.204) | D95: All Users | E95: 210 | F95: 1:N authentication succeeded (Face)
A96: 45640.165 | B96: 542361075 | C96: FaceStation 2 542361075 (192.168.50.204) | D96: All Users | E96: 159 | F96: 1:N authentication succeeded (Face)
A97: 45640.165 | B97: 542361075 | C97: FaceStation 2 542361075 (192.168.50.204) | D97: All Users | E97: 242 | F97: 1:N authentication succeeded (Face)
A98: 45640.164 | B98: 542361075 | C98: FaceStation 2 542361075 (192.168.50.204) | D98: All Users | E98: 242 | F98: 1:N authentication succeeded (Face)
A99: 45640.16 | B99: 542361075 | C99: FaceStation 2 542361075 (192.168.50.204) | D99: All Users | E99: 27 | F99: 1:N authentication succeeded (Face)
A100: 45640.16 | B100: 542361075 | C100: FaceStation 2 542361075 (192.168.50.204) | D100: All Users | E100: 33 | F100: 1:N authentication succeeded (Face)
A101: 45640.157 | B101: 542361075 | C101: FaceStation 2 542361075 (192.168.50.204) | D101: All Users | E101: 158 | F101: 1:N authentication succeeded (Face)
... A111: 45640.112 | B111: 542361075 | C111: FaceStation 2 542361075 (192.168.50.204) | D111: All Users | E111: 94 | F111: 1:N authentication succeeded (Face)
A112: 45640.11 | B112: 542361075 | C112: FaceStation 2 542361075 (192.168.50.204) | F112: Authentication failed (Timeout)
A113: 45640.108 | B113: 542361075 | C113: FaceStation 2 542361075 (192.168.50.204) | D113: All Users | E113: 214 | F113: 1:N authentication succeeded (Face)
A114: 45640.106 | B114: 542361075 | C114: FaceStation 2 542361075 (192.168.50.204) | D114: All Users | E114: 91 | F114: 1:N authentication succeeded (Face)
A115: 45640.106 | B115: 542361075 | C115: FaceStation 2 542361075 (192.168.50.204) | D115: All Users | E115: 223 | F115: 1:N authentication succeeded (Face)
A116: 45640.089 | B116: 542361075 | C116: FaceStation 2 542361075 (192.168.50.204) | D116: All Users | E116: 227 | F116: 1:N authentication succeeded (Face)
A117: 45640.089 | B117: 542361075 | C117: FaceStation 2 542361075 (192.168.50.204) | D117: All Users | E117: 135 | F117: 1:N authentication succeeded (Face)
A118: 45640.088 | B118: 542361075 | C118: FaceStation 2 542361075 (192.168.50.204) | D118: All Users | E118: 214 | F118: 1:N authentication succeeded (Face)
A119: 45640.086 | B119: 542361075 | C119: FaceStation 2 542361075 (192.168.50.204) | D119: All Users | E119: 14 | F119: 1:N authentication succeeded (Face)
A120: 45640.085 | B120: 542361075 | C120: FaceStation 2 542361075 (192.168.50.204) | D120: All Users | E120: 91 | F120: 1:N authentication succeeded (Face)
A121: 45640.083 | B121: 542361075 | C121: FaceStation 2 542361075 (192.168.50.204) | D121: All Users | E121: 29 | F121: 1:N authentication succeeded (Face)
A122: 45640.083 | B122: 542361075 | C122: FaceStation 2 542361075 (192.168.50.204) | D122: All Users | E122: 74 | F122: 1:N authentication succeeded (Face)
A123: 45640.083 | B123: 542361075 | C123: FaceStation 2 542361075 (192.168.50.204) | D123: All Users | E123: 251 | F123: 1:N authentication succeeded (Face)
A124: 45640.068 | B124: 542361075 | C124: FaceStation 2 542361075 (192.168.50.204) | D124: All Users | E124: 227 | F124: 1:N authentication succeeded (Face)
... A149: 45639.973 | B149: 542361075 | C149: FaceStation 2 542361075 (192.168.50.204) | D149: All Users | E149: 29 | F149: 1:N authentication succeeded (Face)
A150: 45639.973 | B150: 542361075 | C150: FaceStation 2 542361075 (192.168.50.204) | F150: Authentication failed (Timeout)
A151: 45639.973 | B151: 542361075 | C151: FaceStation 2 542361075 (192.168.50.204) | D151: All Users | E151: 223 | F151: 1:N authentication succeeded (Face)
A152: 45639.973 | B152: 542361075 | C152: FaceStation 2 542361075 (192.168.50.204) | D152: All Users | E152: 181 | F152: 1:N authentication succeeded (Face)
A153: 45639.972 | B153: 542361075 | C153: FaceStation 2 542361075 (192.168.50.204) | D153: All Users | E153: 91 | F153: 1:N authentication succeeded (Face)
A154: 45639.972 | B154: 542361075 | C154: FaceStation 2 542361075 (192.168.50.204) | D154: All Users | E154: 33 | F154: 1:N authentication succeeded (Face)
A155: 45639.972 | B155: 542361075 | C155: FaceStation 2 542361075 (192.168.50.204) | D155: All Users | E155: 27 | F155: 1:N authentication succeeded (Face)
A156: 45639.971 | B156: 542361075 | C156: FaceStation 2 542361075 (192.168.50.204) | D156: All Users | E156: 37 | F156: 1:N authentication succeeded (Face)
A157: 45639.964 | B157: 542361075 | C157: FaceStation 2 542361075 (192.168.50.204) | D157: All Users | E157: 94 | F157: 1:N authentication succeeded (Face)
A158: 45639.964 | B158: 542361075 | C158: FaceStation 2 542361075 (192.168.50.204) | D158: All Users | E158: 14 | F158: 1:N authentication succeeded (Face)
A159: 45639.962 | B159: 542361075 | C159: FaceStation 2 542361075 (192.168.50.204) | D159: All Users | E159: 159 | F159: 1:N authentication succeeded (Face)
A160: 45639.962 | B160: 542361075 | C160: FaceStation 2 542361075 (192.168.50.204) | D160: All Users | E160: 7 | F160: 1:N authentication succeeded (Face)
A161: 45639.783 | B161: 542361075 | C161: FaceStation 2 542361075 (192.168.50.204) | D161: All Users | E161: 34 | F161: 1:N authentication succeeded (Face)
A162: 45639.732 | B162: 542361075 | C162: FaceStation 2 542361075 (192.168.50.204) | D162: All Users | E162: 32 | F162: 1:N authentication succeeded (Face)
... A167: 45639.712 | B167: 542361075 | C167: FaceStation 2 542361075 (192.168.50.204) | D167: All Users | E167: 30 | F167: 1:N authentication succeeded (Face)
A168: 45639.711 | B168: 542361075 | C168: FaceStation 2 542361075 (192.168.50.204) | F168: BioStar disconnected
A169: 45639.71 | B169: 542361075 | C169: FaceStation 2 542361075 (192.168.50.204) | D169: All Users | E169: 2 | F169: 1:N authentication succeeded (Face)
A170: 45639.71 | B170: 542361075 | C170: FaceStation 2 542361075 (192.168.50.204) | D170: All Users | E170: 195 | F170: 1:N authentication succeeded (Face)
A171: 45639.709 | B171: 542361075 | C171: FaceStation 2 542361075 (192.168.50.204) | D171: All Users | E171: 212 | F171: 1:N authentication succeeded (Face)
...
