Workbook

Sheet NOMINA TEJIDO 
A1: 1 | AA1: MARTES 06/03 | AF1: MIERCOLES 07/03 | AK1: JUEVES 08/03 | AP1: VIERNES 09/03 | AU1: SABADO 10/03 | BU1: 1
A2: 2 | B2: TEJIDO | T2: SUELDO ESTIMADO FALTA SOLO RELOJ | U2: BONO | V2: DEL 08 AL 14 ENERO 24 | X2: 7.18 | Y2: 7.18 | BA2: 0 | BU2: 2
A3: 3 | E3: L | G3: M | I3: M | K3: J | M3: V | O3: S | R3: COSTOS | V3: 0 | W3: NOMINA | X3: PXP | Y3: PXA | Z3: TOTAL | AA3: INC | AB3: NOMINA | AC3: PXP | AD3: PXA | AE3: TOTAL | AF3: INC | AG3: NOMINA | AH3: PXP | AI3: PXA | AJ3: TOTAL | AK3: INC | AL3: NOMINA | AM3: PXP | AN3: PXA | AO3: TOTAL | AP3: INC | AQ3: NOMINA | AR3: PXP | AS3: PXA | AT3: TOTAL | AU3: INC | AV3: NOMINA | AW3: PXP | AX3: PXA | AY3: TOTAL | BB3: CB | BC3: FP | BD3: L | BE3: R | BI3: INC | BJ3: B ASISTENCIA | BK3: T EXT | BM3: PRIMAS | BN3: PAGO EXTRA | BQ3: 3 | BR3: =0.167*4+4 -> 4.668 | BU3: 3
B4: 164 | C4: =+C3+1 -> 1 | E4: 1 | G4: 1 | I4: 1 | K4: 1 | M4: 1 | O4: 1 | Q4: =IF((E4+G4+I4+K4+M4+O4)=6,1,0) -> 1 | R4: =IF(Q4=1,1550,850) -> 1550 | S4: =+BH4 -> 0 | T4: =+BA4 -> 929 | U4: =+BP4 -> 0 | V4: =+BG4 -> BONO+ B ASIS | W4: =(R4-86.16)/6*E4 -> 243.97333 | X4: =$Y$2*E4*Q4 -> 7.18 | Y4: =$Y$2*E4*Q4 -> 7.18 | Z4: =Y4+X4+W4 -> 258.33333 | AB4: =(R4-86.16)/6*G4 -> 243.97333 | AC4: =$Y$2*G4*Q4 -> 7.18 | AD4: =$Y$2*G4*Q4 -> 7.18 | AE4: =AD4+AC4+AB4 -> 258.33333 | AG4: =(R4-86.16)/6*I4 -> 243.97333 | AH4: =$Y$2*I4*Q4 -> 7.18 | AI4: =$Y$2*I4*Q4 -> 7.18 | AJ4: =AI4+AH4+AG4 -> 258.33333 | AL4: =(R4-86.16)/6*K4 -> 243.97333 | AM4: =$Y$2*K4*Q4 -> 7.18 | AN4: =$Y$2*K4*Q4 -> 7.18 | AO4: =AN4+AM4+AL4 -> 258.33333 | AQ4: =(R4-86.16)/6*M4 -> 243.97333 | AR4: =$Y$2*M4*Q4 -> 7.18 | AS4: =$Y$2*M4*Q4 -> 7.18 | AT4: =AS4+AR4+AQ4 -> 258.33333 | AV4: =(R4-86.16)/6*O4 -> 243.97333 | AW4: =$Y$2*O4*Q4 -> 7.18 | AX4: =$Y$2*O4*Q4 -> 7.18 | AY4: =AX4+AW4+AV4 -> 258.33333 | AZ4: =+AY4+AT4+AO4++AJ4+AE4+Z4 -> 1550 | BA4: 929 | BG4: BONO+ B ASIS
A5: 420 | B5: 2 | C5: =+C4+1 -> 2 | D5: Antunez Requejo Gabriela | E5: 1 | G5: 1 | I5: 1 | K5: 1 | M5: 1 | O5: 1 | Q5: =IF((E5+G5+I5+K5+M5+O5)=6,1,0) -> 1 | R5: =IF(Q5=1,1550,850) -> 1550 | S5: =+BH5 -> 0 | T5: =+BA5 -> 2100 | U5: =+BP5 -> 0 | V5: =+BG5 -> BONO+ B ASIS | W5: =(R5-86.16)/6*E5 -> 243.97333 | X5: =$Y$2*E5*Q5 -> 7.18 | Y5: =$Y$2*E5*Q5 -> 7.18 | Z5: =Y5+X5+W5 -> 258.33333 | AB5: =(R5-86.16)/6*G5 -> 243.97333 | AC5: =$Y$2*G5*Q5 -> 7.18 | AD5: =$Y$2*G5*Q5 -> 7.18 | AE5: =AD5+AC5+AB5 -> 258.33333 | AG5: =(R5-86.16)/6*I5 -> 243.97333 | AH5: =$Y$2*I5*Q5 -> 7.18 | AI5: =$Y$2*I5*Q5 -> 7.18 | AJ5: =AI5+AH5+AG5 -> 258.33333 | AL5: =(R5-86.16)/6*K5 -> 243.97333 | AM5: =$Y$2*K5*Q5 -> 7.18 | AN5: =$Y$2*K5*Q5 -> 7.18 | AO5: =AN5+AM5+AL5 -> 258.33333 | AQ5: =(R5-86.16)/6*M5 -> 243.97333 | AR5: =$Y$2*M5*Q5 -> 7.18 | AS5: =$Y$2*M5*Q5 -> 7.18 | AT5: =AS5+AR5+AQ5 -> 258.33333 | AV5: =(R5-86.16)/6*O5 -> 243.97333 | AW5: =$Y$2*O5*Q5 -> 7.18 | AX5: =$Y$2*O5*Q5 -> 7.18 | AY5: =AX5+AW5+AV5 -> 258.33333 | AZ5: =+AY5+AT5+AO5++AJ5+AE5+Z5 -> 1550 | BA5: =((AZ5-BB5-BC5-BD5-BE5-BF5)+BI5+BJ5+BK5+BL5+BM5+BN5+BO5) -> 2100 | BG5: BONO+ B ASIS | BI5: 300 | BJ5: 250 | BU5: 420
A6: 424 | B6: 6 | C6: =+C5+1 -> 3 | D6: Balderas Balderas Myriam Ivet | E6: 1 | G6: 1 | I6: 1 | K6: 1 | M6: 1 | O6: 1 | Q6: =IF((E6+G6+I6+K6+M6+O6)=6,1,0) -> 1 | R6: 3000 | S6: =+BH6 -> 0 | T6: =+BA6 -> 3000 | U6: =+BP6 -> 0 | V6: =+BG6 -> 0 | W6: =(R6-86.16)/6*E6 -> 485.64 | X6: =$Y$2*E6*Q6 -> 7.18 | Y6: =$Y$2*E6*Q6 -> 7.18 | Z6: =Y6+X6+W6 -> 500 | AB6: =(R6-86.16)/6*G6 -> 485.64 | AC6: =$Y$2*G6*Q6 -> 7.18 | AD6: =$Y$2*G6*Q6 -> 7.18 | AE6: =AD6+AC6+AB6 -> 500 | AG6: =(R6-86.16)/6*I6 -> 485.64 | AH6: =$Y$2*I6*Q6 -> 7.18 | AI6: =$Y$2*I6*Q6 -> 7.18 | AJ6: =AI6+AH6+AG6 -> 500 | AL6: =(R6-86.16)/6*K6 -> 485.64 | AM6: =$Y$2*K6*Q6 -> 7.18 | AN6: =$Y$2*K6*Q6 -> 7.18 | AO6: =AN6+AM6+AL6 -> 500 | AQ6: =(R6-86.16)/6*M6 -> 485.64 | AR6: =$Y$2*M6*Q6 -> 7.18 | AS6: =$Y$2*M6*Q6 -> 7.18 | AT6: =AS6+AR6+AQ6 -> 500 | AV6: =(R6-86.16)/6*O6 -> 485.64 | AW6: =$Y$2*O6*Q6 -> 7.18 | AX6: =$Y$2*O6*Q6 -> 7.18 | AY6: =AX6+AW6+AV6 -> 500 | AZ6: =+AY6+AT6+AO6++AJ6+AE6+Z6 -> 3000 | BA6: =((AZ6-BB6-BC6-BD6-BE6-BF6)+BI6+BJ6+BK6+BL6+BM6+BN6+BO6) -> 3000 | BU6: 424
B7: 149 | C7: =+C6+1 -> 4 | D7: Carrillo Alvarado Erika Miranda | E7: 1 | G7: 1 | I7: 1 | K7: 1 | M7: 1 | O7: 1 | Q7: =IF((E7+G7+I7+K7+M7+O7)=6,1,0) -> 1 | R7: =IF(Q7=1,1550,850) -> 1550 | S7: =+BH7 -> 0 | T7: =+BA7 -> 1800 | U7: =+BP7 -> 0 | V7: =+BG7 -> BONO+ B ASIS | W7: =(R7-86.16)/6*E7 -> 243.97333 | X7: =$Y$2*E7*Q7 -> 7.18 | Y7: =$Y$2*E7*Q7 -> 7.18 | Z7: =Y7+X7+W7 -> 258.33333 | AB7: =(R7-86.16)/6*G7 -> 243.97333 | AC7: =$Y$2*G7*Q7 -> 7.18 | AD7: =$Y$2*G7*Q7 -> 7.18 | AE7: =AD7+AC7+AB7 -> 258.33333 | AG7: =(R7-86.16)/6*I7 -> 243.97333 | AH7: =$Y$2*I7*Q7 -> 7.18 | AI7: =$Y$2*I7*Q7 -> 7.18 | AJ7: =AI7+AH7+AG7 -> 258.33333 | AL7: =(R7-86.16)/6*K7 -> 243.97333 | AM7: =$Y$2*K7*Q7 -> 7.18 | AN7: =$Y$2*K7*Q7 -> 7.18 | AO7: =AN7+AM7+AL7 -> 258.33333 | AQ7: =(R7-86.16)/6*M7 -> 243.97333 | AR7: =$Y$2*M7*Q7 -> 7.18 | AS7: =$Y$2*M7*Q7 -> 7.18 | AT7: =AS7+AR7+AQ7 -> 258.33333 | AV7: =(R7-86.16)/6*O7 -> 243.97333 | AW7: =$Y$2*O7*Q7 -> 7.18 | AX7: =$Y$2*O7*Q7 -> 7.18 | AY7: =AX7+AW7+AV7 -> 258.33333 | AZ7: =+AY7+AT7+AO7++AJ7+AE7+Z7 -> 1550 | BA7: =((AZ7-BB7-BC7-BD7-BE7-BF7)+BI7+BJ7+BK7+BL7+BM7+BN7+BO7) -> 1800 | BG7: BONO+ B ASIS | BI7: 100 | BJ7: 150
B8: 95 | C8: =+C7+1 -> 5 | D8: Carrillo Delgado Judith | E8: 1 | G8: 1 | I8: 1 | K8: 1 | M8: 1 | O8: 1 | Q8: =IF((E8+G8+I8+K8+M8+O8)=6,1,0) -> 1 | R8: =IF(Q8=1,1550,850) -> 1550 | S8: =+BH8 -> 0 | T8: =+BA8 -> 1950 | U8: =+BP8 -> 0 | V8: =+BG8 -> BONO+ B ASIS | W8: =(R8-86.16)/6*E8 -> 243.97333 | X8: =$Y$2*E8*Q8 -> 7.18 | Y8: =$Y$2*E8*Q8 -> 7.18 | Z8: =Y8+X8+W8 -> 258.33333 | AB8: =(R8-86.16)/6*G8 -> 243.97333 | AC8: =$Y$2*G8*Q8 -> 7.18 | AD8: =$Y$2*G8*Q8 -> 7.18 | AE8: =AD8+AC8+AB8 -> 258.33333 | AG8: =(R8-86.16)/6*I8 -> 243.97333 | AH8: =$Y$2*I8*Q8 -> 7.18 | AI8: =$Y$2*I8*Q8 -> 7.18 | AJ8: =AI8+AH8+AG8 -> 258.33333 | AL8: =(R8-86.16)/6*K8 -> 243.97333 | AM8: =$Y$2*K8*Q8 -> 7.18 | AN8: =$Y$2*K8*Q8 -> 7.18 | AO8: =AN8+AM8+AL8 -> 258.33333 | AQ8: =(R8-86.16)/6*M8 -> 243.97333 | AR8: =$Y$2*M8*Q8 -> 7.18 | AS8: =$Y$2*M8*Q8 -> 7.18 | AT8: =AS8+AR8+AQ8 -> 258.33333 | AV8: =(R8-86.16)/6*O8 -> 243.97333 | AW8: =$Y$2*O8*Q8 -> 7.18 | AX8: =$Y$2*O8*Q8 -> 7.18 | AY8: =AX8+AW8+AV8 -> 258.33333 | AZ8: =+AY8+AT8+AO8++AJ8+AE8+Z8 -> 1550 | BA8: =((AZ8-BB8-BC8-BD8-BE8-BF8)+BI8+BJ8+BK8+BL8+BM8+BN8+BO8) -> 1950 | BG8: BONO+ B ASIS | BI8: 250 | BJ8: 150
B9: 59 | C9: =+C8+1 -> 6 | D9: Castro Viaña Mario Ivan | E9: 1 | G9: 1 | I9: 1 | K9: 1 | M9: 1 | O9: 1 | Q9: =IF((E9+G9+I9+K9+M9+O9)=6,1,0) -> 1 | R9: =IF(Q9=1,1550,850) -> 1550 | S9: =+BH9 -> 0 | T9: =+BA9 -> 1950 | U9: =+BP9 -> 0 | V9: =+BG9 -> BONO+ B ASIS | W9: =(R9-86.16)/6*E9 -> 243.97333 | X9: =$Y$2*E9*Q9 -> 7.18 | Y9: =$Y$2*E9*Q9 -> 7.18 | Z9: =Y9+X9+W9 -> 258.33333 | AB9: =(R9-86.16)/6*G9 -> 243.97333 | AC9: =$Y$2*G9*Q9 -> 7.18 | AD9: =$Y$2*G9*Q9 -> 7.18 | AE9: =AD9+AC9+AB9 -> 258.33333 | AG9: =(R9-86.16)/6*I9 -> 243.97333 | AH9: =$Y$2*I9*Q9 -> 7.18 | AI9: =$Y$2*I9*Q9 -> 7.18 | AJ9: =AI9+AH9+AG9 -> 258.33333 | AL9: =(R9-86.16)/6*K9 -> 243.97333 | AM9: =$Y$2*K9*Q9 -> 7.18 | AN9: =$Y$2*K9*Q9 -> 7.18 | AO9: =AN9+AM9+AL9 -> 258.33333 | AQ9: =(R9-86.16)/6*M9 -> 243.97333 | AR9: =$Y$2*M9*Q9 -> 7.18 | AS9: =$Y$2*M9*Q9 -> 7.18 | AT9: =AS9+AR9+AQ9 -> 258.33333 | AV9: =(R9-86.16)/6*O9 -> 243.97333 | AW9: =$Y$2*O9*Q9 -> 7.18 | AX9: =$Y$2*O9*Q9 -> 7.18 | AY9: =AX9+AW9+AV9 -> 258.33333 | AZ9: =+AY9+AT9+AO9++AJ9+AE9+Z9 -> 1550 | BA9: =((AZ9-BB9-BC9-BD9-BE9-BF9)+BI9+BJ9+BK9+BL9+BM9+BN9+BO9) -> 1950 | BG9: BONO+ B ASIS | BI9: 250 | BJ9: 150
B10: 73 | C10: =+C9+1 -> 7 | D10: Garcia Ortega Leslie Coraima | E10: 1 | G10: 1 | I10: 1 | K10: 1 | M10: 1 | O10: 1 | Q10: =IF((E10+G10+I10+K10+M10+O10)=6,1,0) -> 1 | R10: =IF(Q10=1,1550,850) -> 1550 | S10: =+BH10 -> 0 | T10: =+BA10 -> 1950 | U10: =+BP10 -> 0 | V10: =+BG10 -> BONO+ B ASIS | W10: =(R10-86.16)/6*E10 -> 243.97333 | X10: =$Y$2*E10*Q10 -> 7.18 | Y10: =$Y$2*E10*Q10 -> 7.18 | Z10: =Y10+X10+W10 -> 258.33333 | AB10: =(R10-86.16)/6*G10 -> 243.97333 | AC10: =$Y$2*G10*Q10 -> 7.18 | AD10: =$Y$2*G10*Q10 -> 7.18 | AE10: =AD10+AC10+AB10 -> 258.33333 | AG10: =(R10-86.16)/6*I10 -> 243.97333 | AH10: =$Y$2*I10*Q10 -> 7.18 | AI10: =$Y$2*I10*Q10 -> 7.18 | AJ10: =AI10+AH10+AG10 -> 258.33333 | AL10: =(R10-86.16)/6*K10 -> 243.97333 | AM10: =$Y$2*K10*Q10 -> 7.18 | AN10: =$Y$2*K10*Q10 -> 7.18 | AO10: =AN10+AM10+AL10 -> 258.33333 | AQ10: =(R10-86.16)/6*M10 -> 243.97333 | AR10: =$Y$2*M10*Q10 -> 7.18 | AS10: =$Y$2*M10*Q10 -> 7.18 | AT10: =AS10+AR10+AQ10 -> 258.33333 | AV10: =(R10-86.16)/6*O10 -> 243.97333 | AW10: =$Y$2*O10*Q10 -> 7.18 | AX10: =$Y$2*O10*Q10 -> 7.18 | AY10: =AX10+AW10+AV10 -> 258.33333 | AZ10: =+AY10+AT10+AO10++AJ10+AE10+Z10 -> 1550 | BA10: =((AZ10-BB10-BC10-BD10-BE10-BF10)+BI10+BJ10+BK10+BL10+BM10+BN10+BO10) -> 1950 | BG10: BONO+ B ASIS | BI10: 250 | BJ10: 150
A11: 424 | B11: 26 | C11: =+C10+1 -> 8 | D11: Medrano Suarez Jose Adolfo | E11: 1 | G11: 1 | I11: 1 | K11: 1 | M11: 1 | O11: 1 | Q11: =IF((E11+G11+I11+K11+M11+O11)=6,1,0) -> 1 | R11: 2500 | S11: =+BH11 -> 0 | T11: =+BA11 -> 2500 | U11: =+BP11 -> 0 | V11: =+BG11 -> 0 | W11: =(R11-86.16)/6*E11 -> 402.30667 | X11: =$Y$2*E11*Q11 -> 7.18 | Y11: =$Y$2*E11*Q11 -> 7.18 | Z11: =Y11+X11+W11 -> 416.66667 | AB11: =(R11-86.16)/6*G11 -> 402.30667 | AC11: =$Y$2*G11*Q11 -> 7.18 | AD11: =$Y$2*G11*Q11 -> 7.18 | AE11: =AD11+AC11+AB11 -> 416.66667 | AG11: =(R11-86.16)/6*I11 -> 402.30667 | AH11: =$Y$2*I11*Q11 -> 7.18 | AI11: =$Y$2*I11*Q11 -> 7.18 | AJ11: =AI11+AH11+AG11 -> 416.66667 | AL11: =(R11-86.16)/6*K11 -> 402.30667 | AM11: =$Y$2*K11*Q11 -> 7.18 | AN11: =$Y$2*K11*Q11 -> 7.18 | AO11: =AN11+AM11+AL11 -> 416.66667 | AQ11: =(R11-86.16)/6*M11 -> 402.30667 | AR11: =$Y$2*M11*Q11 -> 7.18 | AS11: =$Y$2*M11*Q11 -> 7.18 | AT11: =AS11+AR11+AQ11 -> 416.66667 | AV11: =(R11-86.16)/6*O11 -> 402.30667 | AW11: =$Y$2*O11*Q11 -> 7.18 | AX11: =$Y$2*O11*Q11 -> 7.18 | AY11: =AX11+AW11+AV11 -> 416.66667 | AZ11: =+AY11+AT11+AO11++AJ11+AE11+Z11 -> 2500 | BA11: =((AZ11-BB11-BC11-BD11-BE11-BF11)+BI11+BJ11+BK11+BL11+BM11+BN11+BO11) -> 2500 | BU11: 424
B12: 169 | C12: =+C11+1 -> 9 | D12: Ramirez Requejo Maria Guadalupe | E12: 1 | G12: 1 | I12: 1 | K12: 1 | M12: 1 | O12: 1 | Q12: =IF((E12+G12+I12+K12+M12+O12)=6,1,0) -> 1 | R12: =IF(Q12=1,1550,850) -> 1550 | S12: =+BH12 -> 0 | T12: =+BA12 -> 1700 | U12: =+BP12 -> 0 | V12: =+BG12 -> BONO | W12: =(R12-86.16)/6*E12 -> 243.97333 | X12: =$Y$2*E12*Q12 -> 7.18 | Y12: =$Y$2*E12*Q12 -> 7.18 | Z12: =Y12+X12+W12 -> 258.33333 | AB12: =(R12-86.16)/6*G12 -> 243.97333 | AC12: =$Y$2*G12*Q12 -> 7.18 | AD12: =$Y$2*G12*Q12 -> 7.18 | AE12: =AD12+AC12+AB12 -> 258.33333 | AG12: =(R12-86.16)/6*I12 -> 243.97333 | AH12: =$Y$2*I12*Q12 -> 7.18 | AI12: =$Y$2*I12*Q12 -> 7.18 | AJ12: =AI12+AH12+AG12 -> 258.33333 | AL12: =(R12-86.16)/6*K12 -> 243.97333 | AM12: =$Y$2*K12*Q12 -> 7.18 | AN12: =$Y$2*K12*Q12 -> 7.18 | AO12: =AN12+AM12+AL12 -> 258.33333 | AQ12: =(R12-86.16)/6*M12 -> 243.97333 | AR12: =$Y$2*M12*Q12 -> 7.18 | AS12: =$Y$2*M12*Q12 -> 7.18 | AT12: =AS12+AR12+AQ12 -> 258.33333 | AV12: =(R12-86.16)/6*O12 -> 243.97333 | AW12: =$Y$2*O12*Q12 -> 7.18 | AX12: =$Y$2*O12*Q12 -> 7.18 | AY12: =AX12+AW12+AV12 -> 258.33333 | AZ12: =+AY12+AT12+AO12++AJ12+AE12+Z12 -> 1550 | BA12: =((AZ12-BB12-BC12-BD12-BE12-BF12)+BI12+BJ12+BK12+BL12+BM12+BN12+BO12) -> 1700 | BG12: BONO | BJ12: 150
B13: 152 | C13: =+C12+1 -> 10 | D13: Ruiz Valenzuela Cynthia Marissa | E13: 1 | G13: 1 | I13: 1 | K13: 1 | M13: 1 | O13: 1 | Q13: =IF((E13+G13+I13+K13+M13+O13)=6,1,0) -> 1 | R13: =IF(Q13=1,1550,850) -> 1550 | S13: =+BH13 -> 0 | T13: =+BA13 -> 2000 | U13: =+BP13 -> 0 | V13: =+BG13 -> BONO+B ASIS | W13: =(R13-86.16)/6*E13 -> 243.97333 | X13: =$Y$2*E13*Q13 -> 7.18 | Y13: =$Y$2*E13*Q13 -> 7.18 | Z13: =Y13+X13+W13 -> 258.33333 | AB13: =(R13-86.16)/6*G13 -> 243.97333 | AC13: =$Y$2*G13*Q13 -> 7.18 | AD13: =$Y$2*G13*Q13 -> 7.18 | AE13: =AD13+AC13+AB13 -> 258.33333 | AG13: =(R13-86.16)/6*I13 -> 243.97333 | AH13: =$Y$2*I13*Q13 -> 7.18 | AI13: =$Y$2*I13*Q13 -> 7.18 | AJ13: =AI13+AH13+AG13 -> 258.33333 | AL13: =(R13-86.16)/6*K13 -> 243.97333 | AM13: =$Y$2*K13*Q13 -> 7.18 | AN13: =$Y$2*K13*Q13 -> 7.18 | AO13: =AN13+AM13+AL13 -> 258.33333 | AQ13: =(R13-86.16)/6*M13 -> 243.97333 | AR13: =$Y$2*M13*Q13 -> 7.18 | AS13: =$Y$2*M13*Q13 -> 7.18 | AT13: =AS13+AR13+AQ13 -> 258.33333 | AV13: =(R13-86.16)/6*O13 -> 243.97333 | AW13: =$Y$2*O13*Q13 -> 7.18 | AX13: =$Y$2*O13*Q13 -> 7.18 | AY13: =AX13+AW13+AV13 -> 258.33333 | AZ13: =+AY13+AT13+AO13++AJ13+AE13+Z13 -> 1550 | BA13: =((AZ13-BB13-BC13-BD13-BE13-BF13)+BI13+BJ13+BK13+BL13+BM13+BN13+BO13) -> 2000 | BG13: BONO+B ASIS | BI13: 300 | BJ13: 150
B14: 146 | C14: =+C13+1 -> 11 | D14: Salazar Martinez Yohana Cecilia | E14: 1 | G14: 1 | I14: 1 | K14: 1 | M14: 1 | O14: 1 | Q14: =IF((E14+G14+I14+K14+M14+O14)=6,1,0) -> 1 | R14: =IF(Q14=1,1550,850) -> 1550 | S14: =+BH14 -> 0 | T14: =+BA14 -> 1950 | U14: =+BP14 -> 0 | V14: =+BG14 -> BONO+B ASIS | W14: =(R14-86.16)/6*E14 -> 243.97333 | X14: =$Y$2*E14*Q14 -> 7.18 | Y14: =$Y$2*E14*Q14 -> 7.18 | Z14: =Y14+X14+W14 -> 258.33333 | AB14: =(R14-86.16)/6*G14 -> 243.97333 | AC14: =$Y$2*G14*Q14 -> 7.18 | AD14: =$Y$2*G14*Q14 -> 7.18 | AE14: =AD14+AC14+AB14 -> 258.33333 | AG14: =(R14-86.16)/6*I14 -> 243.97333 | AH14: =$Y$2*I14*Q14 -> 7.18 | AI14: =$Y$2*I14*Q14 -> 7.18 | AJ14: =AI14+AH14+AG14 -> 258.33333 | AL14: =(R14-86.16)/6*K14 -> 243.97333 | AM14: =$Y$2*K14*Q14 -> 7.18 | AN14: =$Y$2*K14*Q14 -> 7.18 | AO14: =AN14+AM14+AL14 -> 258.33333 | AQ14: =(R14-86.16)/6*M14 -> 243.97333 | AR14: =$Y$2*M14*Q14 -> 7.18 | AS14: =$Y$2*M14*Q14 -> 7.18 | AT14: =AS14+AR14+AQ14 -> 258.33333 | AV14: =(R14-86.16)/6*O14 -> 243.97333 | AW14: =$Y$2*O14*Q14 -> 7.18 | AX14: =$Y$2*O14*Q14 -> 7.18 | AY14: =AX14+AW14+AV14 -> 258.33333 | AZ14: =+AY14+AT14+AO14++AJ14+AE14+Z14 -> 1550 | BA14: =((AZ14-BB14-BC14-BD14-BE14-BF14)+BI14+BJ14+BK14+BL14+BM14+BN14+BO14) -> 1950 | BG14: BONO+B ASIS | BI14: 250 | BJ14: 150
A15: 470 | B15: 51 | C15: =+C14+1 -> 12 | D15: Valenzuela Rosales Jose Miguel | E15: 1 | G15: 1 | I15: 1 | K15: 1 | M15: 1 | O15: 1 | Q15: =IF((E15+G15+I15+K15+M15+O15)=6,1,0) -> 1 | R15: 3000 | S15: =+BH15 -> 0 | T15: =+BA15 -> 5585.71 | U15: =+BP15 -> 0 | V15: =+BG15 -> BONO+FINIQUITO | W15: =(R15-86.16)/6*E15 -> 485.64 | X15: =$Y$2*E15*Q15 -> 7.18 | Y15: =$Y$2*E15*Q15 -> 7.18 | Z15: =Y15+X15+W15 -> 500 | AB15: =(R15-86.16)/6*G15 -> 485.64 | AC15: =$Y$2*G15*Q15 -> 7.18 | AD15: =$Y$2*G15*Q15 -> 7.18 | AE15: =AD15+AC15+AB15 -> 500 | AG15: =(R15-86.16)/6*I15 -> 485.64 | AH15: =$Y$2*I15*Q15 -> 7.18 | AI15: =$Y$2*I15*Q15 -> 7.18 | AJ15: =AI15+AH15+AG15 -> 500 | AL15: =(R15-86.16)/6*K15 -> 485.64 | AM15: =$Y$2*K15*Q15 -> 7.18 | AN15: =$Y$2*K15*Q15 -> 7.18 | AO15: =AN15+AM15+AL15 -> 500 | AQ15: =(R15-86.16)/6*M15 -> 485.64 | AR15: =$Y$2*M15*Q15 -> 7.18 | AS15: =$Y$2*M15*Q15 -> 7.18 | AT15: =AS15+AR15+AQ15 -> 500 | AV15: =(R15-86.16)/6*O15 -> 485.64 | AW15: =$Y$2*O15*Q15 -> 7.18 | AX15: =$Y$2*O15*Q15 -> 7.18 | AY15: =AX15+AW15+AV15 -> 500 | AZ15: =+AY15+AT15+AO15++AJ15+AE15+Z15 -> 3000 | BA15: =((AZ15-BB15-BC15-BD15-BE15-BF15)+BI15+BJ15+BK15+BL15+BM15+BN15+BO15) -> 5585.71 | BG15: BONO+FINIQUITO | BI15: 1000 | BL15: 1585.71 | BU15: 470
A16: 429 | E16: =SUM(E4:E15) -> 12 | G16: =SUM(G4:G15) -> 12 | I16: =SUM(I4:I15) -> 12 | K16: =SUM(K4:K15) -> 12 | M16: =SUM(M4:M15) -> 12 | O16: =SUM(O4:O15) -> 12 | BU16: 429
A17: 430 | BU17: 430
A18: 431 | B18: REAL | C18: PR | G18: L | I18: M | K18: M | M18: J | O18: V | Q18: S | BU18: 431
A19: 432 | B19: =E16 -> 12 | C19: =G25 -> 12 | D19: =+B19-C19 -> 0 | R19: PROM | BU19: 432
A20: 433 | B20: =G16 -> 12 | C20: =I25 -> 12 | D20: =+B20-C20 -> 0 | E20: LIDER | G20: 1 | I20: 1 | K20: 1 | M20: 1 | O20: 1 | Q20: 1 | R20: =AVERAGE(G20,I20,K20,M20,O20,Q20) -> 1 | BU20: 433
A21: 434 | B21: =I16 -> 12 | C21: =K25 -> 12 | D21: =+B21-C21 -> 0 | E21: CALIDAD | G21: 1 | I21: 1 | K21: 1 | M21: 1 | O21: 1 | Q21: 1 | R21: =AVERAGE(G21,I21,K21,M21,O21,Q21) -> 1 | BU21: 434
A22: 435 | B22: =K16 -> 12 | C22: =M25 -> 12 | D22: =+B22-C22 -> 0 | E22: MECANICO | G22: 2 | I22: 2 | K22: 2 | M22: 2 | O22: 2 | Q22: 2 | R22: =AVERAGE(G22,I22,K22,M22,O22,Q22) -> 2 | BU22: 435
A23: 436 | B23: =M16 -> 12 | C23: =O25 -> 12 | D23: =+B23-C23 -> 0 | E23: MANUAL | G23: 8 | I23: 8 | K23: 8 | M23: 8 | O23: 8 | Q23: 8 | R23: =AVERAGE(G23,I23,K23,M23,O23,Q23) -> 8 | BU23: 436
A24: 437 | B24: =O16 -> 12 | C24: =Q25 -> 12 | D24: =+B24-C24 -> 0 | E24: MTTO | G24: 0 | I24: 0 | K24: 0 | M24: 0 | O24: 0 | Q24: 0 | R24: =AVERAGE(G24,I24,K24,M24,O24,Q24) -> 0 | BU24: 437
A25: 438 | G25: =SUM(G20:G24) -> 12 | I25: =SUM(I20:I24) -> 12 | K25: =SUM(K20:K24) -> 12 | M25: =SUM(M20:M24) -> 12 | O25: =SUM(O20:O24) -> 12 | Q25: =SUM(Q20:Q24) -> 12 | R25: =AVERAGE(G25,I25,K25,M25,O25,Q25) -> 12 | BU25: 438
A26: 439 | BU26: 439
A27: 440 | BU27: 440
A28: 441 | BU28: 441
A29: 442 | B29: TEJIDO 2 | D29: 3ER TURNO | R29: =$V2 -> DEL 08 AL 14 ENERO 24 | BU29: 442
A30: 443 | E30: L | G30: M | I30: M | K30: J | M30: V | O30: S | V30: 3 | BU30: 443
A31: 444 | B31: 9 | C31: =+C30+1 -> 1 | D31: Bustamante Villegas Osvaldo | E31: 1 | G31: 1 | I31: 1 | K31: 1 | M31: 1 | O31: 1 | Q31: =IF((E31+G31+I31+K31+M31+O31)=6,1,0) -> 1 | R31: 3000 | S31: =+BH31 -> 0 | T31: =+BA31 -> 3000 | U31: =+BP31 -> 0 | V31: =+BG31 -> 0 | W31: =(R31-86.16)/6*E31 -> 485.64 | X31: =$Y$2*E31*Q31 -> 7.18 | Y31: =$Y$2*E31*Q31 -> 7.18 | Z31: =Y31+X31+W31 -> 500 | AB31: =(R31-86.16)/6*G31 -> 485.64 | AC31: =$Y$2*G31*Q31 -> 7.18 | AD31: =$Y$2*G31*Q31 -> 7.18 | AE31: =AD31+AC31+AB31 -> 500 | AG31: =(R31-86.16)/6*I31 -> 485.64 | AH31: =$Y$2*I31*Q31 -> 7.18 | AI31: =$Y$2*I31*Q31 -> 7.18 | AJ31: =AI31+AH31+AG31 -> 500 | AL31: =(R31-86.16)/6*K31 -> 485.64 | AM31: =$Y$2*K31*Q31 -> 7.18 | AN31: =$Y$2*K31*Q31 -> 7.18 | AO31: =AN31+AM31+AL31 -> 500 | AQ31: =(R31-86.16)/6*M31 -> 485.64 | AR31: =$Y$2*M31*Q31 -> 7.18 | AS31: =$Y$2*M31*Q31 -> 7.18 | AT31: =AS31+AR31+AQ31 -> 500 | AV31: =(R31-86.16)/6*O31 -> 485.64 | AW31: =$Y$2*O31*Q31 -> 7.18 | AX31: =$Y$2*O31*Q31 -> 7.18 | AY31: =AX31+AW31+AV31 -> 500 | AZ31: =+AY31+AT31+AO31++AJ31+AE31+Z31 -> 3000 | BA31: =((AZ31-BB31-BC31-BD31-BE31-BF31)+BI31+BJ31+BK31+BL31+BM31+BN31+BO31) -> 3000 | BU31: 444
A32: 445 | B32: 12 | C32: =+C31+1 -> 2 | D32: Diaz Martinez Angela Elizabeth | E32: 1 | G32: 1 | I32: 1 | K32: 1 | M32: 1 | O32: 1 | Q32: =IF((E32+G32+I32+K32+M32+O32)=6,1,0) -> 1 | R32: =IF(Q32=1,1550,850) -> 1550 | S32: =+BH32 -> 0 | T32: =+BA32 -> 2100 | U32: =+BP32 -> 0 | V32: =+BG32 -> BONO+B ASIS | W32: =(R32-86.16)/6*E32 -> 243.97333 | X32: =$Y$2*E32*Q32 -> 7.18 | Y32: =$Y$2*E32*Q32 -> 7.18 | Z32: =Y32+X32+W32 -> 258.33333 | AB32: =(R32-86.16)/6*G32 -> 243.97333 | AC32: =$Y$2*G32*Q32 -> 7.18 | AD32: =$Y$2*G32*Q32 -> 7.18 | AE32: =AD32+AC32+AB32 -> 258.33333 | AG32: =(R32-86.16)/6*I32 -> 243.97333 | AH32: =$Y$2*I32*Q32 -> 7.18 | AI32: =$Y$2*I32*Q32 -> 7.18 | AJ32: =AI32+AH32+AG32 -> 258.33333 | AL32: =(R32-86.16)/6*K32 -> 243.97333 | AM32: =$Y$2*K32*Q32 -> 7.18 | AN32: =$Y$2*K32*Q32 -> 7.18 | AO32: =AN32+AM32+AL32 -> 258.33333 | AQ32: =(R32-86.16)/6*M32 -> 243.97333 | AR32: =$Y$2*M32*Q32 -> 7.18 | AS32: =$Y$2*M32*Q32 -> 7.18 | AT32: =AS32+AR32+AQ32 -> 258.33333 | AV32: =(R32-86.16)/6*O32 -> 243.97333 | AW32: =$Y$2*O32*Q32 -> 7.18 | AX32: =$Y$2*O32*Q32 -> 7.18 | AY32: =AX32+AW32+AV32 -> 258.33333 | AZ32: =+AY32+AT32+AO32++AJ32+AE32+Z32 -> 1550 | BA32: =((AZ32-BB32-BC32-BD32-BE32-BF32)+BI32+BJ32+BK32+BL32+BM32+BN32+BO32) -> 2100 | BG32: BONO+B ASIS | BI32: 300 | BJ32: 250 | BU32: 445
B33: 168 | C33: =+C32+1 -> 3 | D33: Espinoza Ponce Juan Jose | E33: 1 | G33: 1 | I33: 1 | K33: 1 | M33: 1 | O33: 1 | Q33: =IF((E33+G33+I33+K33+M33+O33)=6,1,0) -> 1 | R33: =IF(Q33=1,1550,850) -> 1550 | S33: =+BH33 -> 0 | T33: =+BA33 -> 1800 | U33: =+BP33 -> 0 | V33: =+BG33 -> B ASIS | W33: =(R33-86.16)/6*E33 -> 243.97333 | X33: =$Y$2*E33*Q33 -> 7.18 | Y33: =$Y$2*E33*Q33 -> 7.18 | Z33: =Y33+X33+W33 -> 258.33333 | AB33: =(R33-86.16)/6*G33 -> 243.97333 | AC33: =$Y$2*G33*Q33 -> 7.18 | AD33: =$Y$2*G33*Q33 -> 7.18 | AE33: =AD33+AC33+AB33 -> 258.33333 | AG33: =(R33-86.16)/6*I33 -> 243.97333 | AH33: =$Y$2*I33*Q33 -> 7.18 | AI33: =$Y$2*I33*Q33 -> 7.18 | AJ33: =AI33+AH33+AG33 -> 258.33333 | AL33: =(R33-86.16)/6*K33 -> 243.97333 | AM33: =$Y$2*K33*Q33 -> 7.18 | AN33: =$Y$2*K33*Q33 -> 7.18 | AO33: =AN33+AM33+AL33 -> 258.33333 | AQ33: =(R33-86.16)/6*M33 -> 243.97333 | AR33: =$Y$2*M33*Q33 -> 7.18 | AS33: =$Y$2*M33*Q33 -> 7.18 | AT33: =AS33+AR33+AQ33 -> 258.33333 | AV33: =(R33-86.16)/6*O33 -> 243.97333 | AW33: =$Y$2*O33*Q33 -> 7.18 | AX33: =$Y$2*O33*Q33 -> 7.18 | AY33: =AX33+AW33+AV33 -> 258.33333 | AZ33: =+AY33+AT33+AO33++AJ33+AE33+Z33 -> 1550 | BA33: =((AZ33-BB33-BC33-BD33-BE33-BF33)+BI33+BJ33+BK33+BL33+BM33+BN33+BO33) -> 1800 | BG33: B ASIS | BI33: 100 | BJ33: 150
A34: 445 | B34: 16 | C34: =+C33+1 -> 4 | D34: Favela Saucedo Idalia Azucena | E34: 0 | F34: INC | G34: 0 | H34: INC | I34: 0 | J34: INC | K34: 0 | L34: INC | M34: 0 | N34: INC | O34: 0 | P34: INC | Q34: =IF((E34+G34+I34+K34+M34+O34)=6,1,0) -> 0 | R34: =IF(Q34=1,1550,850) -> 850 | S34: =+BH34 -> 0 | T34: =+BA34 -> 0 | U34: =+BP34 -> 0 | V34: =+BG34 -> 0 | W34: =(R34-86.16)/6*E34 -> 0 | X34: =$Y$2*E34*Q34 -> 0 | Y34: =$Y$2*E34*Q34 -> 0 | Z34: =Y34+X34+W34 -> 0 | AB34: =(R34-86.16)/6*G34 -> 0 | AC34: =$Y$2*G34*Q34 -> 0 | AD34: =$Y$2*G34*Q34 -> 0 | AE34: =AD34+AC34+AB34 -> 0 | AG34: =(R34-86.16)/6*I34 -> 0 | AH34: =$Y$2*I34*Q34 -> 0 | AI34: =$Y$2*I34*Q34 -> 0 | AJ34: =AI34+AH34+AG34 -> 0 | AL34: =(R34-86.16)/6*K34 -> 0 | AM34: =$Y$2*K34*Q34 -> 0 | AN34: =$Y$2*K34*Q34 -> 0 | AO34: =AN34+AM34+AL34 -> 0 | AQ34: =(R34-86.16)/6*M34 -> 0 | AR34: =$Y$2*M34*Q34 -> 0 | AS34: =$Y$2*M34*Q34 -> 0 | AT34: =AS34+AR34+AQ34 -> 0 | AV34: =(R34-86.16)/6*O34 -> 0 | AW34: =$Y$2*O34*Q34 -> 0 | AX34: =$Y$2*O34*Q34 -> 0 | AY34: =AX34+AW34+AV34 -> 0 | AZ34: =+AY34+AT34+AO34++AJ34+AE34+Z34 -> 0 | BA34: =((AZ34-BB34-BC34-BD34-BE34-BF34)+BI34+BJ34+BK34+BL34+BM34+BN34+BO34) -> 0 | BU34: 445
B35: 171 | C35: =+C34+1 -> 5 | D35: Juarez Sifuentes Sandra | E35: 1 | G35: 1 | I35: 1 | K35: 1 | M35: 1 | O35: 0 | P35: F | Q35: =IF((E35+G35+I35+K35+M35+O35)=6,1,0) -> 0 | R35: =IF(Q35=1,1550,850) -> 850 | S35: =+BH35 -> 0 | T35: =+BA35 -> 966.66333 | U35: =+BP35 -> 0 | V35: =+BG35 -> 0 | W35: =(R35-86.16)/6*E35 -> 127.30667 | X35: =$Y$2*E35*Q35 -> 0 | Y35: =$Y$2*E35*Q35 -> 0 | Z35: =Y35+X35+W35 -> 127.30667 | AB35: =(R35-86.16)/6*G35 -> 127.30667 | AC35: =$Y$2*G35*Q35 -> 0 | AD35: =$Y$2*G35*Q35 -> 0 | AE35: =AD35+AC35+AB35 -> 127.30667 | AG35: =(R35-86.16)/6*I35 -> 127.30667 | AH35: =$Y$2*I35*Q35 -> 0 | AI35: =$Y$2*I35*Q35 -> 0 | AJ35: =AI35+AH35+AG35 -> 127.30667 | AL35: =(R35-86.16)/6*K35 -> 127.30667 | AM35: =$Y$2*K35*Q35 -> 0 | AN35: =$Y$2*K35*Q35 -> 0 | AO35: =AN35+AM35+AL35 -> 127.30667 | AQ35: =(R35-86.16)/6*M35 -> 127.30667 | AR35: =$Y$2*M35*Q35 -> 0 | AS35: =$Y$2*M35*Q35 -> 0 | AT35: =AS35+AR35+AQ35 -> 127.30667 | AV35: =(R35-86.16)/6*O35 -> 0 | AW35: =$Y$2*O35*Q35 -> 0 | AX35: =$Y$2*O35*Q35 -> 0 | AY35: =AX35+AW35+AV35 -> 0 | AZ35: =+AY35+AT35+AO35++AJ35+AE35+Z35 -> 636.53333 | BA35: =((AZ35-BB35-BC35-BD35-BE35-BF35)+BI35+BJ35+BK35+BL35+BM35+BN35+BO35) -> 966.66333 | BL35: 330.13
B36: 92 | C36: =+C35+1 -> 6 | D36: Martinez Sifuentes Mariana | E36: 1 | G36: 1 | I36: 1 | K36: 1 | M36: 1 | O36: 1 | Q36: =IF((E36+G36+I36+K36+M36+O36)=6,1,0) -> 1 | R36: =IF(Q36=1,1550,850) -> 1550 | S36: =+BH36 -> 0 | T36: =+BA36 -> 1800 | U36: =+BP36 -> 0 | V36: =+BG36 -> B ASIS | W36: =(R36-86.16)/6*E36 -> 243.97333 | X36: =$Y$2*E36*Q36 -> 7.18 | Y36: =$Y$2*E36*Q36 -> 7.18 | Z36: =Y36+X36+W36 -> 258.33333 | AB36: =(R36-86.16)/6*G36 -> 243.97333 | AC36: =$Y$2*G36*Q36 -> 7.18 | AD36: =$Y$2*G36*Q36 -> 7.18 | AE36: =AD36+AC36+AB36 -> 258.33333 | AG36: =(R36-86.16)/6*I36 -> 243.97333 | AH36: =$Y$2*I36*Q36 -> 7.18 | AI36: =$Y$2*I36*Q36 -> 7.18 | AJ36: =AI36+AH36+AG36 -> 258.33333 | AL36: =(R36-86.16)/6*K36 -> 243.97333 | AM36: =$Y$2*K36*Q36 -> 7.18 | AN36: =$Y$2*K36*Q36 -> 7.18 | AO36: =AN36+AM36+AL36 -> 258.33333 | AQ36: =(R36-86.16)/6*M36 -> 243.97333 | AR36: =$Y$2*M36*Q36 -> 7.18 | AS36: =$Y$2*M36*Q36 -> 7.18 | AT36: =AS36+AR36+AQ36 -> 258.33333 | AV36: =(R36-86.16)/6*O36 -> 243.97333 | AW36: =$Y$2*O36*Q36 -> 7.18 | AX36: =$Y$2*O36*Q36 -> 7.18 | AY36: =AX36+AW36+AV36 -> 258.33333 | AZ36: =+AY36+AT36+AO36++AJ36+AE36+Z36 -> 1550 | BA36: =((AZ36-BB36-BC36-BD36-BE36-BF36)+BI36+BJ36+BK36+BL36+BM36+BN36+BO36) -> 1800 | BG36: B ASIS | BI36: 100 | BJ36: 150
B37: 91 | C37: =+C36+1 -> 7 | D37: Medellin Rodriguez Yesenia Abigail | E37: 1 | G37: 1 | I37: 1 | K37: 1 | M37: 1 | O37: 1 | Q37: =IF((E37+G37+I37+K37+M37+O37)=6,1,0) -> 1 | R37: =IF(Q37=1,1550,850) -> 1550 | S37: =+BH37 -> 0 | T37: =+BA37 -> 1950 | U37: =+BP37 -> 0 | V37: =+BG37 -> BONO+B ASIS | W37: =(R37-86.16)/6*E37 -> 243.97333 | X37: =$Y$2*E37*Q37 -> 7.18 | Y37: =$Y$2*E37*Q37 -> 7.18 | Z37: =Y37+X37+W37 -> 258.33333 | AB37: =(R37-86.16)/6*G37 -> 243.97333 | AC37: =$Y$2*G37*Q37 -> 7.18 | AD37: =$Y$2*G37*Q37 -> 7.18 | AE37: =AD37+AC37+AB37 -> 258.33333 | AG37: =(R37-86.16)/6*I37 -> 243.97333 | AH37: =$Y$2*I37*Q37 -> 7.18 | AI37: =$Y$2*I37*Q37 -> 7.18 | AJ37: =AI37+AH37+AG37 -> 258.33333 | AL37: =(R37-86.16)/6*K37 -> 243.97333 | AM37: =$Y$2*K37*Q37 -> 7.18 | AN37: =$Y$2*K37*Q37 -> 7.18 | AO37: =AN37+AM37+AL37 -> 258.33333 | AQ37: =(R37-86.16)/6*M37 -> 243.97333 | AR37: =$Y$2*M37*Q37 -> 7.18 | AS37: =$Y$2*M37*Q37 -> 7.18 | AT37: =AS37+AR37+AQ37 -> 258.33333 | AV37: =(R37-86.16)/6*O37 -> 243.97333 | AW37: =$Y$2*O37*Q37 -> 7.18 | AX37: =$Y$2*O37*Q37 -> 7.18 | AY37: =AX37+AW37+AV37 -> 258.33333 | AZ37: =+AY37+AT37+AO37++AJ37+AE37+Z37 -> 1550 | BA37: =((AZ37-BB37-BC37-BD37-BE37-BF37)+BI37+BJ37+BK37+BL37+BM37+BN37+BO37) -> 1950 | BG37: BONO+B ASIS | BI37: 250 | BJ37: 150
A38: 448 | B38: 27 | C38: =+C37+1 -> 8 | D38: Minor Flores Adilene | E38: 1 | G38: 1 | I38: 1 | K38: 0 | L38: PSG | M38: 1 | O38: 1 | Q38: =IF((E38+G38+I38+K38+M38+O38)=6,1,0) -> 0 | R38: =IF(Q38=1,1550,850) -> 850 | S38: =+BH38 -> 0 | T38: =+BA38 -> 1508.3333 | U38: =+BP38 -> 0 | V38: =+BG38 -> BONO | W38: =(R38-86.16)/6*E38 -> 127.30667 | X38: =$Y$2*E38*Q38 -> 0 | Y38: =$Y$2*E38*Q38 -> 0 | Z38: =Y38+X38+W38 -> 127.30667 | AB38: =(R38-86.16)/6*G38 -> 127.30667 | AC38: =$Y$2*G38*Q38 -> 0 | AD38: =$Y$2*G38*Q38 -> 0 | AE38: =AD38+AC38+AB38 -> 127.30667 | AG38: =(R38-86.16)/6*I38 -> 127.30667 | AH38: =$Y$2*I38*Q38 -> 0 | AI38: =$Y$2*I38*Q38 -> 0 | AJ38: =AI38+AH38+AG38 -> 127.30667 | AL38: =(R38-86.16)/6*K38 -> 0 | AM38: =$Y$2*K38*Q38 -> 0 | AN38: =$Y$2*K38*Q38 -> 0 | AO38: =AN38+AM38+AL38 -> 0 | AQ38: =(R38-86.16)/6*M38 -> 127.30667 | AR38: =$Y$2*M38*Q38 -> 0 | AS38: =$Y$2*M38*Q38 -> 0 | AT38: =AS38+AR38+AQ38 -> 127.30667 | AV38: =(R38-86.16)/6*O38 -> 127.30667 | AW38: =$Y$2*O38*Q38 -> 0 | AX38: =$Y$2*O38*Q38 -> 0 | AY38: =AX38+AW38+AV38 -> 127.30667 | AZ38: =+AY38+AT38+AO38++AJ38+AE38+Z38 -> 636.53333 | BA38: =((AZ38-BB38-BC38-BD38-BE38-BF38)+BI38+BJ38+BK38+BL38+BM38+BN38+BO38) -> 1508.3333 | BG38: BONO | BI38: 300 | BL38: =271.8+300 -> 571.8 | BU38: 448
A39: 449 | B39: 28 | C39: =+C38+1 -> 9 | D39: Moran Hernandez Raul | E39: 1 | G39: 1 | I39: 1 | K39: 1 | M39: 1 | O39: 1 | Q39: =IF((E39+G39+I39+K39+M39+O39)=6,1,0) -> 1 | R39: =IF(Q39=1,3000,850) -> 3000 | S39: =+BH39 -> 0 | T39: =+BA39 -> 3000 | U39: =+BP39 -> 0 | V39: =+BG39 -> 0 | W39: =(R39-86.16)/6*E39 -> 485.64 | X39: =$Y$2*E39*Q39 -> 7.18 | Y39: =$Y$2*E39*Q39 -> 7.18 | Z39: =Y39+X39+W39 -> 500 | AB39: =(R39-86.16)/6*G39 -> 485.64 | AC39: =$Y$2*G39*Q39 -> 7.18 | AD39: =$Y$2*G39*Q39 -> 7.18 | AE39: =AD39+AC39+AB39 -> 500 | AG39: =(R39-86.16)/6*I39 -> 485.64 | AH39: =$Y$2*I39*Q39 -> 7.18 | AI39: =$Y$2*I39*Q39 -> 7.18 | AJ39: =AI39+AH39+AG39 -> 500 | AL39: =(R39-86.16)/6*K39 -> 485.64 | AM39: =$Y$2*K39*Q39 -> 7.18 | AN39: =$Y$2*K39*Q39 -> 7.18 | AO39: =AN39+AM39+AL39 -> 500 | AQ39: =(R39-86.16)/6*M39 -> 485.64 | AR39: =$Y$2*M39*Q39 -> 7.18 | AS39: =$Y$2*M39*Q39 -> 7.18 | AT39: =AS39+AR39+AQ39 -> 500 | AV39: =(R39-86.16)/6*O39 -> 485.64 | AW39: =$Y$2*O39*Q39 -> 7.18 | AX39: =$Y$2*O39*Q39 -> 7.18 | AY39: =AX39+AW39+AV39 -> 500 | AZ39: =+AY39+AT39+AO39++AJ39+AE39+Z39 -> 3000 | BA39: =((AZ39-BB39-BC39-BD39-BE39-BF39)+BI39+BJ39+BK39+BL39+BM39+BN39+BO39) -> 3000 | BU39: 449
A40: 448 | B40: 170 | C40: =+C39+1 -> 10 | D40: Ochoa Vital Edna Lizeth | E40: 1 | G40: 1 | I40: 1 | K40: 1 | M40: 1 | O40: 1 | Q40: =IF((E40+G40+I40+K40+M40+O40)=6,1,0) -> 1 | R40: =IF(Q40=1,1550,850) -> 1550 | S40: =+BH40 -> 0 | T40: =+BA40 -> 1950 | U40: =+BP40 -> 0 | V40: =+BG40 -> BONO+B ASIS | W40: =(R40-86.16)/6*E40 -> 243.97333 | X40: =$Y$2*E40*Q40 -> 7.18 | Y40: =$Y$2*E40*Q40 -> 7.18 | Z40: =Y40+X40+W40 -> 258.33333 | AB40: =(R40-86.16)/6*G40 -> 243.97333 | AC40: =$Y$2*G40*Q40 -> 7.18 | AD40: =$Y$2*G40*Q40 -> 7.18 | AE40: =AD40+AC40+AB40 -> 258.33333 | AG40: =(R40-86.16)/6*I40 -> 243.97333 | AH40: =$Y$2*I40*Q40 -> 7.18 | AI40: =$Y$2*I40*Q40 -> 7.18 | AJ40: =AI40+AH40+AG40 -> 258.33333 | AL40: =(R40-86.16)/6*K40 -> 243.97333 | AM40: =$Y$2*K40*Q40 -> 7.18 | AN40: =$Y$2*K40*Q40 -> 7.18 | AO40: =AN40+AM40+AL40 -> 258.33333 | AQ40: =(R40-86.16)/6*M40 -> 243.97333 | AR40: =$Y$2*M40*Q40 -> 7.18 | AS40: =$Y$2*M40*Q40 -> 7.18 | AT40: =AS40+AR40+AQ40 -> 258.33333 | AV40: =(R40-86.16)/6*O40 -> 243.97333 | AW40: =$Y$2*O40*Q40 -> 7.18 | AX40: =$Y$2*O40*Q40 -> 7.18 | AY40: =AX40+AW40+AV40 -> 258.33333 | AZ40: =+AY40+AT40+AO40++AJ40+AE40+Z40 -> 1550 | BA40: =((AZ40-BB40-BC40-BD40-BE40-BF40)+BI40+BJ40+BK40+BL40+BM40+BN40+BO40) -> 1950 | BG40: BONO+B ASIS | BI40: 250 | BJ40: 150 | BU40: 448
A41: 467 | B41: 32 | C41: =+C44+1 -> 1 | D41: Ramirez Flores Jose Alejandro | E41: 1 | G41: 1 | I41: 1 | K41: 1 | M41: 1 | O41: 1 | Q41: =IF((E41+G41+I41+K41+M41+O41)=6,1,0) -> 1 | R41: =IF(Q41=1,1550,850) -> 1550 | S41: =+BH41 -> 0 | T41: =+BA41 -> 1950 | U41: =+BP41 -> 0 | V41: =+BG41 -> BONO+B ASIS | W41: =(R41-86.16)/6*E41 -> 243.97333 | X41: =$Y$2*E41*Q41 -> 7.18 | Y41: =$Y$2*E41*Q41 -> 7.18 | Z41: =Y41+X41+W41 -> 258.33333 | AB41: =(R41-86.16)/6*G41 -> 243.97333 | AC41: =$Y$2*G41*Q41 -> 7.18 | AD41: =$Y$2*G41*Q41 -> 7.18 | AE41: =AD41+AC41+AB41 -> 258.33333 | AG41: =(R41-86.16)/6*I41 -> 243.97333 | AH41: =$Y$2*I41*Q41 -> 7.18 | AI41: =$Y$2*I41*Q41 -> 7.18 | AJ41: =AI41+AH41+AG41 -> 258.33333 | AL41: =(R41-86.16)/6*K41 -> 243.97333 | AM41: =$Y$2*K41*Q41 -> 7.18 | AN41: =$Y$2*K41*Q41 -> 7.18 | AO41: =AN41+AM41+AL41 -> 258.33333 | AQ41: =(R41-86.16)/6*M41 -> 243.97333 | AR41: =$Y$2*M41*Q41 -> 7.18 | AS41: =$Y$2*M41*Q41 -> 7.18 | AT41: =AS41+AR41+AQ41 -> 258.33333 | AV41: =(R41-86.16)/6*O41 -> 243.97333 | AW41: =$Y$2*O41*Q41 -> 7.18 | AX41: =$Y$2*O41*Q41 -> 7.18 | AY41: =AX41+AW41+AV41 -> 258.33333 | AZ41: =+AY41+AT41+AO41++AJ41+AE41+Z41 -> 1550 | BA41: =((AZ41-BB41-BC41-BD41-BE41-BF41)+BI41+BJ41+BK41+BL41+BM41+BN41+BO41) -> 1950 | BG41: BONO+B ASIS | BI41: 250 | BJ41: 150 | BU41: 467
A42: 448 | B42: 33 | C42: =+C41+1 -> 2 | D42: Ramirez Vital Jose Armando | E42: 1 | G42: 1 | I42: 1 | K42: 1 | M42: 1 | O42: 1 | Q42: =IF((E42+G42+I42+K42+M42+O42)=6,1,0) -> 1 | R42: =IF(Q42=1,1550,850) -> 1550 | S42: =+BH42 -> 0 | T42: =+BA42 -> 1950 | U42: =+BP42 -> 0 | V42: =+BG42 -> BONO+B ASIS | W42: =(R42-86.16)/6*E42 -> 243.97333 | X42: =$Y$2*E42*Q42 -> 7.18 | Y42: =$Y$2*E42*Q42 -> 7.18 | Z42: =Y42+X42+W42 -> 258.33333 | AB42: =(R42-86.16)/6*G42 -> 243.97333 | AC42: =$Y$2*G42*Q42 -> 7.18 | AD42: =$Y$2*G42*Q42 -> 7.18 | AE42: =AD42+AC42+AB42 -> 258.33333 | AG42: =(R42-86.16)/6*I42 -> 243.97333 | AH42: =$Y$2*I42*Q42 -> 7.18 | AI42: =$Y$2*I42*Q42 -> 7.18 | AJ42: =AI42+AH42+AG42 -> 258.33333 | AL42: =(R42-86.16)/6*K42 -> 243.97333 | AM42: =$Y$2*K42*Q42 -> 7.18 | AN42: =$Y$2*K42*Q42 -> 7.18 | AO42: =AN42+AM42+AL42 -> 258.33333 | AQ42: =(R42-86.16)/6*M42 -> 243.97333 | AR42: =$Y$2*M42*Q42 -> 7.18 | AS42: =$Y$2*M42*Q42 -> 7.18 | AT42: =AS42+AR42+AQ42 -> 258.33333 | AV42: =(R42-86.16)/6*O42 -> 243.97333 | AW42: =$Y$2*O42*Q42 -> 7.18 | AX42: =$Y$2*O42*Q42 -> 7.18 | AY42: =AX42+AW42+AV42 -> 258.33333 | AZ42: =+AY42+AT42+AO42++AJ42+AE42+Z42 -> 1550 | BA42: =((AZ42-BB42-BC42-BD42-BE42-BF42)+BI42+BJ42+BK42+BL42+BM42+BN42+BO42) -> 1950 | BG42: BONO+B ASIS | BI42: 250 | BJ42: 150 | BU42: 448
B43: 156 | C43: =+C39+1 -> 10 | D43: Padilla Reyes Laura Monserrat | E43: 0 | F43: B | G43: 0 | H43: B | I43: 0 | J43: B | K43: 0 | L43: B | M43: 0 | N43: B | O43: 0 | P43: B | Q43: 0 | R43: 0 | S43: =+BH43 -> 0 | T43: =+BA43 -> 0 | U43: =+BP43 -> 0 | V43: =+BG43 -> 0 | W43: =(R43-86.16)/6*E43 -> 0 | X43: =$Y$2*E43*Q43 -> 0 | Y43: =$Y$2*E43*Q43 -> 0 | Z43: =Y43+X43+W43 -> 0 | AB43: =(R43-86.16)/6*G43 -> 0 | AC43: =$Y$2*G43*Q43 -> 0 | AD43: =$Y$2*G43*Q43 -> 0 | AE43: =AD43+AC43+AB43 -> 0 | AG43: =(R43-86.16)/6*I43 -> 0 | AH43: =$Y$2*I43*Q43 -> 0 | AI43: =$Y$2*I43*Q43 -> 0 | AJ43: =AI43+AH43+AG43 -> 0 | AL43: =(R43-86.16)/6*K43 -> 0 | AM43: =$Y$2*K43*Q43 -> 0 | AN43: =$Y$2*K43*Q43 -> 0 | AO43: =AN43+AM43+AL43 -> 0 | AQ43: =(R43-86.16)/6*M43 -> 0 | AR43: =$Y$2*M43*Q43 -> 0 | AS43: =$Y$2*M43*Q43 -> 0 | AT43: =AS43+AR43+AQ43 -> 0 | AV43: =(R43-86.16)/6*O43 -> 0 | AW43: =$Y$2*O43*Q43 -> 0 | AX43: =$Y$2*O43*Q43 -> 0 | AY43: =AX43+AW43+AV43 -> 0 | AZ43: =+AY43+AT43+AO43++AJ43+AE43+Z43 -> 0 | BA43: 0
A44: 451 | E44: =SUM(E31:E42) -> 11 | G44: =SUM(G31:G42) -> 11 | I44: =SUM(I31:I42) -> 11 | K44: =SUM(K31:K42) -> 10 | M44: =SUM(M31:M42) -> 11 | O44: =SUM(O31:O42) -> 10 | BU44: 451
A45: 452 | BU45: 452
A46: 453 | B46: REAL | C46: PR | G46: L | I46: M | K46: M | M46: J | O46: V | Q46: S | BU46: 453
A47: 454 | B47: =E44 -> 11 | C47: =G51 -> 11 | D47: =+B47-C47 -> 0 | R47: PROM | BU47: 454
A48: 455 | B48: =G44 -> 11 | C48: =I51 -> 11 | D48: =+B48-C48 -> 0 | E48: LIDER | G48: 0 | I48: 0 | K48: 0 | M48: 0 | O48: 0 | Q48: 0 | R48: =AVERAGE(G48,I48,K48,M48,O48,Q48) -> 0 | BU48: 455
A49: 456 | B49: =I44 -> 11 | C49: =K51 -> 11 | D49: =+B49-C49 -> 0 | E49: MECANICO | G49: 2 | I49: 2 | K49: 2 | M49: 2 | O49: 2 | Q49: 2 | R49: =AVERAGE(G49,I49,K49,M49,O49,Q49) -> 2 | BU49: 456
A50: 457 | B50: =K44 -> 10 | C50: =M51 -> 10 | D50: =+B50-C50 -> 0 | E50: MANUAL | G50: 9 | I50: 9 | K50: 9 | M50: 8 | O50: 9 | Q50: 8 | R50: =AVERAGE(G50,I50,K50,M50,O50,Q50) -> 8.6666667 | BU50: 457
A51: 458 | B51: =M44 -> 11 | C51: =O51 -> 11 | D51: =+B51-C51 -> 0 | G51: =SUM(G48:G50) -> 11 | I51: =SUM(I48:I50) -> 11 | K51: =SUM(K48:K50) -> 11 | M51: =SUM(M48:M50) -> 10 | O51: =SUM(O48:O50) -> 11 | Q51: =SUM(Q44:Q50) -> 10 | R51: =AVERAGE(G51,I51,K51,M51,O51,Q51) -> 10.666667 | BU51: 458
A52: 459 | B52: =O44 -> 10 | C52: =Q51 -> 10 | D52: =+B52-C52 -> 0 | T52: =SUM(R48:R50) -> 10.666667 | BU52: 459
A53: 463 | BU53: 463
A54: 464 | B54: TEJIDO 3 | D54: 3ER TURNO | R54: =$V2 -> DEL 08 AL 14 ENERO 24 | BU54: 464
A55: 465 | E55: L | G55: M | I55: M | K55: J | M55: V | O55: S | BU55: 465
B56: 116 | C56: =+C55+1 -> 1 | D56: Antunez Orona Juan Manuel | E56: 1 | G56: 1 | I56: 1 | K56: 1 | M56: 1 | O56: 1 | Q56: 1 | R56: =IF(Q56=1,1550,850) -> 1550 | S56: =+BH56 -> 0 | T56: =+BA56 -> 2050 | U56: =+BP56 -> 0 | V56: =+BG56 -> BONO+B ASIS | W56: =(R56-86.16)/6*E56 -> 243.97333 | X56: =$Y$2*E56*Q56 -> 7.18 | Y56: =$Y$2*E56*Q56 -> 7.18 | Z56: =Y56+X56+W56 -> 258.33333 | AB56: =(R56-86.16)/6*G56 -> 243.97333 | AC56: =$Y$2*G56*Q56 -> 7.18 | AD56: =$Y$2*G56*Q56 -> 7.18 | AE56: =AD56+AC56+AB56 -> 258.33333 | AG56: =(R56-86.16)/6*I56 -> 243.97333 | AH56: =$Y$2*I56*Q56 -> 7.18 | AI56: =$Y$2*I56*Q56 -> 7.18 | AJ56: =AI56+AH56+AG56 -> 258.33333 | AL56: =(R56-86.16)/6*K56 -> 243.97333 | AM56: =$Y$2*K56*Q56 -> 7.18 | AN56: =$Y$2*K56*Q56 -> 7.18 | AO56: =AN56+AM56+AL56 -> 258.33333 | AQ56: =(R56-86.16)/6*M56 -> 243.97333 | AR56: =$Y$2*M56*Q56 -> 7.18 | AS56: =$Y$2*M56*Q56 -> 7.18 | AT56: =AS56+AR56+AQ56 -> 258.33333 | AV56: =(R56-86.16)/6*O56 -> 243.97333 | AW56: =$Y$2*O56*Q56 -> 7.18 | AX56: =$Y$2*O56*Q56 -> 7.18 | AY56: =AX56+AW56+AV56 -> 258.33333 | AZ56: =+AY56+AT56+AO56++AJ56+AE56+Z56 -> 1550 | BA56: =((AZ56-BB56-BC56-BD56-BE56-BF56)+BI56+BJ56+BK56+BL56+BM56+BN56+BO56) -> 2050 | BG56: BONO+B ASIS | BI56: 250 | BJ56: 250
B57: 117 | C57: =+C56+1 -> 2 | D57: Antunez Salazar Aracely | E57: 1 | G57: 1 | I57: 1 | K57: 1 | M57: 1 | O57: 1 | Q57: 1 | R57: =IF(Q57=1,1550,850) -> 1550 | S57: =+BH57 -> 0 | T57: =+BA57 -> 2050 | U57: =+BP57 -> 0 | V57: =+BG57 -> BONO+B ASIS | W57: =(R57-86.16)/6*E57 -> 243.97333 | X57: =$Y$2*E57*Q57 -> 7.18 | Y57: =$Y$2*E57*Q57 -> 7.18 | Z57: =Y57+X57+W57 -> 258.33333 | AB57: =(R57-86.16)/6*G57 -> 243.97333 | AC57: =$Y$2*G57*Q57 -> 7.18 | AD57: =$Y$2*G57*Q57 -> 7.18 | AE57: =AD57+AC57+AB57 -> 258.33333 | AG57: =(R57-86.16)/6*I57 -> 243.97333 | AH57: =$Y$2*I57*Q57 -> 7.18 | AI57: =$Y$2*I57*Q57 -> 7.18 | AJ57: =AI57+AH57+AG57 -> 258.33333 | AL57: =(R57-86.16)/6*K57 -> 243.97333 | AM57: =$Y$2*K57*Q57 -> 7.18 | AN57: =$Y$2*K57*Q57 -> 7.18 | AO57: =AN57+AM57+AL57 -> 258.33333 | AQ57: =(R57-86.16)/6*M57 -> 243.97333 | AR57: =$Y$2*M57*Q57 -> 7.18 | AS57: =$Y$2*M57*Q57 -> 7.18 | AT57: =AS57+AR57+AQ57 -> 258.33333 | AV57: =(R57-86.16)/6*O57 -> 243.97333 | AW57: =$Y$2*O57*Q57 -> 7.18 | AX57: =$Y$2*O57*Q57 -> 7.18 | AY57: =AX57+AW57+AV57 -> 258.33333 | AZ57: =+AY57+AT57+AO57++AJ57+AE57+Z57 -> 1550 | BA57: =((AZ57-BB57-BC57-BD57-BE57-BF57)+BI57+BJ57+BK57+BL57+BM57+BN57+BO57) -> 2050 | BG57: BONO+B ASIS | BI57: 250 | BJ57: 250
B58: 162 | C58: =+C57+1 -> 3 | D58: Armijo Tostado Liliana Jaretzy | E58: 1 | G58: 1 | I58: 1 | K58: 1 | M58: 1 | O58: 1 | Q58: 1 | R58: =IF(Q58=1,1550,850) -> 1550 | S58: =+BH58 -> 0 | T58: =+BA58 -> 2050 | U58: =+BP58 -> 0 | V58: =+BG58 -> BONO+B ASIS | W58: =(R58-86.16)/6*E58 -> 243.97333 | X58: =$Y$2*E58*Q58 -> 7.18 | Y58: =$Y$2*E58*Q58 -> 7.18 | Z58: =Y58+X58+W58 -> 258.33333 | AB58: =(R58-86.16)/6*G58 -> 243.97333 | AC58: =$Y$2*G58*Q58 -> 7.18 | AD58: =$Y$2*G58*Q58 -> 7.18 | AE58: =AD58+AC58+AB58 -> 258.33333 | AG58: =(R58-86.16)/6*I58 -> 243.97333 | AH58: =$Y$2*I58*Q58 -> 7.18 | AI58: =$Y$2*I58*Q58 -> 7.18 | AJ58: =AI58+AH58+AG58 -> 258.33333 | AL58: =(R58-86.16)/6*K58 -> 243.97333 | AM58: =$Y$2*K58*Q58 -> 7.18 | AN58: =$Y$2*K58*Q58 -> 7.18 | AO58: =AN58+AM58+AL58 -> 258.33333 | AQ58: =(R58-86.16)/6*M58 -> 243.97333 | AR58: =$Y$2*M58*Q58 -> 7.18 | AS58: =$Y$2*M58*Q58 -> 7.18 | AT58: =AS58+AR58+AQ58 -> 258.33333 | AV58: =(R58-86.16)/6*O58 -> 243.97333 | AW58: =$Y$2*O58*Q58 -> 7.18 | AX58: =$Y$2*O58*Q58 -> 7.18 | AY58: =AX58+AW58+AV58 -> 258.33333 | AZ58: =+AY58+AT58+AO58++AJ58+AE58+Z58 -> 1550 | BA58: =((AZ58-BB58-BC58-BD58-BE58-BF58)+BI58+BJ58+BK58+BL58+BM58+BN58+BO58) -> 2050 | BG58: BONO+B ASIS | BI58: 250 | BJ58: 250
A59: 470 | B59: 7 | C59: =+C58+1 -> 4 | D59: Beberaje Cruz Ramon Humberto | E59: 1 | G59: 1 | I59: 1 | K59: 1 | M59: 1 | O59: 1 | Q59: 1 | R59: =IF(Q59=1,6000,850) -> 6000 | S59: =+BH59 -> 0 | T59: =+BA59 -> 6000 | U59: =+BP59 -> 0 | V59: =+BG59 -> 0 | W59: =(R59-86.16)/6*E59 -> 985.64 | X59: =$Y$2*E59*Q59 -> 7.18 | Y59: =$Y$2*E59*Q59 -> 7.18 | Z59: =Y59+X59+W59 -> 1000 | AB59: =(R59-86.16)/6*G59 -> 985.64 | AC59: =$Y$2*G59*Q59 -> 7.18 | AD59: =$Y$2*G59*Q59 -> 7.18 | AE59: =AD59+AC59+AB59 -> 1000 | AG59: =(R59-86.16)/6*I59 -> 985.64 | AH59: =$Y$2*I59*Q59 -> 7.18 | AI59: =$Y$2*I59*Q59 -> 7.18 | AJ59: =AI59+AH59+AG59 -> 1000 | AL59: =(R59-86.16)/6*K59 -> 985.64 | AM59: =$Y$2*K59*Q59 -> 7.18 | AN59: =$Y$2*K59*Q59 -> 7.18 | AO59: =AN59+AM59+AL59 -> 1000 | AQ59: =(R59-86.16)/6*M59 -> 985.64 | AR59: =$Y$2*M59*Q59 -> 7.18 | AS59: =$Y$2*M59*Q59 -> 7.18 | AT59: =AS59+AR59+AQ59 -> 1000 | AV59: =(R59-86.16)/6*O59 -> 985.64 | AW59: =$Y$2*O59*Q59 -> 7.18 | AX59: =$Y$2*O59*Q59 -> 7.18 | AY59: =AX59+AW59+AV59 -> 1000 | AZ59: =+AY59+AT59+AO59++AJ59+AE59+Z59 -> 6000 | BA59: =((AZ59-BB59-BC59-BD59-BE59-BF59)+BI59+BJ59+BK59+BL59+BM59+BN59+BO59) -> 6000 | BU59: 470
B60: 175 | C60: =+C59+1 -> 5 | D60: Carrillo Ojeda Jose Guadalupe | E60: 1 | G60: 1 | I60: 1 | K60: 1 | M60: 0 | N60: F | O60: 0 | P60: F | Q60: 1 | R60: =IF(Q60=1,1550,850) -> 1550 | S60: =+BH60 -> 0 | T60: =+BA60 -> 828.56 | U60: =+BP60 -> 0 | V60: =+BG60 -> 0 | W60: =(R60-86.16)/6*E60 -> 243.97333 | X60: =$Y$2*E60*Q60 -> 7.18 | Y60: =$Y$2*E60*Q60 -> 7.18 | Z60: =Y60+X60+W60 -> 258.33333 | AB60: =(R60-86.16)/6*G60 -> 243.97333 | AC60: =$Y$2*G60*Q60 -> 7.18 | AD60: =$Y$2*G60*Q60 -> 7.18 | AE60: =AD60+AC60+AB60 -> 258.33333 | AG60: =(R60-86.16)/6*I60 -> 243.97333 | AH60: =$Y$2*I60*Q60 -> 7.18 | AI60: =$Y$2*I60*Q60 -> 7.18 | AJ60: =AI60+AH60+AG60 -> 258.33333 | AL60: =(R60-86.16)/6*K60 -> 243.97333 | AM60: =$Y$2*K60*Q60 -> 7.18 | AN60: =$Y$2*K60*Q60 -> 7.18 | AO60: =AN60+AM60+AL60 -> 258.33333 | AQ60: =(R60-86.16)/6*M60 -> 0 | AR60: =$Y$2*M60*Q60 -> 0 | AS60: =$Y$2*M60*Q60 -> 0 | AT60: =AS60+AR60+AQ60 -> 0 | AV60: =(R60-86.16)/6*O60 -> 0 | AW60: =$Y$2*O60*Q60 -> 0 | AX60: =$Y$2*O60*Q60 -> 0 | AY60: =AX60+AW60+AV60 -> 0 | AZ60: =+AY60+AT60+AO60++AJ60+AE60+Z60 -> 1033.3333 | BA60: 828.56
A61: 468 | B61: 14 | C61: =+C60+1 -> 6 | D61: Esquivel Picon Miguel Angel | E61: 1 | G61: 1 | I61: 1 | K61: 1 | M61: 1 | O61: 1 | Q61: 1 | R61: =IF(Q61=1,1550,850) -> 1550 | S61: =+BH61 -> 0 | T61: =+BA61 -> 1950 | U61: =+BP61 -> 0 | V61: =+BG61 -> BONO+B ASIS | W61: =(R61-86.16)/6*E61 -> 243.97333 | X61: =$Y$2*E61*Q61 -> 7.18 | Y61: =$Y$2*E61*Q61 -> 7.18 | Z61: =Y61+X61+W61 -> 258.33333 | AB61: =(R61-86.16)/6*G61 -> 243.97333 | AC61: =$Y$2*G61*Q61 -> 7.18 | AD61: =$Y$2*G61*Q61 -> 7.18 | AE61: =AD61+AC61+AB61 -> 258.33333 | AG61: =(R61-86.16)/6*I61 -> 243.97333 | AH61: =$Y$2*I61*Q61 -> 7.18 | AI61: =$Y$2*I61*Q61 -> 7.18 | AJ61: =AI61+AH61+AG61 -> 258.33333 | AL61: =(R61-86.16)/6*K61 -> 243.97333 | AM61: =$Y$2*K61*Q61 -> 7.18 | AN61: =$Y$2*K61*Q61 -> 7.18 | AO61: =AN61+AM61+AL61 -> 258.33333 | AQ61: =(R61-86.16)/6*M61 -> 243.97333 | AR61: =$Y$2*M61*Q61 -> 7.18 | AS61: =$Y$2*M61*Q61 -> 7.18 | AT61: =AS61+AR61+AQ61 -> 258.33333 | AV61: =(R61-86.16)/6*O61 -> 243.97333 | AW61: =$Y$2*O61*Q61 -> 7.18 | AX61: =$Y$2*O61*Q61 -> 7.18 | AY61: =AX61+AW61+AV61 -> 258.33333 | AZ61: =+AY61+AT61+AO61++AJ61+AE61+Z61 -> 1550 | BA61: =((AZ61-BB61-BC61-BD61-BE61-BF61)+BI61+BJ61+BK61+BL61+BM61+BN61+BO61) -> 1950 | BG61: BONO+B ASIS | BI61: 250 | BJ61: 150 | BU61: 468
B62: 174 | C62: =+C61+1 -> 7 | D62: Mijarez Rodriguez San Juana Guadalupe | E62: 0 | F62: F | G62: 1 | I62: 1 | K62: 1 | M62: 1 | O62: 1 | Q62: 1 | R62: =IF(Q62=1,1550,850) -> 1550 | S62: =+BH62 -> 0 | T62: =+BA62 -> 2114.2767 | U62: =+BP62 -> 0 | V62: =+BG62 -> 0 | W62: =(R62-86.16)/6*E62 -> 0 | X62: =$Y$2*E62*Q62 -> 0 | Y62: =$Y$2*E62*Q62 -> 0 | Z62: =Y62+X62+W62 -> 0 | AB62: =(R62-86.16)/6*G62 -> 243.97333 | AC62: =$Y$2*G62*Q62 -> 7.18 | AD62: =$Y$2*G62*Q62 -> 7.18 | AE62: =AD62+AC62+AB62 -> 258.33333 | AG62: =(R62-86.16)/6*I62 -> 243.97333 | AH62: =$Y$2*I62*Q62 -> 7.18 | AI62: =$Y$2*I62*Q62 -> 7.18 | AJ62: =AI62+AH62+AG62 -> 258.33333 | AL62: =(R62-86.16)/6*K62 -> 243.97333 | AM62: =$Y$2*K62*Q62 -> 7.18 | AN62: =$Y$2*K62*Q62 -> 7.18 | AO62: =AN62+AM62+AL62 -> 258.33333 | AQ62: =(R62-86.16)/6*M62 -> 243.97333 | AR62: =$Y$2*M62*Q62 -> 7.18 | AS62: =$Y$2*M62*Q62 -> 7.18 | AT62: =AS62+AR62+AQ62 -> 258.33333 | AV62: =(R62-86.16)/6*O62 -> 243.97333 | AW62: =$Y$2*O62*Q62 -> 7.18 | AX62: =$Y$2*O62*Q62 -> 7.18 | AY62: =AX62+AW62+AV62 -> 258.33333 | AZ62: =+AY62+AT62+AO62++AJ62+AE62+Z62 -> 1291.6667 | BA62: =((AZ62-BB62-BC62-BD62-BE62-BF62)+BI62+BJ62+BK62+BL62+BM62+BN62+BO62) -> 2114.2767 | BI62: 250 | BL62: =414.28+158.33 -> 572.61
B63: 140 | C63: =+C62+1 -> 8 | D63: Morales Holguin Sergio Joel | E63: 0 | F63: F | G63: 1 | I63: 0 | J63: F | K63: 0 | L63: F | M63: 1 | O63: 1 | Q63: 1 | R63: =IF(Q63=1,1550,850) -> 1550 | S63: =+BH63 -> 0 | T63: =+BA63 -> 414.28 | U63: =+BP63 -> 0 | V63: =+BG63 -> 0 | W63: =(R63-86.16)/6*E63 -> 0 | X63: =$Y$2*E63*Q63 -> 0 | Y63: =$Y$2*E63*Q63 -> 0 | Z63: =Y63+X63+W63 -> 0 | AB63: =(R63-86.16)/6*G63 -> 243.97333 | AC63: =$Y$2*G63*Q63 -> 7.18 | AD63: =$Y$2*G63*Q63 -> 7.18 | AE63: =AD63+AC63+AB63 -> 258.33333 | AG63: =(R63-86.16)/6*I63 -> 0 | AH63: =$Y$2*I63*Q63 -> 0 | AI63: =$Y$2*I63*Q63 -> 0 | AJ63: =AI63+AH63+AG63 -> 0 | AL63: =(R63-86.16)/6*K63 -> 0 | AM63: =$Y$2*K63*Q63 -> 0 | AN63: =$Y$2*K63*Q63 -> 0 | AO63: =AN63+AM63+AL63 -> 0 | AQ63: =(R63-86.16)/6*M63 -> 243.97333 | AR63: =$Y$2*M63*Q63 -> 7.18 | AS63: =$Y$2*M63*Q63 -> 7.18 | AT63: =AS63+AR63+AQ63 -> 258.33333 | AV63: =(R63-86.16)/6*O63 -> 243.97333 | AW63: =$Y$2*O63*Q63 -> 7.18 | AX63: =$Y$2*O63*Q63 -> 7.18 | AY63: =AX63+AW63+AV63 -> 258.33333 | AZ63: =+AY63+AT63+AO63++AJ63+AE63+Z63 -> 775 | BA63: 414.28
B64: 176 | C64: =+C63+1 -> 9 | D64: Sandoval Martinez Vianey Nataly | E64: 1 | G64: 1 | I64: 1 | K64: 1 | M64: 1 | O64: 1 | Q64: 1 | R64: =IF(Q64=1,1550,850) -> 1550 | T64: =+BA64 -> 1950 | U64: =+BP64 -> 0 | V64: =+BG64 -> B ASIS | W64: =(R64-86.16)/6*E64 -> 243.97333 | X64: =$Y$2*E64*Q64 -> 7.18 | Y64: =$Y$2*E64*Q64 -> 7.18 | Z64: =Y64+X64+W64 -> 258.33333 | AB64: =(R64-86.16)/6*G64 -> 243.97333 | AC64: =$Y$2*G64*Q64 -> 7.18 | AD64: =$Y$2*G64*Q64 -> 7.18 | AE64: =AD64+AC64+AB64 -> 258.33333 | AG64: =(R64-86.16)/6*I64 -> 243.97333 | AH64: =$Y$2*I64*Q64 -> 7.18 | AI64: =$Y$2*I64*Q64 -> 7.18 | AJ64: =AI64+AH64+AG64 -> 258.33333 | AL64: =(R64-86.16)/6*K64 -> 243.97333 | AM64: =$Y$2*K64*Q64 -> 7.18 | AN64: =$Y$2*K64*Q64 -> 7.18 | AO64: =AN64+AM64+AL64 -> 258.33333 | AQ64: =(R64-86.16)/6*M64 -> 243.97333 | AR64: =$Y$2*M64*Q64 -> 7.18 | AS64: =$Y$2*M64*Q64 -> 7.18 | AT64: =AS64+AR64+AQ64 -> 258.33333 | AV64: =(R64-86.16)/6*O64 -> 243.97333 | AW64: =$Y$2*O64*Q64 -> 7.18 | AX64: =$Y$2*O64*Q64 -> 7.18 | AY64: =AX64+AW64+AV64 -> 258.33333 | AZ64: =+AY64+AT64+AO64++AJ64+AE64+Z64 -> 1550 | BA64: =((AZ64-BB64-BC64-BD64-BE64-BF64)+BI64+BJ64+BK64+BL64+BM64+BN64+BO64) -> 1950 | BG64: B ASIS | BI64: 150 | BJ64: 250
B65: 53 | C65: =+C64+1 -> 10 | D65: Vargas Cuellar Juana Gabriela | E65: 1 | G65: 1 | I65: 1 | K65: 1 | M65: 1 | O65: 1 | Q65: 1 | R65: =IF(Q65=1,1600,850) -> 1600 | S65: =+BH65 -> 0 | T65: =+BA65 -> 2107.14 | U65: =+BP65 -> 0 | V65: =+BG65 -> BONO+B ASIS+ T EXT | W65: =(R65-86.16)/6*E65 -> 252.30667 | X65: =$Y$2*E65*Q65 -> 7.18 | Y65: =$Y$2*E65*Q65 -> 7.18 | Z65: =Y65+X65+W65 -> 266.66667 | AB65: =(R65-86.16)/6*G65 -> 252.30667 | AC65: =$Y$2*G65*Q65 -> 7.18 | AD65: =$Y$2*G65*Q65 -> 7.18 | AE65: =AD65+AC65+AB65 -> 266.66667 | AG65: =(R65-86.16)/6*I65 -> 252.30667 | AH65: =$Y$2*I65*Q65 -> 7.18 | AI65: =$Y$2*I65*Q65 -> 7.18 | AJ65: =AI65+AH65+AG65 -> 266.66667 | AL65: =(R65-86.16)/6*K65 -> 252.30667 | AM65: =$Y$2*K65*Q65 -> 7.18 | AN65: =$Y$2*K65*Q65 -> 7.18 | AO65: =AN65+AM65+AL65 -> 266.66667 | AQ65: =(R65-86.16)/6*M65 -> 252.30667 | AR65: =$Y$2*M65*Q65 -> 7.18 | AS65: =$Y$2*M65*Q65 -> 7.18 | AT65: =AS65+AR65+AQ65 -> 266.66667 | AV65: =(R65-86.16)/6*O65 -> 252.30667 | AW65: =$Y$2*O65*Q65 -> 7.18 | AX65: =$Y$2*O65*Q65 -> 7.18 | AY65: =AX65+AW65+AV65 -> 266.66667 | AZ65: =+AY65+AT65+AO65++AJ65+AE65+Z65 -> 1600 | BA65: =((AZ65-BB65-BC65-BD65-BE65-BF65)+BI65+BJ65+BK65+BL65+BM65+BN65+BO65) -> 2107.14 | BG65: BONO+B ASIS+ T EXT | BI65: 300 | BJ65: 150 | BK65: 57.14
B66: 0 | C66: =+C65+1 -> 11 | D66: JUAREZ/SIFUENTES,BENITO | E66: 0 | F66: B | G66: 0 | H66: B | I66: 0 | J66: B | K66: 0 | L66: B | M66: 0 | N66: B | O66: 0 | P66: B | Q66: 0 | R66: 0 | S66: =+BH66 -> 0 | T66: =+BA66 -> 0 | U66: =+BP66 -> 0 | V66: =+BG66 -> 0 | W66: =(R66-86.16)/6*E66 -> 0 | X66: =$Y$2*E66*Q66 -> 0 | Z66: =Y66+X66+W66 -> 0 | AB66: =(R66-86.16)/6*G66 -> 0 | AG66: =(R66-86.16)/6*I66 -> 0 | AH66: =$Y$2*I66*Q66 -> 0 | AI66: =$Y$2*I66*Q66 -> 0 | AJ66: =AI66+AH66+AG66 -> 0 | AL66: =(R66-86.16)/6*K66 -> 0 | AM66: =$Y$2*K66*Q66 -> 0 | AQ66: =(R66-86.16)/6*M66 -> 0 | AR66: =$Y$2*M66*Q66 -> 0 | AS66: =$Y$2*M66*Q66 -> 0 | AT66: =AS66+AR66+AQ66 -> 0 | AV66: =(R66-86.16)/6*O66 -> 0 | AW66: =$Y$2*O66*Q66 -> 0 | AX66: =$Y$2*O66*Q66 -> 0 | AY66: =AX66+AW66+AV66 -> 0 | AZ66: 0
B67: 161 | C67: =+C66+1 -> 12 | D67: Vargas Chavez Sarai del Carmen | E67: 0 | F67: B | G67: 0 | H67: B | I67: 0 | J67: B | K67: 0 | L67: B | M67: 0 | N67: B | O67: 0 | P67: B | Q67: 0 | R67: 0 | S67: =+BH67 -> 0 | T67: =+BA67 -> 0 | U67: =+BP67 -> 0 | V67: =+BG67 -> 0 | W67: =(R67-86.16)/6*E67 -> 0 | X67: =$Y$2*E67*Q67 -> 0 | Y67: =$Y$2*E67*Q67 -> 0 | Z67: =Y67+X67+W67 -> 0 | AB67: =(R67-86.16)/6*G67 -> 0 | AC67: =$Y$2*G67*Q67 -> 0 | AD67: =$Y$2*G67*Q67 -> 0 | AE67: =AD67+AC67+AB67 -> 0 | AG67: =(R67-86.16)/6*I67 -> 0 | AH67: =$Y$2*I67*Q67 -> 0 | AI67: =$Y$2*I67*Q67 -> 0 | AJ67: =AI67+AH67+AG67 -> 0 | AL67: =(R67-86.16)/6*K67 -> 0 | AM67: =$Y$2*K67*Q67 -> 0 | AN67: =$Y$2*K67*Q67 -> 0 | AO67: =AN67+AM67+AL67 -> 0 | AQ67: =(R67-86.16)/6*M67 -> 0 | AR67: =$Y$2*M67*Q67 -> 0 | AS67: =$Y$2*M67*Q67 -> 0 | AT67: =AS67+AR67+AQ67 -> 0 | AV67: =(R67-86.16)/6*O67 -> 0 | AW67: =$Y$2*O67*Q67 -> 0 | AX67: =$Y$2*O67*Q67 -> 0 | AY67: =AX67+AW67+AV67 -> 0 | AZ67: =+AY67+AT67+AO67++AJ67+AE67+Z67 -> 0 | BA67: 0
A68: 472 | E68: =SUM(E56:E67) -> 8 | G68: =SUM(G56:G67) -> 10 | I68: =SUM(I56:I67) -> 9 | K68: =SUM(K56:K67) -> 9 | M68: =SUM(M56:M67) -> 9 | O68: =SUM(O56:O67) -> 9 | BU68: 472
A69: 473 | BU69: 473
A70: 474 | B70: REAL | C70: PR | G70: L | I70: M | K70: M | M70: J | O70: V | Q70: S | BU70: 474
A71: 475 | B71: =E68 -> 8 | C71: =G75 -> 8 | D71: =+B71-C71 -> 0 | R71: PROM | BU71: 475
A72: 476 | B72: =G68 -> 10 | C72: =I75 -> 10 | D72: =+B72-C72 -> 0 | E72: LIDER | G72: 1 | I72: 1 | K72: 1 | M72: 1 | O72: 1 | Q72: 1 | R72: =AVERAGE(G72,I72,K72,M72,O72,Q72) -> 1 | BU72: 476
A73: 477 | B73: =I68 -> 9 | C73: =K75 -> 9 | D73: =+B73-C73 -> 0 | E73: MECANICO | G73: 1 | I73: 1 | K73: 1 | M73: 1 | O73: 1 | Q73: 1 | R73: =AVERAGE(G73,I73,K73,M73,O73,Q73) -> 1 | BU73: 477
A74: 478 | B74: =K68 -> 9 | C74: =M75 -> 9 | D74: =+B74-C74 -> 0 | E74: MANUAL | G74: 6 | I74: 8 | K74: 7 | M74: 7 | O74: 7 | Q74: 7 | R74: =AVERAGE(G74,I74,K74,M74,O74,Q74) -> 7 | BU74: 478
A75: 479 | B75: =M68 -> 9 | C75: =O75 -> 9 | D75: =+B75-C75 -> 0 | G75: =SUM(G72:G74) -> 8 | I75: =SUM(I72:I74) -> 10 | K75: =SUM(K72:K74) -> 9 | M75: =SUM(M72:M74) -> 9 | O75: =SUM(O72:O74) -> 9 | Q75: =SUM(Q68:Q74) -> 9 | R75: =AVERAGE(G75,I75,K75,M75,O75,Q75) -> 9 | BU75: 479
A76: 480 | B76: =O68 -> 9 | C76: =Q75 -> 9 | D76: =+B76-C76 -> 0 | T76: =SUM(R72:R74) -> 9 | BU76: 480
A78: 482 | BU78: 482
A79: 483 | B79: PUÑO | D79: 3ER TURNO | R79: =$V2 -> DEL 08 AL 14 ENERO 24 | BU79: 483
A80: 484 | E80: L | G80: M | I80: M | K80: J | M80: V | O80: S | BU80: 484
B81: 71 | C81: =C80+1 -> 1 | D81: Aguilar Muñoz Eduardo | E81: 1 | G81: 1 | I81: 1 | K81: 0 | L81: SUSP | M81: 1 | O81: 1 | Q81: 1 | R81: 2000 | S81: =+BH81 -> 0 | T81: =+BA81 -> 1714 | U81: =+BP81 -> 0 | V81: =+BG81 -> 0 | W81: =(R81-86.16)/6*E81 -> 318.97333 | X81: =$Y$2*E81*Q81 -> 7.18 | Y81: =$Y$2*E81*Q81 -> 7.18 | Z81: =Y81+X81+W81 -> 333.33333 | AB81: =(R81-86.16)/6*G81 -> 318.97333 | AC81: =$Y$2*G81*Q81 -> 7.18 | AD81: =$Y$2*G81*Q81 -> 7.18 | AE81: =AD81+AC81+AB81 -> 333.33333 | AG81: =(R81-86.16)/6*I81 -> 318.97333 | AH81: =$Y$2*I81*Q81 -> 7.18 | AI81: =$Y$2*I81*Q81 -> 7.18 | AJ81: =AI81+AH81+AG81 -> 333.33333 | AL81: =(R81-86.16)/6*K81 -> 0 | AM81: =$Y$2*K81*Q81 -> 0 | AN81: =$Y$2*K81*Q81 -> 0 | AO81: =AN81+AM81+AL81 -> 0 | AQ81: =(R81-86.16)/6*M81 -> 318.97333 | AR81: =$Y$2*M81*Q81 -> 7.18 | AS81: =$Y$2*M81*Q81 -> 7.18 | AT81: =AS81+AR81+AQ81 -> 333.33333 | AV81: =(R81-86.16)/6*O81 -> 318.97333 | AW81: =$Y$2*O81*Q81 -> 7.18 | AX81: =$Y$2*O81*Q81 -> 7.18 | AY81: =AX81+AW81+AV81 -> 333.33333 | AZ81: =+AY81+AT81+AO81++AJ81+AE81+Z81 -> 1666.6667 | BA81: 1714
B82: 147 | C82: =C81+1 -> 2 | D82: Alaniz Mayorga Yulissa | E82: 1 | G82: 1 | I82: 1 | K82: 1 | M82: 1 | O82: 1 | Q82: 1 | R82: =IF(Q82=1,1550,850) -> 1550 | S82: =+BH82 -> 0 | T82: =+BA82 -> 2000 | U82: =+BP82 -> 0 | V82: =+BG82 -> BONO+B ASIS | W82: =(R82-86.16)/6*E82 -> 243.97333 | X82: =$Y$2*E82*Q82 -> 7.18 | Y82: =$Y$2*E82*Q82 -> 7.18 | Z82: =Y82+X82+W82 -> 258.33333 | AB82: =(R82-86.16)/6*G82 -> 243.97333 | AC82: =$Y$2*G82*Q82 -> 7.18 | AD82: =$Y$2*G82*Q82 -> 7.18 | AE82: =AD82+AC82+AB82 -> 258.33333 | AG82: =(R82-86.16)/6*I82 -> 243.97333 | AH82: =$Y$2*I82*Q82 -> 7.18 | AI82: =$Y$2*I82*Q82 -> 7.18 | AJ82: =AI82+AH82+AG82 -> 258.33333 | AL82: =(R82-86.16)/6*K82 -> 243.97333 | AM82: =$Y$2*K82*Q82 -> 7.18 | AN82: =$Y$2*K82*Q82 -> 7.18 | AO82: =AN82+AM82+AL82 -> 258.33333 | AQ82: =(R82-86.16)/6*M82 -> 243.97333 | AR82: =$Y$2*M82*Q82 -> 7.18 | AS82: =$Y$2*M82*Q82 -> 7.18 | AT82: =AS82+AR82+AQ82 -> 258.33333 | AV82: =(R82-86.16)/6*O82 -> 243.97333 | AW82: =$Y$2*O82*Q82 -> 7.18 | AX82: =$Y$2*O82*Q82 -> 7.18 | AY82: =AX82+AW82+AV82 -> 258.33333 | AZ82: =+AY82+AT82+AO82++AJ82+AE82+Z82 -> 1550 | BA82: =((AZ82-BB82-BC82-BD82-BE82-BF82)+BI82+BJ82+BK82+BL82+BM82+BN82+BO82) -> 2000 | BG82: BONO+B ASIS | BI82: 300 | BJ82: 150
B83: 127 | C83: =C82+1 -> 3 | D83: Carranza Chavarria Esmeralda | E83: 1 | G83: 1 | I83: 1 | K83: 1 | M83: 1 | O83: 1 | Q83: 1 | R83: =IF(Q83=1,1550,850) -> 1550 | S83: =+BH83 -> 0 | T83: =+BA83 -> 1800 | U83: =+BP83 -> 0 | V83: =+BG83 -> BONO | W83: =(R83-86.16)/6*E83 -> 243.97333 | X83: =$Y$2*E83*Q83 -> 7.18 | Y83: =$Y$2*E83*Q83 -> 7.18 | Z83: =Y83+X83+W83 -> 258.33333 | AB83: =(R83-86.16)/6*G83 -> 243.97333 | AC83: =$Y$2*G83*Q83 -> 7.18 | AD83: =$Y$2*G83*Q83 -> 7.18 | AE83: =AD83+AC83+AB83 -> 258.33333 | AG83: =(R83-86.16)/6*I83 -> 243.97333 | AH83: =$Y$2*I83*Q83 -> 7.18 | AI83: =$Y$2*I83*Q83 -> 7.18 | AJ83: =AI83+AH83+AG83 -> 258.33333 | AL83: =(R83-86.16)/6*K83 -> 243.97333 | AM83: =$Y$2*K83*Q83 -> 7.18 | AN83: =$Y$2*K83*Q83 -> 7.18 | AO83: =AN83+AM83+AL83 -> 258.33333 | AQ83: =(R83-86.16)/6*M83 -> 243.97333 | AR83: =$Y$2*M83*Q83 -> 7.18 | AS83: =$Y$2*M83*Q83 -> 7.18 | AT83: =AS83+AR83+AQ83 -> 258.33333 | AV83: =(R83-86.16)/6*O83 -> 243.97333 | AW83: =$Y$2*O83*Q83 -> 7.18 | AX83: =$Y$2*O83*Q83 -> 7.18 | AY83: =AX83+AW83+AV83 -> 258.33333 | AZ83: =+AY83+AT83+AO83++AJ83+AE83+Z83 -> 1550 | BA83: =((AZ83-BB83-BC83-BD83-BE83-BF83)+BI83+BJ83+BK83+BL83+BM83+BN83+BO83) -> 1800 | BG83: BONO | BI83: 250 | BJ83: 0
B84: 69 | C84: =C83+1 -> 4 | D84: Carranza Hernandez Maria Fernanda | E84: 1 | G84: 1 | I84: 1 | K84: 1 | M84: 1 | O84: 1 | Q84: 1 | R84: =IF(Q84=1,1550,850) -> 1550 | S84: =+BH84 -> 0 | T84: =+BA84 -> 1800 | U84: =+BP84 -> 0 | V84: =+BG84 -> BONO | W84: =(R84-86.16)/6*E84 -> 243.97333 | X84: =$Y$2*E84*Q84 -> 7.18 | Y84: =$Y$2*E84*Q84 -> 7.18 | Z84: =Y84+X84+W84 -> 258.33333 | AB84: =(R84-86.16)/6*G84 -> 243.97333 | AC84: =$Y$2*G84*Q84 -> 7.18 | AD84: =$Y$2*G84*Q84 -> 7.18 | AE84: =AD84+AC84+AB84 -> 258.33333 | AG84: =(R84-86.16)/6*I84 -> 243.97333 | AH84: =$Y$2*I84*Q84 -> 7.18 | AI84: =$Y$2*I84*Q84 -> 7.18 | AJ84: =AI84+AH84+AG84 -> 258.33333 | AL84: =(R84-86.16)/6*K84 -> 243.97333 | AM84: =$Y$2*K84*Q84 -> 7.18 | AN84: =$Y$2*K84*Q84 -> 7.18 | AO84: =AN84+AM84+AL84 -> 258.33333 | AQ84: =(R84-86.16)/6*M84 -> 243.97333 | AR84: =$Y$2*M84*Q84 -> 7.18 | AS84: =$Y$2*M84*Q84 -> 7.18 | AT84: =AS84+AR84+AQ84 -> 258.33333 | AV84: =(R84-86.16)/6*O84 -> 243.97333 | AW84: =$Y$2*O84*Q84 -> 7.18 | AX84: =$Y$2*O84*Q84 -> 7.18 | AY84: =AX84+AW84+AV84 -> 258.33333 | AZ84: =+AY84+AT84+AO84++AJ84+AE84+Z84 -> 1550 | BA84: =((AZ84-BB84-BC84-BD84-BE84-BF84)+BI84+BJ84+BK84+BL84+BM84+BN84+BO84) -> 1800 | BG84: BONO | BI84: 250
B85: 107 | C85: =C84+1 -> 5 | D85: Chavarria Machado Samuel | E85: 1 | G85: 1 | I85: 1 | K85: 1 | M85: 1 | O85: 1 | Q85: 1 | R85: 2000 | S85: =+BH85 -> 0 | T85: =+BA85 -> 2500 | U85: =+BP85 -> 0 | V85: =+BG85 -> BONO+B ASIS | W85: =(R85-86.16)/6*E85 -> 318.97333 | X85: =$Y$2*E85*Q85 -> 7.18 | Y85: =$Y$2*E85*Q85 -> 7.18 | Z85: =Y85+X85+W85 -> 333.33333 | AB85: =(R85-86.16)/6*G85 -> 318.97333 | AC85: =$Y$2*G85*Q85 -> 7.18 | AD85: =$Y$2*G85*Q85 -> 7.18 | AE85: =AD85+AC85+AB85 -> 333.33333 | AG85: =(R85-86.16)/6*I85 -> 318.97333 | AH85: =$Y$2*I85*Q85 -> 7.18 | AI85: =$Y$2*I85*Q85 -> 7.18 | AJ85: =AI85+AH85+AG85 -> 333.33333 | AL85: =(R85-86.16)/6*K85 -> 318.97333 | AM85: =$Y$2*K85*Q85 -> 7.18 | AN85: =$Y$2*K85*Q85 -> 7.18 | AO85: =AN85+AM85+AL85 -> 333.33333 | AQ85: =(R85-86.16)/6*M85 -> 318.97333 | AR85: =$Y$2*M85*Q85 -> 7.18 | AS85: =$Y$2*M85*Q85 -> 7.18 | AT85: =AS85+AR85+AQ85 -> 333.33333 | AV85: =(R85-86.16)/6*O85 -> 318.97333 | AW85: =$Y$2*O85*Q85 -> 7.18 | AX85: =$Y$2*O85*Q85 -> 7.18 | AY85: =AX85+AW85+AV85 -> 333.33333 | AZ85: =+AY85+AT85+AO85++AJ85+AE85+Z85 -> 2000 | BA85: =((AZ85-BB85-BC85-BD85-BE85-BF85)+BI85+BJ85+BK85+BL85+BM85+BN85+BO85) -> 2500 | BG85: BONO+B ASIS | BI85: 350 | BJ85: 150
A86: 421 | B86: 63 | C86: =C85+1 -> 6 | D86: Cuapio Flores Mario | E86: 1 | G86: 1 | I86: 1 | K86: 1 | M86: 1 | O86: 1 | Q86: 1 | R86: 7000 | S86: =+BH86 -> 0 | T86: =+BA86 -> 10500 | U86: =+BP86 -> 0 | V86: =+BG86 -> PV2A 2/2 | W86: =(R86-86.16)/6*E86 -> 1152.3067 | X86: =$Y$2*E86*Q86 -> 7.18 | Y86: =$Y$2*E86*Q86 -> 7.18 | Z86: =Y86+X86+W86 -> 1166.6667 | AB86: =(R86-86.16)/6*G86 -> 1152.3067 | AC86: =$Y$2*G86*Q86 -> 7.18 | AD86: =$Y$2*G86*Q86 -> 7.18 | AE86: =AD86+AC86+AB86 -> 1166.6667 | AG86: =(R86-86.16)/6*I86 -> 1152.3067 | AH86: =$Y$2*I86*Q86 -> 7.18 | AI86: =$Y$2*I86*Q86 -> 7.18 | AJ86: =AI86+AH86+AG86 -> 1166.6667 | AL86: =(R86-86.16)/6*K86 -> 1152.3067 | AM86: =$Y$2*K86*Q86 -> 7.18 | AN86: =$Y$2*K86*Q86 -> 7.18 | AO86: =AN86+AM86+AL86 -> 1166.6667 | AQ86: =(R86-86.16)/6*M86 -> 1152.3067 | AR86: =$Y$2*M86*Q86 -> 7.18 | AS86: =$Y$2*M86*Q86 -> 7.18 | AT86: =AS86+AR86+AQ86 -> 1166.6667 | AV86: =(R86-86.16)/6*O86 -> 1152.3067 | AW86: =$Y$2*O86*Q86 -> 7.18 | AX86: =$Y$2*O86*Q86 -> 7.18 | AY86: =AX86+AW86+AV86 -> 1166.6667 | AZ86: =+AY86+AT86+AO86++AJ86+AE86+Z86 -> 7000 | BA86: =7000+BI86+BJ86+BK86+BL86+BM86 -> 10500 | BG86: PV2A 2/2 | BM86: 3500 | BU86: 421
B87: 94 | C87: =C86+1 -> 7 | D87: Dominguez Soto Jesus Alberto | E87: 1 | G87: 1 | I87: 1 | K87: 1 | M87: 1 | O87: 1 | Q87: 1 | R87: 2000 | S87: =+BH87 -> 0 | T87: =+BA87 -> 2600 | U87: =+BP87 -> 0 | V87: =+BG87 -> BONO+B ASIS | W87: =(R87-86.16)/6*E87 -> 318.97333 | X87: =$Y$2*E87*Q87 -> 7.18 | Y87: =$Y$2*E87*Q87 -> 7.18 | Z87: =Y87+X87+W87 -> 333.33333 | AB87: =(R87-86.16)/6*G87 -> 318.97333 | AC87: =$Y$2*G87*Q87 -> 7.18 | AD87: =$Y$2*G87*Q87 -> 7.18 | AE87: =AD87+AC87+AB87 -> 333.33333 | AG87: =(R87-86.16)/6*I87 -> 318.97333 | AH87: =$Y$2*I87*Q87 -> 7.18 | AI87: =$Y$2*I87*Q87 -> 7.18 | AJ87: =AI87+AH87+AG87 -> 333.33333 | AL87: =(R87-86.16)/6*K87 -> 318.97333 | AM87: =$Y$2*K87*Q87 -> 7.18 | AN87: =$Y$2*K87*Q87 -> 7.18 | AO87: =AN87+AM87+AL87 -> 333.33333 | AQ87: =(R87-86.16)/6*M87 -> 318.97333 | AR87: =$Y$2*M87*Q87 -> 7.18 | AS87: =$Y$2*M87*Q87 -> 7.18 | AT87: =AS87+AR87+AQ87 -> 333.33333 | AV87: =(R87-86.16)/6*O87 -> 318.97333 | AW87: =$Y$2*O87*Q87 -> 7.18 | AX87: =$Y$2*O87*Q87 -> 7.18 | AY87: =AX87+AW87+AV87 -> 333.33333 | AZ87: =+AY87+AT87+AO87++AJ87+AE87+Z87 -> 2000 | BA87: =((AZ87-BB87-BC87-BD87-BE87-BF87)+BI87+BJ87+BK87+BL87+BM87+BN87+BO87) -> 2600 | BG87: BONO+B ASIS | BI87: 350 | BJ87: 250
B88: 167 | C88: =C87+1 -> 8 | D88: Dominguez Soto Maria de los Angeles | E88: 1 | G88: 1 | I88: 1 | K88: 1 | M88: 1 | O88: 1 | Q88: 1 | R88: =IF(Q88=1,1550,850) -> 1550 | S88: =+BH88 -> 0 | T88: =+BA88 -> 1800 | U88: =+BP88 -> 0 | V88: =+BG88 -> B ASIS | W88: =(R88-86.16)/6*E88 -> 243.97333 | X88: =$Y$2*E88*Q88 -> 7.18 | Y88: =$Y$2*E88*Q88 -> 7.18 | Z88: =Y88+X88+W88 -> 258.33333 | AB88: =(R88-86.16)/6*G88 -> 243.97333 | AC88: =$Y$2*G88*Q88 -> 7.18 | AD88: =$Y$2*G88*Q88 -> 7.18 | AE88: =AD88+AC88+AB88 -> 258.33333 | AG88: =(R88-86.16)/6*I88 -> 243.97333 | AH88: =$Y$2*I88*Q88 -> 7.18 | AI88: =$Y$2*I88*Q88 -> 7.18 | AJ88: =AI88+AH88+AG88 -> 258.33333 | AL88: =(R88-86.16)/6*K88 -> 243.97333 | AM88: =$Y$2*K88*Q88 -> 7.18 | AN88: =$Y$2*K88*Q88 -> 7.18 | AO88: =AN88+AM88+AL88 -> 258.33333 | AQ88: =(R88-86.16)/6*M88 -> 243.97333 | AR88: =$Y$2*M88*Q88 -> 7.18 | AS88: =$Y$2*M88*Q88 -> 7.18 | AT88: =AS88+AR88+AQ88 -> 258.33333 | AV88: =(R88-86.16)/6*O88 -> 243.97333 | AW88: =$Y$2*O88*Q88 -> 7.18 | AX88: =$Y$2*O88*Q88 -> 7.18 | AY88: =AX88+AW88+AV88 -> 258.33333 | AZ88: =+AY88+AT88+AO88++AJ88+AE88+Z88 -> 1550 | BA88: =((AZ88-BB88-BC88-BD88-BE88-BF88)+BI88+BJ88+BK88+BL88+BM88+BN88+BO88) -> 1800 | BG88: B ASIS | BI88: 100 | BJ88: 150
B89: 143 | C89: =C88+1 -> 9 | D89: Estrada Hernandez Arantxa | E89: 1 | G89: 1 | I89: 1 | K89: 1 | M89: 1 | O89: 1 | Q89: 1 | R89: =IF(Q89=1,1550,850) -> 1550 | S89: =+BH89 -> 0 | T89: =+BA89 -> 2107.14 | U89: =+BP89 -> 0 | V89: =+BG89 -> BONO+B ASIS+T EXT | W89: =(R89-86.16)/6*E89 -> 243.97333 | X89: =$Y$2*E89*Q89 -> 7.18 | Y89: =$Y$2*E89*Q89 -> 7.18 | Z89: =Y89+X89+W89 -> 258.33333 | AB89: =(R89-86.16)/6*G89 -> 243.97333 | AC89: =$Y$2*G89*Q89 -> 7.18 | AD89: =$Y$2*G89*Q89 -> 7.18 | AE89: =AD89+AC89+AB89 -> 258.33333 | AG89: =(R89-86.16)/6*I89 -> 243.97333 | AH89: =$Y$2*I89*Q89 -> 7.18 | AI89: =$Y$2*I89*Q89 -> 7.18 | AJ89: =AI89+AH89+AG89 -> 258.33333 | AL89: =(R89-86.16)/6*K89 -> 243.97333 | AM89: =$Y$2*K89*Q89 -> 7.18 | AN89: =$Y$2*K89*Q89 -> 7.18 | AO89: =AN89+AM89+AL89 -> 258.33333 | AQ89: =(R89-86.16)/6*M89 -> 243.97333 | AR89: =$Y$2*M89*Q89 -> 7.18 | AS89: =$Y$2*M89*Q89 -> 7.18 | AT89: =AS89+AR89+AQ89 -> 258.33333 | AV89: =(R89-86.16)/6*O89 -> 243.97333 | AW89: =$Y$2*O89*Q89 -> 7.18 | AX89: =$Y$2*O89*Q89 -> 7.18 | AY89: =AX89+AW89+AV89 -> 258.33333 | AZ89: =+AY89+AT89+AO89++AJ89+AE89+Z89 -> 1550 | BA89: =((AZ89-BB89-BC89-BD89-BE89-BF89)+BI89+BJ89+BK89+BL89+BM89+BN89+BO89) -> 2107.14 | BG89: BONO+B ASIS+T EXT | BI89: 250 | BJ89: 250 | BK89: 57.14
B90: 70 | C90: =C89+1 -> 10 | D90: Gonzalez Lopez Violeta | E90: 0 | F90: INC | G90: 0 | H90: INC | I90: 0 | J90: INC | K90: 0 | L90: INC | M90: 0 | N90: INC | O90: 0 | P90: INC | Q90: 0 | R90: =IF(Q90=1,1550,850) -> 850 | S90: =+BH90 -> 0 | T90: =+BA90 -> 0 | U90: =+BP90 -> 0 | V90: =+BG90 -> 0 | W90: =(R90-86.16)/6*E90 -> 0 | X90: =$Y$2*E90*Q90 -> 0 | Y90: =$Y$2*E90*Q90 -> 0 | Z90: =Y90+X90+W90 -> 0 | AB90: =(R90-86.16)/6*G90 -> 0 | AC90: =$Y$2*G90*Q90 -> 0 | AD90: =$Y$2*G90*Q90 -> 0 | AE90: =AD90+AC90+AB90 -> 0 | AG90: =(R90-86.16)/6*I90 -> 0 | AH90: =$Y$2*I90*Q90 -> 0 | AI90: =$Y$2*I90*Q90 -> 0 | AJ90: =AI90+AH90+AG90 -> 0 | AL90: =(R90-86.16)/6*K90 -> 0 | AM90: =$Y$2*K90*Q90 -> 0 | AN90: =$Y$2*K90*Q90 -> 0 | AO90: =AN90+AM90+AL90 -> 0 | AQ90: =(R90-86.16)/6*M90 -> 0 | AR90: =$Y$2*M90*Q90 -> 0 | AS90: =$Y$2*M90*Q90 -> 0 | AT90: =AS90+AR90+AQ90 -> 0 | AV90: =(R90-86.16)/6*O90 -> 0 | AW90: =$Y$2*O90*Q90 -> 0 | AX90: =$Y$2*O90*Q90 -> 0 | AY90: =AX90+AW90+AV90 -> 0 | AZ90: =+AY90+AT90+AO90++AJ90+AE90+Z90 -> 0
A91: 522 | B91: 120 | C91: =C90+1 -> 11 | D91: Guerrero Zamarron Melani Abigail | E91: 1 | G91: 1 | I91: 1 | K91: 1 | M91: 1 | O91: 1 | Q91: 1 | R91: =IF(Q91=1,1550,850) -> 1550 | S91: =+BH91 -> 0 | T91: =+BA91 -> 1950 | U91: =+BP91 -> 0 | V91: =+BG91 -> BONO+B ASIS | W91: =(R91-86.16)/6*E91 -> 243.97333 | X91: =$Y$2*E91*Q91 -> 7.18 | Y91: =$Y$2*E91*Q91 -> 7.18 | Z91: =Y91+X91+W91 -> 258.33333 | AB91: =(R91-86.16)/6*G91 -> 243.97333 | AC91: =$Y$2*G91*Q91 -> 7.18 | AD91: =$Y$2*G91*Q91 -> 7.18 | AE91: =AD91+AC91+AB91 -> 258.33333 | AG91: =(R91-86.16)/6*I91 -> 243.97333 | AH91: =$Y$2*I91*Q91 -> 7.18 | AI91: =$Y$2*I91*Q91 -> 7.18 | AJ91: =AI91+AH91+AG91 -> 258.33333 | AL91: =(R91-86.16)/6*K91 -> 243.97333 | AM91: =$Y$2*K91*Q91 -> 7.18 | AN91: =$Y$2*K91*Q91 -> 7.18 | AO91: =AN91+AM91+AL91 -> 258.33333 | AQ91: =(R91-86.16)/6*M91 -> 243.97333 | AR91: =$Y$2*M91*Q91 -> 7.18 | AS91: =$Y$2*M91*Q91 -> 7.18 | AT91: =AS91+AR91+AQ91 -> 258.33333 | AV91: =(R91-86.16)/6*O91 -> 243.97333 | AW91: =$Y$2*O91*Q91 -> 7.18 | AX91: =$Y$2*O91*Q91 -> 7.18 | AY91: =AX91+AW91+AV91 -> 258.33333 | AZ91: =+AY91+AT91+AO91++AJ91+AE91+Z91 -> 1550 | BA91: =((AZ91-BB91-BC91-BD91-BE91-BF91)+BI91+BJ91+BK91+BL91+BM91+BN91+BO91) -> 1950 | BG91: BONO+B ASIS | BI91: 250 | BJ91: 150 | BU91: 522
B92: 142 | C92: =C91+1 -> 12 | D92: Limon Campos Beatriz Adriana | E92: 1 | G92: 1 | I92: 1 | K92: 1 | M92: 1 | O92: 1 | Q92: 1 | R92: =IF(Q92=1,1550,850) -> 1550 | S92: =+BH92 -> 0 | T92: =+BA92 -> 1950 | U92: =+BP92 -> 0 | V92: =+BG92 -> BONO+B ASIS | W92: =(R92-86.16)/6*E92 -> 243.97333 | X92: =$Y$2*E92*Q92 -> 7.18 | Y92: =$Y$2*E92*Q92 -> 7.18 | Z92: =Y92+X92+W92 -> 258.33333 | AB92: =(R92-86.16)/6*G92 -> 243.97333 | AC92: =$Y$2*G92*Q92 -> 7.18 | AD92: =$Y$2*G92*Q92 -> 7.18 | AE92: =AD92+AC92+AB92 -> 258.33333 | AG92: =(R92-86.16)/6*I92 -> 243.97333 | AH92: =$Y$2*I92*Q92 -> 7.18 | AI92: =$Y$2*I92*Q92 -> 7.18 | AJ92: =AI92+AH92+AG92 -> 258.33333 | AL92: =(R92-86.16)/6*K92 -> 243.97333 | AM92: =$Y$2*K92*Q92 -> 7.18 | AN92: =$Y$2*K92*Q92 -> 7.18 | AO92: =AN92+AM92+AL92 -> 258.33333 | AQ92: =(R92-86.16)/6*M92 -> 243.97333 | AR92: =$Y$2*M92*Q92 -> 7.18 | AS92: =$Y$2*M92*Q92 -> 7.18 | AT92: =AS92+AR92+AQ92 -> 258.33333 | AV92: =(R92-86.16)/6*O92 -> 243.97333 | AW92: =$Y$2*O92*Q92 -> 7.18 | AX92: =$Y$2*O92*Q92 -> 7.18 | AY92: =AX92+AW92+AV92 -> 258.33333 | AZ92: =+AY92+AT92+AO92++AJ92+AE92+Z92 -> 1550 | BA92: =((AZ92-BB92-BC92-BD92-BE92-BF92)+BI92+BJ92+BK92+BL92+BM92+BN92+BO92) -> 1950 | BG92: BONO+B ASIS | BI92: 250 | BJ92: 150
B93: 138 | C93: =C92+1 -> 13 | D93: Martinez Robles Luis Miguel | E93: 1 | G93: 1 | I93: 1 | K93: 1 | M93: 1 | O93: 1 | Q93: 1 | R93: 2000 | S93: =+BH93 -> 0 | T93: =+BA93 -> 2150 | U93: =+BP93 -> 0 | V93: =+BG93 -> B ASIS | W93: =(R93-86.16)/6*E93 -> 318.97333 | X93: =$Y$2*E93*Q93 -> 7.18 | Y93: =$Y$2*E93*Q93 -> 7.18 | Z93: =Y93+X93+W93 -> 333.33333 | AB93: =(R93-86.16)/6*G93 -> 318.97333 | AC93: =$Y$2*G93*Q93 -> 7.18 | AD93: =$Y$2*G93*Q93 -> 7.18 | AE93: =AD93+AC93+AB93 -> 333.33333 | AG93: =(R93-86.16)/6*I93 -> 318.97333 | AH93: =$Y$2*I93*Q93 -> 7.18 | AI93: =$Y$2*I93*Q93 -> 7.18 | AJ93: =AI93+AH93+AG93 -> 333.33333 | AL93: =(R93-86.16)/6*K93 -> 318.97333 | AM93: =$Y$2*K93*Q93 -> 7.18 | AN93: =$Y$2*K93*Q93 -> 7.18 | AO93: =AN93+AM93+AL93 -> 333.33333 | AQ93: =(R93-86.16)/6*M93 -> 318.97333 | AR93: =$Y$2*M93*Q93 -> 7.18 | AS93: =$Y$2*M93*Q93 -> 7.18 | AT93: =AS93+AR93+AQ93 -> 333.33333 | AV93: =(R93-86.16)/6*O93 -> 318.97333 | AW93: =$Y$2*O93*Q93 -> 7.18 | AX93: =$Y$2*O93*Q93 -> 7.18 | AY93: =AX93+AW93+AV93 -> 333.33333 | AZ93: =+AY93+AT93+AO93++AJ93+AE93+Z93 -> 2000 | BA93: =((AZ93-BB93-BC93-BD93-BE93-BF93)+BI93+BJ93+BK93+BL93+BM93+BN93+BO93) -> 2150 | BG93: B ASIS | BJ93: 150
B94: 135 | C94: =C93+1 -> 14 | D94: Martinez Rosales Sugey Marisol | E94: 1 | G94: 1 | I94: 1 | K94: 1 | M94: 1 | O94: 1 | Q94: 1 | R94: =IF(Q94=1,1550,850) -> 1550 | S94: =+BH94 -> 0 | T94: =+BA94 -> 1950 | U94: =+BP94 -> 0 | V94: =+BG94 -> BONO+B ASIS | W94: =(R94-86.16)/6*E94 -> 243.97333 | X94: =$Y$2*E94*Q94 -> 7.18 | Y94: =$Y$2*E94*Q94 -> 7.18 | Z94: =Y94+X94+W94 -> 258.33333 | AB94: =(R94-86.16)/6*G94 -> 243.97333 | AC94: =$Y$2*G94*Q94 -> 7.18 | AD94: =$Y$2*G94*Q94 -> 7.18 | AE94: =AD94+AC94+AB94 -> 258.33333 | AG94: =(R94-86.16)/6*I94 -> 243.97333 | AH94: =$Y$2*I94*Q94 -> 7.18 | AI94: =$Y$2*I94*Q94 -> 7.18 | AJ94: =AI94+AH94+AG94 -> 258.33333 | AL94: =(R94-86.16)/6*K94 -> 243.97333 | AM94: =$Y$2*K94*Q94 -> 7.18 | AN94: =$Y$2*K94*Q94 -> 7.18 | AO94: =AN94+AM94+AL94 -> 258.33333 | AQ94: =(R94-86.16)/6*M94 -> 243.97333 | AR94: =$Y$2*M94*Q94 -> 7.18 | AS94: =$Y$2*M94*Q94 -> 7.18 | AT94: =AS94+AR94+AQ94 -> 258.33333 | AV94: =(R94-86.16)/6*O94 -> 243.97333 | AW94: =$Y$2*O94*Q94 -> 7.18 | AX94: =$Y$2*O94*Q94 -> 7.18 | AY94: =AX94+AW94+AV94 -> 258.33333 | AZ94: =+AY94+AT94+AO94++AJ94+AE94+Z94 -> 1550 | BA94: =((AZ94-BB94-BC94-BD94-BE94-BF94)+BI94+BJ94+BK94+BL94+BM94+BN94+BO94) -> 1950 | BG94: BONO+B ASIS | BI94: 250 | BJ94: 150
B95: 150 | C95: =C94+1 -> 15 | D95: Moreno Martinez Marisol | E95: 1 | G95: 1 | I95: 1 | K95: 1 | M95: 1 | O95: 1 | Q95: 1 | R95: =IF(Q95=1,1550,850) -> 1550 | S95: =+BH95 -> 0 | T95: =+BA95 -> 1950 | U95: =+BP95 -> 0 | V95: =+BG95 -> BONO+B ASIS | W95: =(R95-86.16)/6*E95 -> 243.97333 | X95: =$Y$2*E95*Q95 -> 7.18 | Y95: =$Y$2*E95*Q95 -> 7.18 | Z95: =Y95+X95+W95 -> 258.33333 | AB95: =(R95-86.16)/6*G95 -> 243.97333 | AC95: =$Y$2*G95*Q95 -> 7.18 | AD95: =$Y$2*G95*Q95 -> 7.18 | AE95: =AD95+AC95+AB95 -> 258.33333 | AG95: =(R95-86.16)/6*I95 -> 243.97333 | AH95: =$Y$2*I95*Q95 -> 7.18 | AI95: =$Y$2*I95*Q95 -> 7.18 | AJ95: =AI95+AH95+AG95 -> 258.33333 | AL95: =(R95-86.16)/6*K95 -> 243.97333 | AM95: =$Y$2*K95*Q95 -> 7.18 | AN95: =$Y$2*K95*Q95 -> 7.18 | AO95: =AN95+AM95+AL95 -> 258.33333 | AQ95: =(R95-86.16)/6*M95 -> 243.97333 | AR95: =$Y$2*M95*Q95 -> 7.18 | AS95: =$Y$2*M95*Q95 -> 7.18 | AT95: =AS95+AR95+AQ95 -> 258.33333 | AV95: =(R95-86.16)/6*O95 -> 243.97333 | AW95: =$Y$2*O95*Q95 -> 7.18 | AX95: =$Y$2*O95*Q95 -> 7.18 | AY95: =AX95+AW95+AV95 -> 258.33333 | AZ95: =+AY95+AT95+AO95++AJ95+AE95+Z95 -> 1550 | BA95: =((AZ95-BB95-BC95-BD95-BE95-BF95)+BI95+BJ95+BK95+BL95+BM95+BN95+BO95) -> 1950 | BG95: BONO+B ASIS | BI95: 250 | BJ95: 150
B96: 145 | C96: =C95+1 -> 16 | D96: Muñoz Rodriguez Susana | E96: 1 | G96: 1 | I96: 1 | K96: 1 | M96: 1 | O96: 1 | Q96: 1 | R96: =IF(Q96=1,1550,850) -> 1550 | S96: =+BH96 -> 0 | T96: =+BA96 -> 1950 | U96: =+BP96 -> 0 | V96: =+BG96 -> BONO+B ASIS | W96: =(R96-86.16)/6*E96 -> 243.97333 | X96: =$Y$2*E96*Q96 -> 7.18 | Y96: =$Y$2*E96*Q96 -> 7.18 | Z96: =Y96+X96+W96 -> 258.33333 | AB96: =(R96-86.16)/6*G96 -> 243.97333 | AC96: =$Y$2*G96*Q96 -> 7.18 | AD96: =$Y$2*G96*Q96 -> 7.18 | AE96: =AD96+AC96+AB96 -> 258.33333 | AG96: =(R96-86.16)/6*I96 -> 243.97333 | AH96: =$Y$2*I96*Q96 -> 7.18 | AI96: =$Y$2*I96*Q96 -> 7.18 | AJ96: =AI96+AH96+AG96 -> 258.33333 | AL96: =(R96-86.16)/6*K96 -> 243.97333 | AM96: =$Y$2*K96*Q96 -> 7.18 | AN96: =$Y$2*K96*Q96 -> 7.18 | AO96: =AN96+AM96+AL96 -> 258.33333 | AQ96: =(R96-86.16)/6*M96 -> 243.97333 | AR96: =$Y$2*M96*Q96 -> 7.18 | AS96: =$Y$2*M96*Q96 -> 7.18 | AT96: =AS96+AR96+AQ96 -> 258.33333 | AV96: =(R96-86.16)/6*O96 -> 243.97333 | AW96: =$Y$2*O96*Q96 -> 7.18 | AX96: =$Y$2*O96*Q96 -> 7.18 | AY96: =AX96+AW96+AV96 -> 258.33333 | AZ96: =+AY96+AT96+AO96++AJ96+AE96+Z96 -> 1550 | BA96: =((AZ96-BB96-BC96-BD96-BE96-BF96)+BI96+BJ96+BK96+BL96+BM96+BN96+BO96) -> 1950 | BG96: BONO+B ASIS | BI96: 250 | BJ96: 150
A97: 469 | B97: 45 | C97: =C96+1 -> 17 | D97: Sanchez Flores Miguel Angel | E97: 1 | G97: 1 | I97: 1 | K97: 1 | M97: 1 | O97: 1 | Q97: 1 | R97: =IF(Q97=1,3500,600) -> 3500 | S97: =+BH97 -> 0 | T97: =+BA97 -> 3500 | U97: =+BP97 -> 0 | V97: =+BG97 -> 0 | W97: =(R97-86.16)/6*E97 -> 568.97333 | X97: =$Y$2*E97*Q97 -> 7.18 | Y97: =$Y$2*E97*Q97 -> 7.18 | Z97: =Y97+X97+W97 -> 583.33333 | AB97: =(R97-86.16)/6*G97 -> 568.97333 | AC97: =$Y$2*G97*Q97 -> 7.18 | AD97: =$Y$2*G97*Q97 -> 7.18 | AE97: =AD97+AC97+AB97 -> 583.33333 | AG97: =(R97-86.16)/6*I97 -> 568.97333 | AH97: =$Y$2*I97*Q97 -> 7.18 | AI97: =$Y$2*I97*Q97 -> 7.18 | AJ97: =AI97+AH97+AG97 -> 583.33333 | AL97: =(R97-86.16)/6*K97 -> 568.97333 | AM97: =$Y$2*K97*Q97 -> 7.18 | AN97: =$Y$2*K97*Q97 -> 7.18 | AO97: =AN97+AM97+AL97 -> 583.33333 | AQ97: =(R97-86.16)/6*M97 -> 568.97333 | AR97: =$Y$2*M97*Q97 -> 7.18 | AS97: =$Y$2*M97*Q97 -> 7.18 | AT97: =AS97+AR97+AQ97 -> 583.33333 | AV97: =(R97-86.16)/6*O97 -> 568.97333 | AW97: =$Y$2*O97*Q97 -> 7.18 | AX97: =$Y$2*O97*Q97 -> 7.18 | AY97: =AX97+AW97+AV97 -> 583.33333 | AZ97: =+AY97+AT97+AO97++AJ97+AE97+Z97 -> 3500 | BA97: =((AZ97-BB97-BC97-BD97-BE97-BF97)+BI97+BJ97+BK97+BL97+BM97+BN97+BO97) -> 3500 | BU97: 469
B98: 179 | C98: =C97+1 -> 18 | D98: Vargas Juarez Jorge | E98: 1 | G98: 1 | I98: 1 | K98: 1 | M98: 1 | O98: 1 | Q98: 1 | R98: =IF(Q98=1,1550,850) -> 1550 | S98: =+BH98 -> 0 | T98: =+BA98 -> 1850 | U98: =+BP98 -> 0 | V98: =+BG98 -> 0 | W98: =(R98-86.16)/6*E98 -> 243.97333 | X98: =$Y$2*E98*Q98 -> 7.18 | Y98: =$Y$2*E98*Q98 -> 7.18 | Z98: =Y98+X98+W98 -> 258.33333 | AB98: =(R98-86.16)/6*G98 -> 243.97333 | AC98: =$Y$2*G98*Q98 -> 7.18 | AD98: =$Y$2*G98*Q98 -> 7.18 | AE98: =AD98+AC98+AB98 -> 258.33333 | AG98: =(R98-86.16)/6*I98 -> 243.97333 | AH98: =$Y$2*I98*Q98 -> 7.18 | AI98: =$Y$2*I98*Q98 -> 7.18 | AJ98: =AI98+AH98+AG98 -> 258.33333 | AL98: =(R98-86.16)/6*K98 -> 243.97333 | AM98: =$Y$2*K98*Q98 -> 7.18 | AN98: =$Y$2*K98*Q98 -> 7.18 | AO98: =AN98+AM98+AL98 -> 258.33333 | AQ98: =(R98-86.16)/6*M98 -> 243.97333 | AR98: =$Y$2*M98*Q98 -> 7.18 | AS98: =$Y$2*M98*Q98 -> 7.18 | AT98: =AS98+AR98+AQ98 -> 258.33333 | AV98: =(R98-86.16)/6*O98 -> 243.97333 | AW98: =$Y$2*O98*Q98 -> 7.18 | AX98: =$Y$2*O98*Q98 -> 7.18 | AY98: =AX98+AW98+AV98 -> 258.33333 | AZ98: =+AY98+AT98+AO98++AJ98+AE98+Z98 -> 1550 | BA98: =((AZ98-BB98-BC98-BD98-BE98-BF98)+BI98+BJ98+BK98+BL98+BM98+BN98+BO98) -> 1850 | BI98: 150 | BJ98: 150
B99: 111 | C99: =C98+1 -> 19 | D99: Viaña Dominguez Gladis Nayeli | E99: 1 | G99: 1 | I99: 1 | K99: 1 | M99: 1 | O99: 1 | Q99: 1 | R99: =IF(Q99=1,1550,850) -> 1550 | S99: =+BH99 -> 0 | T99: =+BA99 -> 1950 | U99: =+BP99 -> 0 | V99: =+BG99 -> BONO+B ASIS | W99: =(R99-86.16)/6*E99 -> 243.97333 | X99: =$Y$2*E99*Q99 -> 7.18 | Y99: =$Y$2*E99*Q99 -> 7.18 | Z99: =Y99+X99+W99 -> 258.33333 | AB99: =(R99-86.16)/6*G99 -> 243.97333 | AC99: =$Y$2*G99*Q99 -> 7.18 | AD99: =$Y$2*G99*Q99 -> 7.18 | AE99: =AD99+AC99+AB99 -> 258.33333 | AG99: =(R99-86.16)/6*I99 -> 243.97333 | AH99: =$Y$2*I99*Q99 -> 7.18 | AI99: =$Y$2*I99*Q99 -> 7.18 | AJ99: =AI99+AH99+AG99 -> 258.33333 | AL99: =(R99-86.16)/6*K99 -> 243.97333 | AM99: =$Y$2*K99*Q99 -> 7.18 | AN99: =$Y$2*K99*Q99 -> 7.18 | AO99: =AN99+AM99+AL99 -> 258.33333 | AQ99: =(R99-86.16)/6*M99 -> 243.97333 | AR99: =$Y$2*M99*Q99 -> 7.18 | AS99: =$Y$2*M99*Q99 -> 7.18 | AT99: =AS99+AR99+AQ99 -> 258.33333 | AV99: =(R99-86.16)/6*O99 -> 243.97333 | AW99: =$Y$2*O99*Q99 -> 7.18 | AX99: =$Y$2*O99*Q99 -> 7.18 | AY99: =AX99+AW99+AV99 -> 258.33333 | AZ99: =+AY99+AT99+AO99++AJ99+AE99+Z99 -> 1550 | BA99: =((AZ99-BB99-BC99-BD99-BE99-BF99)+BI99+BJ99+BK99+BL99+BM99+BN99+BO99) -> 1950 | BG99: BONO+B ASIS | BI99: 250 | BJ99: 150
B100: 173 | C100: =C99+1 -> 20 | D100: Villegas Galvan Cristian Jose | E100: 1 | F100: NI | G100: 1 | I100: 1 | K100: 1 | M100: 1 | O100: 1 | Q100: 1 | R100: 2000 | S100: =+BH100 -> 0 | T100: =+BA100 -> 2150 | U100: =+BP100 -> 0 | V100: =+BG100 -> B ASIS | W100: =(R100-86.16)/6*E100 -> 318.97333 | X100: =$Y$2*E100*Q100 -> 7.18 | Y100: =$Y$2*E100*Q100 -> 7.18 | Z100: =Y100+X100+W100 -> 333.33333 | AB100: =(R100-86.16)/6*G100 -> 318.97333 | AC100: =$Y$2*G100*Q100 -> 7.18 | AD100: =$Y$2*G100*Q100 -> 7.18 | AE100: =AD100+AC100+AB100 -> 333.33333 | AG100: =(R100-86.16)/6*I100 -> 318.97333 | AH100: =$Y$2*I100*Q100 -> 7.18 | AI100: =$Y$2*I100*Q100 -> 7.18 | AJ100: =AI100+AH100+AG100 -> 333.33333 | AL100: =(R100-86.16)/6*K100 -> 318.97333 | AM100: =$Y$2*K100*Q100 -> 7.18 | AN100: =$Y$2*K100*Q100 -> 7.18 | AO100: =AN100+AM100+AL100 -> 333.33333 | AQ100: =(R100-86.16)/6*M100 -> 318.97333 | AR100: =$Y$2*M100*Q100 -> 7.18 | AS100: =$Y$2*M100*Q100 -> 7.18 | AT100: =AS100+AR100+AQ100 -> 333.33333 | AV100: =(R100-86.16)/6*O100 -> 318.97333 | AW100: =$Y$2*O100*Q100 -> 7.18 | AX100: =$Y$2*O100*Q100 -> 7.18 | AY100: =AX100+AW100+AV100 -> 333.33333 | AZ100: =+AY100+AT100+AO100++AJ100+AE100+Z100 -> 2000 | BA100: =((AZ100-BB100-BC100-BD100-BE100-BF100)+BI100+BJ100+BK100+BL100+BM100+BN100+BO100) -> 2150 | BG100: B ASIS | BJ100: 150
A101: 489 | E101: =SUM(E81:E100) -> 19 | G101: =SUM(G81:G100) -> 19 | I101: =SUM(I81:I100) -> 19 | K101: =SUM(K81:K100) -> 18 | M101: =SUM(M81:M100) -> 19 | O101: =SUM(O81:O100) -> 19 | AI101: =$Y$2*I101*Q101 -> 0 | AT101: =AS101+AR101+AQ101 -> 0 | BU101: 489
...

Sheet NOM
B1: SEMANA DEL 23 AL 29 DE JUNIO DEL 2025 | Y1: REBAJE X FALTAS
B2: TEJIDO
B3: TURNO1
B4: Responsable de llenado: | R4: Salario | S4: Bono productividad | T4: DIF NOM | U4: Bono extra | V4: Primas, finiquitos, etc | W4: otros | X4: Nominal
B5: # EMP | C5: NOMBRE | D5: PUESTO | E5: L | G5: M | I5: M | K5: J | M5: V | O5: S | Q5: D
A6: =A5+1 -> 1 | B6: 2 | C6: Antunez Requejo Gabriela | D6: Calidad | E6: 1 | F6: VAC | G6: 1 | H6: VAC | I6: 1 | J6: VAC | K6: 1 | L6: VAC | M6: 1 | N6: VAC | R6: 2300 | U6: 150 | X6: =+R6+S6+T6+U6+V6+W6 -> 2450
A7: =#REF!+1 -> #REF! | B7: 6 | C7: Balderas Balderas Myriam Ivet | D7: Lider | E7: 1 | F7: VAC | G7: 1 | H7: VAC | I7: 1 | J7: VAC | K7: 1 | L7: VAC | M7: 1 | N7: VAC | R7: 3000 | U7: 250 | X7: =+R7+S7+T7+U7+V7+W7 -> 3250
A8: =#REF!+1 -> #REF! | B8: 95 | C8: Carrillo Delgado Judith | D8: Operador | E8: 1 | G8: 1 | I8: 1 | K8: 1 | M8: 1 | R8: 1950 | S8: 250 | X8: =+R8+S8+T8+U8+V8+W8 -> 2200
B9: 222 | C9: Hernandez de la Rosa Maria Fernanda | D9: Operador | E9: 1 | F9: VAC | G9: 1 | I9: 1 | J9: VAC | K9: 1 | M9: 1 | O9: 1 | P9: VAC | R9: 1950 | S9: 200 | X9: =+R9+S9+T9+U9+V9+W9 -> 2150
B10: 260 | C10: Macias Mijares Jose De Jesus | D10: Creeler | E10: 1 | G10: 1 | I10: 1 | K10: 0 | L10: F | M10: 1 | R10: 1392.85 | X10: =+R10+S10+T10+U10+V10+W10 -> 1392.85 | Y10: -557.15
A11: =#REF!+1 -> #REF! | B11: 26 | C11: Medrano Suarez Jose Adolfo | D11: Mecanico | E11: 1 | F11: VAC | G11: 1 | H11: VAC | I11: 1 | J11: VAC | K11: 1 | L11: VAC | M11: 1 | N11: VAC | R11: 2500 | S11: 200 | U11: 200 | X11: =+R11+S11+T11+U11+V11+W11 -> 2900
A12: =#REF!+1 -> #REF! | B12: 28 | C12: Moran Hernandez Raul | D12: Mecanico | E12: 1 | G12: 1 | I12: 1 | K12: 1 | M12: 1 | R12: 5000 | X12: =+R12+S12+T12+U12+V12+W12 -> 5000
A13: =#REF!+1 -> #REF! | B13: 169 | C13: Ramirez Requejo Maria Guadalupe | D13: Operador | E13: 1 | G13: 1 | I13: 1 | K13: 1 | M13: 1 | R13: 1950 | S13: 200 | X13: =+R13+S13+T13+U13+V13+W13 -> 2150
A14: =#REF!+1 -> #REF! | B14: 146 | C14: Salazar Martinez Yohana Cecilia | D14: Operador | E14: 1 | G14: 1 | I14: 1 | J14: VAC | K14: 1 | M14: 1 | O14: 1 | P14: VAC | R14: 1950 | S14: 200 | X14: =+R14+S14+T14+U14+V14+W14 -> 2150
A15: =A13+1 -> #REF! | B15: 51 | C15: Valenzuela Rosales Jose Miguel | D15: Mecanico | E15: 1 | G15: 1 | I15: 1 | K15: 1 | M15: 1 | R15: 5000 | U15: 1000 | W15: 239.37 | X15: =+R15+S15+T15+U15+V15+W15 -> 6239.37
E16: =SUM(E6:E15) -> 10 | G16: =SUM(G6:G15) -> 10 | I16: =SUM(I6:I15) -> 10 | K16: =SUM(K6:K15) -> 9 | M16: =SUM(M6:M15) -> 10 | R16: =SUM(R6:R15) -> 26992.85 | S16: =SUM(S6:S15) -> 1050 | T16: =SUM(T6:T15) -> 0 | U16: =SUM(U6:U15) -> 1600 | V16: =SUM(V6:V15) -> 0 | W16: =SUM(W6:W15) -> 239.37 | X16: =SUM(X6:X15)-Y10-Y9 -> 30439.37
X17: =F29-X16 -> 0
D18: NOMINA | E18: EXTRA | F18: TOTAL | K18: L | M18: M | O18: M | Q18: J | S18: V | U18: S
B19: 1 | C19: LIDER | D19: =3000*B19 -> 3000 | E19: 0 | F19: =D19 -> 3000 | V19: PROM
B20: 1 | C20: CALIDAD | D20: =2300*B20 -> 2300 | E20: 0 | F20: =D20 -> 2300 | I20: LIDER | K20: 1 | M20: 1 | O20: 1 | Q20: 1 | S20: 1 | U20: 0 | V20: =AVERAGE(K20,M20,O20,Q20,S20) -> 1
B21: 3 | C21: MECANICO | D21: =2500+5000+5000 -> 12500 | E21: 0 | F21: =D21 -> 12500 | I21: CALIDAD | K21: 1 | M21: 1 | O21: 1 | Q21: 1 | S21: 1 | U21: 0 | V21: =AVERAGE(K21,M21,O21,Q21,S21) -> 1
B22: 5 | C22: MANUAL | D22: =1950*B22 -> 9750 | E22: 0 | F22: =D22 -> 9750 | I22: MECANICO | K22: 3 | M22: 3 | O22: 3 | Q22: 3 | S22: 3 | U22: 0 | V22: =AVERAGE(K22,M22,O22,Q22,S22) -> 3
I23: MANUAL | K23: 5 | M23: 5 | O23: 5 | Q23: 5 | S23: 5 | U23: 0 | V23: =AVERAGE(K23,M23,O23,Q23,S23) -> 5
B24: =SUM(B19:B23) -> 10 | F24: =SUM(F19:F23) -> 27550 | K24: =SUM(K20:K23) -> 10 | M24: =SUM(M20:M23) -> 10 | O24: =SUM(O20:O23) -> 10 | Q24: =SUM(Q20:Q23) -> 10 | S24: =SUM(S20:S23) -> 10 | U24: =SUM(U20:U23) -> 0 | V24: =AVERAGE(K24,M24,O24,Q24,S24) -> 10
E25: BONO | F25: =+S16 -> 1050
E26: BONOS EXTRA | F26: =+U16 -> 1600
E27: GRASEROS | F27: =W16 -> 239.37
F29: =SUM(F24:F28) -> 30439.37
B32: =+B1 -> SEMANA DEL 23 AL 29 DE JUNIO DEL 2025
B33: TURNO 2
B34: Responsable de llenado: | R34: Salario | S34: Bono productividas | T34: Bono de asitencia | U34: Bono extra | V34: Primas, finiquitos, etc | W34: otros | X34: Nominal
B35: # EMP | C35: NOMBRE | D35: PUESTO | E35: L | G35: M | I35: M | K35: J | M35: V | O35: S | Q35: D
B36: 59 | C36: Castro Viaña Mario Ivan | D36: Mecanico | E36: 1 | G36: 1 | I36: 1 | K36: 1 | M36: 1 | O36: 1 | R36: 2350 | S36: 200 | U36: 150 | X36: =+R36+S36+T36+U36+V36+W36 -> 2700
B37: 12 | C37: Diaz Martinez Angela Elizabeth | D37: Calidad | E37: 1 | G37: 1 | I37: 1 | K37: 1 | M37: 1 | O37: 1 | R37: 2300 | U37: 150 | X37: =+R37+S37+T37+U37+V37+W37 -> 2450
B38: 212 | C38: Hernandez Favela Margarita | D38: Operador | E38: 1 | G38: 1 | I38: 1 | K38: 1 | L38: VAC | M38: 1 | O38: 1 | R38: 1950 | S38: 200 | X38: =+R38+S38+T38+U38+V38+W38 -> 2150
E39: =SUM(E36:E38) -> 3 | G39: =SUM(G36:G38) -> 3 | I39: =SUM(I36:I38) -> 3 | K39: =SUM(K36:K38) -> 3 | M39: =SUM(M36:M38) -> 3 | O39: 3 | R39: =SUM(R36:R38) -> 6600 | S39: =SUM(S36:S38) -> 400 | T39: =SUM(T36:T38) -> 0 | U39: =SUM(U36:U38) -> 300 | V39: =SUM(V36:V38) -> 0 | W39: =SUM(W36:W38) -> 0 | X39: =SUM(X36:X38)-Y36 -> 7300
X40: =F51-X39 -> 0
D41: NOMINA | E41: EXTRA | F41: TOTAL
B42: 0 | C42: SUPERVISORA | D42: 0 | E42: 0 | F42: =D42 -> 0 | K42: L | M42: M | O42: M | Q42: J | S42: V | U42: S
B43: 1 | C43: CALIDAD | D43: =2300*B43 -> 2300 | E43: 0 | F43: =D43 -> 2300 | V43: PROM
B44: 1 | C44: MECANICO | D44: 2350 | E44: 0 | F44: =+D44 -> 2350 | I44: SUPERVISOR | K44: 0 | M44: 0 | O44: 0 | Q44: 0 | S44: 0 | U44: 0 | V44: =AVERAGE(K44,M44,O44,Q44,S44,U44) -> 0
B45: 1 | C45: MANUAL | D45: =1950*B45 -> 1950 | E45: 0 | F45: =D45 -> 1950 | I45: CALIDAD | K45: 1 | M45: 1 | O45: 1 | Q45: 1 | S45: 1 | U45: 0 | V45: =AVERAGE(K45,M45,O45,Q45,S45) -> 1
F46: =SUM(F42:F45) -> 6600 | I46: MECANICO | K46: 1 | M46: 1 | O46: 1 | Q46: 1 | S46: 1 | U46: 0 | V46: =AVERAGE(K46,M46,O46,Q46,S46) -> 1
B47: =SUM(B42:B46) -> 3 | I47: MANUAL | K47: 1 | M47: 1 | O47: 1 | Q47: 1 | S47: 1 | U47: 0 | V47: =AVERAGE(K47,M47,O47,Q47,S47) -> 1
E48: BONO | F48: =S39 -> 400 | K48: =SUM(K44:K47) -> 3 | M48: =SUM(M44:M47) -> 3 | O48: =SUM(O44:O47) -> 3 | Q48: =SUM(Q44:Q47) -> 3 | S48: =SUM(S44:S47) -> 3 | U48: =SUM(U44:U47) -> 0 | V48: =AVERAGE(K48,M48,O48,Q48,S48) -> 3
E49: BONO EXTRA | F49: =U39 -> 300
F51: =SUM(F46:F49) -> 7300
B54: =+B1 -> SEMANA DEL 23 AL 29 DE JUNIO DEL 2025
B55: =+B2 -> TEJIDO
B56: TURNO 3 | R56: Salario | S56: Bono productividas | T56: Bono de asitencia | U56: Bono extra | V56: Primas, finiquitos, etc | W56: otros | X56: Nominal
B57: Responsable de llenado:
B58: # EMP | C58: NOMBRE | D58: PUESTO | E58: L | G58: M | I58: M | K58: J | M58: V | O58: S | Q58: D
B59: 251 | C59: Balderas Aguilar Yhair Otoniel | D59: Operador | E59: 1 | F59: VAC | G59: 1 | H59: VAC | I59: 1 | J59: VAC | K59: 1 | L59: VAC | M59: 1 | R59: 1950 | S59: 200 | U59: 50 | X59: =+R59+S59+T59+U59+V59+W59 -> 2200
B60: 250 | C60: Botello Amaya Brenda Cecilia | D60: Calidad | E60: 1 | G60: 1 | I60: 1 | K60: 1 | M60: 1 | R60: 2300 | U60: 200 | X60: =+R60+S60+T60+U60+V60+W60 -> 2500
B61: 214 | C61: Gress Padilla Leidy Daniela | D61: Operador | E61: 1 | G61: 1 | H61: VAC | I61: 1 | K61: 1 | M61: 1 | R61: 1950 | S61: 200 | U61: 50 | X61: =+R61+S61+T61+U61+V61+W61 -> 2200
B62: 215 | C62: Holguin Salas Hilda Yudit | D62: Operador | E62: 1 | F62: VAC | G62: 1 | H62: VAC | I62: 1 | K62: 1 | M62: 1 | R62: 1950 | S62: 200 | U62: 50 | X62: =+R62+S62+T62+U62+V62+W62 -> 2200
A63: =#REF!+1 -> #REF! | B63: 27 | C63: Minor Flores Adilene | D63: Calidad | E63: 1 | F63: VAC | G63: 1 | H63: VAC | I63: 1 | J63: VAC | K63: 1 | L63: VAC | M63: 1 | N63: VAC | R63: 2300 | U63: 200 | X63: =+R63+S63+T63+U63+V63+W63 -> 2500
B64: 159 | C64: Perez Suarez Herber Antony | D64: Mecanico | E64: 1 | G64: 1 | I64: 1 | K64: 1 | M64: 1 | R64: 6000 | X64: =+R64+S64+T64+U64+V64+W64 -> 6000
B65: 33 | C65: Ramirez Vital Jose Armando | D65: Operador | E65: 1 | G65: 1 | I65: 1 | J65: VAC | K65: 1 | L65: VAC | M65: 1 | N65: VAC | R65: 1950 | S65: 200 | U65: 50 | X65: =+R65+S65+T65+U65+V65+W65 -> 2200
B66: 266 | C66: Rubio Resendiz Emilio | D66: Creeler | E66: 1 | G66: 1 | I66: 1 | K66: 1 | M66: 1 | R66: 1950 | S66: 200 | U66: 50 | X66: =+R66+S66+T66+U66+V66+W66 -> 2200
A67: =A70+1 -> 1 | B67: 228 | C67: Tostado Sifuentes Haxel Rodrigo | D67: Creeler | E67: 1 | G67: 1 | I67: 1 | K67: 1 | M67: 1 | R67: 1950 | S67: 200 | U67: 50 | X67: =+R67+S67+T67+U67+V67+W67 -> 2200
B68: 242 | C68: Villegas Reyes Jesus Maria | D68: Mecanico | E68: 1 | F68: VAC | G68: 1 | H68: VAC | I68: 1 | J68: VAC | K68: 1 | L68: VAC | M68: 1 | N68: VAC | R68: 2350 | U68: 150 | X68: =+R68+S68+T68+U68+V68+W68 -> 2500
E69: =SUM(E59:E68) -> 10 | G69: =SUM(G59:G68) -> 10 | I69: =SUM(I59:I68) -> 10 | K69: =SUM(K59:K68) -> 10 | M69: =SUM(M59:M68) -> 10 | R69: =SUM(R59:R68) -> 24650 | S69: =SUM(S59:S68) -> 1200 | T69: =SUM(T59:T68) -> 0 | U69: =SUM(U59:U68) -> 850 | V69: =SUM(V59:V68) -> 0 | W69: =SUM(W59:W68) -> 0 | X69: =SUM(X59:X68)-Y62-Y65-Y68 -> 26700
X70: =F81-X69 -> 0
D71: NOMINA | E71: EXTRA | F71: TOTAL | K71: L | M71: M | O71: M | Q71: J | S71: V | U71: S
B72: 0 | C72: SUPERVISORA | D72: 0 | E72: 0 | F72: =D72 -> 0 | V72: PROM
B73: 2 | C73: CALIDAD | D73: =2300*B73 -> 4600 | E73: 0 | F73: =D73 -> 4600 | I73: SUPERVISOR | K73: 0 | M73: 0 | O73: 0 | Q73: 0 | S73: 0 | U73: 0 | V73: =AVERAGE(K73,M73,O73,Q73,S73) -> 0
B74: 2 | C74: MECANICO | D74: =2350+6000 -> 8350 | E74: 0 | F74: =D74 -> 8350 | I74: CALIDAD | K74: 2 | M74: 2 | O74: 2 | Q74: 2 | S74: 2 | U74: 0 | V74: =AVERAGE(K74,M74,O74,Q74,S74) -> 2
B75: 6 | C75: MANUAL | D75: =1950*B75 -> 11700 | E75: 0 | F75: =D75 -> 11700 | I75: MECANICO | K75: 2 | M75: 2 | O75: 2 | Q75: 2 | S75: 2 | U75: 0 | V75: =AVERAGE(K75,M75,O75,Q75,S75) -> 2
B76: =SUM(B72:B75) -> 10 | F76: =SUM(F72:F75) -> 24650 | I76: MANUAL | K76: 6 | M76: 6 | O76: 6 | Q76: 6 | S76: 6 | U76: 0 | V76: =AVERAGE(K76,M76,O76,Q76,S76) -> 6
E77: BONO | F77: =+S69 -> 1200 | K77: =SUM(K73:K76) -> 10 | M77: =SUM(M73:M76) -> 10 | O77: =SUM(O73:O76) -> 10 | Q77: =SUM(Q73:Q76) -> 10 | S77: =SUM(S73:S76) -> 10 | U77: =SUM(U73:U76) -> 0 | V77: =AVERAGE(K77,M77,O77,Q77,S77) -> 10
E78: BONO ASISTENCIA | F78: =+T69 -> 0
E79: BONO EXTRA | F79: =U69 -> 850
F81: =SUM(F76:F80) -> 26700
B84: =+B1 -> SEMANA DEL 23 AL 29 DE JUNIO DEL 2025
B85: AE
B86: TURNO 1
B87: Responsable de llenado: | R87: Salario | S87: Bono productividas | T87: Bono de asitencia | U87: Bono extra | V87: Primas, finiquitos, etc | W87: otros | X87: Nominal
B88: # EMP | C88: NOMBRE | D88: PUESTO | E88: L | G88: M | I88: M | K88: J | M88: V | O88: S | Q88: D | U88: Mtto
A89: 4 | B89: 9 | C89: Bustamante Villegas Osvaldo | D89: Mecanico | E89: 1 | G89: 1 | I89: 1 | K89: 1 | M89: 1 | O89: 1 | R89: 3000 | S89: 300 | U89: 250 | X89: =+R89+S89+T89+U89+V89+W89 -> 3550
B90: 264 | C90: Castañeda Flores Jose Alfredo | D90: Operador | E90: 1 | G90: 1 | I90: 1 | K90: 1 | M90: 1 | O90: 1 | R90: 1950 | S90: 200 | X90: =+R90+S90+T90+U90+V90+W90 -> 2150
A91: 2 | B91: 166 | C91: Enriquez Gutierrez Acacia | D91: Operador D | E91: 1 | G91: 1 | I91: 1 | K91: 1 | M91: 1 | O91: 1 | P91: VAC | R91: 1950 | S91: 200 | X91: =(R91+S91+T91+U91+V91+W91) -> 2150
A92: 4 | B92: 19 | C92: Garcia Nuñez Elizabeth | D92: Mecanico | E92: 1 | G92: 1 | I92: 1 | K92: 1 | M92: 1 | O92: 1 | R92: 2350 | U92: 450 | X92: =(R92+S92+T92+U92+V92+W92) -> 2800
B93: 247 | C93: Gomez Mendoza Ruben Dario | D93: Mecanico | E93: 1 | G93: 1 | I93: 1 | K93: 1 | M93: 1 | O93: 1 | R93: 10000 | X93: =(R93+S93+T93+U93+V93+W93) -> 10000
B94: 269 | C94: Pardo Arevalo Aleida Maribi | D94: Operador | E94: 0 | F94: F | G94: 1 | I94: 1 | K94: 1 | M94: 1 | O94: 1 | R94: 1242.85 | X94: =(R94+S94+T94+U94+V94+W94) -> 1242.85 | Y94: -707.15
A95: 5 | B95: 39 | C95: Rodriguez Uribe Erika Elizabeth | D95: Calidad | E95: 1 | F95: VAC | G95: 1 | H95: VAC | I95: 1 | J95: VAC | K95: 1 | L95: VAC | M95: 1 | N95: VAC | O95: 1 | P95: VAC | R95: 2300 | U95: 150 | X95: =(R95+S95+T95+U95+V95+W95) -> 2450
A96: 7 | B96: 141 | C96: Vargas Mendez Ma. Isabel | D96: Operador D | E96: 1 | G96: 1 | I96: 1 | K96: 1 | M96: 1 | O96: 1 | R96: 1950 | S96: 200 | X96: =(R96+S96+T96+U96+V96+W96) -> 2150
B97: 220 | C97: Vargas Torres Pedro | D97: Operador | E97: 1 | G97: 1 | I97: 1 | K97: 1 | M97: 1 | O97: 1 | R97: 1950 | S97: 200 | X97: =+R97+S97+T97+U97+V97+W97 -> 2150
E98: =SUM(E89:E97) -> 8 | G98: =SUM(G89:G97) -> 9 | I98: =SUM(I89:I97) -> 9 | K98: =SUM(K89:K97) -> 9 | M98: =SUM(M89:M97) -> 9 | O98: =SUM(O89:O97) -> 9 | R98: =SUM(R89:R97) -> 26692.85 | S98: =SUM(S89:S97) -> 1100 | T98: =SUM(T89:T97) -> 0 | U98: =SUM(U89:U97) -> 850 | V98: =SUM(V89:V97) -> 0 | W98: =SUM(W89:W97) -> 0 | X98: =SUM(X89:X97)-Y94 -> 29350
D100: NOMINA | E100: EXTRA | F100: TOTAL | K100: L | M100: M | O100: M | Q100: J | S100: V | U100: S | X100: =F109-X98 -> 0
B101: 3 | C101: MECANICO | D101: =2350+3000+10000 -> 15350 | E101: 0 | F101: =+D101 -> 15350 | V101: PROM
B102: 5 | C102: MANUAL | D102: =1950*B102 -> 9750 | E102: 0 | F102: =D102 -> 9750 | I102: LIDER | K102: 0 | M102: 0 | O102: 0 | Q102: 0 | S102: 0 | U102: 0 | V102: =AVERAGE(K102,M102,O102,Q102,S102) -> 0
B103: 1 | C103: CALIDAD | D103: 2300 | E103: 0 | F103: =D103 -> 2300 | I103: CALIDAD | K103: 1 | M103: 1 | O103: 1 | Q103: 1 | S103: 1 | U103: 0 | V103: =AVERAGE(K103,M103,O103,Q103,S103) -> 1
B104: =SUM(B101:B103) -> 9 | F104: =SUM(F101:F103) -> 27400 | I104: MECANICO | K104: 3 | M104: 3 | O104: 3 | Q104: 3 | S104: 3 | U104: 0 | V104: =AVERAGE(K104,M104,O104,Q104,S104) -> 3
E105: BONO | F105: =+S98 -> 1100 | I105: MANUAL | K105: 4 | M105: 5 | O105: 5 | Q105: 5 | S105: 5 | U105: 0 | V105: =AVERAGE(K105,M105,O105,Q105,S105) -> 4.8
E106: BONO EXTRA | F106: =U98 -> 850 | K106: =SUM(K102:K105) -> 8 | M106: =SUM(M102:M105) -> 9 | O106: =SUM(O102:O105) -> 9 | Q106: =SUM(Q102:Q105) -> 9 | S106: =SUM(S102:S105) -> 9 | U106: =SUM(U102:U105) -> 0 | V106: =AVERAGE(K106,M106,O106,Q106,S106) -> 8.8
E107: TIEMPO EXTRA | F107: =W98 -> 0
F109: =SUM(F104:F108) -> 29350
B112: =+B1 -> SEMANA DEL 23 AL 29 DE JUNIO DEL 2025
B113: TURNO 2
...

Sheet LISTAS
B2: SEMANA DEL 16 AL 22 JUNIO DEL 2025 | L2: PARAMETROS A EVALUAR PARA BONO
L3: Deteccion de defectos | M3: limpieza de area | N3: Llenado de formatos | O3: Permisos | P3: Retardos | Q3: BONO
C4: TEJIDO
B5: TURNO1
B6: Responsable de llenado: Myriam Iveth Balderas Balderas
B7: # EMP | C7: NOMBRE | D7: PUESTO | E7: L | F7: M | G7: M | H7: J | I7: V | J7: S | K7: D
A8: 1 | B8: 2 | C8: Antunez Requejo Gabriela | D8: Calidad | E8: VAC | F8: VAC | G8: VAC | H8: VAC | I8: VAC
A9: 2 | B9: 6 | C9: Balderas Balderas Myriam Ivet | D9: Lider | E9: VAC | F9: VAC | G9: VAC | H9: VAC | I9: VAC
A10: 3 | B10: 95 | C10: Carrillo Delgado Judith | D10: Operador | E10: 1 | F10: 1 | G10: 1 | H10: 1 | I10: 1
A11: 4 | B11: 222 | C11: Hernandez de la Rosa Maria Fernanda | D11: Operador | E11: VAC | F11: 1 | G11: VAC | H11: 1 | I11: 1 | J11: VAC
A12: 5 | B12: 260 | C12: Macias Mijares Jose De Jesus | D12: Creeler | E12: 1 | F12: 1 | G12: 1 | H12: F | I12: 1
A13: 6 | B13: 26 | C13: Medrano Suarez Jose Adolfo | D13: Mecanico | E13: VAC | F13: VAC | G13: VAC | H13: VAC | I13: VAC
A14: 7 | B14: 28 | C14: Moran Hernandez Raul | D14: Mecanico | E14: 1 | F14: 1 | G14: 1 | H14: 1 | I14: 1
A15: 8 | B15: 169 | C15: Ramirez Requejo Maria Guadalupe | D15: Operador | E15: 1 | F15: 1 | G15: 1 | H15: 1 | I15: 1 | J15: 1
A16: 9 | B16: 146 | C16: Salazar Martinez Yohana Cecilia | D16: Operador | E16: 1 | F16: 1 | G16: 1 | H16: 1 | I16: 1
A17: 10 | B17: 261 | C17: Valenzuela Gonzalez Cristian Omar | D17: Creeler | E17: D | F17: D | G17: D | H17: D | I17: D
A18: 11 | B18: 51 | C18: Valenzuela Rosales Jose Miguel | D18: Mecanico | E18: 1 | F18: 1 | G18: 1 | H18: 1 | I18: 1
A19: 12 | B19: 265 | C19: Valenzuela Ruiz Brisa Iris | D19: Operador | E19: D | F19: D | G19: D | H19: D | I19: D
B21: =+B2 -> SEMANA DEL 16 AL 22 JUNIO DEL 2025 | L21: PARAMETROS A EVALUAR PARA BONO
L22: Deteccion de defectos | M22: limpieza de area | N22: Llenado de formatos | O22: Permisos | P22: Retardos | Q22: BONO
C23: TEJIDO
B24: TURNO1
B25: Responsable de llenado: Myriam Iveth Balderas Balderas
B26: # EMP | C26: NOMBRE | D26: PUESTO | E26: L | F26: M | G26: M | H26: J | I26: V | J26: S | K26: D
A27: 1 | B27: 59 | C27: Castro Viaña Mario Ivan | D27: Mecanico | E27: A | F27: A | G27: A | H27: A | I27: A | J27: A
A28: 2 | B28: 12 | C28: Diaz Martinez Angela Elizabeth | D28: calidad | E28: A | F28: A | G28: A | H28: A | I28: A | J28: A
A29: 3 | B29: 212 | C29: Hernandez Favela Margarita | D29: operador | E29: A | F29: A | G29: A | H29: VAC | I29: A | J29: A
B31: =+B2 -> SEMANA DEL 16 AL 22 JUNIO DEL 2025 | L31: PARAMETROS A EVALUAR PARA BONO
B32: TEJIDO | L32: Deteccion de defectos | M32: limpieza de area | N32: Llenado de formatos | O32: Permisos | P32: Retardos | Q32: BONO
B33: TURNO 3
B34: Responsable de llenado:Perez Suarez Herber Antony
B35: # EMP | C35: NOMBRE | D35: PUESTO | E35: L | F35: M | G35: M | H35: J | I35: V | J35: S | K35: D
A36: 1 | B36: 251 | C36: Balderas Aguilar Yhair Otoniel | D36: Operador | E36: VAC | F36: VAC | G36: VAC | H36: VAC | I36: 1
A37: 2 | B37: 250 | C37: Botello Amaya Brenda Cecilia | D37: Calidad | E37: 1 | F37: 1 | G37: 1 | H37: 1 | I37: 1
A38: 4 | B38: 214 | C38: Gress Padilla Leidy Daniela | D38: Operador | E38: 1 | F38: VAC | G38: 1 | H38: 1 | I38: 1
A39: 6 | B39: 215 | C39: Holguin Salas Hilda Yudit | D39: Operador | E39: VAC | F39: VAC | G39: 1 | H39: 1 | I39: 1
A40: 7 | B40: 27 | C40: Minor Flores Adilene | D40: Calidad | E40: VAC | F40: VAC | G40: VAC | H40: VAC | I40: VAC
A41: 8 | B41: 159 | C41: Perez Suarez Herber Antony | D41: Mecanico | E41: 1 | F41: 1 | G41: 1 | H41: 1 | I41: 1
A42: 9 | B42: 33 | C42: Ramirez Vital Jose Armando | D42: Operador | E42: 1 | F42: 1 | G42: VAC | H42: VAC | I42: VAC
B43: 266 | C43: Rubio Resendiz Emilio | D43: Creeler | E43: 1 | F43: 1 | G43: 1 | H43: 1 | I43: 1
B44: 228 | C44: Tostado Sifuentes Haxel Rodrigo | D44: Creeler | E44: 1 | F44: 1 | G44: 1 | H44: 1 | I44: 1
B45: 242 | C45: Villegas Reyes Jesus Maria | D45: Mecanico | E45: VAC | F45: VAC | G45: VAC | H45: VAC | I45: VAC
B47: =+B2 -> SEMANA DEL 16 AL 22 JUNIO DEL 2025 | L47: PARAMETROS A EVALUAR PARA BONO
B48: AE | L48: Deteccion de defectos | M48: limpieza de area | N48: Llenado de formatos | O48: Permisos | P48: Retardos | Q48: BONO
B49: TURNO 1
B50: Responsable de llenado:Garcia Nuñez Elizabeth
B51: # EMP | C51: NOMBRE | D51: PUESTO | E51: L | F51: M | G51: M | H51: J | I51: V | J51: S | K51: D
A52: 1 | B52: 9 | C52: Bustamante Villegas Osvaldo | D52: Mecanico | E52: 1 | F52: 1 | G52: 1 | H52: 1 | I52: 1 | J52: 1
A53: 2 | B53: 264 | C53: Castañeda Flores Jose Alfredo | D53: Operador | E53: 1 | F53: 1 | G53: 1 | H53: 1 | I53: 1 | J53: 1
A54: 3 | B54: 166 | C54: Enriquez Gutierrez Acacia | D54: Operador D | E54: 1 | F54: 1 | G54: 1 | H54: 1 | I54: 1 | J54: VAC
A55: 4 | B55: 19 | C55: Garcia Nuñez Elizabeth | D55: Mecanico | E55: 1 | F55: 1 | G55: 1 | H55: 1 | I55: 1 | J55: 1
A56: 5 | B56: 247 | C56: Gomez Mendoza Ruben Dario | D56: Mecanico | E56: 1 | F56: 1 | G56: 1 | H56: 1 | I56: 1 | J56: 1
A57: 6 | B57: 269 | C57: Pardo Arevalo Aleida Maribi | D57: Operador | E57: F | F57: 1 | G57: 1 | H57: 1 | I57: 1 | J57: 1
A58: 8 | B58: 39 | C58: Rodriguez Uribe Erika Elizabeth | D58: Calidad | E58: VAC | F58: VAC | G58: VAC | H58: VAC | I58: VAC | J58: VAC
B59: 141 | C59: Vargas Mendez Ma. Isabel | D59: Operador D | E59: 1 | F59: 1 | G59: 1 | H59: 1 | I59: 1 | J59: 1
B60: 220 | C60: Vargas Torres Pedro | D60: Operador | E60: 1 | F60: 1 | G60: 1 | H60: 1 | I60: 1 | J60: 1
B63: =+B2 -> SEMANA DEL 16 AL 22 JUNIO DEL 2025 | L63: PARAMETROS A EVALUAR PARA BONO
L64: Deteccion de defectos | M64: limpieza de area | N64: Llenado de formatos | O64: Permisos | P64: Retardos | Q64: BONO
B65: Responsable de llenado:Hernandez Gonzalez Myrtala
B66: # EMP | C66: NOMBRE | D66: PUESTO | E66: L | F66: M | G66: M | H66: J | I66: V | J66: S | K66: D
A67: 1 | B67: 158 | C67: Caballero Coyoc Jose Alberto | D67: Mecanico | E67: A | F67: A | G67: A | H67: A | I67: A
A68: 2 | B68: 75 | C68: Flores Miranda Aislen | D68: Operador | E68: A | F68: A | G68: A | H68: A | I68: A
A69: 3 | B69: 74 | C69: Hernandez Gonzalez Myrtala | D69: Operador | E69: VAC | F69: VAC | G69: A | H69: A | I69: A
A70: 4 | B70: 29 | C70: Nuñez Viaña Maria del Rosario | D70: Operador | E70: A | F70: A | G70: A | H70: A | I70: A
A71: 6 | B71: 37 | C71: Rodriguez Castillo Rosa Karen | D71: Mecanico | E71: VAC | F71: VAC | G71: VAC | H71: VAC | I71: VAC
B72: =+B2 -> SEMANA DEL 16 AL 22 JUNIO DEL 2025 | L72: PARAMETROS A EVALUAR PARA BONO
B73: PUÑO | L73: Deteccion de defectos | M73: limpieza de area | N73: Llenado de formatos | O73: Permisos | P73: Retardos | Q73: BONO
B74: TURNO 1
B75: Responsable de llenado:LESLIE GARCIA
B76: # EMP | C76: NOMBRE | D76: PUESTO | E76: L | F76: M | G76: M | H76: J | I76: V | J76: S | K76: D
A77: 1 | B77: 239 | C77: Cordona Perez Rosa Veli | D77: Operador | E77: A | F77: A | G77: A | H77: A | I77: A | J77: A | K77: A
A78: 2 | B78: 63 | C78: Cuapio Flores Mario | D78: MECANICO | E78: A | F78: A | G78: A | H78: A | I78: A | J78: A
A79: 3 | B79: 73 | C79: Garcia Ortega Leslie Coraima | D79: Calidad y Revisadora | E79: A | F79: A | G79: A | H79: A | I79: A | J79: A | K79: A
A80: 4 | B80: 230 | C80: Llamas Perez Prince Anais | D80: Operador puño | E80: A | F80: A | G80: A | H80: A | I80: A | J80: A | K80: A
A81: 5 | B81: 241 | C81: Molina Sifuentes Monserrat Guadalupe | D81: Operador | E81: A | F81: A | G81: A | H81: A | I81: A | J81: A
A82: 6 | B82: 226 | C82: Moreno Martinez Jose uriel | D82: AUX MECANICO | E82: A | F82: A | G82: A | H82: A | I82: A | J82: A
A83: 7 | B83: 262 | C83: Moreno Martinez Zeida Marlen | D83: Empaque | E83: A | F83: A | G83: A | H83: A | I83: A | J83: A
B88: =+B72 -> SEMANA DEL 16 AL 22 JUNIO DEL 2025 | L88: PARAMETROS A EVALUAR PARA BONO
B89: PUÑO | L89: Deteccion de defectos | M89: limpieza de area | N89: Llenado de formatos | O89: Permisos | P89: Retardos | Q89: BONO
B90: TURNO 1
B91: Responsable de llenado:Fernanda Carranza
B92: # EMP | C92: NOMBRE | D92: PUESTO | E92: L | F92: M | G92: M | H92: J | I92: V | J92: S | K92: D
A93: 1 | B93: 107 | C93: Chavarria Machado Samuel | D93: Mecanico | E93: A | F93: A | G93: A | H93: A | I93: A | J93: A
A94: 2 | B94: 271 | C94: Flores Cruz Juana maria | D94: Operador | E94: A | F94: A | G94: A | H94: A | I94: A | J94: A
A95: 3 | B95: 70 | C95: Gonzales Lopez Violeta | D95: Revisadora | E95: A | F95: VAC | G95: A | H95: A | I95: A | J95: A
B96: 235 | C96: Moreno Martinez Angel de Jesus | D96: Aux mecanico | E96: A | F96: A | G96: A | H96: A | I96: A | J96: A
B97: 30 | C97: Pacheco Viaña Jaquelin | D97: Mecanico | E97: A | F97: A | G97: A | H97: A | I97: A | J97: A
B99: =+B2 -> SEMANA DEL 16 AL 22 JUNIO DEL 2025 | L99: PARAMETROS A EVALUAR PARA BONO
B100: TURNO 3 | L100: Deteccion de defectos | M100: limpieza de area | N100: Llenado de formatos | O100: Permisos | P100: Retardos | Q100: BONO
B101: Responsable de llenado:Martinez Rosales Sugey Marisol
B102: # EMP | C102: NOMBRE | D102: PUESTO | E102: L | F102: M | G102: M | H102: J | I102: V | J102: S | K102: D
A103: 1 | B103: 94 | C103: Dominguez Soto Jesus Alberto | D103: MECANICO | E103: A | F103: A | G103: A | H103: A | I103: A | J103: A | K103: A
A104: 2 | B104: 227 | C104: Martinez Rosales Jose Luis | D104: operador | E104: A | F104: A | G104: A | H104: A | I104: A
A105: 3 | B105: 135 | C105: Martinez Rosales Sugey Marisol | D105: CALIDAD | E105: A | F105: A | G105: A | H105: A | I105: VAC
A106: 4 | B106: 254 | C106: Nuñez Viaña Angelica | D106: operador | E106: A | F106: A | G106: A | H106: A | I106: A
B108: =+B2 -> SEMANA DEL 16 AL 22 JUNIO DEL 2025
B109: ADMINISTRATIVOS
B110: # EMP | C110: NOMBRE | D110: PUESTO | E110: L | F110: M | G110: M | H110: J | I110: V | J110: S | K110: D
A111: 1 | B111: 97 | C111: Burciaga Aguirre Marisa Isabel | D111: AUX ADMINISTRATIVO | E111: A | F111: A | G111: A | H111: A | I111: A
A112: 2 | B112: 172 | C112: Campista Hernandez Maria Elena | D112: AUDITORA FINAL | E112: A | F112: A | G112: A | H112: A | I112: A
...

Sheet resumen rh
A6: NOM 28 AL 04 DE MAYO 2025
A7: =+AVERAGE(C7,E7,G7,I7,K7) -> 10 | C7: =NOM!K24 -> 10 | E7: =NOM!M24 -> 10 | G7: =NOM!O24 -> 10 | I7: =NOM!Q24 -> 10 | K7: =NOM!S24 -> 10 | M7: =NOM!U24 -> 0 | N7: TEJIDO
A8: =+AVERAGE(C8,E8,G8,I8,K8,M8) -> 3 | C8: =NOM!E39 -> 3 | E8: =NOM!G39 -> 3 | G8: =NOM!I39 -> 3 | I8: =NOM!K39 -> 3 | K8: =NOM!M39 -> 3 | M8: =NOM!O39 -> 3 | N8: TEJIDO 2
A9: =+AVERAGE(C9,E9,G9,I9,K9) -> 10 | C9: =NOM!K77 -> 10 | E9: =NOM!M77 -> 10 | G9: =NOM!O77 -> 10 | I9: =NOM!Q77 -> 10 | K9: =NOM!S77 -> 10 | M9: =NOM!U77 -> 0 | N9: TEJIDO 3
A10: =+AVERAGE(C10,E10,G10,I10,K10,M10) -> 7 | C10: =NOM!K179 -> 7 | E10: =NOM!M179 -> 7 | G10: =NOM!O179 -> 7 | I10: =NOM!Q179 -> 7 | K10: =NOM!S179 -> 7 | M10: =NOM!U179 -> 7 | N10: PUÑO
A11: =+AVERAGE(C11,E11,G11,I11,K11,M11) -> 5 | C11: =NOM!K207 -> 5 | E11: =NOM!M207 -> 5 | G11: =NOM!O207 -> 5 | I11: =NOM!Q207 -> 5 | K11: =NOM!S207 -> 5 | M11: =NOM!U207 -> 5 | N11: PUÑO2
A12: =+AVERAGE(C12,E12,G12,I12,K12) -> 5 | C12: =NOM!K232 -> 5 | E12: =NOM!M232 -> 5 | G12: =NOM!O232 -> 5 | I12: =NOM!Q232 -> 5 | K12: =NOM!S232 -> 5 | M12: =NOM!U232 -> 0 | N12: PUÑO3
A13: =+AVERAGE(C13,E13,G13,I13,K13,M13) -> 7.3333333 | C13: =NOM!K106 -> 8 | E13: =NOM!M106 -> 9 | G13: =NOM!O106 -> 9 | I13: =NOM!Q106 -> 9 | K13: =NOM!S106 -> 9 | M13: =NOM!U106 -> 0 | N13: AE
A14: =+AVERAGE(C14,E14,G14,I14,K14) -> 0 | C14: 0 | E14: 0 | G14: 0 | I14: 0 | K14: 0 | M14: 0 | N14: AE 2
A15: =+AVERAGE(C15,E15,G15,I15,K15) -> 8 | C15: =NOM!K154 -> 8 | E15: =NOM!M154 -> 8 | G15: =NOM!O154 -> 8 | I15: =NOM!Q154 -> 8 | K15: =NOM!S154 -> 8 | M15: =NOM!U154 -> 0 | N15: AE 3
A16: =+AVERAGE(C16,E16,G16,I16,K16) -> 10 | C16: =NOM!L270 -> 9 | E16: =NOM!N270 -> 11 | G16: =NOM!P270 -> 10 | I16: =NOM!R270 -> 10 | K16: =NOM!T270 -> 10 | M16: =NOM!V270 -> 0 | N16: TEJIDO LEON
A17: =+AVERAGE(C17,E17,G17,I17,K17) -> 1 | C17: =NOM!E280 -> 1 | E17: =NOM!G280 -> 1 | G17: =NOM!I280 -> 1 | I17: =NOM!K280 -> 1 | K17: =NOM!M280 -> 1 | M17: =NOM!O280 -> 1 | N17: APOYO LG
A19: =+AVERAGE(C19,E19,G19,I19,K19) -> 67.8 | C19: =SUM(C7:C18) -> 66 | E19: =SUM(E7:E18) -> 69 | G19: =SUM(G7:G18) -> 68 | I19: =SUM(I7:I18) -> 68 | K19: =SUM(K7:K18) -> 68 | M19: =SUM(M7:M18) -> 16 | N19: TOT

Sheet CHECADAS
A1: Nominas
A2: Numero | B2: NombreCompleto | C2: FechaInicio | D2: FechaFin | E2: L.Entrada | F2: L.Salida | G2: MA.Entrada | H2: MA.Salida | I2: MI.Entrada | J2: MI.Salida | K2: J.Entrada | L2: J.Salida | M2: V.Entrada | N2: V.Salida | O2: S.Entrada | P2: S.Salida | Q2: D.Entrada | R2: D.Salida
A3: 107 | B3: SAMUEL CHAVARRIA MACHADO | C3: 2025-06-23 | D3: 2025-06-29 | E3: 15:40:00 | F3: 0.9849537 | I3: 03:26:56 p. m. | J3: 0.98461806 | K3: 15:26:00 | L3: 0.98501157 | M3: 03:39:04 p. m. | N3: 0.98204861 | O3: 0.64471065 | P3: 0.77542824
A4: 118 | B4: MARIA FERNANDA ROSALES GONZALEZ | C4: 2025-06-23 | D4: 2025-06-29 | E4: 0.98761574 | F4: 0.31275463 | G4: 0.9809375 | H4: 0.31299769 | I4: 0.98175926 | J4: 0.31333333 | K4: 0.98085648 | L4: 0.31296296 | M4: 0.97664352 | N4: 07:30:38 a. m.
A5: 12 | B5: ANGELA ELIZABETH DIAZ MARTINEZ | C5: 2025-06-23 | D5: 2025-06-29 | E5: 15:27:00 | F5: 23:32:00 | G5: 15:27:00 | H5: 0.9799537 | I5: 15:24:00 | J5: 23:36:00 | K5: 15:30:00 | L5: 23:33:00 | M5: 0.65690972 | N5: 0.85211806
A6: 135 | B6: SUGEY MARISOL MARTINEZ ROSALES | C6: 2025-06-23 | D6: 2025-06-29 | F6: 0.31328704 | G6: 0.98099537 | H6: 0.31305556 | I6: 0.98181713 | J6: 0.31715278 | K6: 0.9809375 | L6: 07:30:50 a. m. | M6: |
A7: 141 | B7: MA. ISABEL VARGAS MENDEZ | C7: 2025-06-23 | D7: 2025-06-29 | E7: 07:26:00 | F7: 15:31:00 | G7: 07:25:00 | H7: 15:31:00 | I7: 07:24:00 | J7: 15:31:00 | K7: 07:25:00 | L7: 15:35:00 | M7: 07:25:00 | N7: 03:33:53 p. m. | O7: 0.30895833 | P7: 0.6475463
A8: 1446 | B8: SAUL BAUTISTA REVUELTAS | C8: 2025-06-23 | D8: 2025-06-29
A9: 146 | B9: YOHANA CECILIA SALAZAR MARTINEZ | C9: 2025-06-23 | D9: 2025-06-29 | E9: 07:16:00 | F9: 0.64829861 | G9: 07:22:00 | H9: 03:31:44 p. m. | I9: VAC | K9: 07:20:00 | L9: 03:31:18 p. m. | M9: 07:20:50 a. m. | N9: 0.64673611 | O9: VAC
A10: 158 | B10: JOSE ALBERTO CABALLERO COYOC | C10: 2025-06-23 | D10: 2025-06-29 | E10: 0.64917824 | F10: 0.98047454 | G10: 0.6421412 | H10: 0.98077546 | I10: 0.65003472 | J10: 11:37:39 p. m. | K10: 0.64821759 | L10: 0.98600694 | M10: 03:33:02 p. m. | N10: 11:50:48 p. m. | O10: 0.6515625 | P10: 0.85554398
A11: 159 | B11: HERBER ANTONY PEREZ SUAREZ | C11: 2025-06-23 | D11: 2025-06-29 | E11: 0.97439815 | F11: 07:32:00 | G11: 11:26:08 p. m. | H11: 07:38:00 | I11: 0.98068287 | J11: 07:35:00 | K11: 0.97409722 | L11: 07:32:00 | M11: 11:30:10 p. m. | N11: 0.31988426
A12: 165 | B12: DIEGO FRANCO ALATORRE | C12: 2025-06-23 | D12: 2025-06-29
A13: 166 | B13: ACACIA ENRIQUEZ GUTIERREZ | C13: 2025-06-23 | D13: 2025-06-29 | E13: 07:26:00 | F13: 15:31:00 | G13: 07:25:00 | H13: 15:31:00 | I13: 07:24:00 | J13: 15:31:00 | K13: 07:24:00 | L13: 15:35:00 | M13: 07:25:00 | N13: 0.64849537 | O13: VAC
A14: 169 | B14: MARIA GUADALUPE RAMIREZ REQUEJO | C14: 2025-06-23 | D14: 2025-06-29 | E14: 0.64372685 | F14: 0.98096065 | G14: 03:28:43 p. m. | H14: 0.97938657 | I14: 0.6468287 | J14: 0.97927083 | K14: 0.64704861 | L14: 11:31:00 p. m. | M14: 0.64355324 | N14: 0.98238426 | O14: 0.6437037 | P14: 0.85217593
A15: 172 | B15: MARIA ELENA HERNANDEZ CAMPISTA | C15: 2025-06-23 | D15: 2025-06-29 | E15: 0.28488426 | F15: 0.68074074 | G15: 0.28447917 | H15: 0.68084491 | I15: 0.28356481 | J15: 0.68059028 | K15: 0.28458333 | L15: 0.680625 | M15: 0.28325231 | N15: 0.68131944
A16: 19 | B16: ELIZABETH GARCIA NUÑEZ | C16: 2025-06-23 | D16: 2025-06-29 | E16: 07:40:00 | F16: 15:42:00 | G16: 07:31:00 | H16: 15:33:00 | I16: 07:31:00 | J16: 15:37:00 | K16: 07:34:00 | L16: 15:40:00 | M16: 07:34:00 | N16: 0.65541667 | O16: 0.32449074 | P16: 03:45:47 p. m.
A17: 2 | B17: GABRIELA ANTUNEZ REQUEJO | C17: 2025-06-23 | D17: 2025-06-29 | E17: VAC | G17: VAC | I17: VAC | K17: VAC | M17: VAC
A18: 210 | B18: NANCY LORENA PADILLA ARMIJO | C18: 2025-06-23 | D18: 2025-06-29 | E18: 0.98518519 | F18: 0.31322917 | G18: 0.98642361 | H18: 0.31356481 | I18: 0.98189815 | J18: 0.31388889 | K18: 0.98459491 | L18: 0.31425926 | M18: 11:36:59 p. m. | N18: 07:31:44 a. m.
A19: 212 | B19: MARGARITA HERNANDEZ FAVELA | C19: 2025-06-23 | D19: 2025-06-29 | E19: 15:27:00 | F19: 0.98119213 | G19: 15:26:00 | H19: 0.9799537 | I19: 15:24:00 | J19: 0.97994213 | K19: VAC | M19: 03:30:58 p. m. | N19: 0.97939815 | O19: 03:27:37 p. m. | P19: 08:29:54 p. m.
A20: 214 | B20: LEIDY DANIELA GRESS PADILLA | C20: 2025-06-23 | D20: 2025-06-29 | E20: 11:21:35 p. m. | F20: 07:30:00 | I20: 11:12:17 p. m. | J20: 0.31288194 | K20: 0.97017361 | L20: 07:30:00 | M20: 0.96686343 | N20: 0.31263889
A21: 215 | B21: HILDA YUDITH HOLGUIN SALAS | C21: 2025-06-23 | D21: 2025-06-29 | E21: VAC | G21: VAC | I21: 0.96733796 | J21: 07:30:00 | K21: 10:47:12 p. m. | L21: 07:30:00 | M21: 0.94515046 | N21: 07:30:07 a. m.
A22: 220 | B22: PEDRO VARGAS TORRES | C22: 2025-06-23 | D22: 2025-06-29 | E22: 07:28:00 | F22: 0.64707176 | G22: 07:30:00 | H22: 0.64732639 | I22: 07:29:00 | J22: 03:31:42 p. m. | K22: 07:30:00 | M22: 07:29:00 | N22: 0.64865741 | O22: 07:35:54 a. m. | P22: 03:32:51 p. m.
A23: 222 | B23: MARIA FERNANDA HERNANDEZ DE LA ROSA | C23: 2025-06-23 | D23: 2025-06-29 | E23: VAC | G23: 07:30:00 | H23: 0.64663194 | I23: 0.30542824 | J23: 0.64642361 | K23: VAC | M23: 07:32:00 | O23: VAC
A24: 226 | B24: JOSE URIEL MORENO MARTINEZ | C24: 2025-06-23 | D24: 2025-06-29 | E24: 07:09:13 a. m. | F24: 0.64662037 | G24: 07:06:44 a. m. | H24: 0.64869213 | I24: 0.31890046 | J24: 0.64717593 | K24: 07:32:13 a. m. | L24: 0.64601852 | M24: 0.31357639 | N24: 0.64641204 | O24: 0.31680556
A25: 227 | B25: JOSE LUIS MARTINEZ ROSALES | C25: 2025-06-23 | D25: 2025-06-29 | E25: 0.95601852 | F25: 07:30:00 | G25: 0.9519213 | H25: 07:30:00 | I25: 10:52:51 p. m. | J25: 07:30:00 | K25: 10:48:05 p. m. | L25: 07:31:00 | M25: 0.98649306 | N25: 0.31375
A26: 228 | B26: HAXEL RODRIGO TOSTADO SIFUENTES | C26: 2025-06-23 | D26: 2025-06-29 | E26: 0.98127315 | F26: 0.31263889 | G26: 0.98263889 | H26: 0.31280093 | I26: 0.98269676 | J26: 0.31311343 | K26: 0.98208333 | L26: 0.3127662 | M26: 11:37:02 p. m. | N26: 07:30:15 a. m.
A27: 230 | B27: PRINCE ANAIS LLAMAS PEREZ | C27: 2025-06-23 | D27: 2025-06-29 | E27: 07:16:00 | F27: 0.79332176 | G27: 07:12:46 a. m. | H27: 0.64652778 | I27: 07:15:00 | J27: 0.64605324 | K27: 0.30059028 | L27: 0.64615741 | M27: 07:16:00 | N27: 0.64628472 | O27: 0.31861111 | P27: 0.64677083 | Q27: 0.35207176 | R27: 0.64725694
A28: 235 | B28: ANGEL DE JESUS MORENO MARTINEZ | C28: 2025-06-23 | D28: 2025-06-29 | E28: T*T | F28: T*T | G28: T*T | H28: T*T | I28: T*T | J28: T*T | K28: T*T | L28: T*T | M28: T*T | N28: T*T | O28: T*T | P28: T*T | Q28: T*T
A29: 239 | B29: ROSA VELIA CORDONA PEREZ | C29: 2025-06-23 | D29: 2025-06-29 | E29: 0.30309028 | F29: 0.79320602 | G29: 07:12:37 a. m. | H29: 0.79491898 | I29: 07:15:17 a. m. | J29: 0.70850694 | K29: 0.3006713 | L29: 0.793125 | M29: 07:16:09 a. m. | N29: 0.64618056 | O29: 0.64672454 | P29: 0.35211806 | Q29: 03:32:13 p. m.
A30: 241 | B30: MONSERRAT GUADALUPE MOLINA SIFUENTES | C30: 2025-06-23 | D30: 2025-06-29 | E30: 0.29384259 | F30: 0.6462963 | G30: 0.29850694 | H30: 0.64659722 | I30: 0.29415509 | J30: 03:30:22 p. m. | K30: 0.29313657 | L30: 0.64623843 | M30: 0.29640046 | N30: 0.64622685 | O30: 0.29138889 | P30: 0.64666667
A31: 242 | B31: JESUS MARIA VILLEGAS REYES | C31: 2025-06-23 | D31: 2025-06-29 | E31: VAC | G31: VAC | I31: VAC | K31: VAC | M31: VAC
A32: 245 | B32: PEDRO FRANCISCO VARGAS CASTAÑEDA | C32: 2025-06-23 | D32: 2025-06-29 | E32: FALTA | G32: 07:19:00 | H32: 0.7080787 | I32: 0.30152778 | J32: 0.70599537 | K32: 07:20:00 | L32: 0.70553241 | M32: 07:16:00 | N32: 0.70625
A33: 251 | B33: YHAIR OTONIEL BALDERAS AGUILAR | C33: 2025-06-23 | D33: 2025-06-29 | E33: VAC | G33: VAC | I33: VAC | K33: VAC | M33: 0.94510417 | N33: 0.3125463
A34: 254 | B34: ANGELICA NUÑEZ VIAÑA | C34: 2025-06-23 | D34: 2025-06-29 | E34: 23:11:00 | F34: 07:30:00 | G34: 23:19:00 | H34: 07:30:00 | I34: 23:20:00 | J34: 07:31:00 | K34: 23:21:00 | L34: 07:30:00 | M34: 0.9694213 | N34: 0.31355324
A35: 256 | B35: JORDAN MISSAEL GONZALEZ REYES | C35: 2025-06-23 | D35: 2025-06-29 | E35: 07:47:00 | F35: 17:01:00 | G35: 07:41:00 | H35: 17:00:00 | I35: 07:41:00 | J35: 04:57:37 p. m. | K35: 07:41:00 | L35: 0.705625 | M35: 07:37:00 | N35: 0.70628472 | O35: 0.32936343 | P35: 0.5296875
A36: 26 | B36: JOSE ADOLFO MEDRANO SUAREZ | C36: 2025-06-23 | D36: 2025-06-29 | E36: VAC | G36: VAC | I36: VAC | K36: VAC | M36: VAC
A37: 260 | B37: JOSE DE JESUS MACIAS MIJARES | C37: 2025-06-23 | D37: 2025-06-29 | E37: 07:47:00 | F37: 17:01:00 | G37: 07:45:00 | I37: 07:43:00 | J37: 04:57:48 p. m. | K37: FALTA | M37: 07:35:00 | N37: 0.70631944
A38: 261 | B38: CRISTIAN OMAR VALENZUELA ROSALES | C38: 2025-06-23 | D38: 2025-06-29 | E38: B | G38: B | I38: B | K38: B | M38: B
A39: 262 | B39: ZEIDA MARLEN MORENO MARTINEZ | C39: 2025-06-23 | D39: 2025-06-29 | E39: 07:16:00 | F39: 15:30:00 | G39: 07:12:00 | H39: 15:31:00 | I39: 07:21:00 | J39: 15:30:00 | K39: 07:32:00 | L39: 15:30:00 | M39: 07:16:00 | N39: 03:30:48 p. m. | O39: 0.3075 | P39: 0.64680556
A40: 264 | B40: JOSE ALFREDO CASTAÑEDA FLORES | C40: 2025-06-23 | D40: 2025-06-29 | E40: 0.63988426 | F40: 11:30:25 p. m. | G40: 0.63400463 | H40: 0.97961806 | I40: 0.63506944 | J40: 0.9793287 | K40: 0.63511574 | L40: 0.80033565 | N40: 0.97986111 | O40: 0.63528935 | P40: 0.85420139
A41: 265 | B41: BRISA IRIS VALENZUELA RUIZ | C41: 2025-06-23 | D41: 2025-06-29 | E41: B | G41: B | I41: B | K41: B | M41: B
A42: 266 | B42: emilio rubio resendiz | C42: 2025-06-23 | D42: 2025-06-29 | E42: 0.98131944 | F42: 07:30:00 | G42: 0.98105324 | H42: 07:30:00 | I42: 0.98063657 | J42: 07:31:00 | K42: 0.97953704 | L42: 07:31:00 | M42: 0.97668981 | N42: 07:30:31 a. m.
A43: 267 | B43: daniela garcia nuñez | C43: 2025-06-23 | D43: 2025-06-29 | E43: 0.96643519 | F43: 07:30:00 | G43: 0.97208333 | H43: 0.25150463 | I43: 0.9755787 | J43: 07:31:00 | K43: 0.97386574 | L43: 07:31:00 | M43: 0.97765046 | N43: 0.31449074
A44: 268 | B44: jose manuel macias mijares | C44: 2025-06-23 | D44: 2025-06-29 | E44: 07:47:00 | F44: 17:01:00 | G44: 07:45:00
A45: 269 | B45: aleida maribi pardo arevalo | C45: 2025-06-23 | D45: 2025-06-29 | E45: FALTA | G45: 07:25:00 | H45: 0.64666667 | I45: 07:42:00 | J45: 0.64690972 | K45: 07:35:00 | L45: 0.64667824 | M45: 07:32:00 | N45: 0.44203704 | O45: 0.319375
A46: 27 | B46: ADILENE MINOR FLORES | C46: 2025-06-23 | D46: 2025-06-29 | E46: VAC | G46: VAC | I46: VAC | K46: VAC | M46: VAC
A47: 271 | B47: juana maria flores cruz | C47: 2025-06-23 | D47: 2025-06-29 | E47: 0.6441088 | F47: 11:32:38 p. m. | G47: 0.64447917 | H47: 0.9812963 | I47: 0.64962963 | J47: 0.97978009 | K47: 0.64400463 | L47: 0.98042824 | M47: 0.6447338 | N47: 0.97945602 | O47: 0.65 | P47: 0.85430556
A48: 28 | B48: RAUL MORAN HERNANDEZ | C48: 2025-06-23 | D48: 2025-06-29 | E48: 0.97851852 | F48: 07:33:00 | G48: 0.97644676 | H48: 07:31:00 | I48: 0.97428241 | J48: 07:30:00 | K48: 0.97451389 | L48: 07:30:00 | M48: 0.97505787 | N48: 0.3128125
A49: 29 | B49: MARIA DEL ROSARIO NUÑEZ VIAÑA | C49: 2025-06-23 | D49: 2025-06-29 | E49: 11:11:37 p. m. | F49: 07:30:00 | G49: 0.9721412 | H49: 07:36:00 | I49: 0.97246528 | J49: 07:31:00 | K49: 11:13:12 p. m. | L49: 07:31:00 | M49: 0.3128125 | N49: 0.31413194
A50: 30 | B50: JAQUELINE PACHECO VIAÑA | C50: 2025-06-23 | D50: 2025-06-29 | E50: 0.64581019 | F50: 0.98122685 | G50: 0.64581019 | H50: 11:32:58 p. m. | I50: 0.64667824 | J50: 0.97988426 | K50: 0.64391204 | L50: 11:31:58 p. m. | M50: 0.64953704 | N50: 0.97936343 | O50: 0.64740741 | P50: 0.85591435
A51: 33 | B51: JOSE ARMANDO RAMIREZ VITAL | C51: 2025-06-23 | D51: 2025-06-29 | E51: 11:25:46 p. m. | F51: 0.31271991 | G51: 0.97324074 | I51: 0.975 | J51: 0.30584491 | K51: 0.96950231
A52: 34 | B52: NOE REQUEJO HERNANDEZ | C52: 2025-06-23 | D52: 2025-06-29 | E52: 0.33752315 | F52: 17:03:00 | G52: 07:55:00 | H52: 0.70739583 | I52: 0.33738426 | J52: 0.7059375 | K52: 0.37774306 | L52: 04:53:21 p. m. | M52: 07:57:00 | N52: 0.81679398 | O52: 09:47:11 p. m.
A53: 35 | B53: JOSE EMILIO REYES CHAVARRIA | C53: 2025-06-23 | D53: 2025-06-29 | G53: 07:50:00 | I53: 07:32:00 | K53: 07:50:00 | M53: 07:50:00
A54: 37 | B54: ROSA KAREN RODRIGUEZ CASTILLO | C54: 2025-06-23 | D54: 2025-06-29 | E54: VAC | G54: VAC | I54: VAC | K54: VAC | M54: VAC
A55: 39 | B55: ERIKA ELIZABETH RODRIGUEZ URIBE | C55: 2025-06-23 | D55: 2025-06-29 | E55: VAC | G55: VAC | I55: VAC | K55: VAC | M55: VAC
A56: 41 | B56: ANA LILIANA SALAZAR HOLGUIN | C56: 2025-06-23 | D56: 2025-06-29 | E56: 07:48:00 | F56: 17:03:00 | G56: 07:59:00 | H56: 0.70768519 | I56: 07:57:00 | J56: 17:00:00 | K56: 0.34662037 | L56: 0.70594907 | M56: 07:55:00 | N56: 0.70699074
A57: 51 | B57: JOSE MIGUEL VALENZUELA ROSALES | C57: 2025-06-23 | D57: 2025-06-29 | E57: 0.26905093 | F57: 0.6574537 | G57: 0.31760417 | H57: 0.64583333 | I57: 07:37:00 | K57: 07:34:00 | L57: 0.64716435 | M57: 07:26:00 | O57: 0.31642361 | P57: 0.64819444
A58: 59 | B58: MARIO IVAN CASTRO VIAÑA | C58: 2025-06-23 | D58: 2025-06-29 | E58: 0.97431713 | F58: 0.31487269 | G58: 0.97638889 | H58: 0.31321759 | I58: 0.97369213 | J58: 0.3130787 | K58: 07:30:00 | L58: 0.97445602 | M58: 07:30:00 | N58: 0.97509259 | O58: 0.3127662
A59: 6 | B59: MYRIAM IVET BALDERAS BALDERAS | C59: 2025-06-23 | D59: 2025-06-29 | E59: VAC | G59: VAC | I59: VAC | K59: VAC | M59: VAC
A60: 63 | B60: MARIO CUAPIO FLORES | C60: 2025-06-23 | D60: 2025-06-29 | E60: 07:30:00 | F60: 17:01:00 | G60: 07:30:00 | I60: 07:26:00 | K60: 07:30:00 | L60: 15:44:00 | M60: 07:57:00
A61: 70 | B61: VIOLETA GONZALEZ LOPEZ | C61: 2025-06-23 | D61: 2025-06-29 | E61: 15:31:00 | F61: 23:32:00 | I61: 15:31:00 | J61: 23:30:00 | K61: 15:27:00 | L61: 23:31:00 | M61: 0.64960648 | N61: 0.97953704 | O61: 0.64646991 | P61: 0.85597222
A62: 73 | B62: LESLIE CORAIMA GARCIA ORTEGA | C62: 2025-06-23 | D62: 2025-06-29 | E62: 0.28873843 | F62: 0.64625 | G62: VAC | I62: VAC | K62: 07:13:00 | L62: 03:30:31 p. m. | M62: 07:16:00 | N62: 0.64633102 | O62: 07:22:45 a. m. | P62: 0.64662037 | Q62: 0.33994213 | R62: 0.64730324
A63: 74 | B63: MYRTALA HERNANDEZ GONZALEZ | C63: 2025-06-23 | D63: 2025-06-29 | E63: VAC | G63: VAC | I63: 0.95342593 | J63: 07:31:00 | K63: 0.94939815 | L63: 07:31:00 | M63: 0.94506944 | N63: 0.31407407
A64: 75 | B64: AILEN FLORES MIRANDA | C64: 2025-06-23 | D64: 2025-06-29 | E64: 0.98309028 | F64: 07:32:00 | G64: 0.9808912 | H64: 07:36:00 | I64: 0.9809375 | J64: 07:33:00 | K64: 0.98237269 | L64: 07:31:00 | M64: 11:31:26 p. m. | N64: 0.31664352
A65: 81 | B65: andrea isabel rodriguez lopez | C65: 2025-06-23 | D65: 2025-06-29 | E65: 0.64646991 | F65: 0.98162037 | G65: 0.64846065 | H65: 0.97947917 | I65: 0.64512731 | J65: 0.98600694 | K65: 0.64633102 | L65: 0.98704861 | M65: 0.64646991 | N65: 0.98886574 | O65: 03:31:04 p. m. | P65: 0.85415509
A66: 82382 | B66: MONSERRAT NUÑEZ MARTINEZ | C66: 2025-06-23 | D66: 2025-06-29
A67: 82497 | B67: CATALINA ACEVEDO CAMACHO | C67: 2025-06-23 | D67: 2025-06-29
A68: 82589 | B68: GABRIELA LIZBETH LOZANO GUILLEN | C68: 2025-06-23 | D68: 2025-06-29
A69: 89 | B69: MARIA GUADALUPE HERNANDEZ FLORES | C69: 2025-06-23 | D69: 2025-06-29 | E69: 07:26:00 | F69: 0.83638889 | G69: 07:37:00 | H69: 0.70822917 | I69: 07:35:00 | J69: 17:00:00 | K69: 0.34998843 | L69: 0.70635417 | M69: 07:51:00 | N69: 0.70642361
A70: 9 | B70: OSVALDO BUSTAMANTE VILLEGAS | C70: 2025-06-23 | D70: 2025-06-29 | E70: 0.64447917 | F70: 0.81498843 | G70: 0.0098611111 | H70: 07:47:00 | I70: 0.97424769 | J70: 07:39:00 | K70: 0.97766204 | L70: 07:32:00 | M70: 11:30:13 p. m. | N70: 0.32280093
A71: 94 | B71: JESUS ALBERTO DOMINGUEZ SOTO | C71: 2025-06-23 | D71: 2025-06-29 | E71: 23:22:00 | F71: 07:36:00 | G71: 23:18:00 | H71: 07:42:00 | I71: 23:11:00 | J71: 07:47:00 | K71: 23:11:00 | L71: 07:42:00 | M71: 0.97331019 | N71: 0.31465278 | O71: 0.97190972
A72: 95 | B72: JUDITH CARRILLO DELGADO | C72: 2025-06-23 | D72: 2025-06-29 | E72: 07:34:00 | F72: 17:02:00 | H72: 17:01:00 | I72: 07:33:00 | J72: 17:00:00 | K72: 07:32:00 | M72: 07:24:00 | N72: 0.64943287
A73: 97 | B73: MARISA ISABEL BURCIAGA AGUIRRE | C73: 2025-06-23 | D73: 2025-06-29 | E73: 08:16:18 a. m. | F73: 17:03:00 | G73: 0.33803241 | H73: 0.70765046 | I73: 0.34148148 | J73: 17:00:00 | K73: 08:08:06 a. m. | L73: 0.7058912 | M73: 07:51:00 | N73: 04:57:58 p. m.

Sheet REPORTE
A1: Date | B1: Device ID | C1: Device | D1: User Group | E1: User | F1: Event
A2: 45837.972 | B2: 542361075 | C2: FaceStation 2 542361075 (192.168.50.205) | D2: All Users | E2: 94 | F2: 1:N authentication succeeded (Face)
A3: 45837.647 | B3: 542361075 | C3: FaceStation 2 542361075 (192.168.50.205) | D3: All Users | E3: 239 | F3: 1:N authentication succeeded (Face)
A4: 45837.647 | B4: 542361075 | C4: FaceStation 2 542361075 (192.168.50.205) | D4: All Users | E4: 73 | F4: 1:N authentication succeeded (Face)
A5: 45837.647 | B5: 542361075 | C5: FaceStation 2 542361075 (192.168.50.205) | D5: All Users | E5: 230 | F5: 1:N authentication succeeded (Face)
A6: 45837.352 | B6: 542361075 | C6: FaceStation 2 542361075 (192.168.50.205) | D6: All Users | E6: 239 | F6: 1:N authentication succeeded (Face)
A7: 45837.352 | B7: 542361075 | C7: FaceStation 2 542361075 (192.168.50.205) | D7: All Users | E7: 230 | F7: 1:N authentication succeeded (Face)
A8: 45837.34 | B8: 542361075 | C8: FaceStation 2 542361075 (192.168.50.205) | D8: All Users | E8: 73 | F8: 1:N authentication succeeded (Face)
A9: 45837.323 | B9: 542361075 | C9: FaceStation 2 542361075 (192.168.50.205) | D9: All Users | E9: 35 | F9: 1:N authentication succeeded (Face)
A10: 45837.315 | B10: 542361075 | C10: FaceStation 2 542361075 (192.168.50.205) | D10: All Users | E10: 63 | F10: 1:N authentication succeeded (Face)
A11: 45837.315 | B11: 542361075 | C11: FaceStation 2 542361075 (192.168.50.205) | D11: All Users | E11: 94 | F11: 1:N authentication succeeded (Face)
A12: 45837.284 | B12: 542361075 | C12: FaceStation 2 542361075 (192.168.50.205) | F12: Tamper off
A13: 45837.284 | B13: 542361075 | C13: FaceStation 2 542361075 (192.168.50.205) | F13: Device started
A14: 45837.284 | B14: 542361075 | C14: FaceStation 2 542361075 (192.168.50.205) | F14: Network connected
A15: 45836.973 | B15: 542361075 | C15: FaceStation 2 542361075 (192.168.50.205) | D15: All Users | E15: 94 | F15: 1:N authentication succeeded (Face)
A16: 45836.856 | B16: 542361075 | C16: FaceStation 2 542361075 (192.168.50.205) | D16: All Users | E16: 70 | F16: 1:N authentication succeeded (Face)
A17: 45836.856 | B17: 542361075 | C17: FaceStation 2 542361075 (192.168.50.205) | D17: All Users | E17: 30 | F17: 1:N authentication succeeded (Face)
A18: 45836.856 | B18: 542361075 | C18: FaceStation 2 542361075 (192.168.50.205) | D18: All Users | E18: 158 | F18: 1:N authentication succeeded (Face)
A19: 45836.855 | B19: 542361075 | C19: FaceStation 2 542361075 (192.168.50.205) | D19: All Users | E19: 235 | F19: 1:N authentication succeeded (Face)
A20: 45836.854 | B20: 542361075 | C20: FaceStation 2 542361075 (192.168.50.205) | D20: All Users | E20: 271 | F20: 1:N authentication succeeded (Face)
A21: 45836.854 | B21: 542361075 | C21: FaceStation 2 542361075 (192.168.50.205) | D21: All Users | E21: 264 | F21: 1:N authentication succeeded (Face)
A22: 45836.854 | B22: 542361075 | C22: FaceStation 2 542361075 (192.168.50.205) | D22: All Users | E22: 81 | F22: 1:N authentication succeeded (Face)
A23: 45836.854 | B23: 542361075 | C23: FaceStation 2 542361075 (192.168.50.205) | D23: All Users | E23: 212 | F23: 1:N authentication succeeded (Face)
A24: 45836.852 | B24: 542361075 | C24: FaceStation 2 542361075 (192.168.50.205) | D24: All Users | E24: 169 | F24: 1:N authentication succeeded (Face)
A25: 45836.852 | B25: 542361075 | C25: FaceStation 2 542361075 (192.168.50.205) | D25: All Users | E25: 12 | F25: 1:N authentication succeeded (Face)
A26: 45836.813 | B26: 542361075 | C26: FaceStation 2 542361075 (192.168.50.205) | D26: All Users | E26: 264 | F26: 1:N authentication succeeded (Face)
... A32: 45836.657 | B32: 542361075 | C32: FaceStation 2 542361075 (192.168.50.205) | D32: All Users | E32: 19 | F32: 1:N authentication succeeded (Face)
A33: 45836.657 | B33: 542361075 | C33: FaceStation 2 542361075 (192.168.50.205) | F33: Authentication failed (Timeout)
A34: 45836.657 | B34: 542361075 | C34: FaceStation 2 542361075 (192.168.50.205) | D34: All Users | E34: 247 | F34: 1:N authentication succeeded (Face)
A35: 45836.657 | B35: 542361075 | C35: FaceStation 2 542361075 (192.168.50.205) | F35: Authentication failed (Timeout)
A36: 45836.652 | B36: 542361075 | C36: FaceStation 2 542361075 (192.168.50.205) | D36: All Users | E36: 158 | F36: 1:N authentication succeeded (Face)
A37: 45836.65 | B37: 542361075 | C37: FaceStation 2 542361075 (192.168.50.205) | D37: All Users | E37: 271 | F37: 1:N authentication succeeded (Face)
A38: 45836.648 | B38: 542361075 | C38: FaceStation 2 542361075 (192.168.50.205) | D38: All Users | E38: 51 | F38: 1:N authentication succeeded (Face)
A39: 45836.648 | B39: 542361075 | C39: FaceStation 2 542361075 (192.168.50.205) | D39: All Users | E39: 220 | F39: 1:N authentication succeeded (Face)
A40: 45836.648 | B40: 542361075 | C40: FaceStation 2 542361075 (192.168.50.205) | D40: All Users | E40: 141 | F40: 1:N authentication succeeded (Face)
A41: 45836.648 | B41: 542361075 | C41: FaceStation 2 542361075 (192.168.50.205) | D41: All Users | E41: 145 | F41: 1:N authentication succeeded (Face)
A42: 45836.647 | B42: 542361075 | C42: FaceStation 2 542361075 (192.168.50.205) | D42: All Users | E42: 30 | F42: 1:N authentication succeeded (Face)
A43: 45836.647 | B43: 542361075 | C43: FaceStation 2 542361075 (192.168.50.205) | D43: All Users | E43: 262 | F43: 1:N authentication succeeded (Face)
A44: 45836.647 | B44: 542361075 | C44: FaceStation 2 542361075 (192.168.50.205) | D44: All Users | E44: 230 | F44: 1:N authentication succeeded (Face)
A45: 45836.647 | B45: 542361075 | C45: FaceStation 2 542361075 (192.168.50.205) | D45: All Users | E45: 239 | F45: 1:N authentication succeeded (Face)
A46: 45836.647 | B46: 542361075 | C46: FaceStation 2 542361075 (192.168.50.205) | D46: All Users | E46: 241 | F46: 1:N authentication succeeded (Face)
A47: 45836.647 | B47: 542361075 | C47: FaceStation 2 542361075 (192.168.50.205) | D47: All Users | E47: 73 | F47: 1:N authentication succeeded (Face)
... A118: 45836.063 | B118: 542361075 | C118: FaceStation 2 542361075 (192.168.50.205) | D118: All Users | E118: 215 | F118: 1:N authentication succeeded (Face)
A119: 45836.063 | B119: 542361075 | C119: FaceStation 2 542361075 (192.168.50.205) | F119: Authentication failed (Timeout)
A120: 45836.063 | B120: 542361075 | C120: FaceStation 2 542361075 (192.168.50.205) | F120: Authentication failed (Timeout)
A121: 45836.047 | B121: 542361075 | C121: FaceStation 2 542361075 (192.168.50.205) | D121: All Users | E121: 94 | F121: 1:N authentication succeeded (Face)
A122: 45836.024 | B122: 542361075 | C122: FaceStation 2 542361075 (192.168.50.205) | D122: All Users | E122: 94 | F122: 1:N authentication succeeded (Face)
A123: 45835.994 | B123: 542361075 | C123: FaceStation 2 542361075 (192.168.50.205) | D123: All Users | E123: 158 | F123: 1:N authentication succeeded (Face)
A124: 45835.989 | B124: 542361075 | C124: FaceStation 2 542361075 (192.168.50.205) | D124: All Users | E124: 81 | F124: 1:N authentication succeeded (Face)
A125: 45835.986 | B125: 542361075 | C125: FaceStation 2 542361075 (192.168.50.205) | D125: All Users | E125: 227 | F125: 1:N authentication succeeded (Face)
A126: 45835.984 | B126: 542361075 | C126: FaceStation 2 542361075 (192.168.50.205) | D126: All Users | E126: 228 | F126: 1:N authentication succeeded (Face)
A127: 45835.984 | B127: 542361075 | C127: FaceStation 2 542361075 (192.168.50.205) | D127: All Users | E127: 210 | F127: 1:N authentication succeeded (Face)
A128: 45835.982 | B128: 542361075 | C128: FaceStation 2 542361075 (192.168.50.205) | D128: All Users | E128: 169 | F128: 1:N authentication succeeded (Face)
A129: 45835.982 | B129: 542361075 | C129: FaceStation 2 542361075 (192.168.50.205) | D129: All Users | E129: 107 | F129: 1:N authentication succeeded (Face)
A130: 45835.98 | B130: 542361075 | C130: FaceStation 2 542361075 (192.168.50.205) | D130: All Users | E130: 75 | F130: 1:N authentication succeeded (Face)
A131: 45835.98 | B131: 542361075 | C131: FaceStation 2 542361075 (192.168.50.205) | D131: All Users | E131: 264 | F131: 1:N authentication succeeded (Face)
A132: 45835.98 | B132: 542361075 | C132: FaceStation 2 542361075 (192.168.50.205) | D132: All Users | E132: 70 | F132: 1:N authentication succeeded (Face)
... A160: 45835.706 | B160: 542361075 | C160: FaceStation 2 542361075 (192.168.50.205) | D160: All Users | E160: 245 | F160: 1:N authentication succeeded (Face)
A161: 45835.706 | B161: 542361075 | C161: FaceStation 2 542361075 (192.168.50.205) | F161: BioStar disconnected
A162: 45835.69 | B162: 542361075 | C162: FaceStation 2 542361075 (192.168.50.205) | D162: All Users | E162: 145 | F162: 1:N authentication succeeded (Face)
A163: 45835.681 | B163: 542361075 | C163: FaceStation 2 542361075 (192.168.50.205) | D163: All Users | E163: 172 | F163: 1:N authentication succeeded (Face)
A164: 45835.681 | B164: 542361075 | C164: FaceStation 2 542361075 (192.168.50.205) | D164: All Users | E164: 172 | F164: 1:N authentication succeeded (Face)
A165: 45835.655 | B165: 542361075 | C165: FaceStation 2 542361075 (192.168.50.205) | D165: All Users | E165: 19 | F165: 1:N authentication succeeded (Face)
A166: 45835.655 | B166: 542361075 | C166: FaceStation 2 542361075 (192.168.50.205) | F166: Authentication failed (Timeout)
A167: 45835.655 | B167: 542361075 | C167: FaceStation 2 542361075 (192.168.50.205) | F167: Authentication failed (Timeout)
A168: 45835.655 | B168: 542361075 | C168: FaceStation 2 542361075 (192.168.50.205) | F168: Authentication failed (Timeout)
A169: 45835.655 | B169: 542361075 | C169: FaceStation 2 542361075 (192.168.50.205) | F169: Authentication failed (Timeout)
A170: 45835.655 | B170: 542361075 | C170: FaceStation 2 542361075 (192.168.50.205) | F170: Authentication failed (Timeout)
A171: 45835.655 | B171: 542361075 | C171: FaceStation 2 542361075 (192.168.50.205) | F171: Authentication failed (Timeout)
A172: 45835.655 | B172: 542361075 | C172: FaceStation 2 542361075 (192.168.50.205) | F172: Authentication failed (Timeout)
A173: 45835.655 | B173: 542361075 | C173: FaceStation 2 542361075 (192.168.50.205) | F173: Authentication failed (Timeout)
A174: 45835.654 | B174: 542361075 | C174: FaceStation 2 542361075 (192.168.50.205) | D174: All Users | E174: 247 | F174: 1:N authentication succeeded (Face)
A175: 45835.652 | B175: 542361075 | C175: FaceStation 2 542361075 (192.168.50.205) | D175: All Users | E175: 107 | F175: 1:N authentication succeeded (Face)
A176: 45835.65 | B176: 542361075 | C176: FaceStation 2 542361075 (192.168.50.205) | D176: All Users | E176: 70 | F176: 1:N authentication succeeded (Face)
A177: 45835.65 | B177: 542361075 | C177: FaceStation 2 542361075 (192.168.50.205) | D177: All Users | E177: 30 | F177: 1:N authentication succeeded (Face)
A178: 45835.649 | B178: 542361075 | C178: FaceStation 2 542361075 (192.168.50.205) | D178: All Users | E178: 95 | F178: 1:N authentication succeeded (Face)
A179: 45835.649 | B179: 542361075 | C179: FaceStation 2 542361075 (192.168.50.205) | D179: All Users | E179: 220 | F179: 1:N authentication succeeded (Face)
A180: 45835.649 | B180: 542361075 | C180: FaceStation 2 542361075 (192.168.50.205) | D180: All Users | E180: 146 | F180: 1:N authentication succeeded (Face)
A181: 45835.649 | B181: 542361075 | C181: FaceStation 2 542361075 (192.168.50.205) | D181: All Users | E181: 222 | F181: 1:N authentication succeeded (Face)
A182: 45835.649 | B182: 542361075 | C182: FaceStation 2 542361075 (192.168.50.205) | D182: All Users | E182: 141 | F182: 1:N authentication succeeded (Face)
A183: 45835.648 | B183: 542361075 | C183: FaceStation 2 542361075 (192.168.50.205) | D183: All Users | E183: 166 | F183: 1:N authentication succeeded (Face)
A184: 45835.648 | B184: 542361075 | C184: FaceStation 2 542361075 (192.168.50.205) | D184: All Users | E184: 158 | F184: 1:N authentication succeeded (Face)
A185: 45835.647 | B185: 542361075 | C185: FaceStation 2 542361075 (192.168.50.205) | D185: All Users | E185: 63 | F185: 1:N authentication succeeded (Face)
... A195: 45835.644 | B195: 542361075 | C195: FaceStation 2 542361075 (192.168.50.205) | D195: All Users | E195: 169 | F195: 1:N authentication succeeded (Face)
A196: 45835.559 | B196: 542361075 | C196: FaceStation 2 542361075 (192.168.50.205) | F196: BioStar connected
A197: 45835.558 | B197: 542361075 | C197: FaceStation 2 542361075 (192.168.50.205) | F197: BioStar disconnected
A198: 45835.52 | B198: 542361075 | C198: FaceStation 2 542361075 (192.168.50.205) | D198: All Users | E198: 220 | F198: 1:N authentication succeeded (Face)
A199: 45835.497 | B199: 542361075 | C199: FaceStation 2 542361075 (192.168.50.205) | D199: All Users | E199: 220 | F199: 1:N authentication succeeded (Face)
A200: 45835.442 | B200: 542361075 | C200: FaceStation 2 542361075 (192.168.50.205) | D200: All Users | E200: 269 | F200: 1:N authentication succeeded (Face)
A201: 45835.442 | B201: 542361075 | C201: FaceStation 2 542361075 (192.168.50.205) | D201: All Users | E201: 95 | F201: 1:N authentication succeeded (Face)
A202: 45835.442 | B202: 542361075 | C202: FaceStation 2 542361075 (192.168.50.205) | D202: All Users | E202: 146 | F202: 1:N authentication succeeded (Face)
A203: 45835.442 | B203: 542361075 | C203: FaceStation 2 542361075 (192.168.50.205) | D203: All Users | E203: 222 | F203: 1:N authentication succeeded (Face)
A204: 45835.42 | B204: 542361075 | C204: FaceStation 2 542361075 (192.168.50.205) | D204: All Users | E204: 222 | F204: 1:N authentication succeeded (Face)
A205: 45835.418 | B205: 542361075 | C205: FaceStation 2 542361075 (192.168.50.205) | D205: All Users | E205: 95 | F205: 1:N authentication succeeded (Face)
A206: 45835.418 | B206: 542361075 | C206: FaceStation 2 542361075 (192.168.50.205) | D206: All Users | E206: 721 | F206: 1:N authentication succeeded (Face)
A207: 45835.411 | B207: 542361075 | C207: FaceStation 2 542361075 (192.168.50.205) | F207: Device time changed
A208: 45835.411 | B208: 542361075 | C208: FaceStation 2 542361075 (192.168.50.205) | F208: Device time changed
A209: 45835.332 | B209: 542361075 | C209: FaceStation 2 542361075 (192.168.50.205) | F209: BioStar connected
A210: 45835.332 | B210: 542361075 | C210: FaceStation 2 542361075 (192.168.50.205) | D210: All Users | E210: 63 | F210: 1:N authentication succeeded (Face)
A211: 45835.331 | B211: 542361075 | C211: FaceStation 2 542361075 (192.168.50.205) | D211: All Users | E211: 34 | F211: 1:N authentication succeeded (Face)
...
